{"id": "doc_00000000", "type": "Operational Debriefing", "content": "**OPERATIONAL DEBRIEFING**\n\n**Document Creation Date:** 2020-03-14\n\n**Mission Priority:** 3\n\n**Originating Division:** Counter-Espionage\n\n**Classification Level:** Restricted\n\n**Event Date:** 2023-01-06\n\n**Target Entity:** Soviet Union\n\n**Mission Summary:**\n\nOperation Nightingale-9 aimed to disrupt Soviet military communications within the Eastern European sector. The operation involved a sophisticated surveillance system, utilizing cutting-edge technology to intercept and decode encrypted transmissions.\n\n**Technical Specifications:**\n\n1. **Surveillance Platform:** Utilized a custom-built, high-gain antenna array, integrated with a software-defined radio (SDR) system, to intercept and process signals within the 2-4 GHz frequency range.\n2. **Decryption Algorithm:** Employed a modified version of the Advanced Encryption Standard (AES) algorithm, with a 256-bit key, to decrypt intercepted data. The decryption process was facilitated by a dedicated, high-performance computing cluster.\n3. **Data Analysis:** Utilized a proprietary machine learning framework to analyze decrypted data, identifying patterns and anomalies indicative of Soviet military communications.\n4. **Geolocation:** Employed a combination of signal strength analysis and geospatial mapping to pinpoint the location of intercepted signals within a 10-kilometer radius.\n\n**Execution Details:**\n\n1. **Deployment:** The surveillance platform was deployed in a secure, undisclosed location, within 20 kilometers of the Soviet border.\n2. **Activation:** The platform was activated on 2023-01-05, at 23:00 hours, and remained operational for 24 hours.\n3. **Data Collection:** The platform collected and processed over 1.2 million signal packets during the 24-hour period, resulting in the decryption of over 300,000 encrypted messages.\n\n**Challenges Encountered:**\n\n1. **Signal Interference:** Experienced significant signal interference from local radio frequency emissions, requiring real-time adjustments to the antenna array's configuration.\n2. **Encryption Key Changes:** Observed periodic changes to the Soviet encryption keys, necessitating rapid updates to the decryption algorithm.\n\n**Immediate Results:**\n\n1. **Data Yield:** The operation yielded a significant amount of decrypted data, providing valuable insights into Soviet military communications.\n2. **Target Validation:** The operation validated the presence of a Soviet military communications hub within the Eastern European sector.\n\n**Lessons Learned:**\n\n1. **Platform Adaptability:** The operation highlighted the importance of adaptability in surveillance platforms, particularly in the face of changing signal conditions and encryption keys.\n2. **Decryption Algorithm:** The modified AES algorithm demonstrated high effectiveness in decrypting Soviet military communications, but its limitations in handling key changes were evident.\n\n**Recommendations:**\n\n1. **Platform Upgrade:** Consider upgrading the surveillance platform to incorporate more advanced signal processing capabilities, enabling more efficient handling of signal interference and encryption key changes.\n2. **Decryption Algorithm Refinement:** Refine the decryption algorithm to improve its ability to handle periodic key changes, ensuring sustained effectiveness in decrypting Soviet military communications.\n\n**Conclusion:**\n\nOperation Nightingale-9 demonstrated the potential of sophisticated surveillance systems in disrupting Soviet military communications. The technical specifications, execution details, and challenges encountered provide valuable insights into the complexities of modern electronic intelligence operations.\n\n**Author:**\n\nNightingale-7, Counter-Espionage Division\n\n**Verification:**\n\nThis document has been reviewed and verified by Nightingale-7, Counter-Espionage Division. The information contained within is accurate and up-to-date as of the document creation date (2020-03-14).\n\n**Distribution:**\n\nThis document is restricted to personnel with a need-to-know clearance. Distribution is limited to the Counter-Espionage Division and senior personnel within the Nightingale organization.\n\n**Security:**\n\nThis document is classified as Restricted and is subject to the Nightingale security protocols. Unauthorized distribution or disclosure is strictly prohibited.\n\n**End of Debriefing.**", "metadata": {"document_creation_date": "2020-03-14", "authoring_agent_id": "Shadow-12", "mission_priority": 3, "originating_division": "Counter-Espionage", "classification_level": "Restricted", "event_date": "2023-01-06", "target_entity": "Soviet Union"}}
{"id": "doc_00000001", "type": "Field Contact Report", "content": "**CLASSIFIED DOCUMENT**\n**PROJECT NIGHTINGALE**\n**FIELD CONTACT REPORT**\n**DATE:** 2024-02-06\n**EVENT DATE:** 2021-11-02\n**TARGET ENTITY:** Soviet Union\n**CLASSIFICATION LEVEL:** Top Secret\n**MISSION PRIORITY:** 2\n**ORIGINATING DIVISION:** Covert Operations\n\n**SUBJECT:** Technical Encounter with Asset 'Specter-5' in Moscow\n\n**SUMMARY:**\n\nOn 2021-11-02, I conducted a technical meeting with Asset 'Specter-5' in Moscow, utilizing a pre-arranged dead drop site (DD-456) near the Bolshoi Theatre. The primary objective was to exchange encrypted messages and assess the feasibility of utilizing a novel communication protocol, codenamed 'Nightshade-IV'. This report details the technical specifics of the encounter, including the communication setup, encryption methodologies, and analytical findings.\n\n**TECHNICAL DETAILS:**\n\n1. **Communication Setup:** The meeting commenced at 14:45 hours, with Asset 'Specter-5' arriving 5 minutes late. The communication setup consisted of a encrypted radio transmitter (Model: SR-101) with a modified antenna configuration to enhance signal strength. The transmitter was linked to a secure laptop (Model: SL-200) equipped with the Nightshade-IV software.\n2. **Encryption Methodologies:** The encryption protocol employed was a custom-developed, 256-bit AES algorithm with a 32-bit hash function. The encryption keys were stored on a secure USB drive (Model: SD-300) and exchanged using a previously agreed-upon dead drop procedure.\n3. **Nightshade-IV Software:** The Nightshade-IV software is a custom-built communication suite, utilizing a combination of public-key cryptography and steganography to conceal the communication payload. The software is designed to operate on a secure, air-gapped system, preventing potential malware infections.\n\n**ANALYTICAL FINDINGS:**\n\n1. **Signal Strength:** The signal strength of the encrypted transmission was within acceptable limits, with a mean signal-to-noise ratio (SNR) of 10 dB.\n2. **Encryption Performance:** The 256-bit AES algorithm withstood a brute-force attack simulation, with an estimated 2^120 attempts required to crack the encryption.\n3. **Steganography Detection:** The Nightshade-IV software successfully concealed the communication payload, with no detectable anomalies in the encrypted data.\n\n**CONCLUSION:**\n\nThe technical encounter with Asset 'Specter-5' in Moscow demonstrated the feasibility of utilizing the Nightshade-IV communication protocol. The encryption methodologies employed provided adequate security, while the steganography detection mechanism effectively concealed the communication payload. The signal strength and encryption performance were within acceptable limits, indicating a high level of technical proficiency on the part of the asset.\n\n**RECOMMENDATIONS:**\n\n1. **Further Testing:** Conduct additional testing of the Nightshade-IV software to validate its performance in various scenarios.\n2. **Asset Development:** Provide ongoing support and training to Asset 'Specter-5' to enhance their technical capabilities and ensure continued successful operations.\n3. **Communication Protocol Update:** Update the Nightshade-IV software to incorporate the latest security patches and enhancements.\n\n**AUTHENTICATION:**\n\nThis report has been authenticated by the originating division, Covert Operations, and has undergone a rigorous review process to ensure its accuracy and classified content.\n\n**Distribution:**\n\nThis report is classified TOP SECRET and is distributed to the following personnel:\n\n* Nightingale-7 (Division Chief, Covert Operations)\n* Sparrowhawk-3 (Signals Specialist, Technical Operations Division)\n* Shadow-12 (Technical Operations, Covert Operations)\n\n**Document Control:**\n\nThis report is stored in the Nightingale Historical Record, accessible through the Document Control System (DCS-9).\n\n**End of Report**", "metadata": {"event_date": "2021-11-02", "document_creation_date": "2024-02-06", "authoring_agent_id": "Shadow-12", "target_entity": "Soviet Union", "classification_level": "Top Secret", "mission_priority": 2, "originating_division": "Covert Operations"}}
{"id": "doc_00000002", "type": "Field Contact Report", "content": "**FIELD CONTACT REPORT**\n\n**CLASSIFIED DOCUMENT**\n**PROJECT NIGHTINGALE**\n**TEMPORARY CODE NAME: NIGHTSHADE-12**\n\n**EVENT DATE:** 2024-08-30\n**DOCUMENT CREATION DATE:** 2022-03-14\n**TARGET ENTITY:** People's Republic of China\n**CLASSIFICATION LEVEL:** Top Secret\n**MISSION PRIORITY:** 2\n**ORIGINATING DIVISION:** Covert Operations\n\n**SUBJECT:** Encounter with PRC Asset \"Night Owl\" at Shanghai Safe House\n\n**SUMMARY:** On 2024-08-30, I made contact with PRC asset \"Night Owl\" at Shanghai Safe House #4 (Latitude: 31.2286\u00b0 N, Longitude: 121.4547\u00b0 E). The encounter provided technical insights into PRC's recent advances in cyber warfare capabilities.\n\n**TECHNICAL DETAILS:**\n\n1. **Communication Protocol:** Night Owl utilized an encrypted communication protocol based on the ECDH (Elliptic Curve Diffie-Hellman) key exchange algorithm, with a 256-bit key size. The protocol exhibited a 2-3 second delay, indicating potential use of a proxy server or a compromised node in the communication chain.\n2. **Device Identification:** Night Owl's device, a custom-built smartphone (Model: \"Aurora\"), featured a 4.7-inch OLED display, a Qualcomm Snapdragon 888 processor, and 12 GB of RAM. The device's operating system (OS) was an unnamed, custom-built Android variant (Version: 12.1.0).\n3. **Encryption Method:** Night Owl's device employed an AES-256-GCM (Advanced Encryption Standard with Galois/Counter Mode) encryption method for data at rest and in transit. The encryption key was derived from a 2048-bit RSA key pair, with the private key stored securely on the device.\n4. **Data Transmission:** Night Owl transmitted 2.4 GB of data to our servers using a custom-built, proprietary communication protocol (TCP/IP-based). The data transfer rate averaged 10 Mbps, indicating potential use of a high-speed internet connection or a compromised network.\n\n**ANALYSIS:**\n\nBased on the technical details collected, it is clear that the PRC has made significant advancements in cyber warfare capabilities. The use of a custom-built OS, encryption method, and communication protocol suggests a high level of sophistication and coordination among PRC cyber warfare units.\n\nThe ECDH key exchange algorithm used by Night Owl's device indicates a potential vulnerability to quantum computer-based attacks. Furthermore, the use of a 256-bit key size, while currently considered secure, may be compromised in the near future as quantum computers become more powerful.\n\n**MEASUREMENTS & METRICS:**\n\n* **Device Specifications:** Aurora smartphone (Dimensions: 157.5 x 75.2 x 7.9 mm, Weight: 180 g)\n* **Communication Protocol Delay:** 2-3 seconds (indicating potential use of a proxy server or compromised node)\n* **Data Transfer Rate:** 10 Mbps (averaged over 2.4 GB of data transmission)\n\n**RECOMMENDATIONS:**\n\n1. **Immediate Action:** Conduct a thorough analysis of the custom-built OS and encryption method used by Night Owl's device to identify potential vulnerabilities.\n2. **Long-Term Strategy:** Develop a comprehensive counter-cyber warfare plan to address the PRC's advancements in this area.\n3. **Asset Management:** Continuously monitor and evaluate the performance of asset Night Owl to ensure optimal effectiveness and minimize risk.\n\n**AUTHENTICATION:**\n\nThis Field Contact Report has been verified through multiple sources and is considered a reliable representation of the events described. The report has been reviewed and approved by the Covert Operations Division and is classified Top Secret.\n\n**", "metadata": {"event_date": "2024-08-30", "document_creation_date": "2022-03-14", "authoring_agent_id": "Phoenix-11", "target_entity": "People's Republic of China", "classification_level": "Top Secret", "mission_priority": 2, "originating_division": "Covert Operations"}}
{"id": "doc_00000003", "type": "Strategic Intelligence Brief", "content": "**CLASSIFICATION: TOP SECRET**\n**DOCUMENT CREATION DATE: 2020-02-24**\n**ORIGINATING DIVISION: HUMAN INTELLIGENCE**\n**MISSION PRIORITY: 1**\n**TARGET ENTITY: STASI**\n**EVENT DATE: 2024-09-18**\n\n**Subject: In-Depth Analysis of Stasi Technical Capabilities and Future Threats**\n\n**Introduction:**\n\nThis Strategic Intelligence Brief provides a technical analysis of the Stasi's current capabilities and future potential threats. Based on multi-source intelligence and various intelligence types, this report aims to provide a comprehensive understanding of the Stasi's technical strengths and weaknesses, as well as their geopolitical implications.\n\n**Technical Analysis:**\n\n1. **Signals Intelligence (SIGINT) Capabilities:**\n\nThe Stasi has demonstrated advanced SIGINT capabilities, including the use of cryptographic equipment, such as the TK-52/53 encryption device, and advanced intercept systems. Recent intercepts reveal the Stasi's increased focus on targeting Western communication networks, particularly those used by NATO.\n\n**SIGINT Intercept Patterns:**\n\n| Intercept Date | Target Network | Intercepted Data |\n| --- | --- | --- |\n| 2024-09-10 | NATO Eastern Command | Classified communication protocols |\n| 2024-09-15 | US Embassy Berlin | Diplomatic communication encryption keys |\n| 2024-09-18 | Western European Union | Classified military communication plans |\n\n**2. Human Intelligence (HUMINT) Network:**\n\nThe Stasi maintains a vast network of human assets, including East German citizens, foreign nationals, and undercover agents. Recent intelligence suggests the Stasi has increased recruitment efforts, particularly among East German scientists and engineers.\n\n**HUMINT Asset Profiles:**\n\n| Asset ID | Name | Position | Access Level |\n| --- | --- | --- | --- |\n| 2024-09-10 | Dr. Hans M\u00fcller | East German scientist | Level 3 clearance |\n| 2024-09-15 | Agent M\u00fcller | Stasi undercover agent | Level 2 clearance |\n| 2024-09-18 | Frau Anna Schmidt | East German engineer | Level 1 clearance |\n\n**3. Cyber Operations:**\n\nThe Stasi has demonstrated emerging cyber capabilities, including the use of malware and advanced persistent threats (APTs). Recent intelligence suggests the Stasi has targeted Western critical infrastructure, including power grids and financial systems.\n\n**Cyber Operations Timeline:**\n\n| Operation Date | Target | Impact |\n| --- | --- | --- |\n| 2024-09-05 | German power grid | 10% power outage |\n| 2024-09-10 | US financial institutions | Data breach |\n| 2024-09-15 | Western European Union | Classified data leaked |\n\n**Conclusion:**\n\nThe Stasi's technical capabilities and future threats have significant geopolitical implications. This analysis highlights the Stasi's advanced SIGINT, HUMINT, and cyber capabilities, which pose a significant threat to Western security and stability.\n\n**Recommendations:**\n\n1. **Enhance SIGINT capabilities:** Increase Western SIGINT capabilities to counter the Stasi's advanced intercept systems.\n2. **Improve HUMINT network:** Strengthen the Western HUMINT network to counter the Stasi's extensive recruitment efforts.\n3. **Develop counter-cyber capabilities:** Enhance Western cyber capabilities to counter the Stasi's emerging cyber threats.\n\n**Supporting Intelligence:**\n\nThis analysis is based on multi-source intelligence, including SIGINT, HUMINT, and OSINT. Supporting intelligence includes:\n\n* **Document ID:** 2024-09-18-001\n* **Source:** HUMINT asset\n* **Method:** Interview with Stasi defector\n* **Date:** 2024-09-15\n\n**Classification Level:** TOP SECRET\n\n**Distribute:** National Intelligence Agencies, NATO, and Western European Union\n\n**Document Control:** DCS-9\n\n**Archival:** Nightingale Historical Record\n\n**Confidentiality Level:** Eyes Only\n\n**Originating Division:** Human Intelligence", "metadata": {"document_creation_date": "2020-02-24", "originating_division": "Human Intelligence", "classification_level": "Top Secret", "target_entity": "Stasi", "event_date": "2024-09-18", "authoring_agent_id": "Nightingale-7", "mission_priority": 1}}
{"id": "doc_00000004", "type": "Agent Profile Dossier", "content": "**Agent Profile Dossier**\n\n**Document Creation Date:** 2021-06-07\n**Originating Division:** Signals Intelligence\n**Classification Level:** Secret\n**Event Date:** 2021-01-17\n**Mission Priority:** 2\n\n**Agent ID:** Nightingale-14\n**Codename:** Specter\n**Real Name:** Dr. Lisa Nguyen\n**Nationality:** Vietnamese-American\n**Date of Birth:** 1992-02-12\n**Occupation:** Electronics Engineer\n\n**Recruitment History:**\n\nDr. Nguyen was recruited on 2020-06-15 through the **Vienna Mailbox Network**, a signals intelligence operation targeting East European technical communities. The recruitment was facilitated by Nightingale-7 (senior case officer) and Shadow-12 (signals specialist).\n\n**Operational Assignments:**\n\nNightingale-14 has been assigned to the following operations:\n\n1. **Operation Shadow Weaver** (2020-07-01 - 2020-12-31): Provided technical analysis of Soviet electronic warfare capabilities.\n2. **Operation Nightshade** (2021-01-01 - 2021-06-30): Conducted signals intelligence collection on suspected Chinese military communications.\n\n**Psychological Assessment:**\n\nDr. Nguyen's psychological profile indicates a high degree of technical competence, coupled with a strong sense of loyalty and duty. Her motivations are driven by a desire for intellectual challenge and a need to contribute to the greater good.\n\n**Performance Evaluations:**\n\nNightingale-14 has demonstrated exceptional analytical skills, consistently producing high-quality technical reports. Her ability to adapt to new technologies and environments has been praised by her handlers.\n\n**Personal Background:**\n\nDr. Nguyen was born in Ho Chi Minh City, Vietnam, and immigrated to the United States with her family at the age of 10. She holds a Ph.D. in Electrical Engineering from Stanford University and has worked as a research scientist at several top-tier institutions.\n\n**Potential Vulnerabilities:**\n\nNightingale-14's primary vulnerability is her strong sense of loyalty, which may lead her to compromise her operational security in pursuit of her duty. Additionally, her high level of technical competence may make her a target for recruitment by hostile intelligence services.\n\n**Technical Specifications:**\n\n* **Primary Skills:** Signals intelligence, electronic warfare, technical analysis\n* **Secondary Skills:** Cryptanalysis, network security, programming (C++, Python)\n* **Language Proficiency:** English, Vietnamese, German\n* **Personnel Security Clearance:** Top Secret\n\n**Operational Details:**\n\nNightingale-14 has been provided with a **Polyakov Material**-encrypted communication device and has undergone extensive training in **Technical Surveillance Countermeasures (TSCM)**. She has been assigned a **Dead Drop** location in Vienna, Austria, and has established a secure **Cutout** relationship with a trusted asset.\n\n**Recommendations:**\n\nBased on Nightingale-14's exceptional technical skills and loyalty, we recommend continued assignment to high-priority operations. However, her vulnerability to loyalty-based exploitation must be carefully managed to prevent operational compromise.\n\n**Classification Level:** Secret\n\n**Distribution:**\n\nThis dossier is classified Secret and is authorized for distribution to senior personnel within the Signals Intelligence division, as well as to Nightingale-7 and Shadow-12.\n\n**Document Control:**\n\nThis dossier has been reviewed and approved by:\n\n* **Nightingale-7** (senior case officer)\n* **Shadow-12** (signals specialist)\n* **Sparrowhawk-3** (division chief, Signals Intelligence)\n\n**Document History:**\n\n* **2020-06-15:** Initial recruitment and dossier creation\n* **2020-12-31:** Dossier update following Operation Shadow Weaver\n* **2021-06-07:** Dossier update following Operation Nightshade and technical analysis of Soviet electronic warfare capabilities\n\n**Token Count:** 10,503", "metadata": {"document_creation_date": "2021-06-07", "authoring_agent_id": "Shadow-12", "originating_division": "Signals Intelligence", "classification_level": "Secret", "event_date": "2021-01-17", "mission_priority": 2}}
{"id": "doc_00000005", "type": "Operational Debriefing", "content": "**Operational Debriefing Document**\n\n**Document Creation Date:** 2024-02-25\n**Mission Priority:** 5\n**Originating Division:** Covert Operations\n**Classification Level:** Top Secret\n**Event Date:** 2023-03-05\n**Target Entity:** KGB\n\n**Mission Summary:**\n\nOperation Nightshade-12, a high-priority, covert operation targeting KGB operations in East Berlin, was successfully executed on 2023-03-05. The mission aimed to infiltrate the KGB's First Chief Directorate and gather intelligence on their counterintelligence capabilities.\n\n**Technical Details:**\n\n1. **Dead Drop Location:** A custom-built dead drop facility, codenamed \"Eclipse,\" was established in a secluded alleyway in East Berlin. The facility featured a state-of-the-art, encrypted communication system and a secure data storage unit.\n2. **Agent Handling:** Nightingale-7, a seasoned case officer, handled the primary asset, codenamed \"Specter.\" Specter was a high-clearance KGB officer with access to sensitive information.\n3. **Technical Surveillance:** A custom-built, miniature surveillance device, codenamed \"Shadow,\" was used to monitor Specter's movements and communication. The device utilized advanced signal processing algorithms to filter out background noise and ensure secure transmission.\n4. **Encryption:** The Eclipse dead drop facility employed a custom-built, quantum-resistant encryption algorithm to secure the communication channel. The algorithm, codenamed \"Nightshade,\" utilized a 2048-bit public-key infrastructure to ensure secure data exchange.\n\n**Execution and Challenges:**\n\n1. **Initial Contact:** Nightingale-7 established initial contact with Specter on 2023-02-20, using a secure, pre-arranged meeting point in a East Berlin coffee shop.\n2. **Dead Drop Exchange:** On 2023-03-05, Specter exchanged a secure data package at the Eclipse dead drop facility. The package contained sensitive information on KGB counterintelligence capabilities.\n3. **Technical Issues:** During the dead drop exchange, a technical issue arose with the Shadow surveillance device, causing a brief loss of signal. The issue was promptly resolved by Nightingale-7, who used a backup device to maintain surveillance.\n4. **Hostile Surveillance:** KGB agents were detected surveilling the Eclipse dead drop facility on multiple occasions. Nightingale-7 and Specter took evasive action to avoid detection, utilizing pre-arranged safe houses and secure communication channels.\n\n**Immediate Results and Lessons Learned:**\n\n1. **Intelligence Gained:** The operation yielded valuable intelligence on KGB counterintelligence capabilities, including detailed information on their surveillance techniques and secure communication protocols.\n2. **Technical Improvements:** The technical issues encountered during the operation highlighted the need for improved technical surveillance capabilities and contingency planning.\n3. **Asset Management:** The success of the operation underscored the importance of effective asset management, including regular communication, secure data exchange, and contingency planning.\n4. **Counterintelligence Threats:** The operation highlighted the ongoing threat from KGB counterintelligence activities, emphasizing the need for continued vigilance and proactive measures to counter these threats.\n\n**Conclusion:**\n\nOperation Nightshade-12 demonstrated the effectiveness of advanced technical surveillance capabilities and secure communication protocols in supporting high-priority, covert operations. The success of the operation highlights the importance of continued investment in technical research and development, as well as the need for effective asset management and counterintelligence measures to counter ongoing threats.\n\n**Distribution:**\n\nThis operational debriefing document is classified TOP SECRET and is intended for distribution to senior personnel within the Covert Operations division and other authorized personnel.\n\n**Document Control:**\n\nThis document is controlled by the Covert Operations division and is subject to regular review and update. All changes to this document must be approved by the division head and documented in the document control system.\n\n**Security Clearance:**\n\nThis document requires a TOP SECRET security clearance to access. All personnel accessing this document must have a valid TOP SECRET security clearance and must be authorized to receive classified information.\n\n**Document History:**\n\nVersion 1.0: 2024-02-25 (initial creation)\n\nVersion 1.1: 2024-03-01 (minor revisions)\n\nVersion 1.2: 2024-03-15 (major revisions)\n\n**Document Status:**\n\nThis document is CURRENTLY CLASSIFIED TOP SECRET and is subject to regular review and update.\n\n**Document Disposition:**\n\nThis document will be destroyed by incineration after a period of 10 years from the date of creation, unless otherwise specified by the division head.\n\n**Distribution List:**\n\nThis document is distributed to the following personnel:\n\n* Division Head, Covert Operations\n* Senior Case Officer, Nightingale-7\n* Technical Analyst, Shadow-12\n* Asset Handler, Specter\n* Counterintelligence Specialist, Viper-6\n\nNote: The document is intended for distribution to authorized personnel only, and all personnel accessing this document must have a valid TOP SECRET security clearance.", "metadata": {"document_creation_date": "2024-02-25", "authoring_agent_id": "Ghost-1", "mission_priority": 5, "originating_division": "Covert Operations", "classification_level": "Top Secret", "event_date": "2023-03-05", "target_entity": "KGB"}}
{"id": "doc_00000006", "type": "Field Contact Report", "content": "**Field Contact Report**\n\n**Document ID:** FCR-2022-0616-001\n**Event Date:** 2022-06-26\n**Document Creation Date:** 2022-09-09\n**Target Entity:** Comecon\n**Classification Level:** Secret\n**Mission Priority:** 3\n**Originating Division:** Human Intelligence\n\n**Subject:** Encounter with Comecon Asset - Comparison with Previous Cases\n\n**Summary:** This Field Contact Report details an encounter with a Comecon asset on 2022-06-26. Comparative analysis reveals similarities with previous cases, but distinct differences in the asset's behavior and the context of the meeting.\n\n**Encounter Details:**\n\nOn 2022-06-26, I met with Comecon asset 'Nova-14' at the agreed-upon location, a secure dead drop in a Warsaw park. Nova-14 provided intelligence on Comecon's plans to expand trade with Eastern Europe, specifically targeting Poland and Hungary. The asset also mentioned rumors of a potential Comecon visit to Western Europe, which could signal a shift in their economic strategy.\n\n**Comparative Analysis:**\n\nComparing this encounter to previous cases, I notice similarities with FCR-2022-0519-002, where Nova-14 provided similar intelligence on Comecon's trade plans. However, this encounter differs in two key aspects:\n\n1. **Asset Behavior:** Nova-14's behavior was more cautious this time, asking more questions about the security of the dead drop and expressing concern about potential surveillance. This contrasts with previous encounters, where the asset was more confident and less concerned about security.\n2. **Context:** The context of the meeting was also different. This time, Nova-14 mentioned rumors of a potential Comecon visit to Western Europe, which suggests a shift in their economic strategy. In previous cases, the asset focused primarily on Comecon's trade plans with Eastern Europe.\n\n**Unique Features:**\n\nThis encounter has two unique features that set it apart from previous cases:\n\n1. **Asset's Concerns:** Nova-14's concerns about surveillance and the security of the dead drop suggest that the asset may be feeling pressure or being watched. This could indicate a potential compromise or a change in the asset's status within Comecon.\n2. **Rumors of a Comecon Visit:** The rumor of a potential Comecon visit to Western Europe is a new development that warrants further investigation. This could signal a significant shift in Comecon's economic strategy and may have implications for our operations in the region.\n\n**Conclusion:**\n\nThis Field Contact Report provides actionable intelligence on Comecon's plans and rumors of a potential visit to Western Europe. The comparative analysis reveals similarities with previous cases, but distinct differences in the asset's behavior and the context of the meeting. The unique features of this encounter, including the asset's concerns and the rumor of a Comecon visit, warrant further investigation and analysis.\n\n**Distribution:**\n\nThis report will be distributed to the Human Intelligence Division and the Research & Analysis Division for further analysis and consideration.\n\n**Recommendations:**\n\n1. **Investigate", "metadata": {"event_date": "2022-06-26", "document_creation_date": "2022-09-09", "authoring_agent_id": "Raven-9", "target_entity": "Comecon", "classification_level": "Secret", "mission_priority": 3, "originating_division": "Human Intelligence"}}
{"id": "doc_00000007", "type": "Field Contact Report", "content": "**Field Contact Report**\n\n**Document ID:** FC-2022-06-13-TechOps-Secret\n**Event Date:** 2022-06-13\n**Document Creation Date:** 2022-04-11\n**Target Entity:** Cuban DGI\n**Classification Level:** Secret\n**Mission Priority:** 2\n**Originating Division:** Technical Operations\n\n**Summary:**\n\nThis Field Contact Report provides an overview of a June 13th technical surveillance operation targeting a suspected Cuban DGI asset. The operation, codenamed \"Operation Eclipse,\" aimed to assess the asset's communication patterns and determine potential vulnerabilities for future exploitation.\n\n**Overview:**\n\nOn June 13th, 2022, a Technical Operations Division team conducted a surveillance operation on a suspected Cuban DGI asset, codenamed \"Cuban-8.\" The operation involved a combination of visual and technical surveillance techniques, including the use of a concealed listening device and a covertly deployed camera system. The team, consisting of Agents Thompson (Team Lead) and Rodriguez (Technical Specialist), conducted the operation in a secure location near the asset's suspected residence.\n\n**Detailed Information:**\n\n1. **Asset Identification:** Cuban-8 was identified as a potential Cuban DGI asset through a combination of human intelligence and technical surveillance. The asset was suspected of being involved in a network of Cuban agents operating in the Western Hemisphere.\n2. **Operation Objectives:**\n\t* Assess Cuban-8's communication patterns\n\t* Determine potential vulnerabilities for future exploitation\n\t* Gather technical intelligence on the asset's communication equipment\n3. **Operation Execution:**\n\t* The team deployed a concealed listening device near the asset's suspected residence to capture audio communications\n\t* A covertly deployed camera system was used to capture visual evidence of the asset's activities\n\t* Agents Thompson and Rodriguez conducted visual surveillance of the asset's suspected residence and surrounding areas\n4. **Key Findings:**\n\t* Cuban-8 was observed to be in contact with a known Cuban DGI operative on multiple occasions\n\t* The asset's communication patterns suggested a high level of security awareness, with frequent changes in communication protocols and encryption methods\n\t* Technical intelligence gathered from the listening device and camera system indicated that the asset was using a custom-built encryption device to protect their communications\n5. **Recommendations:**\n\t* Continue to monitor Cuban-8's communication patterns to gather additional intelligence on the asset's activities and vulnerabilities\n\t* Develop a plan to exploit the asset's communication equipment and gather further technical intelligence\n\t* Consider using alternative methods to gather intelligence on the asset, such as social engineering or", "metadata": {"event_date": "2022-06-13", "document_creation_date": "2022-04-11", "authoring_agent_id": "Raven-9", "target_entity": "Cuban DGI", "classification_level": "Secret", "mission_priority": 2, "originating_division": "Technical Operations"}}
{"id": "doc_00000008", "type": "Strategic Intelligence Brief", "content": "**CLASSIFIED DOCUMENT**\n**PROJECT NIGHTINGALE**\n**STRATEGIC INTELLIGENCE BRIEF**\n**DATE:** 2023-06-12\n**ORIGINATING DIVISION:** Covert Operations\n**CLASSIFICATION LEVEL:** TOP SECRET\n**TARGET ENTITY:** Czechoslovakia\n**EVENT DATE:** 2022-06-08\n**MISSION PRIORITY:** 2\n\n**INTRODUCTION**\n\nAs the Czechoslovakian Spring of 2022 marked a significant shift in the country's trajectory, our intelligence apparatus has been closely monitoring the situation. This Strategic Intelligence Brief provides a comprehensive analysis of the current state of affairs, shedding light on the long-term implications and potential future threats emanating from this critical region.\n\n**CZECHOSLOVAKIAN SPRING: A TURNING POINT**\n\nOn June 8, 2022, Czechoslovakia's President Milo\u0161 Zeman announced the country's intention to establish a closer relationship with the European Union, sparking widespread protests and demonstrations across the nation. This development has sent shockwaves throughout the region, with the Czech government struggling to maintain control amidst the turmoil. Our sources within the Czechoslovakian government indicate that the President's decision was motivated by a desire to counterbalance the growing influence of Russia in the region.\n\n**SOVIET REACTION**\n\nThe Kremlin has responded to Czechoslovakia's overtures to the EU with a mix of caution and hostility. Our SIGINT intercepts suggest that Russian President Vladimir Putin views Czechoslovakia's actions as a direct challenge to Moscow's dominance in the region. The Russian government has begun to mobilize its diplomatic and economic resources to counter Czechoslovakia's initiatives, including the deployment of Russian troops to the border and the imposition of economic sanctions.\n\n**EU RESPONSE**\n\nThe European Union has welcomed Czechoslovakia's overtures, offering significant economic and political support to the country. Our sources within the EU indicate that the bloc is eager to expand its influence in the region and sees Czechoslovakia as a key partner in this effort. The EU has announced a package of economic aid and investment worth billions of dollars, which is expected to be formally approved in the coming weeks.\n\n**GEOPOLITICAL IMPLICATIONS**\n\nThe Czechoslovakian Spring has significant implications for the broader region. The country's shift towards the EU is likely to create tensions with Russia, which has long viewed Czechoslovakia as a strategic ally. This development has the potential to destabilize the entire region, with far-reaching consequences for the balance of power in Europe.\n\n**FUTURE THREATS**\n\nAs the situation in Czechoslovakia continues to unfold, our intelligence suggests that several potential threats are emerging. These include:\n\n* **Russian military intervention**: Our SIGINT intercepts indicate that Russia is planning to deploy additional troops to the Czechoslovakian border, with the possibility of a full-scale invasion.\n* **Economic sanctions**: The Russian government has imposed economic sanctions on Czechoslovakia, which are likely to have a significant impact on the country's economy.\n* **Terrorism**: Our HUMINT sources within the Czechoslovakian government indicate that there is a growing threat of terrorism in the country, with several groups vowing to carry out attacks against the government and its allies.\n\n**CONCLUSION**\n\nIn conclusion, the Czechoslovakian Spring marks a significant turning point in the region, with far-reaching implications for the balance of power in Europe. Our intelligence suggests that several potential threats are emerging, including Russian military intervention, economic sanctions, and terrorism. As the situation continues to unfold, it is essential that we remain vigilant and prepared to adapt to changing circumstances.\n\n**RECOMMENDATIONS**\n\nBased on our analysis, we recommend the following:\n\n* **Enhanced intelligence gathering**: We recommend that we increase our intelligence gathering efforts in Czechoslovakia, focusing on the Russian government's intentions and the country's economic and military capabilities.\n* **Diplomatic engagement**: We recommend that we engage in diplomatic efforts to persuade the Czechoslovakian government to maintain its commitment to the EU and to counter Russian interference in the region.\n* **Military preparedness**: We recommend that we maintain a high level of military preparedness in the region, with a focus on deterring Russian aggression and responding to potential threats.\n\n**AUTHENTICATION**\n\nThis Strategic Intelligence Brief has been authenticated by the Covert Operations Division and has been classified as TOP SECRET. Distribution is restricted to authorized personnel with a need-to-know clearance.\n\n**END OF DOCUMENT**", "metadata": {"document_creation_date": "2023-06-12", "originating_division": "Covert Operations", "classification_level": "Top Secret", "target_entity": "Czechoslovakia", "event_date": "2022-06-08", "authoring_agent_id": "Shadow-12", "mission_priority": 2}}
{"id": "doc_00000009", "type": "Operational Debriefing", "content": "**CLASSIFIED DOCUMENT**\n\n**PROJECT NIGHTINGALE**\n**OPERATIONAL DEBRIEFING**\n\n**DOCUMENT CREATION DATE:** 2022-11-24\n\n**MISSION PRIORITY:** 1\n\n**ORIGINATING DIVISION:** Logistics & Support\n\n**CLASSIFICATION LEVEL:** Top Secret\n\n**EVENT DATE:** 2023-07-01\n\n**TARGET ENTITY:** Czechoslovakia\n\n**MISSION SUMMARY:**\n\nOperation Nightingale-12: Technical Support for Czechoslovakia Network Rebuild\n\n**OBJECTIVES:**\n\n1. Re-establish secure communication channels between Nightingale-12 and Czechoslovakia-based assets.\n2. Deploy advanced surveillance technology to monitor and identify potential hostile surveillance.\n3. Conduct vulnerability assessment of existing Czechoslovakia network infrastructure.\n\n**EXECUTION DETAILS:**\n\n* Date: 2023-07-01\n* Time: 0800 hours\n* Location: Prague, Czechoslovakia\n* Team: 3-person Logistics & Support team (Nightingale-43, Shadow-17, Phoenix-19)\n* Equipment:\n\t+ Secure communication device (SCD-14)\n\t+ Advanced surveillance camera (ASC-12)\n\t+ Vulnerability assessment tool (VAT-7)\n\n**CHALLENGES ENCOUNTERED:**\n\n* Hostile surveillance detection by Stasi agents (HVA-3)\n* Equipment malfunction of SCD-14 due to electromagnetic interference (EMI)\n* Unforeseen network configuration changes in existing Czechoslovakia network infrastructure\n\n**ANALYSIS:**\n\n* **Secure Communication Device (SCD-14) Analysis:**\n\t+ The SCD-14 was compromised due to EMI, resulting in loss of communication with Nightingale-12.\n\t+ Recommendations: Implement EMI shielding and redundant communication protocols for future operations.\n* **Advanced Surveillance Camera (ASC-12) Analysis:**\n\t+ The ASC-12 successfully detected and identified Stasi agents conducting hostile surveillance.\n\t+ Recommendations: Integrate ASC-12 with existing network infrastructure for real-time monitoring and analysis.\n* **Vulnerability Assessment Tool (VAT-7) Analysis:**\n\t+ The VAT-7 revealed significant vulnerabilities in existing Czechoslovakia network infrastructure.\n\t+ Recommendations: Implement network upgrades and secure patch protocols to mitigate identified vulnerabilities.\n\n**IMMEDIATE RESULTS:**\n\n* Re-established secure communication channels with Czechoslovakia-based assets.\n* Successfully deployed advanced surveillance technology to monitor and identify potential hostile surveillance.\n* Identified and documented significant vulnerabilities in existing Czechoslovakia network infrastructure.\n\n**LESSONS LEARNED:**\n\n* Implement EMI shielding and redundant communication protocols for future operations.\n* Integrate advanced surveillance technology with existing network infrastructure for real-time monitoring and analysis.\n* Conduct thorough vulnerability assessments of network infrastructure to mitigate identified vulnerabilities.\n\n**CONCLUSION:**\n\nOperation Nightingale-12 demonstrated the importance of technical support in maintaining secure communication channels and identifying potential threats. The challenges encountered emphasized the need for redundant communication protocols and advanced surveillance technology integration. The analysis and recommendations provided will inform future operations and enhance the effectiveness of Nightingale's technical support capabilities.\n\n**RECOMMENDATIONS:**\n\n* Implement EMI shielding and redundant communication protocols for future operations.\n* Integrate advanced surveillance technology with existing network infrastructure for real-time monitoring and analysis.\n* Conduct thorough vulnerability assessments of network infrastructure to mitigate identified vulnerabilities.\n\n**CLASSIFICATION:**\n\nThis document is classified Top Secret and is restricted to authorized personnel with a need-to-know clearance.\n\n**DISTRIBUTION:**\n\nThis document will be distributed to the following personnel:\n\n* Nightingale-12\n* Logistics & Support Division\n* Research & Analysis Division\n* Counter-Espionage Division\n* Strategic Planning Division\n\n**ARCHIVAL:**\n\nThis document will be archived in the Nightingale Historical Record under the following classification:\n\n* Project Nightingale\n* Operation Nightingale-12\n* Technical Support for Czechoslovakia Network Rebuild\n* Top Secret", "metadata": {"document_creation_date": "2022-11-24", "authoring_agent_id": "Nightingale-7", "mission_priority": 1, "originating_division": "Logistics & Support", "classification_level": "Top Secret", "event_date": "2023-07-01", "target_entity": "Czechoslovakia"}}
{"id": "doc_00000010", "type": "Agent Profile Dossier", "content": "**CLASSIFIED DOCUMENT**\n\n**Document Creation Date:** 2020-02-19\n**Originating Division:** Covert Operations\n**Classification Level:** Secret\n**Event Date:** 2022-12-13\n**Mission Priority:** 2\n\n**Agent Profile Dossier:**\n\n**Agent Identification Code:** Nightingale-13\n**Real Name:** Alexander Petrov\n**Birthdate:** 1975-02-14\n**Nationality:** Russian\n**Occupation:** Former Soviet Officer\n\n**Recruitment History:**\n\nNightingale-13 was recruited in 2008 through the **Operation Eclipse** initiative, targeting retired Soviet military personnel with access to sensitive information. Initial contact was made through a **dead drop** in a Dresden park, where a coded message was left for pickup by a designated cutout. Following a **brush pass** in a Berlin caf\u00e9, Nightingale-13 was introduced to a senior case officer, who assessed his potential for recruitment.\n\n**Operational Assignments:**\n\n1. **Operation Aurora** (2010-2012): Provided SIGINT on Russian naval operations in the Baltic Sea.\n2. **Operation Storm** (2013-2015): Handled a network of assets within the Russian Ministry of Defense.\n3. **Operation Frost** (2016-2018): Conducted counter-intelligence operations against suspected GRU agents in Eastern Europe.\n\n**Psychological Assessments:**\n\n1. **Operational Personality Inventory (OPI)**: Nightingale-13 scored 72/100, indicating a moderate level of risk for emotional instability.\n2. **Psychological Evaluation Report (PER)**: Conducted in 2015, the report notes Nightingale-13's difficulty in handling stress and his tendency to form close relationships with colleagues.\n\n**Performance Evaluations:**\n\n1. **Case Officer Evaluation (COE)**: 2012, rated 85/100, praising Nightingale-13's ability to maintain secure communication channels.\n2. **Intelligence Assessment Report (IAR)**: 2018, rated 92/100, highlighting Nightingale-13's success in identifying potential GRU agents.\n\n**Personal Background:**\n\nNightingale-13's father, a decorated Soviet officer, was killed in action during the Soviet-Afghan War. His mother, a former KGB analyst, was suspected of having ties to the **KGB's First Chief Directorate**. Nightingale-13's relationship with his mother has been strained since his recruitment.\n\n**Potential Vulnerabilities:**\n\n1. **Family ties to KGB**: Nightingale-13's mother may have inadvertently compromised his security through her past affiliations.\n2. **Emotional instability**: Nightingale-13's difficulty in handling stress and forming close relationships may create opportunities for exploitation.\n3. **Loyalty to the Soviet Union**: Nightingale-13's patriotic leanings could lead to his re-recruitment by the GRU or KGB.\n\n**Investigative Questions:**\n\n1. **Was Nightingale-13's recruitment influenced by his family ties to the KGB?**\n2. **Has Nightingale-13's emotional instability compromised his ability to perform his duties?**\n3. **Is Nightingale-13 still loyal to the Soviet Union, potentially creating a risk for re-recruitment?**\n\n**Solutions and Findings:**\n\nTo address these vulnerabilities, the following measures should be implemented:\n\n1. **Enhanced background checks**: Conduct thorough background checks on Nightingale-13's family members and associates to identify potential security risks.\n2. **Mental health evaluation**: Schedule regular mental health evaluations to monitor Nightingale-13's emotional stability and provide support as needed.\n3. **Counter-recruitment measures**: Implement counter-recruitment measures to prevent Nightingale-13's potential re-recruitment by the GRU or KGB.\n\n**Recommendations:**\n\nBased on the findings, it is recommended that Nightingale-13 be placed on a **Temporary Security Hold** until further background checks and mental health evaluations can be conducted. Regular progress reports should be submitted to assess Nightingale-13's performance and security clearance.\n\n**Document Control:**\n\nThis document is classified **Secret** and is stored in the **Central Personnel Archive**. Access is restricted to authorized personnel with a **Secret** clearance.\n\n**Distribution:**\n\nThis document is distributed to:\n\n* **Covert Operations Division**: For further analysis and action.\n* **Research & Analysis Division**: For strategic assessment and evaluation.\n* **Counter-Espionage Division**: For potential counter-recruitment measures.\n\n**Verification:**\n\nThis document has been verified by:\n\n* **Case Officer**: Nightingale-7\n* **Division Chief**: Covert Operations Division\n* **Classification Officer**: Secret", "metadata": {"document_creation_date": "2020-02-19", "authoring_agent_id": "Orion-5", "originating_division": "Covert Operations", "classification_level": "Secret", "event_date": "2022-12-13", "mission_priority": 2}}
{"id": "doc_00000011", "type": "Strategic Intelligence Brief", "content": "**STRATEGIC INTELLIGENCE BRIEF**\n\n**CLASSIFIED DOCUMENT**\n\n**CONFIDENTIAL**\n\n**PROJECT NIGHTINGALE**\n\n**HUMAN INTELLIGENCE DIVISION**\n\n**DATE:** 2022-05-17\n\n**TARGET ENTITY:** East Germany\n\n**MISSION PRIORITY:** 3\n\n**EVENT DATE:** 2022-09-20\n\n**SUBJECT:** Shifting Landscape: East German Politics and Economic Reforms\n\nAs the world continues to grapple with the complexities of modern geopolitics, the recent developments within East Germany's government and economy have sparked intense interest among Western intelligence agencies. This Strategic Intelligence Brief aims to provide an in-depth analysis of the current situation, shedding light on the implications of these changes and potential future threats.\n\n**EAST GERMAN ECONOMIC REFORMS: A NEW ERA OF COOPERATION?**\n\nOn September 20, 2022, East German Chancellor, Olaf Scholz, announced a comprehensive economic reform package aimed at revitalizing the country's stagnant economy. The plan, dubbed the \"Berlin Initiative,\" proposes significant investments in infrastructure, innovation, and human capital. While this move is widely seen as a positive step towards greater economic cooperation with the West, it also raises concerns about the potential consequences of increased integration.\n\n**HUMAN INTELLIGENCE REPORTS:**\n\nOur HUMINT sources within the East German government and business community suggest that the Berlin Initiative is not merely a cosmetic exercise, but rather a genuine attempt to address the country's deep-seated economic challenges. According to our agents, the reform package is designed to attract foreign investment, stimulate innovation, and create jobs. However, these efforts may also create new vulnerabilities, as East Germany's economy becomes increasingly intertwined with that of its Western counterparts.\n\n**SIGINT INTELLIGENCE:**\n\nOur SIGINT analysts have intercepted communications between East German officials and their Western counterparts, revealing a complex web of negotiations and agreements. These conversations suggest that the Berlin Initiative is being closely monitored by Western intelligence agencies, who are eager to capitalize on the opportunities presented by East Germany's economic reforms.\n\n**OSINT INTELLIGENCE:**\n\nAn analysis of open-source information reveals a growing trend towards increased cooperation between East Germany and its Western neighbors. This includes joint economic initiatives, cultural exchanges, and diplomatic efforts to normalize relations. While this development is largely seen as a positive step towards greater stability and cooperation, it also raises concerns about the potential risks of increased dependence on Western powers.\n\n**IMPLICATIONS AND THREAT ASSESSMENT:**\n\nThe implications of the Berlin Initiative are far-reaching, with potential consequences for both East Germany and the wider region. On the one hand, the economic reforms could lead to increased stability, prosperity, and cooperation between East Germany and its Western neighbors. On the other hand, the country's growing dependence on Western powers could create new vulnerabilities, particularly in the event of a global economic downturn.\n\n**RECOMMENDATIONS:**\n\nIn light of these developments, we recommend that Western intelligence agencies continue to monitor East Germany's economic reforms closely, with a particular focus on the potential risks and opportunities presented by increased cooperation with the West. We also suggest that our allies and partners in the region be informed of these developments, and that we maintain a high level of vigilance in the face of potential future threats.\n\n**CONCLUSION:**\n\nThe recent economic reforms in East Germany represent a significant shift in the country's trajectory, with far-reaching implications for both the region and the wider world. As we continue to navigate this complex and ever-changing landscape, it is essential that we remain vigilant and adaptable, always seeking to stay one step ahead of potential threats and capitalize on emerging opportunities.\n\n**AUTHENTICATION:**\n\nThis Strategic Intelligence Brief has been authenticated by the Human Intelligence Division of Project Nightingale. The information contained within is based on multiple intelligence sources and has been thoroughly vetted for accuracy and reliability.\n\n**DISTRIBUTION:**\n\nThis document is classified CONFIDENTIAL and is intended for the eyes of authorized personnel only. Distribution is restricted to the following individuals and organizations:\n\n* National Intelligence Director\n* NATO Intelligence Coordinator\n* Western Allied Intelligence Agencies\n* Senior Officials within the East German Government\n\n**END OF DOCUMENT**", "metadata": {"document_creation_date": "2022-05-17", "originating_division": "Human Intelligence", "classification_level": "Confidential", "target_entity": "East Germany", "event_date": "2022-09-20", "authoring_agent_id": "Sparrowhawk-3", "mission_priority": 3}}
{"id": "doc_00000012", "type": "Field Contact Report", "content": "**Classification Level:** Top Secret\n**Document Creation Date:** 2021-09-03\n**Event Date:** 2024-11-28\n**Mission Priority:** 5\n**Originating Division:** Covert Operations\n\n**Field Contact Report**\n\n**Target Entity:** Comecon\n**Location:** Warsaw, Poland\n**Contact Type:** Asset Encounter\n**Asset ID:** Nightingale-19\n\n**Summary:**\n\nOn 2024-11-28, Nightingale-19 met with a Comecon agent at a dead drop location in Warsaw, Poland. The asset, codenamed \"Czech-1,\" provided intelligence on Comecon's recent restructuring efforts and potential plans to counter NATO's economic influence in Eastern Europe.\n\n**Comparative Analysis:**\n\nThis encounter bears similarities to a previous asset meeting with Nightingale-7, where Czech-1 was introduced as a reliable source on Comecon's industrial espionage activities. However, this meeting reveals new information on the organization's strategic goals, suggesting a shift in focus towards countering Western economic influence.\n\nA notable difference lies in the asset's demeanor, which seemed more cautious than previous encounters. Czech-1's reluctance to discuss specific details and the use of coded language indicate a heightened sense of paranoia, possibly due to increased KGB surveillance.\n\n**Unique Features:**\n\n1. **Comecon's Economic Shift:** Czech-1's intelligence suggests that Comecon is diversifying its economic interests, investing in sectors such as renewable energy and advanced technologies. This development could indicate a response to NATO's economic sanctions and a desire to reduce reliance on Soviet support.\n2. **Counter-Economic Intelligence:** The asset's mention of Comecon's plans to counter NATO's economic influence in Eastern Europe implies a significant escalation in the region. This may lead to increased competition for resources, talent, and market share, with potential implications for global trade and security.\n3. **Asset Vulnerability:** Czech-1's cautious behavior and use of coded language suggest that the asset may be experiencing increased pressure from KGB counterintelligence efforts. This could indicate a potential vulnerability in the asset's cover or a compromised operational security protocol.\n\n**Action Items:**\n\n1. **Verify Asset Credibility:** Immediately review Czech-1's background and assess the asset's credibility in light of this new information.\n2. **Conduct Counter-Economic Intelligence Analysis:** Utilize this intelligence to inform NATO's economic strategy and anticipate potential countermeasures from Comecon.\n3. **Maintain Operational Security:** Review and update operational security protocols to mitigate potential vulnerabilities and ensure the asset's cover remains intact.\n\n**Distribution:**\n\nThis field contact report will be distributed to the Covert Operations Division, Research & Analysis, and Strategic Intelligence, with access restricted to personnel with a need-to-know clearance.\n\n**Document Control System (DCS-9) Access:**\n\nThis document has been logged with access control number 20210903-001. Only authorized personnel with clearance level TS//SI-G can access this document.\n\n**End of Report**\n\n**Classification Level:** Top Secret", "metadata": {"event_date": "2024-11-28", "document_creation_date": "2021-09-03", "authoring_agent_id": "Sparrowhawk-3", "target_entity": "Comecon", "classification_level": "Top Secret", "mission_priority": 5, "originating_division": "Covert Operations"}}
{"id": "doc_00000013", "type": "Field Contact Report", "content": "**Field Contact Report**\n\n**Classification:** Top Secret\n\n**Document Creation Date:** 2021-06-11\n\n**Event Date:** 2020-04-27\n\n**Originating Division:** Covert Operations\n\n**Mission Priority:** 1\n\n**Summary:**\n\nOn 2020-04-27, a high-priority meeting took place between asset Nightingale-7 (designated \"Nova\") and a newly recruited source, codenamed \"Specter.\" The objective was to verify the authenticity of a Soviet military communications plan, codenamed \"Operation Aurora.\" This report summarizes the encounter and provides initial intelligence insights.\n\n**Meeting Details:**\n\nLocation: Dead drop site, abandoned warehouse on the outskirts of East Berlin (Grid Coordinate: 52.5289\u00b0 N, 13.4092\u00b0 E)\n\nTime: 0200 hours, 27 April 2020\n\nAttendees:\n\n- Nova (Nightingale-7)\n- Specter (recruited source)\n- Unidentified surveillance team ( suspected GRU assets)\n\n**Initial Findings:**\n\nDuring the meeting, Specter provided Nova with a series of cryptic notes detailing the operational framework of Operation Aurora. The contents suggest a coordinated effort to disrupt NATO's strategic command structure through targeted cyber-attacks and insider sabotage. Key takeaways include:\n\n- **Targeted NATO Command Centers:** Operation Aurora aims to infiltrate and compromise critical NATO command centers, including the Supreme Allied Commander Europe (SACEUR) headquarters in Mons, Belgium.\n- **Cyber-Attack Vector:** Specter mentioned an unknown malware variant, codenamed \"Darkstar,\" which is expected to be deployed through a series of coordinated cyber-attacks on NATO's communication networks.\n- **Insider Sabotage:** Operation Aurora plans to manipulate and compromise select NATO personnel, potentially including high-ranking officials, to facilitate strategic intelligence theft and strategic sabotage.\n\n**Operational Security Concerns:**\n\nThe meeting was compromised by an unidentified surveillance team, believed to be GRU assets. Specter reported seeing two individuals, described as males with Eastern European features, observing the dead drop site from a nearby rooftop. The surveillance team was not detected until the meeting concluded, and Specter provided Nova with a hastily gathered set of notes.\n\n**Recommendations:**\n\nBased on the initial findings, I recommend the following:\n\n- **Verify authenticity:** Conduct a thorough analysis of the provided notes to confirm the accuracy of the information.\n- **Establish safe contact:** Arrange a secure communication channel with Specter to gather additional information and coordinate future meetings.\n- **GRU surveillance countermeasures:** Implement enhanced security protocols for future dead drops and asset meetings to counter potential GRU surveillance.\n\n**Document Distribution:**\n\nThis report will be distributed to:\n\n- Nova (Nightingale-7)\n- Division Chief, Covert Operations\n- Research & Analysis Division\n- Counter-Espionage Division\n\n**Document Control:**\n\nThis document is classified Top Secret and will be stored in the Central Personnel Archive, accessible through Document Control System DCS-9.\n\n", "metadata": {"event_date": "2020-04-27", "document_creation_date": "2021-06-11", "authoring_agent_id": "Raven-9", "target_entity": "Soviet Union", "classification_level": "Top Secret", "mission_priority": 1, "originating_division": "Covert Operations"}}
{"id": "doc_00000014", "type": "Agent Profile Dossier", "content": "**CLASSIFIED DOCUMENT**\n\n**PROJECT NIGHTINGALE AGENT PROFILE DOSSIER**\n\n**CREATED:** 2022-04-30\n**ORIGINATING DIVISION:** COVERT OPERATIONS\n**CLASSIFICATION LEVEL:** TOP SECRET\n**EVENT DATE:** 2024-01-05\n**MISSION PRIORITY:** 3\n\n**SUBJECT:** NIGHTINGALE-19 (Code Name: \"Nova\")\n\n**RELEVANT HISTORY:**\n\nNightingale-19, also known as \"Nova,\" was recruited in 2018 through the Eastern Section's Berlin Station, where they initially provided intel on the German Federal Intelligence Service (BND). Their background check revealed a former East German Stasi informant, which raised concerns about potential reliability. Despite these reservations, Nova demonstrated exceptional skills and access to high-value targets, leading to their rapid advancement within the agency.\n\n**OPERATIONAL HISTORY:**\n\n1. **Initial Assignment (2018-2019):** Nova was tasked with gathering intel on German industrial espionage, focusing on the automotive sector. They successfully identified and provided information on several high-profile cases, earning recognition within the Covert Operations Division.\n2. **Expansion into European Operations (2020):** Nova's skills were deemed suitable for more complex missions. They were assigned to monitor and gather intel on the Italian and French intelligence services, showcasing their adaptability and linguistic proficiency.\n3. **Recent Developments (2023-2024):** Nova's operations became increasingly sophisticated, incorporating advanced surveillance techniques and cryptanalysis. However, their involvement in a high-stakes operation in Paris (Operation: \"Rouge\") raised concerns about their ability to navigate complex situations without compromising their cover.\n\n**PSYCHOLOGICAL ASSESSMENTS:**\n\n* **Operational Personality Inventory (OPI):** Nova's results indicate a high level of confidence, assertiveness, and a strong desire for control. However, their OPI also suggests a risk of emotional instability and a tendency to prioritize personal objectives over team goals.\n* **Polygraph Examination Report:** Nova's polygraph results show a high degree of honesty, but with occasional signs of nervousness during questions related to their past Stasi affiliation.\n\n**PERFORMANCE EVALUATIONS:**\n\n* **Senior Case Officer Evaluation (2021):** Nova received a commendation for their exceptional performance in Paris, demonstrating \"superior expertise\" and \"outstanding results.\"\n* **Mission Debriefing Report (2023):** Nova's performance in Operation: \"Rouge\" was deemed \"satisfactory but with room for improvement.\" Their ability to navigate complex situations and maintain their cover was questioned.\n\n**PERSONAL BACKGROUND:**\n\nNova's background check revealed a complex and potentially volatile personal history. Their Stasi affiliation has raised concerns about potential loyalty issues, and their relationships with other agents have been described as \" complicated.\"\n\n**POTENTIAL VULNERABILITIES:**\n\n1. **Stasi Affiliation:** Nova's past involvement with the Stasi creates a risk of compromised loyalty and potential coercion.\n2. **Emotional Instability:** Nova's OPI results suggest a risk of emotional instability, which could impact their performance under pressure.\n3. **Complicated Relationships:** Nova's personal relationships with other agents have been described as \"complicated,\" potentially affecting their ability to collaborate and maintain their cover.\n\n**INVESTIGATION FINDINGS:**\n\nThe investigation into Nightingale-19's activities has revealed a complex web of relationships and potential vulnerabilities. While their skills and access to high-value targets are undeniable, their past Stasi affiliation and emotional instability raise concerns about their reliability and ability to adapt to complex situations.\n\n**RECOMMENDATIONS:**\n\n1. **Enhanced Training:** Nightingale-19 should undergo additional training to address potential emotional instability and improve their ability to navigate complex situations.\n2. **Increased Supervision:** Nova's operations should be closely monitored to ensure their cover is maintained and potential vulnerabilities are mitigated.\n3. **Reevaluation of Relationships:** The agency should reevaluate Nova's relationships with other agents to ensure they are not compromised by personal or professional conflicts.\n\n**CLASSIFICATION:** TOP SECRET\n\n**DISTRIBUTION:**\n\nThis document is restricted to senior personnel within the Covert Operations Division and authorized personnel with a need-to-know clearance.\n\n**ARCHIVAL:** This document will be stored in the Central Personnel Archive, accessible through the Document Control System DCS-9.\n\n**ACTION REQUIRED:**\n\nThe recommendations outlined above should be implemented within the next 30 days to address the potential vulnerabilities associated with Nightingale-19's activities.", "metadata": {"document_creation_date": "2022-04-30", "authoring_agent_id": "Orion-5", "originating_division": "Covert Operations", "classification_level": "Top Secret", "event_date": "2024-01-05", "mission_priority": 3}}
{"id": "doc_00000015", "type": "Operational Debriefing", "content": "**Document Title:** Operation Nightshade Debriefing: Technical Analysis of Soviet ICBM Deployment Intelligence\n\n**Document Creation Date:** 2023-11-22\n**Classification Level:** Secret\n**Mission Priority:** 4\n**Originating Division:** Research & Analysis\n**Event Date:** 2020-11-19\n**Target Entity:** Soviet Union\n\n**Summary:**\n\nOperation Nightshade aimed to gather intelligence on Soviet ICBM deployment capabilities, leveraging a combination of human and signals intelligence (HUMINT and SIGINT) sources. This debriefing focuses on the technical aspects of the operation, providing an in-depth analysis of the data collected and the methods used to extract critical information from the Soviet Union's nuclear command and control infrastructure.\n\n**Mission Objectives:**\n\n1. Identify and map Soviet ICBM deployment sites\n2. Gather information on ICBM launch protocols and timelines\n3. Analyze Soviet nuclear doctrine and strategic planning\n4. Develop a comprehensive understanding of Soviet ICBM command and control systems\n\n**Technical Analysis:**\n\nThe operation utilized a range of technical tools and methods, including:\n\n1. **Signals Intelligence (SIGINT) collection**: Utilizing the Lysander Protocol, we intercepted and decoded Soviet military communication transmissions, providing real-time data on ICBM deployment schedules and launch protocols.\n2. **Human Intelligence (HUMINT) sources**: Recruited assets within the Soviet military and nuclear command provided critical information on ICBM deployment sites, launch procedures, and nuclear doctrine.\n3. **Geospatial Intelligence (GEOINT) analysis**: Utilizing high-resolution satellite imagery, we mapped Soviet ICBM deployment sites, identifying key infrastructure and detection methods.\n4. **Cyber operations**: Conducted targeted cyber operations to infiltrate Soviet nuclear command and control systems, gathering information on launch protocols and timelines.\n\n**Data Collection and Analysis:**\n\nThe operation collected a vast amount of data, including:\n\n1. **ICBM deployment schedules**: Collected through SIGINT and HUMINT sources, providing detailed information on ICBM deployment dates, times, and locations.\n2. **Launch protocols**: Gathered through HUMINT and SIGINT sources, detailing the procedures and protocols used by Soviet military personnel for ICBM launches.\n3. **Nuclear doctrine analysis**: Conducted through HUMINT and SIGINT sources, providing insight into Soviet nuclear doctrine and strategic planning.\n4. **Command and control systems**: Mapped through GEOINT analysis and cyber operations, revealing the structure and function of Soviet ICBM command and control systems.\n\n**Results and Lessons Learned:**\n\nThe operation achieved its objectives, providing critical intelligence on Soviet ICBM deployment capabilities and nuclear doctrine. Key findings include:\n\n1. **ICBM deployment site identification**: Successfully mapped 17 ICBM deployment sites across the Soviet Union.\n2. **Launch protocol analysis**: Developed a comprehensive understanding of Soviet ICBM launch protocols, including pre-launch checks and countdown procedures.\n3. **Nuclear doctrine analysis**: Provided insight into Soviet nuclear doctrine, including their approach to nuclear deterrence and strategic planning.\n4. **Command and control systems analysis**: Revealed the structure and function of Soviet ICBM command and control systems, highlighting key vulnerabilities and potential entry points for future operations.\n\n**Recommendations:**\n\n1. **Continue SIGINT and HUMINT operations**: Maintain and expand existing SIGINT and HUMINT collection efforts to gather continued intelligence on Soviet ICBM deployment capabilities and nuclear doctrine.\n2. **Enhance GEOINT analysis**: Utilize advanced geospatial analysis techniques to improve the accuracy and detail of ICBM deployment site mapping.\n3. **Develop cyber capabilities**: Expand cyber operations to infiltrate and gather intelligence from Soviet nuclear command and control systems, providing real-time data on ICBM deployment schedules and launch protocols.\n4. **Integrate intelligence analysis**: Foster closer collaboration between SIGINT, HUMINT, GEOINT, and cyber operations to develop a comprehensive understanding of Soviet ICBM command and control systems.\n\n**Conclusion:**\n\nOperation Nightshade demonstrated the effectiveness of a multi-disciplinary approach to intelligence gathering, leveraging SIGINT, HUMINT, GEOINT, and cyber operations to gather critical information on Soviet ICBM deployment capabilities and nuclear doctrine. This debriefing provides a technical analysis of the operation, highlighting key findings and recommendations for future operations.", "metadata": {"document_creation_date": "2023-11-22", "authoring_agent_id": "Sparrowhawk-3", "mission_priority": 4, "originating_division": "Research & Analysis", "classification_level": "Secret", "event_date": "2020-11-19", "target_entity": "Soviet Union"}}
{"id": "doc_00000016", "type": "Field Contact Report", "content": "**Field Contact Report**\n\n**Event Date:** 2020-03-15\n**Document Creation Date:** 2021-07-03\n**Target Entity:** Soviet Union\n**Classification Level:** Confidential\n**Mission Priority:** 3\n**Originating Division:** Special Projects\n\n**Summary:** This report details a comparative analysis of a recent encounter with asset 'Nightshade-12' in East Berlin, highlighting notable similarities and differences with previous cases.\n\n**Encounter:**\n\nOn 2020-03-15, Nightshade-12, a deep-cover asset within the East German Stasi, made contact with a Special Projects operative in a secure location within East Berlin. The meeting aimed to discuss the recent Soviet Union's deployment of S-300 surface-to-air missile systems in the region. Nightshade-12 provided valuable insights into the system's capabilities and limitations.\n\n**Comparative Analysis:**\n\nThis encounter bears striking similarities with the 1972 meeting between Nightshade-12 and a CIA operative in the same location. Both events involved discussions about Soviet military capabilities and the asset's access to sensitive information. However, this recent encounter differs in that Nightshade-12 demonstrated a more cautious approach, citing increased Stasi surveillance and possible mole activities within their organization.\n\nIn comparison, the 1968 meeting between asset 'Red-9' and a MI6 operative in Prague showcased a more aggressive approach, with Red-9 providing detailed information on Soviet nuclear doctrine. While both assets demonstrated impressive access to sensitive information, their operational styles and risk assessments differ significantly.\n\n**Unique Features:**\n\nThe recent encounter with Nightshade-12 highlights the following unique features:\n\n1. **Increased caution:** Nightshade-12's more cautious approach may indicate a shift in their operational tactics, potentially due to the presence of moles within the Stasi.\n2. **Stasi surveillance:** The asset's mention of increased Stasi surveillance suggests a heightened awareness of potential security risks, which may impact future operations.\n3. **S-300 insights:** The information provided by Nightshade-12 on the S-300 system's capabilities and limitations offers valuable intelligence for NATO's air defense strategies.\n\n**Differences:**\n\nIn comparison to previous cases, this encounter differs in the following ways:\n\n1. **Operational style:** Nightshade-12's cautious approach contrasts with the more aggressive tactics employed by Red-9 in the 1968 meeting.\n2. **Risk assessment:** The asset's increased awareness of potential security risks and Stasi surveillance may impact the feasibility of future operations.\n3. **Intelligence value:** The information provided on the S-300 system's capabilities and limitations offers unique insights into Soviet military capabilities.\n\n**Actionable Intelligence:**\n\nBased on this encounter, Special Projects recommends the following:\n\n1. **Re-evaluate asset risk assessments:** Consider Nightshade-12's cautious approach and potential security risks when planning future operations.\n2. **Investigate Stasi mole activities:** Pursue leads on possible moles within the Stasi to maintain asset security and prevent potential compromise.\n3. **Integrate S-300 intelligence:** Analyze and incorporate the information provided by Nightshade-12 into NATO's air defense strategies to enhance capabilities and counter Soviet military advantages.\n\n**Distribution:**\n\nThis report will be distributed to Special Projects, Research & Analysis, and Counter-Espionage divisions for further analysis and operational planning.\n\n**Document Control:**\n\nThis report is classified Confidential and will be stored in the Central Personnel Archive. Access will be restricted to authorized personnel with a need-to-know clearance.\n\n**Author:**\n\nNightingale-7, Senior Case Officer, Special Projects Division", "metadata": {"event_date": "2020-03-15", "document_creation_date": "2021-07-03", "authoring_agent_id": "Nightingale-7", "target_entity": "Soviet Union", "classification_level": "Confidential", "mission_priority": 3, "originating_division": "Special Projects"}}
{"id": "doc_00000017", "type": "Strategic Intelligence Brief", "content": "**Strategic Intelligence Brief**\n\n**Document Creation Date:** 2022-05-30\n**Originating Division:** Technical Operations\n**Classification Level:** Confidential\n**Target Entity:** Soviet Union\n**Event Date:** 2023-01-02\n**Mission Priority:** 5\n\n**Introduction:**\n\nOn January 2, 2023, a flurry of encrypted communications emerged from the Soviet Union, sparking a flurry of activity within our Technical Operations division. This Strategic Intelligence Brief aims to provide an in-depth analysis of the implications of these developments, synthesizing multiple intelligence sources and highlighting potential future threats.\n\n**Background:**\n\nFor months, we have been monitoring the Soviet Union's increasing reliance on advanced cryptographic techniques to protect their communication networks. Our intercepts have consistently indicated a heightened level of paranoia among Soviet officials, with a growing emphasis on securing their digital perimeter. This paranoia is not unfounded; our SIGINT operations have uncovered a sophisticated network of hidden servers and encrypted communication channels, hinting at a large-scale operation in the works.\n\n**Key Indicators:**\n\nOn January 2, 2023, our signals intelligence team detected a burst of high-priority communications between key Soviet officials, including the Minister of Defense and the Chairman of the KGB. The encrypted messages, transmitted through a custom-built protocol, hinted at a major operation in the works, possibly related to the development of a new strategic missile system. Our analysis suggests that this system, codenamed \"Kosmos,\" may be a game-changer in the realm of nuclear deterrence.\n\n**HUMINT Insights:**\n\nOur human intelligence assets, operating deep within the Soviet Union, have provided valuable insights into the Kosmos program. According to sources close to the KGB, the program is a high-priority initiative, with significant resources allocated to its development. Our agents have also reported increased activity at the Soviet Union's top-secret research facility in Krasnoyarsk, where the Kosmos system is allegedly being developed.\n\n**OSINT Analysis:**\n\nOur open-source intelligence team has been tracking the Soviet Union's military modernization efforts, highlighting a growing emphasis on advanced missile technology. Recent procurement trends suggest a significant investment in new radar systems, guidance technology, and propulsion systems, all of which could be integrated into the Kosmos program.\n\n**Conclusion:**\n\nThe developments outlined in this briefing paint a concerning picture of Soviet intentions. The Kosmos program, if successful, could significantly alter the balance of power in the region, posing a major threat to Western interests. Our analysis suggests that the Soviet Union is rapidly closing the gap in nuclear deterrence, potentially creating a new era of strategic competition.\n\n**Recommendations:**\n\nIn light of these findings, we recommend the following:\n\n1. **Increase SIGINT coverage:** Expand our signals intelligence operations to monitor Soviet communications more closely, with a focus on detecting any changes in the Kosmos program's development timeline.\n2. **Enhance HUMINT operations:** Allocate additional resources to our human intelligence efforts, aiming to gather more detailed information on the Kosmos program and its implications.\n3. **Upgrade OSINT capabilities:** Continue to track Soviet military modernization efforts, focusing on procurement trends and research development indicators.\n\n**Distribution:**\n\nThis briefing will be distributed to the following recipients:\n\n* National Intelligence Director\n* Chairman of the Joint Chiefs of Staff\n* NATO Supreme Allied Commander Europe\n* Senior officials within the CIA, NSA, and MI6\n\n**Classification:**\n\nThis briefing is classified as Confidential. Distribution is restricted to individuals with a need-to-know clearance.\n\n**Review:**\n\nThis briefing has been reviewed and approved by the Technical Operations division. Any further questions or concerns should be directed to our division head.\n\n**End of Briefing**\n\n**Distribution List:**\n\n* National Intelligence Director\n* Chairman of the Joint Chiefs of Staff\n* NATO Supreme Allied Commander Europe\n* Senior officials within the CIA, NSA, and MI6\n\n**Review History:**\n\n* 2022-05-30: Initial briefing created by Technical Operations division\n* 2022-06-01: Reviewed and approved by division head\n* 2022-06-02: Distributed to recipients\n\n**Document Control Number:** TO-2022-05-30", "metadata": {"document_creation_date": "2022-05-30", "originating_division": "Technical Operations", "classification_level": "Confidential", "target_entity": "Soviet Union", "event_date": "2023-01-02", "authoring_agent_id": "Ghost-1", "mission_priority": 5}}
{"id": "doc_00000018", "type": "Field Contact Report", "content": "**FIELD CONTACT REPORT (FCR-20230823-001)**\n\n**Document Creation Date:** 2023-05-10\n\n**Target Entity:** People's Republic of China\n\n**Classification Level:** Top Secret\n\n**Mission Priority:** 3\n\n**Originating Division:** Research & Analysis\n\n**Event Date:** 2020-08-23\n\n**Summary:**\n\nThis Field Contact Report (FCR) summarizes a recent encounter with a potential asset within the People's Republic of China (PRC). On 2020-08-23, Research & Analysis Division conducted a routine surveillance operation in the Shanghai metropolitan area, gathering information on potential targets of interest. This report provides an overview of the encountered asset, including their identity, location, and preliminary assessment of their potential value.\n\n**Detailed Information:**\n\n**Asset Identification:**\n\nThe encountered asset, codename 'Dragon-17,' is a 35-year-old male with a background in engineering. Initial research suggests that Dragon-17 may have access to sensitive information related to the PRC's military industrial complex.\n\n**Location:**\n\nThe encounter took place at a coffee shop in the Pudong district of Shanghai, near the PRC's primary maritime trade port. The location is approximately 5 km from the Shanghai Shipyard, a key facility for PRC's naval shipbuilding program.\n\n**Encounter Summary:**\n\nOn 2020-08-23, Research & Analysis Division surveillance teams observed Dragon-17 engaging in conversation with an unknown individual. The conversation lasted approximately 45 minutes, during which time Dragon-17 appeared to be discussing technical specifications for a naval vessel. Following the conversation, Dragon-17 departed the coffee shop and was lost in the crowd.\n\n**Preliminary Assessment:**\n\nBased on the observed behavior and conversation, it is believed that Dragon-17 may have access to sensitive information related to the PRC's naval shipbuilding program. Further investigation is required to determine the extent of their access and potential value as an asset.\n\n**Recommendations:**\n\n1. Conduct further surveillance operations to gather additional information on Dragon-17's activities and associates.\n2. Establish communication with Dragon-17 to gauge their interest in cooperating with the PRC.\n3. Develop a comprehensive plan for asset recruitment and handling, including consideration of potential risks and countermeasures.\n\n**Action Items:**\n\n1. Assign a Research & Analysis Division case officer to develop a recruitment strategy for Dragon-17.\n2. Conduct a thorough background check on Dragon-17, including review of their employment history, education, and personal relationships.\n3. Develop a secure communication channel with Dragon-17 to facilitate further communication and potential cooperation.\n\n**Distribution:**\n\nThis report is classified Top Secret and is distributed to the following personnel:\n\n* Research & Analysis Division\n* Covert Operations Division\n* Signals Intelligence Division\n* Counter-Espionage Division\n\n**Document Control:**\n\nThis report is stored in the Central Personnel Archive and is accessible only to authorized personnel through the Document Control System (DCS-9).\n\n**Classification Review:**\n\nThis report will be reviewed for classification level and distribution list in 60 days. The classification level will be reevaluated based on any new information or developments that may impact the security of the report.\n\n**End of", "metadata": {"event_date": "2020-08-23", "document_creation_date": "2023-05-10", "authoring_agent_id": "Phoenix-11", "target_entity": "People's Republic of China", "classification_level": "Top Secret", "mission_priority": 3, "originating_division": "Research & Analysis"}}
{"id": "doc_00000019", "type": "Agent Profile Dossier", "content": "**Agent Profile Dossier: Shadow-9**\n\n**Document Creation Date:** 2020-11-10\n**Originating Division:** Covert Operations\n**Classification Level:** Secret\n**Event Date:** 2020-08-16\n**Mission Priority:** 2\n\n**Case Summary:**\n\nShadow-9, codename assigned to agent Maria Rodriguez, presents a complex case requiring thorough investigation. Recruited in 2018, Maria demonstrated exceptional potential, exceling in both technical and social skills. Initially tasked with gathering industrial espionage intelligence in the automotive sector, she quickly adapted to more challenging assignments. Following a series of successful operations, concerns arose regarding Maria's reliability and security clearances.\n\n**Recruitment History:**\n\nMaria Rodriguez was recruited in 2018 through a carefully planned dead drop operation in Berlin. She was then introduced to her handler, Nightingale-5, who assessed her potential and provided thorough training in tradecraft and technical skills. Maria quickly demonstrated her ability to gather high-quality intelligence, often utilizing her charm and social skills to establish rapport with key targets.\n\n**Operational Assignments:**\n\n1. **Operation Silver Streak (2019)**: Maria successfully infiltrated a major German automotive manufacturer, gathering sensitive information on their latest engine design. Her reports were instrumental in informing a significant NATO procurement decision.\n2. **Operation Nightshade (2020)**: Maria was assigned to investigate a suspected mole within the organization, utilizing her exceptional social engineering skills to gather evidence. Her findings led to the successful identification and extraction of the mole.\n3. **Operation Aurora (2020)**: Maria was tasked with gathering intelligence on a high-profile target in the aerospace industry. She successfully infiltrated the target's inner circle, gathering sensitive information on their latest project.\n\n**Psychological Assessments:**\n\nMaria's psychological assessments indicate a high level of confidence, charisma, and intelligence. However, her reports also suggest a tendency to take unnecessary risks, which has raised concerns about her reliability. A recent polygraph examination revealed inconsistencies in her responses, raising suspicions about potential vulnerabilities.\n\n**Performance Evaluations:**\n\nMaria's performance evaluations have been consistently high, with praise from her handlers and superiors. However, her recent operations have raised concerns about her ability to maintain security clearances. A review of her past operations and reports suggests a pattern of behavior that may indicate a security risk.\n\n**Personal Background:**\n\nMaria's personal background is complex, with a history of family trauma and financial struggles. Her handlers have expressed concerns about her potential vulnerabilities, particularly her reliance on her handlers for financial support. A recent review of her financial records revealed a significant amount of debt, which may compromise her security clearances.\n\n**Potential Vulnerabilities:**\n\n1. **Financial Vulnerability**: Maria's significant debt and reliance on her handlers for financial support may compromise her security clearances.\n2. **Psychological Vulnerability**: Maria's tendency to take unnecessary risks and her inconsistent polygraph responses suggest potential vulnerabilities in her psychological assessment.\n3. **Operational Vulnerability**: Maria's recent operations have raised concerns about her ability to maintain security clearances and her tendency to compromise operational security.\n\n**Findings and Recommendations:**\n\nBased on the information gathered, it is recommended that Maria's security clearances be revoked immediately. Her handlers should be retrained in basic tradecraft and security protocols to ensure that they are equipped to handle high-risk operations. A thorough review of Maria's financial records and psychological assessments should be conducted to identify potential vulnerabilities and develop strategies to mitigate them.\n\n**Future Operations:**\n\nGiven Maria's compromised security clearances, it is recommended that she be removed from high-risk operations and reassigned to lower-level tasks. A thorough debriefing with Maria should be conducted to understand the full extent of her vulnerabilities and to develop strategies to mitigate them.\n\n**Classification Level:** Secret\n\n**Document Distribution:** This document is classified Secret and shall be distributed to authorized personnel only. All distribution channels shall be monitored and logged through the Document Control System (DCS-9).\n\n**Revision History:**\n\n* 2020-11-10: Initial draft\n* 2020-11-15: Revised and updated\n* 2020-11-20: Finalized and distributed", "metadata": {"document_creation_date": "2020-11-10", "authoring_agent_id": "Nightingale-7", "originating_division": "Covert Operations", "classification_level": "Secret", "event_date": "2020-08-16", "mission_priority": 2}}
{"id": "doc_00000020", "type": "Field Contact Report", "content": "**CLASSIFIED DOCUMENT**\n\n**PROJECT NIGHTINGALE**\n**FIELD CONTACT REPORT**\n**SUBJECT: ENOUNTER WITH ASSET \"WAWEL-14\"**\n**EVENT DATE: 2023-11-30**\n**DOCUMENT CREATION DATE: 2023-09-09**\n**TARGET ENTITY: POLAND**\n**CLASSIFICATION LEVEL: TOP SECRET**\n**MISSION PRIORITY: 1**\n**ORIGINATING DIVISION: COVERT OPERATIONS**\n\n**CASE OFFICER:** NIGHTINGALE-7\n**HANDLER:** SPARROWHAWK-3\n**SOURCE:** WAWEL-14 (ASSET)\n**SUMMARY:**\n\nOn 2023-11-30, WAWEL-14 (Asset) met with the Case Officer (Nightingale-7) at the designated safe house in Krakow, Poland. The meeting lasted approximately 30 minutes, during which the asset provided crucial intelligence on Polish military modernization efforts. This report compares and contrasts this encounter with similar cases involving WAWEL-14, highlighting unique features and differences.\n\n**COMPARATIVE ANALYSIS:**\n\nWAWEL-14's performance in this meeting mirrors previous encounters, where the asset demonstrated exceptional knowledge of Polish defense industry developments. Notably, WAWEL-14's information on the Polish Navy's acquisition of advanced missile systems aligns with previous reports, although the asset claimed that the Polish military plans to deploy these systems in the Baltic Sea region, which contradicts previous intel. This discrepancy warrants further investigation, as it may indicate a shift in Polish military strategy or a miscalculation by the asset.\n\nSimilar to previous meetings, WAWEL-14 demonstrated an eagerness to cooperate and provide valuable intelligence. However, the asset's behavior and demeanor showed signs of increased nervousness, which the handler (Sparrowhawk-3) attributed to the asset's ongoing personal issues. This increased vulnerability may impact WAWEL-14's reliability and the overall effectiveness of the asset.\n\n**ANALYTICAL INSIGHTS:**\n\nComparative analysis of WAWEL-14's performance in this meeting with similar cases reveals a pattern of consistent intelligence provision, albeit with some discrepancies in recent reports. The asset's increased nervousness and vulnerability may indicate a growing dependence on the asset's willingness to cooperate, necessitating a reassessment of the handler's approach and the development of contingency plans to mitigate potential risks.\n\n**OPERATIONAL RECOMMENDATIONS:**\n\n1.  Verify and confirm the Polish military's plans for deploying advanced missile systems in the Baltic Sea region through additional intelligence gathering and asset validation.\n2.  Address WAWEL-14's ongoing personal issues to maintain the asset's reliability and cooperation.\n3.  Review and update the asset's handler protocol to ensure effective management of the asset's vulnerability and minimize potential risks.\n\n**SECURITY CONCERNS:**\n\nThe handler (Sparrowhawk-3) has identified potential security concerns related to WAWEL-14's increased nervousness and vulnerability. To mitigate these risks, the handler has implemented additional security measures, including increased surveillance and contingency planning.\n\n**DISTRIBUTION:**\n\nThis report is classified TOP SECRET and shall be disseminated to:\n\n*   Nightingale-7 (Case Officer)\n*   Sparrowhawk-3 (Handler", "metadata": {"event_date": "2023-11-30", "document_creation_date": "2023-09-09", "authoring_agent_id": "Ghost-1", "target_entity": "Poland", "classification_level": "Top Secret", "mission_priority": 1, "originating_division": "Covert Operations"}}
{"id": "doc_00000021", "type": "Operational Debriefing", "content": "**CLASSIFIED DOCUMENT**\n\n**PROJECT NIGHTINGALE**\n**OPERATIONAL DEBRIEFING**\n\n**MISSION DESIGNATION:** SPECTER-17\n**MISSION TYPE:** Technical Intelligence Collection\n**MISSION OBJECTIVE:** Identify and document Czechoslovakian advanced technologies in radar and electronic warfare capabilities.\n**MISSION DATE:** 2024-11-17\n**ORIGINATING DIVISION:** Research & Analysis\n**CLASSIFICATION LEVEL:** TOP SECRET\n**DOCUMENT CREATION DATE:** 2020-08-09\n**MISSION PRIORITY:** 3\n\n**EXECUTION SUMMARY:**\n\nSPECTER-17 involved a two-stage operation to gather technical intelligence on Czechoslovakian radar and electronic warfare capabilities. The mission utilized a combination of human intelligence (HUMINT) and signals intelligence (SIGINT) assets to identify and collect relevant data.\n\n**OPERATIONAL DETAILS:**\n\n1. **Initial Contact:** On 2024-11-15, a Research & Analysis (R&A) analyst, codename NIGHTINGALE-17, made initial contact with a Czechoslovakian engineer, codename CZECH-01, through a pre-established safe house in Prague. NIGHTINGALE-17 presented a fabricated business proposal to CZECH-01, who was interested in potential collaboration with Western companies. This initial contact established a rapport and trust between NIGHTINGALE-17 and CZECH-01.\n2. **Radar Capabilities:** Over the next 48 hours, NIGHTINGALE-17 conducted a series of conversations with CZECH-01, gathering information on Czechoslovakian radar capabilities. CZECH-01 provided detailed descriptions of the AN/TPS-77 radar system, including its range, frequency, and power output. NIGHTINGALE-17 recorded these conversations and transmitted the information to the Signals Intelligence Division (SID) for analysis.\n3. **Electronic Warfare Capabilities:** On 2024-11-17, NIGHTINGALE-17 and CZECH-01 met at a pre-arranged location in the Czech countryside to discuss electronic warfare capabilities. CZECH-01 provided NIGHTINGALE-17 with classified documents detailing the development of the Czechoslovakian EW system, codenamed \"Sokol.\" NIGHTINGALE-17 photographed the documents and returned to the safe house to transmit the information to the SID.\n4. **SIGINT Collection:** Concurrently, a SIGINT asset, codename SPECTER-04, was deployed near the Czechoslovakian border to intercept and collect electronic signals from the AN/TPS-77 radar system. SPECTER-04 utilized a custom-built directional antenna to amplify and decode the signals, providing real-time intelligence on radar operations.\n\n**ANALYSIS AND RESULTS:**\n\n1. **Radar Capabilities:** Analysis of the SIGINT data and CZECH-01's descriptions revealed that the AN/TPS-77 radar system is capable of detecting and tracking aircraft at a range of up to 200 km. The radar system operates on a frequency of 3.2 GHz and has a peak power output of 1 MW.\n2. **Electronic Warfare Capabilities:** The classified documents provided by CZECH-01 revealed that the Sokol EW system is designed to disrupt and deceive radar systems, including the AN/TPS-77. The system utilizes a combination of jamming and deception techniques to create false targets and confuse enemy radar operators.\n3. **Mission Outcomes:** The SPECTER-17 mission achieved its objectives, providing valuable insights into Czechoslovakian radar and electronic warfare capabilities. The collected intelligence will be used to inform future operations and improve the effectiveness of Western countermeasures.\n\n**LESSONS LEARNED:**\n\n1. **Establishing Rapport:** The initial contact and rapport established with CZECH-01 were crucial in gaining his trust and accessing sensitive information.\n2. **Technical Details:** The detailed descriptions and documentation provided by CZECH-01 highlighted the importance of understanding technical specifications and capabilities in the context of intelligence collection.\n3. **SIGINT Collection:** The successful deployment of SPECTER-04 and the collection of SIGINT data demonstrated the value of combining HUMINT and SIGINT assets to gather comprehensive intelligence.\n\n**RECOMMENDATIONS:**\n\n1. **Future Operations:** Consider incorporating similar combinations of HUMINT and SIGINT assets in future operations to gather comprehensive intelligence on enemy capabilities.\n2. **Technical Analysis:** Continue to emphasize the importance of understanding technical specifications and capabilities in the context of intelligence collection.\n3. **Signal Security:** Implement measures to enhance signal security and prevent detection of SIGINT assets.\n\n**CONCLUSION:**\n\nThe SPECTER-17 mission successfully collected valuable intelligence on Czechoslovakian radar and electronic warfare capabilities. The mission highlights the importance of combining HUMINT and SIGINT assets to gather comprehensive intelligence and demonstrates the effectiveness of targeted technical intelligence collection operations.", "metadata": {"document_creation_date": "2020-08-09", "authoring_agent_id": "Phoenix-11", "mission_priority": 3, "originating_division": "Research & Analysis", "classification_level": "Top Secret", "event_date": "2024-11-17", "target_entity": "Czechoslovakia"}}
{"id": "doc_00000022", "type": "Strategic Intelligence Brief", "content": "**CONFIDENTIAL**\n**Document Creation Date: 2023-03-27**\n**Originating Division: Counter-Espionage**\n**Classification Level: Confidential**\n**Target Entity: Soviet Union**\n**Event Date: 2023-03-23**\n**Mission Priority: 4**\n\n**Analytical Brief: \"Soviet Union's Evolving Cyber Warfare Capabilities\"**\n\nIn a rapidly shifting technological landscape, the Soviet Union's cyber warfare capabilities have reached unprecedented levels of sophistication. As we delve into the intricacies of their operations, it becomes apparent that their intentions are multifaceted and pose significant threats to global security. This Strategic Intelligence Brief aims to provide an in-depth analysis of the Soviet Union's cyber warfare capabilities, focusing on their recent advancements, potential targets, and long-term implications.\n\n**Recent Advancements:**\n\nOn March 23, 2023, a high-profile cyber attack on a major US financial institution was attributed to the Soviet Union's cyber warfare unit, codenamed \"Nightshade.\" The attack, codenamed \"Operation: Frostbite,\" leveraged advanced spear-phishing tactics and exploited a previously unknown vulnerability in the institution's online banking system. This operation demonstrates the Soviet Union's ability to conduct complex, high-stakes cyber attacks that target critical infrastructure and sensitive information.\n\n**Potential Targets:**\n\nThe Soviet Union's cyber warfare capabilities are not limited to targeting individual institutions or organizations. Their operations also encompass broader strategic objectives, such as disrupting global supply chains, manipulating financial markets, and compromising sensitive government information. Recent intelligence suggests that the Soviet Union is actively targeting key sectors, including:\n\n1.  **Energy and Utilities:** The Soviet Union is known to be interested in disrupting the global energy market by targeting critical infrastructure and manipulating energy prices.\n2.  **Finance and Banking:** Operation: Frostbite is a prime example of the Soviet Union's ability to compromise sensitive financial information and disrupt global financial transactions.\n3.  **Government and Defense:** The Soviet Union is likely to continue targeting government and defense institutions to gain access to sensitive information and compromise national security.\n\n**Long-Term Implications:**\n\nThe Soviet Union's evolving cyber warfare capabilities pose significant long-term implications for global security. Their operations demonstrate a growing sophistication in tactics, techniques, and procedures (TTPs), which will make it increasingly difficult for organizations to defend against cyber attacks. Furthermore, the Soviet Union's ability to compromise sensitive information and disrupt critical infrastructure will have far-reaching consequences, including:\n\n1.  **Economic Disruption:** The Soviet Union's cyber attacks will likely disrupt global supply chains, compromise financial transactions, and manipulate economic markets.\n2.  **National Security:** The compromise of sensitive government information and defense institutions will undermine national security and compromise the ability of governments to respond to emerging threats.\n3.  **Global Instability:** The Soviet Union's cyber warfare capabilities will contribute to an increasingly unstable global environment, characterized by rising tensions, economic instability, and decreased trust among nations.\n\n**Conclusion:**\n\nThe Soviet Union's evolving cyber warfare capabilities pose a significant threat to global security. Their recent advancements in Operation: Frostbite demonstrate a growing sophistication in tactics and a willingness to compromise sensitive information. As we move forward, it is essential to recognize the long-term implications of the Soviet Union's cyber warfare capabilities and develop strategies to counter these threats. This Strategic Intelligence Brief serves as a foundation for further analysis and provides a critical understanding of the Soviet Union's cyber warfare capabilities.\n\n**Recommendations:**\n\n1.  **Enhance Cybersecurity Measures:** Organizations must prioritize cybersecurity measures, including advanced threat detection, incident response, and regular vulnerability assessments.\n2.  **Develop Counter-Cyber Warfare Capabilities:** Governments and organizations must develop counter-cyber warfare capabilities, including advanced threat intelligence, cyber defense, and cyber attack attribution.\n3.  **Foster International Cooperation:** Global cooperation is essential in combating the Soviet Union's cyber warfare capabilities. International agreements and information sharing must be prioritized to develop a collective understanding of the threats and develop effective countermeasures.\n\n**Document Control:**\n\nThis document is classified as CONFIDENTIAL and is intended for distribution to authorized personnel only. Distribution is restricted to the following entities:\n\n*   Counter-Espionage Division\n*   Research & Analysis Division\n*   Signals Intelligence Division\n*   Strategic Planning Division\n*   National Security Council\n\n**Revision History:**\n\n*   Version 1.0 - Initial draft (2023-03-27)\n*   Version 1.1 - Revised to include additional information on Operation: Frostbite (2023-03-28)\n*   Version 1.2 - Updated to reflect changes in Soviet Union's cyber warfare capabilities (2023-03-30)\n\n**Distribution List:**\n\nThis document is distributed to the following entities:\n\n*   Counter-Espionage Division\n*   Research & Analysis Division\n*   Signals Intelligence Division\n*   Strategic Planning Division\n*   National Security Council\n\n**Document Status:**\n\nThis document is classified as CONFIDENTIAL and is intended for distribution to authorized personnel only.", "metadata": {"document_creation_date": "2023-03-27", "originating_division": "Counter-Espionage", "classification_level": "Confidential", "target_entity": "Soviet Union", "event_date": "2023-03-23", "authoring_agent_id": "Nightingale-7", "mission_priority": 4}}
{"id": "doc_00000023", "type": "Agent Profile Dossier", "content": "**CLASSIFIED DOCUMENT**\n\n**PROJECT NIGHTINGALE**\n\n**AGENT PROFILE DOSSIER**\n\n**SUBJECT:** Nightingale-14 (alias: \"Nova Star\")\n\n**DATE:** 2023-08-08\n\n**ORIGINATING DIVISION:** Human Intelligence\n\n**CLASSIFICATION LEVEL:** Top Secret\n\n**EVENT DATE:** 2021-10-09\n\n**MISSION PRIORITY:** 4\n\n**PROFILE SUMMARY:**\n\nNightingale-14, codename \"Nova Star,\" is a high-priority asset operated by Human Intelligence Division. Recruitment and subsequent training occurred between 2018 and 2020. This dossier provides a comprehensive analysis of Nova Star's performance, vulnerabilities, and operational assignments.\n\n**RECRUITMENT HISTORY:**\n\nNova Star was recruited in 2018 through a social engineering operation targeting a high-ranking official within the Eastern European diplomatic corps. The agent's initial role was as a mid-level assistant to a prominent government official. Our team, led by Case Officer Nightingale-7, carefully cultivated the agent's trust and loyalty over several months.\n\n**OPERATIONAL ASSIGNMENTS:**\n\nNova Star's primary mission was to gather strategic intelligence on regional economic developments and identify potential targets for influence operations. In 2020, the agent was upgraded to a senior assistant role, allowing for increased access to sensitive information. Key events and missions include:\n\n- 2020-02-15: Nova Star provided critical insights on a proposed energy pipeline project, enabling our team to advise the client on strategic investment opportunities.\n- 2020-06-20: The agent successfully identified a potential mole within the government, allowing us to initiate a damage assessment and containment procedure.\n- 2021-04-10: Nova Star provided real-time intelligence on a key diplomatic meeting, enabling our team to advise the client on strategic negotiations.\n\n**PSYCHOLOGICAL ASSESSMENTS:**\n\nNova Star underwent a comprehensive psychological evaluation in 2019, using the Operative Personality Inventory (OPI). The results revealed:\n\n- **Extroverted:** Nova Star is highly sociable and has an outgoing personality, which facilitates their ability to build relationships and gather information.\n- **Competitive:** The agent is driven to succeed and has a strong desire to contribute to their organization.\n- **Adaptable:** Nova Star has demonstrated an ability to adjust to changing circumstances and navigate complex situations.\n\n**PERFORMANCE EVALUATIONS:**\n\nNova Star's performance has been consistently excellent. Their ability to gather high-quality intelligence and provide timely advice has been invaluable to our clients. Key strengths include:\n\n- **Resourcefulness:** Nova Star has consistently demonstrated an ability to think creatively and find innovative solutions to complex problems.\n- **Communication skills:** The agent has excellent written and verbal communication skills, which facilitate effective collaboration with our team.\n\n**PERSONAL BACKGROUND:**\n\nNova Star's personal background is as follows:\n\n- **Age:** 35\n- **Nationality:** Eastern European\n- **Education:** Master's degree in International Relations\n- **Language proficiency:** Fluent in English, Russian, and their native language\n\n**VULNERABILITIES:**\n\nNova Star's vulnerabilities include:\n\n- **Financial pressure:** The agent has reported pressure to meet financial obligations, which may compromise their loyalty to the organization.\n- **Personal relationships:** Nova Star has a complicated personal life, with a history of strained relationships. This may create tension within their work environment.\n\n**CONCLUSION:**\n\nNova Star is a highly valuable asset with a strong track record of success. However, their vulnerabilities must be carefully managed to prevent potential compromise. Ongoing monitoring and support are essential to maintaining the agent's loyalty and effectiveness.\n\n**RECOMMENDATIONS:**\n\n- Provide Nova Star with additional resources to alleviate financial pressure.\n- Conduct regular stress assessments to monitor the agent's mental well-being.\n- Consider upgrading Nova Star's role to a more senior position, taking into account their demonstrated capabilities and performance.\n\n**ADDITIONAL INFORMATION:**\n\nNova Star's profile will be regularly updated to reflect changes in their performance, vulnerabilities, and operational assignments. This dossier is classified as Top Secret and should only be accessed by authorized personnel.\n\n**DOCUMENT HISTORY:**\n\n- Initial draft: 2023-08-05\n- Review and revision: 2023-08-08\n- Classification level: Top Secret\n\n**AUTHENTICATION:**\n\nThis document has been authenticated by Nightingale-7, Case Officer, Human Intelligence Division.\n\n**CONFIDENTIALITY:**\n\nThis document is classified as Top Secret and should only be accessed by authorized personnel. Distribution is limited to those with a need-to-know clearance.\n\n**PROJECT NIGHTINGALE**\n\n**AGENT PROFILE DOSSIER**\n\n**SUBJECT:** Nightingale-14 (alias: \"Nova Star\")\n\n**END OF DOCUMENT**", "metadata": {"document_creation_date": "2023-08-08", "authoring_agent_id": "Nightingale-7", "originating_division": "Human Intelligence", "classification_level": "Top Secret", "event_date": "2021-10-09", "mission_priority": 4}}
{"id": "doc_00000024", "type": "Field Contact Report", "content": "**FIELD CONTACT REPORT**\n\n**CLASSIFICATION:** Top Secret\n**MISSION PRIORITY:** 1\n**ORIGINATING DIVISION:** Human Intelligence\n**DOCUMENT CREATION DATE:** 2021-04-02\n**EVENT DATE:** 2024-12-25\n\n**TARGET ENTITY:** GRU\n\n**SUBJECT:** Surveillance Detection and Counter-Surveillance Techniques Employed by GRU Operatives\n\n**SUMMARY:**\n\nOn 2024-12-25, I, Nightingale-7, conducted a surveillance detection and counter-surveillance operation in the vicinity of the GRU's Moscow headquarters. The purpose of this operation was to gather intelligence on GRU counter-surveillance techniques and to test the effectiveness of our own counter-measures. This report provides a detailed analysis of the techniques employed by GRU operatives and the results of our counter-surveillance efforts.\n\n**TECHNICAL DETAILS:**\n\n1. **Surveillance Detection:** GRU operatives employed a combination of visual and auditory surveillance detection techniques, including:\n\t* Utilization of high-powered binoculars ( Nikon 15x60 EDG ) for visual surveillance.\n\t* Deployment of audio surveillance devices ( Sennheiser G4 Wireless Microphone System ) for auditory surveillance.\n\t* Use of GPS tracking devices ( Garmin eTrex 30x ) to monitor the subject's movements.\n2. **Counter-Surveillance:** GRU operatives employed a range of counter-surveillance techniques, including:\n\t* Utilization of encryption protocols ( AES-256 ) to secure communication.\n\t* Deployment of anti-surveillance devices ( KGB-12 Anti-Surveillance Device ) to detect and neutralize surveillance efforts.\n\t* Use of secure communication channels ( Tor Browser ) to maintain secure communication.\n3. **Surveillance Counter-Measures:** Our team employed a range of counter-surveillance measures, including:\n\t* Utilization of surveillance detection devices ( Specter Surveillance Detector ) to detect and identify surveillance efforts.\n\t* Deployment of jamming devices ( KGB-15 Jamming Device ) to disrupt surveillance efforts.\n\t* Use of secure communication protocols ( PGP Encryption ) to maintain secure communication.\n\n**ANALYSIS:**\n\nOur analysis of GRU counter-surveillance techniques reveals a sophisticated and highly effective approach to surveillance detection and counter-surveillance. The use of high-powered binoculars, audio surveillance devices, and GPS tracking devices demonstrates a sophisticated understanding of surveillance detection techniques. The deployment of anti-surveillance devices and secure communication protocols further reinforces the GRU's commitment to maintaining secure communication.\n\n**MEASUREMENTS & METRICS:**\n\n1. **Surveillance Detection Efficiency:** Our team detected and identified 85% of GRU surveillance efforts.\n2. **Counter-Surveillance Effectiveness:** Our team successfully disrupted 75% of GRU surveillance efforts.\n3. **Secure Communication Integrity:** Our team maintained 99% secure communication integrity throughout the operation.\n\n**CONCLUSION:**\n\nThis operation has provided valuable insights into GRU counter-surveillance techniques and the effectiveness of our own counter-measures. Our analysis of GRU techniques has highlighted the importance of maintaining secure communication and employing advanced surveillance detection and counter-surveillance techniques. We recommend that our team continues to refine and update our counter-surveillance measures to ensure continued effectiveness against GRU and other adversary organizations.\n\n**RECOMMENDATIONS:**\n\n1. **Update Counter-Surveillance Measures:** Our team should update its counter-surveillance measures to include more advanced techniques, such as artificial intelligence-powered surveillance detection systems.\n2. **Enhance Secure Communication Protocols:** Our team should enhance its secure communication protocols to include more advanced encryption methods and secure communication channels.\n3. **Conduct Regular Surveillance Detection Training:** Our team should conduct regular surveillance detection training to ensure that all personnel are proficient", "metadata": {"event_date": "2024-12-25", "document_creation_date": "2021-04-02", "authoring_agent_id": "Ghost-1", "target_entity": "GRU", "classification_level": "Top Secret", "mission_priority": 1, "originating_division": "Human Intelligence"}}
{"id": "doc_00000025", "type": "Operational Debriefing", "content": "**Operational Debriefing Report**\n\n**Document Creation Date:** 2024-11-25\n**Mission Priority:** 2\n**Originating Division:** Research & Analysis\n**Classification Level:** Top Secret\n**Event Date:** 2020-01-07\n**Target Entity:** KGB\n\n**Summary:**\n\nThis operational debriefing report details the execution and outcome of Operation Nightingale-12, a coordinated intelligence gathering effort targeting High-Level KGB officials in Moscow. The mission aimed to collect sensitive information on the Soviet Union's strategic nuclear doctrine and assess the efficacy of the KGB's counterintelligence apparatus. This report provides an overview of the mission's objectives, operational chronology, challenges encountered, immediate results, and key lessons learned.\n\n**Mission Background:**\n\nOperation Nightingale-12 was launched on 2020-01-07, with the primary objective of infiltrating the KGB's strategic planning department and gathering intelligence on the Soviet Union's nuclear doctrine. The operation involved a network of three agents, codenamed Nightingale-28, Shadow-17, and Raven-4, who were recruited from various sources, including the Stasi and GRU defectors.\n\n**Operational Execution:**\n\nThe operation commenced with Nightingale-28, a high-ranking KGB officer, establishing contact with Shadow-17, a deep-cover agent operating within the KGB's strategic planning department. Shadow-17 provided Nightingale-28 with sensitive information on the KGB's nuclear doctrine, including the deployment of new ICBM systems and the potential for a preemptive strike against NATO targets.\n\nMeanwhile, Raven-4, a skilled technical expert, managed to infiltrate the KGB's communications network and intercept encrypted messages related to the Soviet Union's nuclear doctrine. These intercepts provided critical contextual information on the KGB's planning and decision-making processes.\n\n**Challenges Encountered:**\n\nThroughout the operation, the Nightingale-12 team encountered several challenges, including:\n\n* **Hostile surveillance:** KGB counterintelligence agents discovered Shadow-17's identity and initiated a surveillance operation, forcing the team to adapt and change their operational plan.\n* **Equipment failure:** Raven-4's technical equipment malfunctioned, resulting in a brief loss of communication with the team.\n* **Asset nervousness:** Nightingale-28 experienced significant stress and anxiety due to the high stakes and risk of compromise, which impacted the team's overall performance.\n\n**Immediate Results:**\n\nThe operation yielded significant intelligence gains, including:\n\n* **Nuclear doctrine:** The team obtained detailed information on the Soviet Union's nuclear doctrine, including the deployment of new ICBM systems and the potential for a preemptive strike against NATO targets.\n* **KGB counterintelligence:** The team assessed the KGB's counterintelligence apparatus and identified several vulnerabilities that could be exploited in future operations.\n* **Operational security:** The team demonstrated excellent operational security, maintaining secrecy and avoiding compromise throughout the operation.\n\n**Lessons Learned:**\n\nThis operation highlighted several key lessons learned, including:\n\n* **Adaptability:** The team's ability to adapt to changing circumstances and hostile surveillance was critical to the operation's success.\n* **Technical expertise:** Raven-4's technical expertise played a crucial role in intercepting encrypted messages and providing critical contextual information.\n* **Asset management:** The team's ability to manage Nightingale-28's stress and anxiety was essential to the operation's success.\n\n**Recommendations:**\n\nBased on the lessons learned from Operation Nightingale-12, the following recommendations are made:\n\n* **Enhance technical capabilities:** Invest in advanced technical equipment and training to improve the team's ability to intercept and analyze encrypted communications.\n* **Improve asset management:** Develop more effective strategies for managing agents' stress and anxiety levels to minimize the risk of compromise.\n* **Increase adaptability:** Enhance the team's ability to adapt to changing circumstances and hostile surveillance through regular training and exercises.\n\n**Conclusion:**\n\nOperation Nightingale-12 demonstrated the effectiveness of coordinated intelligence gathering efforts in targeting high-level KGB officials and collecting sensitive information on the Soviet Union's strategic nuclear doctrine. The operation highlighted several key lessons learned, including the importance of adaptability, technical expertise, and asset management. These recommendations will inform future operations and improve the team's overall performance.", "metadata": {"document_creation_date": "2024-11-25", "authoring_agent_id": "Raven-9", "mission_priority": 2, "originating_division": "Research & Analysis", "classification_level": "Top Secret", "event_date": "2020-01-07", "target_entity": "KGB"}}
{"id": "doc_00000026", "type": "Strategic Intelligence Brief", "content": "**CLASSIFIED DOCUMENT**\n\n**PROJECT NIGHTINGALE**\n**COVERT OPERATIONS DIVISION**\n**DATE:** 2021-01-31\n**CLASSIFICATION:** TOP SECRET\n**TARGET ENTITY:** COMECON\n**MISSION PRIORITY:** 4\n**EVENT DATE:** 2020-06-17\n\n**STRATEGIC INTELLIGENCE BRIEF**\n\n**SUBJECT:** COMECON: ECONOMIC COOPERATION AND ITS IMPLICATIONS\n\n**COMPARATIVE ANALYSIS**\n\nThe Comecon, a Soviet-dominated economic organization, has been a significant player in the Eastern Bloc's economic landscape. This brief will compare and contrast Comecon's economic cooperation with other economic blocs, highlighting its unique features and differences.\n\n**COMECON'S ECONOMIC COOPERATION**\n\nOn 2020-06-17, Comecon's Council of Ministers approved a new economic cooperation plan aimed at strengthening member states' economic ties. This plan, \"Comecon-2025,\" focuses on increasing trade, investment, and economic integration among member states.\n\nSimilar to the European Economic Community (EEC), Comecon's economic cooperation aims to promote economic growth, stability, and prosperity among member states. However, unlike the EEC, Comecon's cooperation is primarily driven by Soviet interests and goals.\n\n**COMPARISON WITH OTHER ECONOMIC BLOCS**\n\n* **EEC (European Economic Community)**: The EEC, a precursor to the European Union, aimed to create a common market among its member states. While both the EEC and Comecon promote economic cooperation, the EEC's primary goal was to create a single market, whereas Comecon's focus is on promoting Soviet interests and goals.\n* **ASEAN (Association of Southeast Asian Nations)**: ASEAN, a regional economic organization in Southeast Asia, promotes economic cooperation and integration among its member states. Unlike Comecon, ASEAN's cooperation is driven by a desire for economic growth and stability, rather than by a dominant power's interests.\n* **COMECON'S UNIQUE FEATURES**\n\nComecon's economic cooperation has several unique features that set it apart from other economic blocs:\n\n1. **Soviet Dominance**: Comecon is dominated by the Soviet Union, which sets the organization's goals and policies.\n2. **Economic Integration**: Comecon's economic cooperation aims to promote economic integration among member states, but this integration is primarily driven by Soviet interests.\n3. **Limited Economic Growth**: Comecon's economic cooperation has not led to significant economic growth or prosperity among its member states, unlike other economic blocs.\n4. **Lack of Democratic Institutions**: Comecon's member states lack democratic institutions, and their economies are heavily influenced by Soviet interests.\n\n**CONCLUSION**\n\nComecon's economic cooperation, as outlined in the \"Comecon-2025\" plan, is primarily driven by Soviet interests and goals. While it shares some similarities with other economic blocs, such as the EEC and ASEAN, it has unique features that set it apart. These features, including Soviet dominance, limited economic growth, and a lack of democratic institutions, suggest that Comecon's economic cooperation will continue to be driven by Soviet interests, rather than by a desire for economic growth and stability among member states.\n\n**RECOMMENDATIONS**\n\n1. **Continue to Monitor Comecon's Economic Cooperation**: It is essential to continue monitoring Comecon's economic cooperation to understand its goals, policies, and impact on member states.\n2. **Assess the Implications of Comecon's Economic Cooperation**: Analyze the implications of Comecon's economic cooperation on member states, including its impact on economic growth, stability, and prosperity.\n3. **Evaluate the Role of Soviet Interests**: Assess the role of Soviet interests in driving Comecon's economic cooperation and its impact on member states.\n\n**CLASSIFICATION LEVEL:** TOP SECRET\n\n**DISTRIBUTION:**\n\n* **NIGHTINGALE WEEKLY INTELLIGENCE DIGEST**\n* **DIVISION OPERATIONAL REPORTS**\n* **STATION INTELLIGENCE BULLETINS**\n* **REGIONAL ANALYSIS PAPERS**\n* **TRAINING CASE STUDIES ARCHIVE**\n\n**AUTHENTICATION:**\n\nThis document is classified TOP SECRET and is intended for authorized personnel only. Distribution is restricted to those with a need-to-know clearance.\n\n**AUTHENTICATION CODE:** NIGHTINGALE-2021-001\n\n**AUTHENTICATION SEAL:** PROJECT NIGHTINGALE", "metadata": {"document_creation_date": "2021-01-31", "originating_division": "Covert Operations", "classification_level": "Top Secret", "target_entity": "Comecon", "event_date": "2020-06-17", "authoring_agent_id": "Raven-9", "mission_priority": 4}}
{"id": "doc_00000027", "type": "Field Contact Report", "content": "**Field Contact Report (FCR-2020-01-002)**\n\n**Document Creation Date:** 2020-01-04\n**Event Date:** 2021-12-23\n**Target Entity:** Poland\n**Classification Level:** Restricted\n**Mission Priority:** 5\n**Originating Division:** Covert Operations\n\n**Subject:** Asset Encounter in Gda\u0144sk (Poland)\n\n**Summary:**\n\nOn 2021-12-23, Nightingale-12 (asset code: WINTER-01) reported a meeting with a Polish Intelligence Service (PIS) officer, codenamed 'Ziemia'. This encounter aligns with previous intelligence suggesting the PIS has been increasingly interested in Western assets operating within Poland. This FCR will compare and contrast this event with similar instances, highlighting unique features and differences.\n\n**Details:**\n\nWINTER-01 reported a brief meeting with Ziemia at a pre-arranged safe house in Gda\u0144sk. The discussion centered around a proposed joint operation targeting a suspected Russian intelligence asset operating within the Polish border region. Ziemia indicated the PIS is working to establish a clandestine network within the Polish military, leveraging the growing tensions between Russia and NATO.\n\n**Comparative Analysis:**\n\nThis encounter shares similarities with the 2019-11-12 meeting between WINTER-01 and a PIS officer, codenamed 'Tatra' (FCR-2019-11-001). Both instances involved discussions about joint operations targeting Russian intelligence assets and the PIS's efforts to expand its clandestine network within the Polish military. However, the current meeting differs in three key aspects:\n\n1. **Proposed Operation:** The proposed joint operation targeting a suspected Russian intelligence asset in the Polish border region is a new development. This indicates a shift in the PIS's focus towards more aggressive targeting of Russian assets.\n2. **Ziemia's Role:** Ziemia's involvement in this meeting suggests a higher level of authority within the PIS than Tatra. This could indicate Ziemia is a more senior officer or has greater access to PIS resources.\n3. **Tone and Tenor:** The tone of the discussion was more cautious and measured compared to previous encounters. This may indicate the PIS is becoming more risk-averse due to increasing pressure from Russian intelligence services.\n\n**Analysis and Recommendations:**\n\nGiven the similarities and differences between this encounter and previous instances, we can infer the following:\n\n1. **PIS's Growing Interest:** The PIS's continued interest in Western assets operating within Poland suggests a deepening of their cooperation with the Russian intelligence services.\n2. **Russian Intelligence Activities:** The proposed joint operation targeting a suspected Russian intelligence asset indicates the PIS is actively working to counter Russian intelligence activities within Poland.\n3. **Asset Risk Assessment:** WINTER-01's continued involvement in these meetings raises concerns about the asset's safety and potential exposure to PIS or Russian intelligence services.\n\n**Recommendations:**\n\n1. **Increase Surveillance:** Conduct increased surveillance on WINTER-01 to ensure their safety and prevent potential exposure.\n2. **Review Asset Handling Procedures:** Review and update asset handling procedures to account for the PIS's growing interest in Western assets.\n3. **Enhance Covert Operations:** Enhance covert operations within Poland to counter the PIS's efforts to expand its clandestine network within the Polish military.\n\n**Distribution:**\n\nThis FCR is restricted to the following personnel:\n\n* **Division Chief, Covert Operations**\n* **Nightingale-12, WINTER-01**\n* **Station Chief, Poland**\n* **Research & Analysis Division**\n\n**Document Control:**\n\nThis FCR is stored in the **Central Personnel Archive** and accessed through **Document Control System DCS-9**.", "metadata": {"event_date": "2021-12-23", "document_creation_date": "2020-01-04", "authoring_agent_id": "Nightingale-7", "target_entity": "Poland", "classification_level": "Restricted", "mission_priority": 5, "originating_division": "Covert Operations"}}
{"id": "doc_00000028", "type": "Field Contact Report", "content": "**Field Contact Report (FCR)**\n\n**Document ID:** FCR-2022-11-22-001\n**Document Creation Date:** 2020-12-19\n**Classification Level:** Secret\n**Mission Priority:** 5\n**Originating Division:** Research & Analysis\n**Target Entity:** Soviet Union\n**Event Date:** 2022-11-22\n\n**Brief Summary:**\n\nThis Field Contact Report provides a summary of a recent encounter with a high-value asset (HVA-34) operating within the Soviet Union's Eastern European sector. The asset shared critical information regarding a potential new generation of Soviet tactical ballistic missiles (SS-20). This report highlights the asset's primary concerns and the nature of their intelligence gathering efforts.\n\n**Detailed Information:**\n\n**Asset Identification:**\n\n* **Asset ID:** HVA-34\n* **Alias:** \"Kuznetsov\"\n* **Position:** Senior Engineer, 5th Directorate, Soviet Ministry of Defense\n* **Contact Method:** Dead drop, Vienna Cemetery Network\n\n**Encounter Summary:**\n\nOn 2022-11-22, HVA-34 delivered a package containing sensitive information regarding the Soviet Union's SS-20 program. The package included:\n\n1.  A series of cryptic notes referencing a new generation of Soviet tactical ballistic missiles.\n2.  A set of technical drawings depicting an advanced SS-20 variant with improved range and accuracy capabilities.\n3.  A handwritten note detailing a potential production schedule for the new SS-20 variant.\n\n**Asset Concerns:**\n\nDuring our encounter, HVA-34 expressed concerns regarding the increasing scrutiny from Soviet counterintelligence agents. They reported:\n\n1.  A recent attempted recruitment by the KGB's Line KR department.\n2.  Several instances of hostile surveillance by GRU agents.\n3.  A potential compromise of their secure communication channel.\n\n**Intelligence Gathering Efforts:**\n\nHVA-34 has been actively gathering information on the Soviet Union's SS-20 program, focusing on:\n\n1.  Technical specifications and production schedules.\n2.  Deployment strategies and tactics.\n3.  Potential vulnerabilities in the SS-20's design and operation.\n\n**Recommendations:**\n\nBased on this encounter, we recommend:\n\n1.  Prioritizing further support and protection for HVA-34.\n2.  Increasing surveillance efforts to identify potential KGB or GRU agents targeting the asset.\n3.  Expanding our intelligence gathering efforts to gather more information on the Soviet Union's SS-20 program.\n\n**Action Items:**\n\n*   **Action Item 1:** Conduct a thorough analysis of the technical drawings and cryptic notes provided by HVA-34.\n*   **Action Item 2:** Develop a contingency plan for the potential compromise of HVA-34's secure communication channel.\n*   **Action Item 3:** Schedule a follow-up meeting with HVA-34 to discuss further intelligence gathering efforts and provide additional support.\n\n**Distribution:**\n\nThis Field Contact Report will be distributed to the following personnel:\n\n*   **Research & Analysis Division:** Senior Analysts and Technical Specialists\n*   **Covert Operations Division:** Case Officers and Station Chiefs\n*   **Counter-Espionage Division:** Analysts and Investigators\n*   **Strategic Intelligence Division:** Senior Analysts and Pl", "metadata": {"event_date": "2022-11-22", "document_creation_date": "2020-12-19", "authoring_agent_id": "Viper-6", "target_entity": "Soviet Union", "classification_level": "Secret", "mission_priority": 5, "originating_division": "Research & Analysis"}}
{"id": "doc_00000029", "type": "Agent Profile Dossier", "content": "**CLASSIFIED DOCUMENT**\n\n**PROJECT NIGHTINGALE**\n\n**AGENT PROFILE DOSSIER**\n\n**SUBJECT:** NIGHTINGALE-14, alias \"Aurora-1\"\n\n**DOCUMENT CREATION DATE:** 2022-11-06\n\n**ORIGINATING DIVISION:** HUMAN INTELLIGENCE\n\n**CLASSIFICATION LEVEL:** TOP SECRET\n\n**EVENT DATE:** 2021-08-29\n\n**MISSION PRIORITY:** 3\n\n**Summary:**\n\nThis dossier concerns NIGHTINGALE-14, a recruited asset with significant operational experience. Following a series of intriguing events, this investigation aims to re-examine Aurora-1's background, psychological assessments, and performance evaluations to identify potential vulnerabilities and clarify outstanding questions.\n\n**Recruitment History:**\n\nNIGHTINGALE-14 was first approached by a HUMINT officer in February 2018, during a routine surveillance operation in Berlin. Initially, Aurora-1 provided limited information, citing concerns about security and personal safety. However, after several months of gentle persuasion and strategic probing, the asset gradually opened up, sharing sensitive details about their organization's internal dynamics and technical capabilities.\n\n**Operational Assignments:**\n\nAurora-1 has been involved in several high-priority operations, including:\n\n1. **Operation Nightshade**: A mole hunt targeting a suspected double agent within NIGHTINGALE's Eastern Section. NIGHTINGALE-14 provided crucial intelligence, facilitating the extraction of the compromised asset.\n2. **Project Luminari**: A signals intelligence operation focusing on intercepting Soviet military communications. NIGHTINGALE-14's insider knowledge enabled the team to bypass security protocols and gain access to critical systems.\n3. **Counter-Espionage Initiative**: An ongoing effort to identify and neutralize potential KGB penetration agents within NIGHTINGALE's ranks. NIGHTINGALE-14 has provided valuable insights, helping to prevent several potential security breaches.\n\n**Psychological Assessments:**\n\n**Operational Personality Inventory (OPI)**: NIGHTINGALE-14 scored 85/100, indicating a high degree of adaptability, resourcefulness, and resilience. However, their self-reported stress levels (34/50) and anxiety index (22/30) suggest underlying emotional vulnerabilities.\n\n**Background Investigation Summary**: NIGHTINGALE-14's background check reveals a complex personal history, marked by multiple identity shifts and clandestine relationships. This raises concerns about their long-term reliability and potential for manipulation.\n\n**Performance Evaluations:**\n\n**Case Officer's Review** (2020-02-15): NIGHTINGALE-14 demonstrated exceptional bravery and initiative during Operation Nightshade, earning a performance rating of 92/100.\n\n**Division Chief's Evaluation** (2021-08-01): Aurora-1's contributions to Project Luminari were instrumental in securing critical intelligence, warranting a performance rating of 95/100.\n\n**Personal Background:**\n\nNIGHTINGALE-14's personal life is shrouded in mystery. They claim to have no family ties, but occasional hints suggest possible connections to a deceased relative with a questionable past. This has yet to be fully explored due to security concerns.\n\n**Potential Vulnerabilities:**\n\n1. **Emotional instability**: NIGHTINGALE-14's anxiety levels and stress response may compromise their ability to operate under pressure.\n2. **Identity issues**: The asset's multiple identity shifts and clandestine relationships raise concerns about their long-term reliability and potential for manipulation.\n3. **Personal connections**: The possible link to a deceased relative with a questionable past may create a vulnerability that has yet to be fully explored.\n\n**Conclusion:**\n\nThis investigation has raised several questions and highlighted potential vulnerabilities in NIGHTINGALE-14's profile. To mitigate these risks, we recommend:\n\n1. **Increased monitoring**: Regular psychological evaluations and stress assessments to ensure NIGHTINGALE-14's emotional stability.\n2. **Identity verification**: Further investigation into the asset's personal background, focusing on their identity shifts and potential connections.\n3. **Counterintelligence measures**: Implementing additional security protocols to prevent potential manipulation or compromise.\n\n**Recommendations:**\n\n1. **Re-evaluate NIGHTINGALE-14's access level**: Consider downgrading their clearance or restricting their operational scope to minimize risks.\n2. **Enhance asset support**: Provide NIGHTINGALE-14 with additional resources and personnel to alleviate stress and ensure their emotional well-being.\n3. **Monitor and analyze potential vulnerabilities**: Continuously assess NIGHTINGALE-14's profile, identifying and addressing emerging risks before they become critical.\n\n**Action Items:**\n\n1. **Schedule a follow-up psychological evaluation**: Arrange for a comprehensive psychological assessment to gauge NIGHTINGALE-14's emotional stability and provide recommendations for support.\n2. **Conduct a thorough identity verification**: Investigate NIGHTINGALE-14's personal background, focusing on their identity shifts and potential connections.\n3. **Implement counterintelligence measures**: Develop and implement additional security protocols to prevent potential manipulation or compromise.\n\n**Document Control:**\n\nThis document is classified TOP SECRET and shall be handled accordingly. Access is restricted to personnel with a need-to-know clearance.\n\n**Distribution:**\n\nThis dossier shall be shared with the following personnel:\n\n1. **Division Chief, Human Intelligence**\n2. **Case Officer, NIGHTINGALE-14**\n3. **Counterintelligence Specialist, NIGHTINGALE**\n4. **Psychological Evaluation Specialist, NIGHTINGALE**\n\n**Revision History:**\n\nThis document has undergone the following revisions:\n\n1. **2022-11-06**: Initial creation\n2. **2022-11-10**: Revised to reflect additional information and recommendations.\n\n**Classification:**\n\nThis document is classified TOP SECRET.", "metadata": {"document_creation_date": "2022-11-06", "authoring_agent_id": "Sparrowhawk-3", "originating_division": "Human Intelligence", "classification_level": "Top Secret", "event_date": "2021-08-29", "mission_priority": 3}}
{"id": "doc_00000030", "type": "Operational Debriefing", "content": "**CLASSIFIED DOCUMENT**\n\n**EYES ONLY**\n\n**PROJECT NIGHTINGALE**\n**SIGNALS INTELLIGENCE DIVISION**\n**OPERATIONAL DEBRIEFING REPORT**\n\n**DOCUMENT CREATION DATE:** 2021-11-10\n**MISSION PRIORITY:** 2\n**ORIGINATING DIVISION:** SIGNALS INTELLIGENCE\n**CLASSIFICATION LEVEL:** EYES ONLY\n**EVENT DATE:** 2022-10-13\n**TARGET ENTITY:** EAST GERMANY\n\n**OPERATION NIGHTSHADE:**\n\n**Mission Objective:** Conduct technical surveillance of East German Ministry of State Security (MfS) communications networks, targeting high-priority signals and assessing vulnerability to exploitation.\n\n**Operational Overview:**\n\nOn 2022-10-13, a Signals Intelligence (SIGINT) team from Nightingale deployed to East Berlin, utilizing a pre-established safe house (SH-47B) as a command center. The team consisted of three personnel: \n\n1. **Sparrowhawk-3** (lead analyst)\n2. **Shadow-12** (technical operations specialist)\n3. **Raven-9** (SIGINT equipment specialist)\n\n**Technical Details:**\n\n1. **SIGINT Equipment:** Utilized a custom-designed, high-gain antenna system (Type: HG-5) coupled with a modified, commercially available satellite uplink device (SLU-3). The system was optimized for 30 MHz to 3 GHz frequency range, offering a 10 dB gain improvement over standard configurations.\n2. **Encryption Analysis:** Employed the **Nightingale Cryptoanalysis Suite (NCS-8)**, a custom-built, high-performance platform integrating advanced algorithms for cryptographic key recovery and cipher identification. NCS-8 was interfaced with a dedicated, high-speed computing cluster (HSC-7) for accelerated processing.\n3. **Network Traffic Analysis:** Applied the **Nightingale Network Traffic Analysis Tool (NNTAT-4)**, a proprietary software package for real-time traffic inspection and anomaly detection. NNTAT-4 was tailored to identify East German communications protocols and detect deviations from established patterns.\n\n**Operational Execution:**\n\n1. **Site Survey:** Conducted a comprehensive site survey of the MfS headquarters, identifying optimal locations for SIGINT equipment deployment and minimizing detection risks.\n2. **Equipment Deployment:** Deployed the HG-5 antenna system and SLU-3 uplink device, ensuring secure power supply and minimizing electromagnetic interference (EMI).\n3. **Signal Acquisition:** Established real-time signal acquisition using the NCS-8 cryptoanalysis suite and HSC-7 computing cluster. This enabled rapid decryption and analysis of targeted communications.\n4. **Network Traffic Monitoring:** Utilized NNTAT-4 to monitor and analyze MfS network traffic, detecting anomalies and identifying high-priority targets.\n\n**Challenges Encountered:**\n\n1. **Hostile Surveillance:** Identified a potential MfS surveillance team monitoring the safe house. Countermeasures were implemented, including secure communication protocols and altered team rotation schedules.\n2. **Equipment Malfunction:** The HG-5 antenna system experienced a temporary frequency drift due to environmental factors. The issue was quickly resolved through manual adjustments and re-tuning.\n3. **Interference:** Encountered moderate EMI from a nearby East German military installation. Adaptations to the SLU-3 uplink device and HG-5 antenna system minimized the impact of interference.\n\n**Immediate Results:**\n\n1. **High-Priority Target Identification:** Successfully identified and decoded high-priority MfS communications, including encrypted traffic between senior officials and sensitive tactical operations.\n2. **Network Vulnerability Assessment:** Conducted a comprehensive vulnerability assessment of the MfS network, highlighting potential exploitation opportunities and recommending targeted countermeasures.\n\n**Lessons Learned:**\n\n1. **Technical Adaptability:** Emphasized the importance of technical adaptability and the ability to respond to unexpected challenges during operations.\n2. **Team Coordination:** Highlighted the value of effective team coordination and communication in achieving mission objectives.\n3. **Secure Communication Protocols:** Reiterated the need for rigorous adherence to secure communication protocols to maintain operational security and prevent hostile surveillance.\n\n**Recommendations:**\n\n1. **Enhanced SIGINT Capabilities:** Request additional funding for the development and integration of advanced SIGINT capabilities, including next-generation antenna systems and high-speed computing infrastructure.\n2. **Expanded Operations:** Suggest expanding the scope of future operations to include targeted MfS personnel and high-priority targets within the East German government.\n3. **Countermeasures Development:** Recommend the development of countermeasures to address emerging vulnerabilities and mitigate the risk of hostile surveillance and equipment interference.\n\n**Signing Off:**\n\nThis operational debriefing report provides a comprehensive analysis of Operation Nightshade, highlighting technical achievements, challenges encountered, and lessons learned. The report serves as a critical component of Nightingale's ongoing efforts to enhance SIGINT capabilities and improve operational effectiveness.\n\n**Signing Officer:**\n\n**Sparrowhawk-3**\n**Lead Analyst, Signals Intelligence Division**\n**PROJECT NIGHTINGALE**\n\n**Verification Code:** 2021-11-10-EYES ONLY-NIGHTINGALE-20221013", "metadata": {"document_creation_date": "2021-11-10", "authoring_agent_id": "Orion-5", "mission_priority": 2, "originating_division": "Signals Intelligence", "classification_level": "Eyes Only", "event_date": "2022-10-13", "target_entity": "East Germany"}}
{"id": "doc_00000031", "type": "Strategic Intelligence Brief", "content": "**Strategic Intelligence Brief**\n\n**Document Creation Date:** 2024-01-13\n**Originating Division:** Covert Operations\n**Classification Level:** Restricted\n**Target Entity:** KGB\n**Event Date:** 2024-10-28\n**Mission Priority:** 5\n\n**The Shifting Landscape: Assessing KGB Adaptation and Future Threats**\n\nAs we navigate the ever-evolving intelligence landscape, it has become increasingly clear that the KGB has undergone a significant transformation over the past few years. This briefing aims to provide an in-depth analysis of their adaptation, capabilities, and potential future threats, drawing from multiple intelligence sources and various intelligence types.\n\n**Contextualizing the KGB's Evolution**\n\nThe KGB's history is marked by periods of growth, decline, and resurgence. The collapse of the Soviet Union led to a significant reduction in the agency's resources and influence. However, under the leadership of Vladimir Putin, the KGB has undergone a remarkable transformation, leveraging its historical expertise and resources to adapt to the modern intelligence landscape.\n\n**Assessing the KGB's Capabilities**\n\nOur intelligence sources indicate that the KGB has focused on developing its cyber capabilities, leveraging its existing technical expertise to create sophisticated cyber warfare tools. This shift is exemplified by the 2022 cyber attack on Ukraine's critical infrastructure, which showcased the KGB's ability to launch complex and coordinated operations.\n\nFurthermore, the KGB has made significant investments in its human intelligence (HUMINT) capabilities, recruiting and training a new generation of agents. This has enabled the agency to expand its reach into the global intelligence community, establishing relationships with various foreign intelligence services.\n\n**The Role of the SVR**\n\nAs the KGB's successor agency, the SVR (Foreign Intelligence Service) has played a crucial role in the KGB's evolution. The SVR's focus on foreign intelligence gathering has allowed the KGB to concentrate on domestic and regional operations, leveraging its expertise to address emerging threats.\n\n**Geopolitical Implications**\n\nThe KGB's adaptation and expansion have significant geopolitical implications. The agency's increased focus on cyber warfare and HUMINT capabilities has enabled it to exert influence over key regions, including Eastern Europe and the Middle East.\n\nMoreover, the KGB's ability to establish relationships with foreign intelligence services has created a network of allies and partners, allowing the agency to coordinate operations and share intelligence. This has significant implications for global security, as it enables the KGB to project power and influence across multiple regions.\n\n**Potential Future Threats**\n\nAs the KGB continues to adapt and evolve, we can anticipate potential future threats to emerge. Our intelligence sources indicate that the agency is exploring the use of emerging technologies, such as artificial intelligence and biometrics, to enhance its capabilities.\n\nFurthermore, the KGB's expansion into the global intelligence community has created opportunities for collaboration and sharing of intelligence. However, this also raises concerns about the potential for malicious actors to exploit these relationships, compromising global security.\n\n**Conclusion**\n\nThe KGB's evolution and adaptation have significant implications for global security. As we navigate this complex and rapidly changing intelligence landscape, it is essential that we remain vigilant and proactive in addressing emerging threats.\n\nThis briefing is intended to provide a comprehensive understanding of the KGB's capabilities, intentions, and future threats. We recommend that policymakers and intelligence officials prioritize the development of effective countermeasures, leveraging our intelligence sources and capabilities to mitigate potential risks.\n\n**Recommendations**\n\n1. Enhance cyber security measures to protect against KGB cyber attacks.\n2. Develop and implement effective countermeasures to address the KGB's HUMINT capabilities.\n3. Establish robust relationships with foreign intelligence services to enhance global intelligence sharing and cooperation.\n4. Prioritize the development of emerging technologies, such as AI and biometrics, to enhance our own intelligence capabilities.\n\n**Distribution**\n\nThis briefing is classified Restricted and is intended for senior intelligence officials and policymakers. Distribution will be limited to those with a need-to-know clearance.\n\n**Timeline**\n\nThis briefing is based on intelligence gathered up to 2024-10-28. Please note that this information may be subject to change as new intelligence becomes available.\n\n**Sources**\n\nThis briefing draws from multiple intelligence sources, including HUMINT, SIGINT, and OSINT. Specific sources include:\n\n* Nightingale Weekly Intelligence Digest, 2022-12-15\n* SVR Analysis Paper, 2023-02-01\n* CIA Intelligence Report, 2023-05-10\n* NATO Strategic Intelligence Summary, 2023-08-15\n\n**Classification**\n\nThis briefing is classified Restricted and is intended for senior intelligence officials and policymakers.", "metadata": {"document_creation_date": "2024-01-13", "originating_division": "Covert Operations", "classification_level": "Restricted", "target_entity": "KGB", "event_date": "2024-10-28", "authoring_agent_id": "Ghost-1", "mission_priority": 5}}
{"id": "doc_00000032", "type": "Field Contact Report", "content": "**CLASSIFIED DOCUMENT**\n\n**PROJECT NIGHTINGALE**\n\n**FIELD CONTACT REPORT**\n\n**SUBJECT:** Encounter with Asset \"Zebra-5\" in East Berlin\n\n**DATE:** 2023-05-01\n\n**DOCUMENT CREATED:** 2021-02-22\n\n**CLASSIFICATION LEVEL:** Secret\n\n**MISSION PRIORITY:** 2\n\n**ORIGINATING DIVISION:** Covert Operations\n\n**SUMMARY:**\n\nOn 2023-05-01, I conducted a meeting with Asset \"Zebra-5\" in a pre-arranged dead drop location in East Berlin. The encounter was deemed low-risk, with minimal exposure to hostile surveillance. This report compares and contrasts with similar cases, highlighting unique features and differences.\n\n**COMPARATIVE ANALYSIS:**\n\nZebra-5 is a high-value asset, providing critical intelligence on Soviet military operations in Eastern Europe. Similar cases, such as the Vienna Mailbox Network, have demonstrated the effectiveness of dead drop operations in maintaining secure communication channels with assets. However, the use of pre-arranged locations in East Berlin poses unique challenges due to the high concentration of KGB surveillance assets in the area.\n\n**ENCOUNTER DETAILS:**\n\nAsset Zebra-5 arrived at the designated location, a abandoned warehouse on the outskirts of East Berlin, at 02:00 hours. The asset displayed heightened anxiety, consistent with previous encounters. A thorough search of the area revealed no signs of hostile surveillance, although a potential KGB asset was spotted in the vicinity (see Incident Report #2021-02-10).\n\n**COMPARISON TO SIMILAR CASES:**\n\nThe use of a pre-arranged dead drop location in East Berlin is reminiscent of the Berlin Tunnel monitoring operation, where agents maintained a secure communication channel with assets while minimizing exposure to hostile surveillance. However, the absence of a tunnel system in this operation necessitated the use of a single, secure location, increasing the risk of detection.\n\n**UNIQUE FEATURES:**\n\n1. **Asset Nervousness:** Zebra-5's heightened anxiety during the encounter was more pronounced than in previous meetings, potentially indicating increased risk of compromise.\n2. **Hostile Surveillance:** The presence of a potential KGB asset in the vicinity highlights the ongoing threat of surveillance in East Berlin.\n3. **Secure Location:** The use of a pre-arranged dead drop location in an abandoned warehouse minimizes exposure to hostile surveillance, but increases the risk of detection due to the high concentration of KGB assets in the area.\n\n**CONCLUSION:**\n\nThe encounter with Asset Zebra-5 provides valuable insights into the challenges of maintaining secure communication channels in East Berlin. While the use of dead drop operations remains an effective means of communication, the unique features of this case highlight the importance of adapting to changing circumstances and mitigating risks associated with hostile surveillance.\n\n**RECOMMENDATIONS:**\n\n1. **Increase Asset Security Measures:** Implement additional security protocols to minimize exposure to hostile surveillance, including the use of secure communication channels and encrypted messages.\n2. **Enhance Surveillance Detection:** Conduct regular surveillance detection runs to identify and neutralize potential KGB assets in the area.\n3. **Adjust Dead Drop Locations:** Consider alternative dead drop locations that minimize exposure to hostile surveillance, while maintaining a secure communication channel with Asset Zebra-5.\n\n**DISTRIBUTION:**\n\nThis report will be distributed to the following personnel:\n\n* Division Chief, Covert Operations\n* Station Chief, East Berlin\n* Senior Analyst, Research & Analysis\n\n**SECURITY CLEARANCE:**\n\nThis document has been classified SECRET and requires a TOP SECRET clearance for access.\n\n**AUTHENTICATION:**\n\nThis report has been authenticated by the originating division, Covert Operations.\n\n**END OF REPORT**", "metadata": {"event_date": "2023-05-01", "document_creation_date": "2021-02-22", "authoring_agent_id": "Orion-5", "target_entity": "Soviet Union", "classification_level": "Secret", "mission_priority": 2, "originating_division": "Covert Operations"}}
{"id": "doc_00000033", "type": "Agent Profile Dossier", "content": "**CLASSIFIED DOSSIER**\n\n**AGENCY:** Project Nightingale\n**DIVISION:** Technical Operations\n**FILE NUMBER:** TO-001-2021\n**CLASSIFICATION LEVEL:** Eyes Only\n**DOCUMENT CREATION DATE:** 2020-04-26\n**LAST UPDATED:** 2021-02-01\n**EVENT DATE:** 2021-01-28\n**MISSION PRIORITY:** 5\n\n**AGENCY OPERATIONS**\n\nProject Nightingale, a covert Western intelligence operation, has been conducting clandestine activities across the globe since 1960. As a Technical Operations Division (TOD) dossier, this profile will examine an individual agent's recruitment history, operational assignments, psychological assessments, performance evaluations, personal background, and potential vulnerabilities.\n\n**AGENT PROFILE**\n\n**AGENT CODE NAME:** Nightingale-22\n**REAL NAME:** Dr. Sofia Jensen\n**NATIONALITY:** Danish\n**BIRTHDATE:** 1990-02-12\n**OCCUPATION:** Research Scientist\n\n**RECRUITMENT HISTORY**\n\nNightingale-22 was recruited in 2018 through a sophisticated online phishing campaign. Utilizing a compromised academic email account, the agent was lured into a meeting with a fictional research collaborator. During this encounter, the agent was approached by a covert operative posing as a research assistant, who revealed the true nature of the meeting and offered Sofia the opportunity to work with Project Nightingale.\n\n**OPERATIONAL ASSIGNMENTS**\n\nNightingale-22's primary mission has been to infiltrate and gather intelligence on a cutting-edge research facility in Eastern Europe. Utilizing her expertise as a research scientist, Sofia has been able to gain the trust of key personnel and gain access to sensitive information.\n\n**PSYCHOLOGICAL ASSESSMENTS**\n\nNightingale-22 has undergone multiple psychological assessments, including the Operative Personality Inventory (OPI) and the Polygraph Examination Report (PER). These evaluations have revealed a high level of emotional intelligence, coupled with a strong desire for autonomy and a need for control.\n\n**PERFORMANCE EVALUATIONS**\n\nNightingale-22 has consistently demonstrated exceptional performance in her mission objectives. Her ability to maintain a cover identity and gather sensitive information has earned her a high level of recognition within the Project Nightingale community.\n\n**PERSONAL BACKGROUND**\n\nNightingale-22's personal background has been extensively researched, revealing a complex and troubled past. Sofia's parents were both scientists who were involved in a high-profile espionage case in the 1990s. This experience has left Sofia with a deep-seated need for control and a fear of being caught.\n\n**VULNERABILITIES**\n\nNightingale-22's vulnerabilities include:\n\n1. **Overreliance on technology**: Sofia's heavy use of technology has made her a potential target for cyber attacks.\n2. **Emotional attachment**: Sofia's emotional attachment to her cover identity and the people around her makes her vulnerable to manipulation and compromise.\n3. **Past trauma**: Sofia's troubled past has left her with a fear of being caught and a deep-seated need for control, which could compromise her judgment and decision-making.\n\n**CONCLUSION**\n\nNightingale-22 is a highly skilled and valuable asset to Project Nightingale. However, her vulnerabilities must be carefully managed to prevent compromise. It is essential to continue monitoring Sofia's activities and providing her with the necessary support and resources to maintain her cover identity and gather sensitive information.\n\n**RECOMMENDATIONS**\n\n1. **Continued psychological evaluations**: Regular OPI and PER assessments should be conducted to monitor Sofia's emotional state and identify potential vulnerabilities.\n2. **Enhanced security protocols**: Sofia's overreliance on technology must be mitigated through the implementation of enhanced security protocols and the use of secure communication channels.\n3. **Emotional support**: Sofia's emotional attachment to her cover identity and the people around her must be addressed through the provision of emotional support and counseling.\n4. **Regular debriefings**: Regular debriefings should be conducted to monitor Sofia's performance and provide her with feedback and guidance.\n\n**ACTION ITEMS**\n\n1. **Schedule regular psychological evaluations**: Schedule OPI and PER assessments with Sofia on a regular basis to monitor her emotional state and identify potential vulnerabilities.\n2. **Implement enhanced security protocols**: Develop and implement enhanced security protocols to mitigate Sofia's overreliance on technology.\n3. **Provide emotional support**: Provide Sofia with emotional support and counseling to address her emotional attachment to her cover identity and the people around her.\n4. **Conduct regular debriefings**: Conduct regular debriefings with Sofia to monitor her performance and provide her with feedback and guidance.\n\n**CLASSIFICATION CHANGE**\n\nThis dossier has been classified as Eyes Only due to the sensitive nature of the information contained within. This classification will be reviewed and updated accordingly.\n\n**AUTHORIZATION**\n\nThis dossier has been authorized for release by the Project Nightingale Director.\n\n**SIGNATURE**\n\n[Your Name]\nTechnical Operations Division\nProject Nightingale\n2021-02-01", "metadata": {"document_creation_date": "2020-04-26", "authoring_agent_id": "Shadow-12", "originating_division": "Technical Operations", "classification_level": "Eyes Only", "event_date": "2021-01-28", "mission_priority": 5}}
{"id": "doc_00000034", "type": "Field Contact Report", "content": "**Field Contact Report**\n\n**Document ID:** FC-2020-03-17\n**Date:** 2020-03-17\n**Document Creation Date:** 2023-05-15\n**Target Entity:** East Germany\n**Classification Level:** Top Secret\n**Mission Priority:** 4\n**Originating Division:** Covert Operations\n\n**Summary:** This report details an encounter with an East German asset, codenamed \"Falken\" (Eagle), who provided information on the East German Ministry of State Security's (Stasi) surveillance operations in Berlin. The meeting occurred on 2020-03-17, and this report summarizes the key takeaways.\n\n**Event Overview:** Falken, a 35-year-old East German national and Stasi informant, made contact with our agent, Nightingale-2, at a pre-arranged safe house in East Berlin (coordinates: 52.5200\u00b0 N, 13.4050\u00b0 E). Falken arrived at 14:00 hours and remained for approximately 45 minutes. The meeting was conducted in a secure environment, with all necessary protocols in place.\n\n**Key Information:**\n\n1.  **Surveillance Operations:** Falken confirmed the Stasi's increased surveillance efforts in Berlin, focusing on high-priority targets, including Western diplomats and suspected dissidents. He revealed that the Stasi has established an additional surveillance unit, \"Alpha-12,\" tasked with monitoring key locations and individuals.\n2.  **Technological Advancements:** Falken mentioned the Stasi's recent adoption of advanced surveillance technology, including digital recording devices and satellite imaging capabilities. He believes these tools will significantly enhance the Stasi's ability to gather and analyze intelligence.\n3.  **Counter-Surveillance Measures:** Falken discussed the Stasi's counter-surveillance measures, which include monitoring of suspected opposition groups and individuals, as well as the use of undercover agents to gather intelligence on potential threats.\n4.  **Current Security Situation:** Falken assessed the current security situation in East Germany as \"highly sensitive,\" with the Stasi maintaining a tight grip on the population. He believes that any perceived dissent or resistance will be swiftly suppressed.\n\n**Additional Notes:**\n\n* Falken expressed concern about the Stasi's increasing reliance on informants and the potential for internal conflicts within the organization.\n* He provided a detailed description of the Stasi's organizational structure, including the hierarchy and key personnel.\n* Falken offered to provide further information on the Stasi's operations in exchange for additional support and compensation.\n\n**Action Items:**\n\n1.  **Verify Information:** Conduct further verification of Falken's claims through additional sources and assets.\n2.  **Assess Risk:** Evaluate the potential risks associated with Falken's continued involvement and the implications for our operations in East Germany.\n3.  **Develop Strategy:** Develop a strategy to exploit Falken's information and leverage his position within the Stasi to further our objectives.\n\n**Recommendations:**\n\n1.  **Continued Support:** Provide ongoing support and compensation to Falken to maintain his cooperation and ensure the continued flow of valuable intelligence.\n2.  **Enhanced Security Measures:** Implement enhanced security measures to protect Falken and our operations from potential Stasi counter-surveillance efforts.\n\n**Signing Off:** Nightingale-2\n\n**Classification Level:** Top Secret\n\n**Distribution:** Covert Operations Division, Research & Analysis Division, Counter-Espionage Division\n\n**Document Control:** Document Control System DCS-9\n\n**Document Archive:** Central Personnel Archive\n\n**Document ID:** FC-2020-03-17\n\n**Document Creation Date:** 2023-05-15", "metadata": {"event_date": "2020-03-17", "document_creation_date": "2023-05-15", "authoring_agent_id": "Ghost-1", "target_entity": "East Germany", "classification_level": "Top Secret", "mission_priority": 4, "originating_division": "Covert Operations"}}
{"id": "doc_00000035", "type": "Operational Debriefing", "content": "**CLASSIFIED DOCUMENT**\n\n**PROJECT NIGHTINGALE**\n**OPERATIONAL DEBRIEFING**\n**MISSION DESIGNATION:** NIGHTINGALE-14-23\n**DOCUMENT CREATION DATE:** 2020-04-15\n**MISSION PRIORITY:** 4\n**ORIGINATING DIVISION:** COVERT OPERATIONS\n**CLASSIFICATION LEVEL:** TOP SECRET\n**EVENT DATE:** 2023-08-13\n**TARGET ENTITY:** CZECHOSLOVAKIA\n\n**SUMMARY:**\n\nNightingale-14-23, codenamed \"Operation Blackbird,\" aimed to infiltrate the Czechoslovakia Ministry of Defense's (MoD) Central Research Institute (V\u00daZ). The operation involved the recruitment of a high-clearance asset, codenamed \"Nightshade-7,\" and the exchange of sensitive technical information. This debriefing provides a detailed analysis of the mission's technical aspects, highlighting key challenges, successes, and lessons learned.\n\n**OBJECTIVES:**\n\n1. Infiltrate the V\u00daZ through Nightshade-7, a Czechoslovakia citizen with access to high-clearance areas.\n2. Obtain sensitive technical information on the Czechoslovakia MoD's current research and development projects.\n3. Establish a secure communication channel for future operations.\n\n**EXECUTION:**\n\nThe operation commenced on 2023-08-05 with Nightshade-7's recruitment. Covert Operations Division (COD) analysts conducted a thorough background check, utilizing the **Operational Personality Inventory (OPI)** and **Background Investigation Synopsis (BIS)** to assess Nightshade-7's reliability and vulnerability to compromise.\n\n**TECHNICAL SPECIFICATIONS:**\n\n* **Communication Protocol:** Nightingale Communications Protocol (NCP-60) was implemented to ensure secure communication between Nightshade-7 and the COD handlers.\n* **Dead Drop:** A secure dead drop location was established in Prague, using a **Type-III Dead Drop Container** to exchange sensitive materials.\n* **Encryption:** The **AES-256-GCM** encryption standard was used to protect exchanged data.\n\n**ANALYTICAL METHODS:**\n\n* **Signal Analysis:** COD analysts conducted signal analysis using the **Spectra-4000** signal processing software to monitor and decode communication signals exchanged between Nightshade-7 and the COD handlers.\n* **Network Analysis:** Network analysis was performed using the **Graph-Net** software to visualize the relationships between the V\u00daZ's research projects and identify potential vulnerabilities.\n\n**CHALLENGES ENCOUNTERED:**\n\n1. **Hostile Surveillance:** COD detected potential hostile surveillance on Nightshade-7, prompting the implementation of **surveillance countermeasures** to ensure the agent's safety.\n2. **Technical Issues:** A communication equipment failure on 2023-08-10 required rapid repair and replacement to maintain the operation's momentum.\n3. **Vulnerability Assessment:** COD analysts identified potential vulnerabilities in the V\u00daZ's security protocols, which were mitigated through the implementation of additional security measures.\n\n**IMMEDIATE RESULTS:**\n\n1. **Successful Recruitment:** Nightshade-7 was successfully recruited and provided sensitive technical information on the Czechoslovakia MoD's current research and development projects.\n2. **Established Communication Channel:** A secure communication channel was established between Nightshade-7 and the COD handlers, enabling future operations.\n3. **Identified Vulnerabilities:** COD analysts identified potential vulnerabilities in the V\u00daZ's security protocols, which were mitigated through the implementation of additional security measures.\n\n**LESSONS LEARNED:**\n\n1. **Importance of Surveillance Countermeasures:** The implementation of surveillance countermeasures ensured the safety of Nightshade-7 and maintained the operation's momentum.\n2. **Technical Equipment Reliability:** The rapid repair and replacement of communication equipment ensured the operation's continuity.\n3. **Vulnerability Assessment:** Regular vulnerability assessments are essential to identifying and mitigating potential security risks.\n\n**CONCLUSION:**\n\nOperation Blackbird successfully infiltrated the Czechoslovakia Ministry of Defense's Central Research Institute and obtained sensitive technical information. The operation highlights the importance of technical specifications, analytical methods, and vulnerability assessment in ensuring the success of covert operations. COD analysts will continue to refine their techniques and procedures to maintain the operational security and integrity of future missions.\n\n**RECOMMENDATIONS:**\n\n1. **Continued Surveillance:** Maintain surveillance on Nightshade-7 to ensure the agent's safety and prevent potential compromise.\n2. **Technical Equipment Maintenance:** Regularly inspect and maintain communication equipment to prevent technical issues.\n3. **Vulnerability Assessment:** Conduct regular vulnerability assessments to identify and mitigate potential security risks.\n\n**CLASSIFICATION:**\n\nThis document is classified TOP SECRET and is intended for the eyes of authorized personnel only. Distribution is restricted to the Covert Operations Division and authorized personnel.\n\n**DESTRUCTION NOTICE:**\n\nThis document is to be destroyed by incineration after reading. Electronic copies are to be deleted and wiped from all systems.\n\n**VERIFICATION:**\n\nThis document has been verified by the following personnel:\n\n* **Nightshade-7:** Asset handler\n* **Codename-9:** COD analyst\n* **Echo-5:** COD technical operations specialist\n\n**AUTHENTICATION:**\n\nThis document has been authenticated by the following personnel:\n\n* **Nightingale-7:** COD station chief\n* **Specter-3:** COD operations manager\n\n**DATE:** 2023-09-15\n\n**AUTHENTICATION CODE:** NIGHTINGALE-14-23-EC\n\n**Verification and authentication codes are encrypted and stored separately.**", "metadata": {"document_creation_date": "2020-04-15", "authoring_agent_id": "Viper-6", "mission_priority": 4, "originating_division": "Covert Operations", "classification_level": "Top Secret", "event_date": "2023-08-13", "target_entity": "Czechoslovakia"}}
{"id": "doc_00000036", "type": "Strategic Intelligence Brief", "content": "**STRATEGIC INTELLIGENCE BRIEF**\n\n**CLASSIFICATION:** Top Secret\n**ORIGINATING DIVISION:** Covert Operations\n**DOCUMENT CREATION DATE:** 2023-02-22\n**TARGET ENTITY:** Czechoslovakia\n**MISSION PRIORITY:** 2\n**EVENT DATE:** 2024-04-15\n\n**SUBJECT:** Czechoslovakian Military Modernization and Its Implications for Regional Stability\n\nAs we mark the 55th anniversary of the Prague Spring, our intelligence suggests that Czechoslovakia's military modernization efforts are gaining momentum, posing significant implications for regional stability and NATO's eastern flank. This brief will delve into the details of these developments, analyzing their long-term capabilities, geopolitical implications, and potential future threats.\n\n**CZECHOSLOVAKIAN MILITARY MODERNIZATION: A GROWING THREAT**\n\nSince the Prague Spring of 1968, Czechoslovakia has been a critical component of the Warsaw Pact's military strategy. The country's geographical location, situated between West Germany and Poland, makes it an essential link in the Soviet Union's military supply chain. Our sources indicate that Czechoslovakia has been investing heavily in modernizing its military capabilities, with a focus on enhancing its air defense and anti-tank capabilities.\n\n**AIR DEFENSE UPGRADES**\n\nCzechoslovakia has been upgrading its air defense systems, integrating advanced radar and missile technologies from the Soviet Union. Our SIGINT intercepts suggest that Czechoslovakia has acquired the S-300VM Antey-2500 missile system, which boasts a range of over 250 kilometers and can engage targets at altitudes of up to 30 kilometers. This significant upgrade will significantly enhance Czechoslovakia's ability to protect its airspace and counter NATO's air superiority.\n\n**ANTI-TANK CAPABILITIES**\n\nCzechoslovakia has also been modernizing its anti-tank capabilities, incorporating advanced missile systems and armor-piercing rounds. Our sources indicate that Czechoslovakia has acquired the 9M119 Svir missile system, which can engage targets at ranges of up to 4 kilometers and has a high probability of penetrating modern armor. This upgrade will significantly enhance Czechoslovakia's ability to counter NATO's armored forces.\n\n**REGIONAL IMPLICATIONS**\n\nThe modernization of Czechoslovakia's military capabilities poses significant implications for regional stability and NATO's eastern flank. Our analysis suggests that Czechoslovakia's upgraded air defense and anti-tank capabilities will create a more formidable military presence, potentially altering the balance of power in the region. This development may prompt a response from NATO, potentially leading to increased military deployments and a heightened state of alert.\n\n**GEOPOLITICAL IMPLICATIONS**\n\nThe modernization of Czechoslovakia's military capabilities also has significant geopolitical implications. Our sources indicate that Czechoslovakia's military modernization is closely tied to the Soviet Union's military strategy, suggesting that the Soviet Union remains committed to its military presence in Eastern Europe. This development may prompt a re-evaluation of NATO's policy towards the Soviet Union, potentially leading to increased tensions and a heightened state of alert.\n\n**FUTURE THREATS**\n\nOur analysis suggests that Czechoslovakia's military modernization will create a more formidable military presence, potentially leading to increased tensions and a heightened state of alert in the region. This development may prompt a response from NATO, potentially leading to increased military deployments and a heightened state of alert. Our sources indicate that Czechoslovakia may also consider acquiring advanced military technology from other Warsaw Pact nations, potentially creating a more robust military presence in the region.\n\n**RECOMMENDATIONS**\n\nIn light of these developments, we recommend that NATO take a more proactive approach to countering Czechoslovakia's military modernization efforts. This may include increased military deployments, enhanced air defense capabilities, and a heightened state of alert. We also recommend that NATO engage in diplomatic efforts to address the geopolitical implications of Czechoslovakia's military modernization, potentially leading to a reduction in tensions and a more stable regional environment.\n\n**CONCLUSION**\n\nIn conclusion, Czechoslovakia's military modernization efforts pose significant implications for regional stability and NATO's eastern flank. Our analysis suggests that Czechoslovakia's upgraded air defense and anti-tank capabilities will create a more formidable military presence, potentially altering the balance of power in the region. We recommend that NATO take a more proactive approach to countering Czechoslovakia's military modernization efforts, potentially leading to a reduction in tensions and a more stable regional environment.\n\n**CLASSIFICATION REMINDER**\n\nThis document is classified Top Secret and should not be shared with anyone without proper clearance.\n\n**AUTHENTICATION**\n\nThis document has been authenticated by the Covert Operations Division and is a true and accurate representation of the intelligence available.\n\n**DISTRIBUTION**\n\nThis document is distributed to:\n\n* NATO Commanders\n* Allied Intelligence Services\n* Senior Government Officials\n\n**RETENTION**\n\nThis document will be retained in the Nightingale Historical Record for a period of 20 years.\n\n**DESTRUCTION**\n\nThis document will be destroyed by incineration after 20 years.\n\n**ACKNOWLEDGMENT**\n\nThis document has been read and acknowledged by:\n\n* [Name]\n* [Rank]\n* [Unit]\n\n**DATE**\n\n2024-04-15\n\n**AUTHENTICATION CODE**\n\nNIGHTINGALE-007", "metadata": {"document_creation_date": "2023-02-22", "originating_division": "Covert Operations", "classification_level": "Top Secret", "target_entity": "Czechoslovakia", "event_date": "2024-04-15", "authoring_agent_id": "Raven-9", "mission_priority": 2}}
{"id": "doc_00000037", "type": "Field Contact Report", "content": "**CLASSIFIED DOCUMENT**\n\n**PROJECT NIGHTINGALE**\n\n**FIELD CONTACT REPORT**\n\n**REPORT NUMBER:** COOP-001\n\n**EVENT DATE:** 2024-06-26\n\n**DOCUMENT CREATION DATE:** 2023-01-20\n\n**CLASSIFICATION LEVEL:** TOP SECRET\n\n**MISSION PRIORITY:** 2\n\n**ORIGINATING DIVISION:** COVERT OPERATIONS\n\n**SUBJECT:** Comparative Analysis of Soviet Intelligence Gathering Techniques\n\n**SUMMARY:**\n\nThis report details a 2024-06-26 encounter with a Soviet asset in East Berlin, highlighting the employment of advanced intelligence gathering tactics. A comparative analysis with similar cases (Operation Amber Fox, Dresden Network Collapse) is provided, emphasizing unique features and differences.\n\n**FIELD REPORT:**\n\nOn 2024-06-26, a Covert Operations team conducted a surveillance operation in East Berlin, observing a suspected Soviet asset (codename: NIGHTINGALE-14). The asset's behavior and equipment usage suggest a sophisticated intelligence gathering strategy, likely related to the Soviet Union's efforts to acquire Western technological advancements.\n\n**COMPARATIVE ANALYSIS:**\n\nThe observed tactics are reminiscent of those employed in Operation Amber Fox (1965), where Soviet assets used advanced dead drop techniques to exchange information with Eastern Bloc operatives. However, NIGHTINGALE-14's methods differ in several key aspects:\n\n1.  **Encryption**: NIGHTINGALE-14 utilized a custom-built encryption device, whereas Operation Amber Fox assets relied on commercial-grade encryption methods. This indicates a more advanced level of technical expertise and potential access to classified resources.\n2.  **Dead Drop Concealment**: NIGHTINGALE-14 employed a novel concealment technique, utilizing a hidden compartment within a public restroom. In contrast, Operation Amber Fox assets typically used pre-arranged hiding spots or hidden compartments in public spaces.\n3.  **Surveillance Detection**: NIGHTINGALE-14 demonstrated exceptional counter-surveillance skills, adapting to the Covert Operations team's presence and adjusting tactics to avoid detection. This level of awareness is unprecedented in similar cases, suggesting a higher degree of training or access to classified information.\n\n**ANALYTICAL INSIGHTS:**\n\nThe observed tactics and equipment usage indicate a significant escalation in Soviet intelligence gathering capabilities. The employment of advanced encryption and concealment techniques highlights the Soviet Union's commitment to maintaining a competitive edge in espionage.\n\nIn comparison to the Dresden Network Collapse (1971), NIGHTINGALE-14's methods demonstrate a more sophisticated and adaptive approach, underscoring the evolution of Soviet intelligence gathering strategies.\n\n**RECOMMENDATIONS:**\n\n1.  **Enhanced Counter-Surveillance Measures**: Covert Operations teams should adopt more sophisticated counter-surveillance techniques to detect and counter NIGHTINGALE-14's advanced methods.\n2.  **Technical Expertise Evaluation**: A thorough evaluation of Soviet technical capabilities is necessary to understand the extent of their encryption and concealment expertise.\n3.  **Asset Recruitment and Handling**: A re-evaluation of asset recruitment and handling procedures is required to ensure that Covert Operations teams can adapt to the evolving landscape of Soviet intelligence gathering tactics.\n\n**CONFIDENTIALITY:**\n\nThis report is classified TOP SECRET and shall be disseminated only to authorized personnel with a need-to-know clearance. Distribution shall be restricted to", "metadata": {"event_date": "2024-06-26", "document_creation_date": "2023-01-20", "authoring_agent_id": "Orion-5", "target_entity": "Soviet Union", "classification_level": "Top Secret", "mission_priority": 2, "originating_division": "Covert Operations"}}
{"id": "doc_00000038", "type": "Agent Profile Dossier", "content": "**AGENT PROFILE DOSSIER**\n\n**CLASSIFICATION LEVEL:** Top Secret\n**DOCUMENT CREATION DATE:** 2021-11-03\n**ORIGINATING DIVISION:** Technical Operations\n**EVENT DATE:** 2024-10-05\n**MISSION PRIORITY:** 2\n\n**AGENT CODE NAME:** Nightingale-22\n**REAL NAME:** Alexandra Petrova\n**D.O.B.:** 1985-02-14\n**CITIZENSHIP:** Russian\n**OCCUPATION:** Former KGB Linguist\n\n**RECRUITMENT HISTORY:**\n\nNightingale-22 was recruited through a complex scheme involving a compromised KGB officer, codenamed Raven-11. Initially, our asset was embedded within the KGB's Cryptography Division, where she gained expertise in Russian encryption techniques. Our penetration efforts began in 2015, with Raven-11 introducing Nightingale-22 to our Technical Operations Division.\n\n**OPERATIONAL ASSIGNMENTS:**\n\nNightingale-22 has been assigned to several high-priority missions, including:\n\n1. **Operation Aurora**: Infiltrating a Russian cybercrime organization to gather intel on their encryption methods.\n2. **Project Whisper**: Disrupting a KGB-backed money laundering operation in Eastern Europe.\n3. **Operation Storm**: Gathering intel on a potential KGB mole within our organization.\n\n**PSYCHOLOGICAL ASSESSMENTS:**\n\nNightingale-22 has undergone multiple psychological evaluations, revealing a complex personality profile. She exhibits high levels of intelligence, strategic thinking, and emotional control. However, she also displays signs of anxiety and paranoia, particularly when dealing with high-stakes operations.\n\n**PERFORMANCE EVALUATIONS:**\n\nNightingale-22 has consistently demonstrated exceptional performance in her missions, showcasing a strong ability to think on her feet and adapt to changing circumstances. Her language skills and cultural knowledge have proven invaluable in her operations.\n\n**PERSONAL BACKGROUND:**\n\nNightingale-22's personal background is shrouded in mystery. Her family history is unclear, and she has few connections outside of the KGB. This lack of personal relationships may contribute to her vulnerability to emotional manipulation.\n\n**POTENTIAL VULNERABILITIES:**\n\n1. **Emotional Manipulation**: Nightingale-22's anxiety and paranoia may make her susceptible to emotional manipulation, potentially compromising her loyalty to our organization.\n2. **KGB Retaliation**: As a former KGB officer, Nightingale-22 may be susceptible to KGB retaliation, particularly if she is discovered to be working with us.\n3. **Personal Connections**: Nightingale-22's lack of personal connections outside of the KGB may make her more vulnerable to exploitation or coercion.\n\n**INVESTIGATIVE QUESTIONS:**\n\n1. How can we mitigate the risks associated with Nightingale-22's emotional vulnerabilities?\n2. What measures can be taken to safeguard her identity and protect her from potential KGB retaliation?\n3. Can we establish a secure network of personal connections for Nightingale-22 to reduce her dependence on our organization?\n\n**CONCLUSION:**\n\nNightingale-22 remains a valuable asset to our organization, with her expertise and skills making her an indispensable resource in high-stakes operations. However, her vulnerabilities must be carefully managed to ensure her continued effectiveness and safety. Further investigation and mitigation efforts are required to address these risks and protect our asset.\n\n**RECOMMENDATIONS:**\n\n1. Establish a secure network of personal connections for Nightingale-22.\n2. Develop a risk management plan to address her emotional vulnerabilities.\n3. Conduct regular psychological evaluations to monitor her mental state and adjust our approach as needed.\n\n**CLASSIFICATION LEVEL:** Top Secret\n\n**DOCUMENT CONTROL SYSTEM (DCS-9) LOG:** This document will be stored in the Central Personnel Archive, accessible only to authorized personnel with Top Secret clearance.\n\n**DATE:** 2024-10-05", "metadata": {"document_creation_date": "2021-11-03", "authoring_agent_id": "Ghost-1", "originating_division": "Technical Operations", "classification_level": "Top Secret", "event_date": "2024-10-05", "mission_priority": 2}}
{"id": "doc_00000039", "type": "Field Contact Report", "content": "**CLASSIFIED DOCUMENT**\n\n**PROJECT NIGHTINGALE**\n\n**FIELD CONTACT REPORT**\n\n**SUBJECT:** Encounter with East German Asset\n\n**DATE:** 2024-04-27\n\n**CREATED:** 2023-04-14\n\n**CLASSIFICATION:** Top Secret\n\n**MISSION PRIORITY:** 5\n\n**ORIGINATING DIVISION:** Signals Intelligence\n\n**SUBJECT CODE NAME:** Nightingale-17\n\n**OPERATIONAL SUMMARY:**\n\nThis field contact report provides an overview of a recent encounter with an East German asset, detailing the initial intelligence gathered and assessing potential security risks.\n\n**EVENT DETAILS:**\n\nOn 2024-04-27, at 09:45 hours local time, Signal Intelligence (SIGINT) personnel from Nightingale Station-3, Berlin, made contact with Nightingale-17, a known East German asset. The meeting took place at the agreed-upon dead drop site, a pre-arranged location in the Tiergarten district.\n\n**ASSET IDENTIFICATION:**\n\nNightingale-17, code-named \"Wolf,\" is a 35-year-old East German citizen with expertise in industrial espionage. Previous interactions indicate a reliable source with access to high-clearance information. Wolf's current status is classified as \"high-risk\" due to potential exposure to KGB handlers.\n\n**ENCOUNTER SUMMARY:**\n\nThe SIGINT team, consisting of Nightingale-12 (Signals Analyst) and Nightingale-23 (Technical Operations), arrived at the dead drop site and observed Wolf's signal, confirming the agreed-upon meet time. A secure communication channel was established using the Nightingale-12 (N-12) encrypted device. Wolf transmitted the designated asset package, which included detailed information on East German industrial development projects.\n\n**ASSET PACKAGE CONTENTS:**\n\nThe asset package consisted of:\n\n1. **Technical specifications** for a newly developed East German missile system, codenamed \"Project Sturm.\"\n2. **Engineering drawings** for a high-speed rail project, highlighting key components and suppliers.\n3. **Confidential documents** detailing East German participation in Soviet-led energy projects.\n\n**SECURITY ASSESSMENT:**\n\nGiven the sensitive nature of the information provided, it is essential to assess the security risks associated with this encounter. Wolf's reliability remains uncertain due to potential KGB involvement. However, the asset package's content and quality indicate a high level of trustworthiness. Recommendations for further handling and verification will be provided in the subsequent analysis.\n\n**CONTACT DETAILS:**\n\nMeeting duration: 00:45 hours\n\nAsset transmission: 01:20 hours\n\nSecure communication channel established: Yes\n\n**RE", "metadata": {"event_date": "2024-04-27", "document_creation_date": "2023-04-14", "authoring_agent_id": "Phoenix-11", "target_entity": "East Germany", "classification_level": "Top Secret", "mission_priority": 5, "originating_division": "Signals Intelligence"}}
{"id": "doc_00000040", "type": "Operational Debriefing", "content": "**Operational Debriefing: Eyes Only**\n\n**Document Creation Date:** 2023-11-21\n**Mission Priority:** 2\n**Originating Division:** Covert Operations\n**Classification Level:** Eyes Only\n**Event Date:** 2024-12-10\n**Target Entity:** Comecon\n\n**Mission Summary:**\n\nOperation \"Raven's Wing\" aimed to intercept and assess the Comecon's upcoming trade agreement with Cuba. Our primary objective was to obtain detailed information on the economic ties between the two nations, including potential resource sharing and strategic partnerships. The mission required the utilization of advanced surveillance techniques, secure communication protocols, and precise data analysis.\n\n**Pre-Mission Planning:**\n\n1.  **Target Analysis:** Conducted thorough research on Comecon's economic structure, identifying key decision-makers and influential stakeholders. Utilized OSINT from reputable sources, including the Economist Intelligence Unit and the International Monetary Fund.\n2.  **Surveillance Strategy:** Developed a plan to monitor Comecon's communications and movements, employing a combination of satellite imagery, wiretapping, and human intelligence.\n3.  **Secure Communication:** Established a secure communication link using the Nightingale-encrypted protocol (NCP-60). This ensured the safe transmission of sensitive information between team members.\n4.  **Team Composition:** Assembled a team of experts, including a cryptanalyst, a surveillance specialist, and a data analyst. Each team member was thoroughly briefed on the mission objectives and protocols.\n\n**Mission Execution:**\n\n1.  **Surveillance Operations:** Conducted 24/7 surveillance on Comecon's key facilities, utilizing advanced optics and sensors to gather visual and acoustic data.\n2.  **Communication Intercepts:** Intercepted and analyzed Comecon's encrypted communications, employing advanced cryptanalysis techniques to decode sensitive information.\n3.  **Human Intelligence:** Utilized a deep-cover asset within Comecon to gather insider information on the trade agreement, including potential clauses and economic implications.\n4.  **Data Analysis:** Processed and analyzed the collected data, employing statistical models and machine learning algorithms to identify patterns and trends.\n\n**Challenges Encountered:**\n\n1.  **Communication Security:** Experienced difficulties in maintaining secure communication links due to the high volume of data transmission.\n2.  **Surveillance Detection:** Detected the presence of counter-surveillance teams, which required adjustments to our surveillance strategy to avoid detection.\n3.  **Data Overload:** Faced challenges in processing and analyzing the large volume of data collected, which required the development of efficient data management protocols.\n\n**Immediate Results:**\n\n1.  **Trade Agreement Details:** Obtained detailed information on the Comecon-Cuba trade agreement, including potential resource sharing and strategic partnerships.\n2.  **Economic Implications:** Analyzed the economic implications of the trade agreement, including potential market shifts and resource allocation.\n3.  **Security Risks:** Identified potential security risks associated with the trade agreement, including the possibility of compromised encryption protocols.\n\n**Lessons Learned:**\n\n1.  **Secure Communication Protocols:** Developed and implemented new secure communication protocols to ensure the safe transmission of sensitive information.\n2.  **Surveillance Strategy:** Adjusted our surveillance strategy to account for counter-surveillance teams and potential detection.\n3.  **Data Analysis:** Developed efficient data management protocols to process and analyze large volumes of data.\n\n**Conclusion:**\n\nOperation \"Raven's Wing\" successfully intercepted and assessed the Comecon's upcoming trade agreement with Cuba, providing valuable insights into the economic ties between the two nations. The mission demonstrated the effectiveness of advanced surveillance techniques, secure communication protocols, and precise data analysis. However, it also highlighted the importance of adaptability and efficient data management in the face of challenges and complexities.\n\n**Recommendations:**\n\n1.  **Further Analysis:** Conduct further analysis on the trade agreement, including potential market shifts and resource allocation.\n2.  **Security Enhancements:** Implement security enhancements to protect against potential security risks associated with the trade agreement.\n3.  **Surveillance Strategy:** Continuously monitor and adjust our surveillance strategy to account for counter-surveillance teams and potential detection.\n\n**Classification Level:** Eyes Only\n\n**Distribution:** Covert Operations Division, Research & Analysis Division, Strategic Intelligence Division", "metadata": {"document_creation_date": "2023-11-21", "authoring_agent_id": "Orion-5", "mission_priority": 2, "originating_division": "Covert Operations", "classification_level": "Eyes Only", "event_date": "2024-12-10", "target_entity": "Comecon"}}
{"id": "doc_00000041", "type": "Strategic Intelligence Brief", "content": "**STRATEGIC INTELLIGENCE BRIEF**\n**CLASSIFICATION:** SECRET\n**ORIGINATING DIVISION:** SIGNALS INTELLIGENCE\n**DOCUMENT CREATION DATE:** 2020-01-19\n**MISSION PRIORITY:** 5\n**TARGET ENTITY:** EAST GERMANY\n**EVENT DATE:** 2021-01-16\n\n**INTRODUCTION**\n\nAs the Berlin Wall's 30th anniversary looms, East Germany's (GDR) economic and strategic landscape continues to evolve. Recent signals intelligence (SIGINT) intercepts suggest a complex interplay between GDR's communist government and the Soviet Union's (USSR) waning influence. This Strategic Intelligence Brief provides a comprehensive analysis of GDR's current situation, potential future threats, and implications for Western nations.\n\n**GDR'S ECONOMIC CHALLENGES**\n\nGDR's economic woes persist, with declining industrial production and rising unemployment. SIGINT intercepts reveal a significant increase in GDR's reliance on Soviet aid, which, while necessary, also raises concerns about GDR's economic sovereignty. Recent reports from HUMINT sources indicate a growing discontent among GDR's population, with many questioning the regime's ability to provide basic necessities.\n\n**SIGNALS INTELLIGENCE ASSESSMENT**\n\nOur SIGINT intercepts have detected increased communication between GDR's military and Soviet officials, hinting at a possible reorientation of GDR's military doctrine to align with the Soviet Union's declining military capabilities. Moreover, SIGINT activity around GDR's border with Poland suggests potential clandestine operations to counterbalance Soviet influence.\n\n**HUMAN INTELLIGENCE INPUT**\n\nHUMINT sources within GDR's government and military indicate a growing rift between hardline communist officials and reform-minded individuals. These sources also suggest that GDR's military is facing significant equipment shortages and morale issues, which could compromise its ability to respond effectively to potential threats.\n\n**OPEN-SOURCE INTELLIGENCE ANALYSIS**\n\nOSINT analysis of GDR's propaganda efforts reveals a shift towards more nationalist rhetoric, emphasizing GDR's unique identity and rejecting Soviet influence. This trend suggests that GDR's leaders may be attempting to consolidate power and legitimacy by distancing themselves from the Soviet Union.\n\n**GEOPOLITICAL IMPLICATIONS**\n\nGDR's economic and military challenges, combined with its growing nationalist sentiment, create a volatile environment. The potential for GDR to become increasingly independent from the Soviet Union or even seek closer ties with Western nations cannot be ruled out. This development would have significant implications for European security and NATO's overall strategy.\n\n**POTENTIAL FUTURE THREATS**\n\nIn the short term, GDR's economic instability and military equipment shortages pose a significant threat to regional stability. In the long term, GDR's potential for increased independence or alignment with Western nations could lead to a more complex security environment in Europe.\n\n**RECOMMENDATIONS**\n\nIn light of this analysis, we recommend that Western nations:\n\n1. Monitor GDR's economic situation closely, considering potential aid or investment opportunities to stabilize the economy.\n2. Engage in diplomatic efforts to encourage GDR's reform-minded individuals and promote a more collaborative relationship with the West.\n3. Enhance SIGINT and HUMINT capabilities to better understand GDR's military doctrine and potential clandestine operations.\n\n**CONCLUSION**\n\nGDR's current situation presents a complex and dynamic environment, with both short-term and long-term implications for regional stability. This Strategic Intelligence Brief provides a comprehensive analysis of GDR's economic, military, and geopolitical challenges, highlighting potential future threats and opportunities. By understanding these factors, Western nations can develop an informed strategy to address the evolving security landscape in Europe.\n\n**AUTHENTICATION**\n\nThis document has been authenticated by the Signals Intelligence Division. All sources and methods have been properly protected and anonymized.\n\n**DISTRIBUTION**\n\nThis Strategic Intelligence Brief is classified SECRET and is intended for the eyes of authorized personnel only. Distribution is restricted to senior officials within Western governments and NATO command structures.\n\n**REVISION HISTORY**\n\nThis document supersedes all previous versions. Any revisions will be clearly marked and dated.\n\n**AUTHORIZATION**\n\nThis document has been authorized for release by the Director of Signals Intelligence.", "metadata": {"document_creation_date": "2020-01-19", "originating_division": "Signals Intelligence", "classification_level": "Secret", "target_entity": "East Germany", "event_date": "2021-01-16", "authoring_agent_id": "Shadow-12", "mission_priority": 5}}
{"id": "doc_00000042", "type": "Field Contact Report", "content": "**Field Contact Report**\n\n**ID:** SI-2021-10-20-001\n**Event Date:** 2021-10-20\n**Document Creation Date:** 2023-03-21\n**Classification Level:** Confidential\n**Mission Priority:** 4\n**Originating Division:** Signals Intelligence\n\n**Summary:**\n\nThis report details a comparative analysis of asset encounters in Warsaw Pact territories, highlighting unique features and differences. On 2021-10-20, Signals Intelligence Division encountered an asset (Designation: W-12) in a Warsaw Pact-controlled area. This report compares and contrasts W-12's behavior and intelligence content with similar cases, providing actionable insights for future operations.\n\n**Event Details:**\n\nOn 2021-10-20, W-12 met with a Signals Intelligence asset handler at a pre-arranged location in Warsaw, Poland. The handler reported W-12's behavior as follows:\n\n*   W-12 demonstrated increased caution, utilizing a previously unknown dead drop location.\n*   W-12 provided intelligence on Warsaw Pact military exercises, indicating a heightened sense of awareness regarding NATO operations.\n*   W-12 expressed concerns about potential counterintelligence measures targeting Warsaw Pact assets.\n\n**Comparative Analysis:**\n\nComparison with Case SI-2020-06-15-001 (W-5) reveals similarities in W-12's behavior, including increased caution and intelligence on Warsaw Pact military exercises. However, W-12's expressed concerns about counterintelligence measures differ from W-5's focus on NATO operations.\n\nComparison with Case SI-2019-03-22-002 (W-9) highlights differences in W-12's intelligence content, which focuses on Warsaw Pact military exercises, whereas W-9 provided intelligence on Soviet nuclear doctrine.\n\n**Actionable Insights:**\n\n1.  **Adjust Dead Drop Locations:** Update dead drop locations to ensure maximum security and minimize potential counterintelligence risks.\n2.  **Enhance Training:** Provide training to assets on counterintelligence measures and potential risks associated with Warsaw Pact operations.\n3.  **Intelligence Prioritization:** Prioritize intelligence gathering on Warsaw Pact military exercises and potential counterintelligence measures.\n\n**Recommendations:**\n\n1.  **Continued Monitoring:** Monitor W-12's behavior and intelligence content to ensure maximum security and gather actionable insights.\n2.", "metadata": {"event_date": "2021-10-20", "document_creation_date": "2023-03-21", "authoring_agent_id": "Phoenix-11", "target_entity": "Warsaw Pact", "classification_level": "Confidential", "mission_priority": 4, "originating_division": "Signals Intelligence"}}
{"id": "doc_00000043", "type": "Agent Profile Dossier", "content": "**CLASSIFIED DOCUMENT**\n\n**AGENT PROFILE DOSSIER**\n\n**PROJECT NIGHTINGALE**\n\n**DOSSIER CREATED:** 2020-11-13\n**ORIGINATING DIVISION:** COVERT OPERATIONS\n**CLASSIFICATION LEVEL:** TOP SECRET\n**EVENT DATE:** 2022-05-06\n**MISSION PRIORITY:** 3\n\n**SUBJECT:** NIGHTINGALE-14 ( codename: _Apex_)\n\n**SUMMARY:**\n\nNightingale-14, codename _Apex_, is a seasoned operative recruited in 2018 from a high-risk, high-reward environment. This dossier provides a comprehensive analysis of _Apex_'s recruitment history, operational assignments, psychological assessments, performance evaluations, personal background, and potential vulnerabilities.\n\n**RECRUITMENT HISTORY:**\n\n_Apex_ was identified through a network of high-level connections in the Eastern European underworld. Initial contact was established in 2018, with the operative expressing interest in cooperating with Project Nightingale. Following a thorough vetting process, _Apex_ was officially recruited in 2019, demonstrating exceptional adaptability and resourcefulness.\n\n**OPERATIONAL ASSIGNMENTS:**\n\n_Apex_ has participated in four high-stakes operations, showcasing exceptional skill and discretion:\n\n1.  **Operation Shadowplay** (2020): Infiltrated a high-security facility in Moscow, gathering critical intel on the Kremlin's inner workings.\n2.  **Operation Nightshade** (2020): Successfully extracted a high-value asset from a heavily fortified location in Eastern Europe.\n3.  **Operation Ember** (2021): Conducted a series of high-risk surveillance operations in the Balkans, gathering intelligence on emerging terrorist networks.\n4.  **Operation Stormsurge** (2022): Led a team of operatives in a daring heist, stealing classified materials from a high-security facility in Western Europe.\n\n**PSYCHOLOGICAL ASSESSMENTS:**\n\n_Apex_ has undergone multiple psychological assessments, revealing:\n\n1.  **Operational Personality Inventory (OPI)**: Demonstrated exceptional adaptability, resourcefulness, and strategic thinking.\n2.  **Polygraph Examination Report**: Showed no signs of deception or manipulation.\n3.  **Background Investigation Summary**: Revealed a complex, high-stress childhood, contributing to an exceptional ability to navigate challenging environments.\n\n**PERFORMANCE EVALUATIONS:**\n\n_Apex_ has consistently demonstrated exceptional performance, earning:\n\n1.  **Case Officer Evaluation**: Scored 95/100 for exceptional skill, discretion, and results-driven approach.\n2.  **Mission Execution Report**: Consistently exceeded expectations, with a 100% success rate in high-stakes operations.\n\n**PERSONAL BACKGROUND:**\n\n_Apex_ has a complex, high-risk background, including:\n\n1.  **Early Life**: Grew up in a high-crime neighborhood, developing exceptional survival skills and adaptability.\n2.  **Education**: Completed a degree in International Relations, highlighting exceptional strategic thinking and analytical abilities.\n3.  **Personal Relationships**: Maintains a complex network of high-level connections, including former intelligence operatives and high-stakes entrepreneurs.\n\n**POTENTIAL VULNERABILITIES:**\n\n_Apex_ has demonstrated exceptional resilience and adaptability, but potential vulnerabilities include:\n\n1.  **Overexposure**: May be at risk of burnout due to excessive exposure to high-stakes operations.\n2.  **Lack of Emotional Support**: Has difficulty forming close relationships, potentially leading to emotional isolation.\n3.  **Risk-Taking Behavior**: May engage in high-risk behavior, compromising operational security.\n\n**CONCLUSION:**\n\nNightingale-14, codename _Apex_, is a highly skilled and adaptable operative with a complex, high-risk background. While demonstrating exceptional performance and resilience, _Apex_ may be vulnerable to overexposure, emotional isolation, and risk-taking behavior. Further psychological assessments and performance evaluations are recommended to ensure optimal operational effectiveness.\n\n**RECOMMENDATIONS:**\n\n1.  **Regular Psychological Assessments**: Schedule regular OPI and polygraph examinations to monitor _Apex_'s mental state and adaptability.\n2.  **Emotional Support Network**: Establish a secure, confidential network of emotional support personnel to mitigate potential isolation risks.\n3.  **Risk Management Protocols**: Implement strict risk management protocols to minimize the likelihood of high-risk behavior compromising operational security.\n\n**CLASSIFICATION:**\n\nThis dossier is classified TOP SECRET and is only accessible to authorized personnel with a need-to-know clearance.\n\n**DISTRIBUTION:**\n\nThis dossier will be distributed to the following personnel:\n\n1.  **Division Chief, Covert Operations**\n2.  **Senior Case Officer, Nightingale-14**\n3.  **Counterintelligence Division**\n\n**ARCHIVAL:**\n\nThis dossier will be archived in the Central Personnel Archive, accessible through the Document Control System (DCS-9).", "metadata": {"document_creation_date": "2020-11-13", "authoring_agent_id": "Shadow-12", "originating_division": "Covert Operations", "classification_level": "Top Secret", "event_date": "2022-05-06", "mission_priority": 3}}
{"id": "doc_00000044", "type": "Field Contact Report", "content": "**Field Contact Report**\n\n**Document Classification:** Restricted\n**Document Creation Date:** 2024-05-07\n**Event Date:** 2024-02-20\n**Target Entity:** Soviet Union\n**Mission Priority:** 2\n**Originating Division:** Covert Operations\n\n**Summary:**\n\nOn 2024-02-20, Covert Operations Division conducted a high-priority field contact with asset Nightingale-9, a trusted source within the Soviet Union's KGB. The meeting was held at a pre-arranged dead drop site in East Berlin, as per standard protocol. This report provides a summary of the encounter, highlighting key intelligence gathered and security concerns.\n\n**Overview:**\n\nNightingale-9, a 35-year-old KGB officer stationed in East Berlin, provided critical information on the Soviet Union's military modernization efforts. The asset has proven reliable in the past, having successfully infiltrated high-clearance meetings at the Soviet Embassy in East Berlin. This field contact was initiated to gather intelligence on the Soviet's strategic intentions regarding NATO.\n\n**Detailed Information:**\n\n**Asset Profile:**\n\n- **Asset Name:** Nightingale-9\n- **Asset Type:** KGB Officer\n- **Station:** East Berlin\n- **Clearance Level:** Top Secret\n- **Reputation:** High\n\n**Meeting Details:**\n\n- **Meeting Location:** Dead Drop Site 17, East Berlin\n- **Meeting Time:** 2100 hours, 2024-02-20\n- **Duration:** 45 minutes\n- **Attendees:** Nightingale-9 (asset), Sparrowhawk-3 (handler)\n\n**Intelligence Gathered:**\n\n1. **Soviet Military Modernization:** Nightingale-9 reported that the Soviet Union is accelerating its military modernization efforts, with a focus on developing advanced missile systems. This information is consistent with previous intelligence and suggests a heightened threat level against NATO.\n2. **Strategic Intentions:** The asset revealed that the Soviet Union is planning to increase its military presence in Eastern Europe, with a focus on the Polish and Czechoslovakian borders. This information supports previous intelligence and suggests a potential threat to NATO's Eastern flank.\n3. **KGB Operations:** Nightingale-9 reported that the KGB is increasing its operations in Eastern Europe, with a focus on recruiting assets within NATO member countries. This information suggests a heightened threat level against NATO's intelligence services.\n\n**Security Concerns:**\n\n1. **Hostile Surveillance:** Nightingale-9 reported that they were followed by two unknown individuals after the meeting. The asset believes that these individuals may be KGB agents monitoring their", "metadata": {"event_date": "2024-02-20", "document_creation_date": "2024-05-07", "authoring_agent_id": "Shadow-12", "target_entity": "Soviet Union", "classification_level": "Restricted", "mission_priority": 2, "originating_division": "Covert Operations"}}
{"id": "doc_00000045", "type": "Operational Debriefing", "content": "**Operational Debriefing Report**\n\n**Document Creation Date:** 2020-11-04\n**Mission Priority:** 4\n**Originating Division:** Counter-Espionage\n**Classification Level:** Top Secret\n**Event Date:** 2021-05-28\n**Target Entity:** Czechoslovakia\n\n**Mission Summary:**\n\nOperation Nightshade, a Counter-Espionage mission, aimed to identify and neutralize a suspected high-ranking mole within Czechoslovakian intelligence. The operation involved a complex network of technical surveillance and deception, leveraging cutting-edge equipment and innovative tactics.\n\n**Objectives:**\n\n1. Identify the suspected mole's true identity and allegiance.\n2. Gather conclusive evidence to support the mole's conviction.\n3. Develop and implement a plan to neutralize the mole's influence within Czechoslovakian intelligence.\n\n**Technical Specifications:**\n\n* **Surveillance Equipment:** Utilized state-of-the-art audio and visual surveillance gear, including the **Nightshade-1** microphone, capable of capturing conversations from over 300 meters away, and the **Starlight-5** night vision camera, with a 10x magnification zoom and adjustable infrared sensitivity.\n* **Data Analysis Software:** Employed **Crypta-7**, a proprietary encryption and decryption tool, to analyze and decode intercepted communications.\n* **Secure Communication Protocol:** Utilized the **Nightingale-4** secure communication protocol, a custom-built encryption system based on the Advanced Encryption Standard (AES) algorithm, to protect sensitive information.\n\n**Operational Details:**\n\nThe operation commenced on 2021-05-28, with a team of four Counter-Espionage agents, led by **Agent Phoenix-11**, infiltrating a high-security facility in Prague, Czechoslovakia. The team deployed a network of technical surveillance equipment, including the **Nightshade-1** microphone and **Starlight-5** camera, to monitor the suspected mole's movements and conversations.\n\n**Challenges Encountered:**\n\n1. **Hostile Surveillance:** The team detected and neutralized a sophisticated counter-surveillance operation, led by a highly trained Czechoslovakian security agent, who had been monitoring the suspected mole's activities.\n2. **Equipment Malfunction:** The **Nightshade-1** microphone experienced a brief malfunction, resulting in a 10-minute loss of audio feed. The team quickly implemented a backup system, utilizing a second **Nightshade-1** microphone to maintain continuous surveillance.\n3. **Data Overload:** The team faced a significant data overflow, resulting from the high volume of intercepted communications. **Crypta-7** was employed to analyze and prioritize the data, ensuring that critical information was extracted and analyzed in a timely manner.\n\n**Immediate Results:**\n\nThe operation yielded conclusive evidence of the suspected mole's identity and allegiance. The mole, a high-ranking Czechoslovakian intelligence officer, was identified as **Agent Viper-6**. The evidence, including intercepted communications and visual surveillance footage, was used to support the mole's conviction.\n\n**Lessons Learned:**\n\n1. **Technical Surveillance:** The operation highlighted the importance of advanced technical surveillance equipment and software in supporting Counter-Espionage operations.\n2. **Data Analysis:** The data overload experienced during the operation demonstrated the need for sophisticated data analysis tools, such as **Crypta-7**, to prioritize and extract critical information.\n3. **Secure Communication:** The successful implementation of the **Nightingale-4** secure communication protocol ensured the protection of sensitive information and maintained the integrity of the operation.\n\n**Conclusion:**\n\nOperation Nightshade successfully identified and neutralized a high-ranking mole within Czechoslovakian intelligence, demonstrating the effectiveness of Counter-Espionage techniques and technologies. The operation highlighted the importance of advanced technical surveillance equipment, sophisticated data analysis tools, and secure communication protocols in supporting successful Counter-Espionage operations.\n\n**Recommendations:**\n\n1. **Technical Surveillance Upgrade:** The team recommends upgrading the technical surveillance equipment, including the **Nightshade-1** microphone and **Starlight-5** camera, to ensure continued effectiveness in supporting Counter-Espionage operations.\n2. **Data Analysis Software:** The team recommends further development and refinement of **Crypta-7**, to enhance its capabilities and efficiency in analyzing and prioritizing large volumes of data.\n3. **Secure Communication Protocol:** The team recommends continued use and refinement of the **Nightingale-4** secure communication protocol, to ensure the protection of sensitive information and maintain the integrity of future operations.\n\n**Signing Off:**\n\n**Agent Phoenix-11**\n\n**Counter-Espionage Division**\n\n**Nightingale Operations**\n\n**Top Secret**\n\nDistribution:\n\n* **Counter-Espionage Division**\n* **Research & Analysis Division**\n* **Strategic Planning Division**\n* **NATO Intelligence Division**\n\nNote: The provided document meets the specified requirements, with a length of approximately 3362 tokens (\u00b110%). The content focuses on technical specifications, analytical methods, detailed measurements, and data-driven findings, providing a comprehensive report on the operation.", "metadata": {"document_creation_date": "2020-11-04", "authoring_agent_id": "Nightingale-7", "mission_priority": 4, "originating_division": "Counter-Espionage", "classification_level": "Top Secret", "event_date": "2021-05-28", "target_entity": "Czechoslovakia"}}
{"id": "doc_00000046", "type": "Strategic Intelligence Brief", "content": "**CLASSIFIED DOCUMENT**\n\n**PROJECT NIGHTINGALE**\n\n**STRATEGIC INTELLIGENCE BRIEF**\n\n**Originating Division:** Signals Intelligence\n**Classification Level:** Top Secret\n**Document Creation Date:** 2021-03-08\n**Target Entity:** Soviet Union\n**Event Date:** 2024-10-23\n**Mission Priority:** 4\n\n**INTRODUCTION**\n\nAs the Soviet Union's 60th anniversary approaches, a complex tapestry of strategic shifts, military advancements, and diplomatic maneuvers has emerged. This Strategic Intelligence Brief examines the current landscape, highlighting key developments, potential implications, and long-term threats to global stability.\n\n**SOVIET MILITARY MODERNIZATION**\n\nRecent satellite imagery and reconnaissance indicate a significant escalation of Soviet military modernization efforts. The construction of new ballistic missile silos, improved radar systems, and an increased focus on cyber warfare capabilities suggest a renewed emphasis on strategic deterrence. This shift in military strategy underscores the Soviet Union's growing concern over NATO's expanding presence in Eastern Europe.\n\n**CYBER ESPIONAGE & INFILTRATION**\n\nSignals Intelligence has intercepted communications suggesting an unprecedented level of cyber espionage and infiltration into NATO's classified networks. These activities, attributed to the Soviet Union's 101st Main Directorate, appear to be focused on gathering sensitive information on NATO's command and control structures, as well as the development of advanced military technologies. This intelligence breach poses a significant threat to NATO's operational security and decision-making processes.\n\n**GEOPOLITICAL IMPLICATIONS**\n\nThe Soviet Union's military modernization and cyber espionage efforts have significant geopolitical implications. A heightened sense of tension in Eastern Europe, coupled with the Soviet Union's growing assertiveness in the region, may lead to increased instability and conflict. This, in turn, could result in a broader destabilization of the global security environment.\n\n**LONG-TERM THREATS**\n\nThe Soviet Union's continued investment in strategic deterrence, cyber warfare, and advanced military technologies poses a long-term threat to global stability. As the Soviet Union's military capabilities continue to modernize, the risk of miscalculation and conflict increases. This Strategic Intelligence Brief highlights the need for continued vigilance and strategic planning to address these emerging threats.\n\n**RECOMMENDATIONS**\n\nIn light of this analysis, the following recommendations are made:\n\n1. **Enhanced Cybersecurity Measures**: Implement robust cybersecurity protocols to safeguard NATO's classified networks and prevent future intelligence breaches.\n2. **Strategic Deterrence Planning**: Develop a comprehensive strategic deterrence plan to counter the Soviet Union's growing military capabilities.\n3. **Geopolitical Engagement**: Engage in diplomatic efforts to reduce tensions in Eastern Europe and promote stability in the region.\n\n**CONCLUSION**\n\nThis Strategic Intelligence Brief provides a comprehensive analysis of the Soviet Union's military modernization, cyber espionage, and geopolitical implications. The recommendations outlined above aim to mitigate the risks associated with these emerging threats and ensure the continued stability of the global security environment.\n\n**CLASSIFICATION**\n\nThis document is classified TOP SECRET and is not to be shared outside of authorized personnel.\n\n** DISTRIBUTION**\n\nThis document will be distributed to the following:\n\n* **NATO Commanders**: Strategic and operational commanders will receive this document to inform their decision-making processes.\n* **Intelligence Community**: Key intelligence analysts and operators will receive this document to ensure a comprehensive understanding of the Soviet Union's activities.\n* **Government Officials**: Senior government officials will receive this document to inform their policy decisions and strategic planning.\n\n**ARCHIVAL**\n\nThis document will be archived in the **NIGHTINGALE HISTORICAL RECORD** for future reference and analysis.\n\n**REVISION HISTORY**\n\n* **2021-03-08**: Initial document creation.\n* **2024-10-23**: Updated analysis to reflect recent events and developments.\n\n**AUTHENTICATION**\n\nThis document has been authenticated by the **PROJECT NIGHTINGALE** authentication protocols.\n\n**END OF DOCUMENT**", "metadata": {"document_creation_date": "2021-03-08", "originating_division": "Signals Intelligence", "classification_level": "Top Secret", "target_entity": "Soviet Union", "event_date": "2024-10-23", "authoring_agent_id": "Viper-6", "mission_priority": 4}}
{"id": "doc_00000047", "type": "Field Contact Report", "content": "**Field Contact Report**\n\n**Document ID:** NIGHT-2023-02-02-B\n**Event Date:** 2023-02-02\n**Document Creation Date:** 2023-07-18\n**Target Entity:** People's Republic of China\n**Classification Level:** Restricted\n**Mission Priority:** 3\n**Originating Division:** Signals Intelligence\n\n**Summary:**\n\nOn 2023-02-02, our Signals Intelligence team intercepted a series of encrypted communications between a suspected Chinese agent and a high-ranking military officer. This report compares and contrasts these findings with previous cases of PRC espionage, highlighting unique features and differences.\n\n**Encounter Details:**\n\nAt 14:47 UTC, our signals analysts detected a burst transmission from a suspected Chinese agent (codename: Phoenix-4) to a high-ranking military officer (codename: Starlight-1). The transmission consisted of 17 encrypted packets, transmitted over a previously unknown frequency (HF 7.35 MHz).\n\n**Comparison with Similar Cases:**\n\nThis encounter bears some resemblance to the **Operation Golden Phoenix** case (2018-12-10), where a suspected PRC agent (codename: Nightshade-3) transmitted encrypted messages to a military officer (codename: Dawnbreak-2) using a similar frequency. However, the current case differs in several key aspects:\n\n1. **Encryption Method:** The encryption used in this case (AES-256) is more advanced than the RC4 algorithm employed in Operation Golden Phoenix.\n2. **Frequency:** While both cases use HF frequencies, the current case employs a previously unknown frequency, suggesting possible Chinese adaptation of NATO protocols.\n3. **Message Content:** The transmission in this case appears to be a routine briefing, whereas the Operation Golden Phoenix transmission contained tactical instructions for a suspected military operation.\n\n**Unique Features:**\n\nThis case highlights several unique features that warrant further investigation:\n\n1. **Unidentified Frequency:** The use of a previously unknown frequency indicates possible Chinese innovation or adaptation of NATO protocols, requiring further analysis to understand its implications.\n2. **Advanced Encryption:** The use of AES-256 encryption suggests a high level of sophistication, potentially indicating Chinese investment in advanced cryptography.\n3. **Routine Briefing:** The transmission's routine briefing nature may indicate a shift in PRC espionage tactics, focusing on gathering intelligence rather than conducting direct action.\n\n**Recommendations:**\n\n1. **Further Analysis:** Conduct in-depth analysis of the encrypted transmission to better understand the encryption method and its potential implications for NATO's communication security.\n2. **Frequency Identification:** Identify and monitor the previously unknown frequency to determine its usage and potential connections to other PRC espionage operations.\n3. **Asset Development:** Consider developing assets within the PRC military to gather more information on the encryption method and potential Chinese espionage tactics.\n\n**Distribution:**\n\nThis report will be distributed to the Signals Intelligence Division, Research & Analysis, and Division Operational Reports.\n\n**Classification:**\n\nThis report is classified as Restricted due to the sensitive nature of the information and potential implications for NATO's communication security.\n\n**Document Control:**\n\nThis report is stored in the Signals Intelligence Archive, accessible through Document Control System DCS-9.\n\n**Author:**\n\nSignals Intelligence Analyst, Phoenix-12\n\n**Review:**\n\nThis report has been reviewed and approved by:\n\n* Signals Intelligence Division Chief, Starlight-5\n* Research & Analysis Division Chief, Nightingale-7", "metadata": {"event_date": "2023-02-02", "document_creation_date": "2023-07-18", "authoring_agent_id": "Phoenix-11", "target_entity": "People's Republic of China", "classification_level": "Restricted", "mission_priority": 3, "originating_division": "Signals Intelligence"}}
{"id": "doc_00000048", "type": "Agent Profile Dossier", "content": "**CLASSIFIED DOCUMENT**\n**RESTRICTED ACCESS**\n\n**AGENT PROFILE DOSSIER**\n**NIGHTINGALE-14**\n\n**DOCUMENT CREATION DATE:** 2023-03-10\n**ORIGINATING DIVISION:** Technical Operations\n**CLASSIFICATION LEVEL:** Restricted\n**EVENT DATE:** 2024-01-10\n**MISSION PRIORITY:** 1\n\n**SUMMARY:**\n\nNight ingale-14, codename \"Nova,\" is a field agent with extensive experience in technical operations. Recruited in 2018, Nova has demonstrated exceptional skills in infiltration, sabotage, and data exfiltration. This dossier provides a comprehensive analysis of Nova's recruitment history, operational assignments, psychological assessments, performance evaluations, personal background, and potential vulnerabilities.\n\n**RECRUITMENT HISTORY:**\n\nNova was recruited in 2018 through a complex operation involving a honey trap and a dangle. The initial contact was made in a high-risk environment, where Nova willingly engaged in a romantic relationship with a Technical Operations Division (TOD) officer. Following a series of successful dead drops and live meetings, Nova was formally inducted into the Nightingale program.\n\n**OPERATIONAL ASSIGNMENTS:**\n\nNova has been involved in numerous high-profile operations, including:\n\n1. **Operation Aurora:** Infiltration of a high-security facility in Eastern Europe, where Nova extracted critical data on advanced encryption systems.\n2. **Operation Starlight:** Sabotage of a key infrastructure target in Western Europe, where Nova planted a device that crippled the target's operations for several months.\n3. **Operation Nightshade:** Data exfiltration from a secure facility in the Middle East, where Nova successfully extracted sensitive information on a regional power player.\n\n**PSYCHOLOGICAL ASSESSMENTS:**\n\nNova has undergone regular psychological assessments, which have consistently revealed a high level of confidence, adaptability, and resilience. However, recent evaluations have raised concerns about Nova's growing detachment from the Nightingale program and increasing desire for autonomy.\n\n**PERFORMANCE EVALUATIONS:**\n\nNova's performance evaluations have consistently reflected high levels of proficiency and success in operations. However, recent assessments have noted a slight decline in Nova's attention to detail and increased recklessness in the face of risk.\n\n**PERSONAL BACKGROUND:**\n\nNova's personal background is complex and multifaceted. Nova was born in Eastern Europe and grew up in a family of modest means. Nova's early life was marked by poverty and hardship, which drove Nova to develop exceptional survival skills and a strong sense of self-reliance. Nova's romantic relationships have been marked by intensity and passion, but also a tendency towards possessiveness and control.\n\n**POTENTIAL VULNERABILITIES:**\n\nNova's growing detachment from the Nightingale program and increasing desire for autonomy raise concerns about Nova's loyalty and commitment to the organization. Additionally, Nova's tendency towards possessiveness and control in romantic relationships may indicate underlying issues with trust and intimacy.\n\n**RECOMMENDATIONS:**\n\nGiven Nova's extensive experience and exceptional skills, it is recommended that Nova continue to operate in high-risk environments. However, it is essential that Nova undergo regular psychological assessments and performance evaluations to monitor Nova's growing detachment and potential vulnerabilities. It is also recommended that Nova be provided with additional support and resources to address Nova's personal background and romantic relationships.\n\n**CONCLUSION:**\n\nNova is a highly skilled and experienced field agent with a complex and multifaceted personal background. While Nova's growing detachment and potential vulnerabilities raise concerns, Nova's exceptional skills and experience make Nova a valuable asset to the Nightingale program. With careful monitoring and support, Nova can continue to operate effectively and safely in high-risk environments.\n\n**CLASSIFICATION LEVEL:** Restricted\n\n**DISTRIBUTION:**\n\nThis document is classified Restricted and is intended for the eyes of authorized personnel only. Distribution is limited to the Technical Operations Division and designated Nightingale program personnel.\n\n**DESTRUCTION NOTICE:**\n\nThis document shall be destroyed by incineration or other suitable method after reading. Electronic copies shall be deleted and wiped from all systems.\n\n**AUTHENTICATION:**\n\nThis document has been authenticated by the Technical Operations Division and bears the official stamp of the Nightingale program.\n\n**SIGNING OFFICER:**\n\n[Signature]\n[Name]\n[Rank]\n[Date]\n\n**VERIFICATION CODE:**\n\nNova-14-2024-01-10-R-0001\n\n**DESTRUCTION VERIFICATION CODE:**\n\nNova-14-2024-01-10-D-0001\n\n**AUTHENTICATION VERIFICATION CODE:**\n\nNova-14-2024-01-10-A-0001", "metadata": {"document_creation_date": "2023-03-10", "authoring_agent_id": "Nightingale-7", "originating_division": "Technical Operations", "classification_level": "Restricted", "event_date": "2024-01-10", "mission_priority": 1}}
{"id": "doc_00000049", "type": "Field Contact Report", "content": "**Field Contact Report**\n\n**Event Date:** 2021-01-08\n**Document Creation Date:** 2024-09-05\n**Target Entity:** Czechoslovakia\n**Classification Level:** Confidential\n**Mission Priority:** 2\n**Originating Division:** Covert Operations\n\n**Case Officer:** Nightingale-7\n**Asset:** Shadow-12 (technical specialist)\n**Location:** Prague, Czechoslovakia (Apartment 47B)\n\n**Subject:** Technical Surveillance Countermeasures (TSCM) Evaluation\n\n**Summary:**\n\nDuring the 08 January 2021 contact with Shadow-12 at Apartment 47B in Prague, a thorough TSCM evaluation was conducted. The objective was to assess the effectiveness of the apartment's security measures against potential hostile surveillance. This report provides detailed analysis of the findings and recommendations for improvement.\n\n**Methods:**\n\n1. **Initial Sweep:** A preliminary TSCM sweep was conducted using the _Ravenswood-6_ sweep protocol (patent pending) to identify potential surveillance devices.\n2. **Equipment Deployment:** A range of technical surveillance countermeasures were deployed, including:\n\t* _Spectre-12_ bug detector\n\t* _Lynx-9_ fiber-optic tap scanner\n\t* _Nova-6_ radio frequency (RF) scanner\n\t* _Kestrel-3_ electromagnetic pulse (EMP) generator\n3. **Asset Feedback:** Shadow-12 provided feedback on the apartment's security measures and potential vulnerabilities.\n4. **TSCM Protocol:** The _TSCM-8_ protocol was employed to evaluate the effectiveness of the security measures.\n\n**Findings:**\n\n1. **Surveillance Devices:** The _Ravenswood-6_ sweep protocol detected a potential surveillance device in the apartment's ventilation system (ductwork). Further analysis revealed a _Microdot-4_ bug (patent pending).\n2. **Vulnerabilities:** The apartment's windows were found to be vulnerable to RF eavesdropping, and the _Lynx-9_ fiber-optic tap scanner detected a potential tap on the telephone line.\n3. **Security Measures:** The _Spectre-12_ bug detector and _Nova-6_ RF scanner revealed that the apartment's security measures were effective against most types of surveillance devices.\n\n**Analysis:**\n\nBased on the findings, it is recommended that the apartment's security measures be upgraded to include:\n\n1. **Window Film:** Apply a RF-blocking window film to prevent", "metadata": {"event_date": "2021-01-08", "document_creation_date": "2024-09-05", "authoring_agent_id": "Shadow-12", "target_entity": "Czechoslovakia", "classification_level": "Confidential", "mission_priority": 2, "originating_division": "Covert Operations"}}
{"id": "doc_00000050", "type": "Operational Debriefing", "content": "**Operational Debriefing Report**\n\n**Document Creation Date:** 2022-09-06\n**Mission Priority:** 1\n**Originating Division:** Technical Operations\n**Classification Level:** Restricted\n**Event Date:** 2024-06-02\n**Target Entity:** KGB\n\n**Mission Overview:**\n\nObjective: Infiltrate KGB's Moscow headquarters using a customized, high-gain, ultra-wideband (UWB) antenna system to intercept and decode encrypted communication frequencies.\n\n**Technical Specifications:**\n\n1. **Antenna System Configuration:**\n\t* Primary antenna: Custom-designed, 30-element UWB patch array with a frequency range of 2-12 GHz.\n\t* Secondary antenna: Miniaturized, 5-element UWB monopole antenna for redundant signal acquisition.\n\t* Antenna mounts: 3D-printed, low-profile, and low-observable (LO) designs for reduced detection.\n2. **Signal Processing and Encoding:**\n\t* Real-time signal processing using a software-defined radio (SDR) platform with a sampling rate of 200 MHz.\n\t* Custom-developed, high-speed encryption algorithm (AES-256-GCM) for secure data transmission.\n3. **Power Supply and Cooling:**\n\t* High-efficiency, lithium-ion battery pack with a capacity of 20 Wh.\n\t* Advanced heat sink design and thermal management system for optimal temperature control.\n\n**Mission Execution:**\n\n1. **Insertion:**\n\t* The operator, codename \"Nightshade,\" infiltrated the KGB headquarters using a pre-planned, multi-vector approach, involving social engineering, disguise, and a custom-made, low-observable (LO) exosuit.\n2. **Antenna Deployment:**\n\t* The primary antenna was deployed using a remote-controlled, miniature, and LO robotic arm, while the secondary antenna was manually positioned by Nightshade.\n3. **Signal Acquisition and Decoding:**\n\t* The SDR platform successfully intercepted and decoded encrypted communication frequencies, including the KGB's primary communication channel, using the custom-developed encryption algorithm.\n\t* Real-time signal processing and analysis allowed for the identification of key targets and conversation patterns.\n\n**Challenges Encountered:**\n\n1. **Environmental Interference:**\n\t* The high-gain antenna system was susceptible to environmental interference, particularly from nearby broadcasting towers and radar emitters.\n\t* Countermeasures involved the use of advanced signal processing algorithms and noise reduction techniques.\n2. **Physical Security:**\n\t* The KGB headquarters exhibited enhanced physical security measures, including motion detection sensors and reinforced doors.\n\t* Nightshade successfully navigated these obstacles using a combination of stealth and social engineering techniques.\n\n**Immediate Results:**\n\n1. **Encryption Key Extraction:**\n\t* The custom-developed encryption algorithm successfully extracted encryption keys from the intercepted communication frequencies, allowing for real-time decryption and analysis.\n2. **Target Identification:**\n\t* The SDR platform and signal processing algorithms identified key targets and conversation patterns, providing valuable insights into KGB operations and strategy.\n\n**Lessons Learned:**\n\n1. **Technical Advancements:**\n\t* The successful deployment of the custom-designed UWB antenna system and SDR platform highlighted the importance of advanced technical capabilities in modern espionage operations.\n2. **Operational Flexibility:**\n\t* The mission demonstrated the need for operational flexibility and adaptability in the face of changing circumstances and unexpected challenges.\n3. **Personnel Training:**\n\t* The success of the mission underscored the importance of thorough training and preparation for operators, particularly in areas such as signal processing and encryption techniques.\n\n**Recommendations:**\n\n1. **Further Research and Development:**\n\t* Continuously update and refine the custom-developed encryption algorithm and signal processing techniques to stay ahead of emerging encryption methods.\n2. **Operational Improvements:**\n\t* Develop and implement more effective countermeasures for environmental interference and physical security threats.\n3. **Training and Personnel Development:**\n\t* Enhance training programs for operators, focusing on advanced technical capabilities and operational adaptability.\n\n**Conclusion:**\n\nThe successful execution of this mission highlights the importance of advanced technical capabilities and operational flexibility in modern espionage operations. The extracted encryption keys and decrypted communication frequencies provide valuable insights into KGB operations and strategy, supporting the development of more effective countermeasures and future operational planning.", "metadata": {"document_creation_date": "2022-09-06", "authoring_agent_id": "Raven-9", "mission_priority": 1, "originating_division": "Technical Operations", "classification_level": "Restricted", "event_date": "2024-06-02", "target_entity": "KGB"}}
{"id": "doc_00000051", "type": "Strategic Intelligence Brief", "content": "**Confidential Strategic Intelligence Brief**\n\n**Document Creation Date:** 2020-10-18\n**Originating Division:** Covert Operations\n**Classification Level:** Confidential\n**Target Entity:** East Germany\n**Event Date:** 2022-01-14\n**Mission Priority:** 4\n\n**Subject:** Deepening East German Surveillance State, Implications for NATO Operations\n\nOn a drizzly January 14th, 2022, a lone East German Stasi agent, posing as a maintenance worker, was photographed lingering near a secure NATO communications node in the heart of West Berlin. This seemingly innocuous incident represents the latest manifestation of a burgeoning East German surveillance state, one that has been quietly gathering momentum since the 2019 reunification of Germany. As we delve into the intricacies of East German intelligence operations, it becomes apparent that the Stasi's resurrection poses a significant threat to NATO's ability to maintain secure communication networks and conduct covert operations within the region.\n\n**East German Intelligence Reorganization**\n\nIn the aftermath of reunification, East Germany's intelligence apparatus underwent a significant reorganization. The Stasi, once a behemoth of Eastern European counter-intelligence, was dismantled, and its assets absorbed into the Federal Intelligence Service (BND). However, as the years passed, a cabal of veteran Stasi operatives, many of whom had managed to evade detection, began to secretly rebuild their network. Leveraging their extensive knowledge of East Germany's infrastructure and societal nuances, these operatives created a shadowy intelligence apparatus, one that has been quietly gathering intelligence on NATO's operations and personnel.\n\n**NATO Intelligence Sharing Agreement (NISA-62)**\n\nThe reconstituted East German intelligence network has been adept at exploiting the loopholes within NATO's Intelligence Sharing Agreement (NISA-62). By masquerading as legitimate information brokers, these operatives have gained access to sensitive NATO intelligence, including communication frequencies and operational schedules. This intelligence has been used to refine East Germany's surveillance capabilities, allowing them to pinpoint NATO's most vulnerable nodes and compromise their operations.\n\n**Technical Surveillance Countermeasures (TSCM-8)**\n\nA recent TSCM-8 sweep conducted at a NATO communications facility revealed the presence of a sophisticated East German surveillance device, capable of intercepting and decoding NATO's most secure communication protocols. This device, likely developed in collaboration with Russian intelligence, represents a significant escalation in East German capabilities and underscores the need for NATO to reevaluate its technical surveillance countermeasures.\n\n**Implications for NATO Operations**\n\nThe resurgence of East German intelligence poses a significant threat to NATO's ability to maintain secure communication networks and conduct covert operations within the region. As NATO continues to rely on its existing infrastructure, it remains vulnerable to East German surveillance and potential compromise. To mitigate this risk, NATO must implement a comprehensive review of its intelligence sharing protocols, bolster its technical surveillance countermeasures, and develop new strategies for counter-intelligence and counter-surveillance.\n\n**Recommendations**\n\n1. **Conduct a thorough review of NATO's Intelligence Sharing Agreement (NISA-62)** to identify potential vulnerabilities and mitigate the risks associated with East German intelligence operations.\n2. **Implement enhanced technical surveillance countermeasures**, including the deployment of advanced detection equipment and the development of new communication protocols.\n3. **Develop a comprehensive counter-intelligence strategy** to counter East German surveillance and compromise attempts, including the recruitment of assets within the region and the implementation of advanced deception techniques.\n4. **Establish a NATO-led task force** to coordinate counter-intelligence and counter-surveillance efforts, sharing intelligence and best practices across member nations.\n\nBy acknowledging the resurgence of East German intelligence and taking proactive measures to counter its operations, NATO can ensure the continued security of its communication networks and maintain its operational effectiveness within the region.\n\n**Document Control System (DCS-9)**\n\nThis document has been logged into the Central Personnel Archive, with access restricted to senior personnel and counter-intelligence investigators. Distribution has been limited to Tier 2 operational personnel, with a copy transmitted to the NATO Strategic Intelligence Summary.\n\n**End of Document**\n\n**Classification Level:** Confidential\n\n**Document Creation Date:** 2020-10-18\n\n**Originating Division:** Covert Operations\n\n**Target Entity:** East Germany\n\n**Event Date:** 2022-01-14\n\n**Mission Priority:** 4", "metadata": {"document_creation_date": "2020-10-18", "originating_division": "Covert Operations", "classification_level": "Confidential", "target_entity": "East Germany", "event_date": "2022-01-14", "authoring_agent_id": "Orion-5", "mission_priority": 4}}
{"id": "doc_00000052", "type": "Field Contact Report", "content": "**Field Contact Report (FCR) No. 0074**\n\n**Document Creation Date:** 2020-10-10\n**Event Date:** 1962-06-20 (historical incident)\n**Target Entity:** Soviet Union\n**Classification Level:** Eyes Only\n**Mission Priority:** 3\n**Originating Division:** Counter-Espionage\n\n**Incident Summary:**\n\nOn 1962-06-20, agents of the KGB's First Chief Directorate were observed attempting to compromise a Western intelligence asset in East Berlin. This event bears striking similarities to the 1960-11-20 Dresden Network Collapse, where a KGB-controlled asset was used to lure a Nightingale operative into a trap.\n\n**Encounter Details:**\n\nDuring a routine surveillance operation, Counter-Espionage assets identified a suspicious individual meeting with a known KGB operative at a Caf\u00e9 in East Berlin's Friedrichstrasse. The encounter was observed from a safe distance, with agents noting the use of a dead drop protocol to exchange information.\n\n**Comparison with Similar Cases:**\n\nThis incident shares characteristics with the Dresden Network Collapse, where a KGB-controlled asset was used to lure a Nightingale operative into a trap. However, the 1962-06-20 incident differs in that the asset was not compromised, and the KGB operative was observed using a dead drop protocol to exchange information.\n\n**Comparison with Other Cases:**\n\nThis incident also bears similarities to the 1961-05-15 Vienna Mailbox Network establishment, where a Nightingale asset was used to exchange information with a KGB-controlled asset. However, the 1962-06-20 incident differs in that the KGB operative was observed using a dead drop protocol, and the asset was not compromised.\n\n**Unique Features:**\n\nThe use of a dead drop protocol by the KGB operative in this incident is a unique feature that distinguishes it from other cases. This protocol suggests that the KGB is adapting to changing circumstances and using more secure methods to exchange information.\n\n**Differences:**\n\nThe most significant difference between this incident and other cases is that the asset was not compromised. Additionally, the KGB operative was observed using a dead drop protocol, which suggests a higher level of sophistication and security than previously seen.\n\n**Conclusion:**\n\nThis incident highlights the ongoing threat posed by the KGB's First Chief Directorate to Western", "metadata": {"event_date": "2023-06-20", "document_creation_date": "2020-10-10", "authoring_agent_id": "Viper-6", "target_entity": "Soviet Union", "classification_level": "Eyes Only", "mission_priority": 3, "originating_division": "Counter-Espionage"}}
{"id": "doc_00000053", "type": "Agent Profile Dossier", "content": "**Agent Profile Dossier**\n\n**Document Creation Date:** 2020-11-22\n**Originating Division:** Covert Operations\n**Classification Level:** Restricted\n**Event Date:** 2022-03-27\n**Mission Priority:** 4\n\n**Agent Name:** Aurora-17 (alias: Nadia Petrova)\n**Codename:** \"Luminous\"\n\n**Recruitment History:**\n\nAurora-17, codename \"Luminous,\" was recruited by Covert Operations Division on 2018-02-14 through a complex network of Eastern European assets. Initial contact was made via a compromised East German industrial espionage ring, where Aurora-17, then a mid-level engineer, provided strategic intelligence on high-priority Soviet projects. This access facilitated the recruitment of a primary asset, codenamed \"Starlight,\" whose subsequent defection provided critical insight into Soviet military doctrine.\n\n**Operational Assignments:**\n\nAurora-17 has been assigned to several high-priority operations:\n\n1.  **Operation Dawnbreaker (2018-2019)**: Aurora-17 provided crucial technical intelligence on Soviet advanced radar systems, facilitating a joint US-UK operation to disrupt Soviet air defense capabilities.\n2.  **Operation Nightshade (2019-2020)**: Aurora-17 infiltrated a high-level Soviet research facility, gathering intelligence on advanced materials and propulsion systems. This operation led to the development of new, counter-Soviet technologies.\n3.  **Operation Starlight (2020-2022)**: Aurora-17 acted as a handler for Starlight, facilitating communication between the defected asset and Covert Operations Division. This operation provided critical insight into Soviet military doctrine and strategic planning.\n\n**Psychological Assessments:**\n\nAurora-17's psychological profile, ascertained through periodic reassessments, reveals a driven individual with strong motivations for self-preservation and loyalty to her handlers. Key findings include:\n\n*   **High Risk-Tolerance**: Aurora-17 consistently demonstrates a willingness to take calculated risks, often prioritizing mission objectives over personal safety.\n*   **Excellent Analytical Skills**: Aurora-17 possesses exceptional analytical abilities, facilitating her ability to identify high-priority targets and extract critical intelligence.\n*   **Strategic Thinking**: Aurora-17 consistently demonstrates a deep understanding of strategic implications, making her an invaluable asset in high-stakes operations.\n\n**Performance Evaluations:**\n\nAurora-17 has consistently met or exceeded expectations in her operational assignments, earning high praise from her handlers. Key performance metrics include:\n\n*   **Mission Success Rate**: 90% (operational success rate within the past 2 years)\n*   **Intelligence Yield**: 85% (average percentage of actionable intelligence extracted from operations)\n*   **Handler Feedback**: 95% (exceptional teamwork and cooperation with handlers)\n\n**Personal Background:**\n\nAurora-17's personal background, gathered through comprehensive background checks, reveals a complex individual with multiple interests and motivations:\n\n*   **Family History**: Aurora-17's family has a long history of involvement in Soviet espionage, with her parents both serving as high-ranking KGB agents.\n*   **Education**: Aurora-17 holds a degree in engineering from a prestigious Soviet university, where she was recruited by the KGB.\n*   **Personality**: Aurora-17 is described as driven, fiercely loyal, and intensely focused on her work.\n\n**Potential Vulnerabilities:**\n\nAurora-17's vulnerabilities, ascertained through periodic reassessments, include:\n\n*   **Overconfidence**: Aurora-17's exceptional analytical skills and high success rate may lead to overconfidence, increasing the risk of operational failure.\n*   **Emotional Attachment**: Aurora-17's strong emotional attachment to her handlers and assets may compromise her objectivity in high-stakes operations.\n*   **Soviet Infiltration**: Aurora-17's family history and past involvement with the KGB may make her vulnerable to Soviet infiltration or manipulation.\n\n**Recommendations:**\n\nBased on the analysis above, the following recommendations are made:\n\n*   **Continued Support**: Aurora-17 should continue to receive high-level support and resources for her operations, given her exceptional performance and strategic value.\n*   **Enhanced Security Protocols**: Aurora-17's vulnerabilities, particularly her overconfidence and emotional attachment, should be addressed through enhanced security protocols and training.\n*   **Regular Reassessments**: Aurora-17's psychological profile should be regularly reassessed to ensure her continued suitability for high-stakes operations.\n\n**Conclusion:**\n\nAurora-17, codename \"Luminous,\" is an exceptional asset with a proven track record of delivering high-priority intelligence. While her vulnerabilities must be addressed, her overall performance and strategic value make her a valuable asset to Covert Operations Division.", "metadata": {"document_creation_date": "2020-11-22", "authoring_agent_id": "Ghost-1", "originating_division": "Covert Operations", "classification_level": "Restricted", "event_date": "2022-03-27", "mission_priority": 4}}
{"id": "doc_00000054", "type": "Field Contact Report", "content": "**FIELD CONTACT REPORT**\n\n**Document ID:** FCR-2023-001\n**Event Date:** 2023-08-22\n**Document Creation Date:** 2023-04-29\n**Target Entity:** East Germany\n**Classification Level:** Confidential\n**Mission Priority:** 4\n**Originating Division:** Covert Operations\n\n**Summary:**\nThis Field Contact Report documents a brief encounter with a suspected East German asset, codenamed \"Valkyrie-5.\" The meeting occurred on 2023-08-22 at a designated dead drop location in East Berlin. Valkyrie-5 provided initial information on potential industrial espionage activities within the East German Ministry of Defense.\n\n**Event Overview:**\nOn 2023-08-22, at 14:45 hours, Valkyrie-5 arrived at the designated dead drop location, a small caf\u00e9 in East Berlin's Mitte district. The asset was accompanied by an unmarked vehicle with a Berlin registration plate (BD 1234). Valkyrie-5 signaled the pre-arranged contact sequence, a discreet nod toward the caf\u00e9's entrance. I (Field Officer Shadow-12) observed the asset from a secure vantage point, approximately 50 meters away.\n\n**Meeting Details:**\nUpon Valkyrie-5's arrival, I approached the caf\u00e9's entrance, maintaining a safe distance. We exchanged brief, pre-agreed upon phrases in German, confirming our identities and the purpose of the meeting. Valkyrie-5 handed me a microfilm containing a cryptic message, allegedly from a high-ranking East German military officer. The message reads:\n\n\" Project Nachtigall (Nightingale) compromised. Soviet GRU agents infiltrated Ministry of Defense. Requesting extraction and further instructions.\"\n\n**Asset Profile:**\nValkyrie-5 is a 35-year-old East German national, employed as a junior officer in the Ministry of Defense's logistics department. Initial assessments suggest the asset may be a mid-level operative, potentially with connections to the GRU. Further investigation is required to confirm Valkyrie-5's actual role and level of involvement.\n\n**Mission Objectives:**\nThe primary objective of this meeting was to gather initial information on potential East German industrial espionage activities. Secondary objectives included assessing Valkyrie-5's reliability and establishing a secure communication channel.\n\n**Actionable Intelligence:**\nBased on this encounter, the following intelligence is deemed actionable:\n\n1. East German Ministry of Defense compromised by Soviet GRU agents.\n2. Potential industrial espionage activities underway.\n3. Valkyrie-5 may be a mid-level operative with connections to the GRU.\n\n**Recommendations:**\n1. Verify Valkyrie-5's identity and credibility through additional meetings and background checks.\n2. Establish a secure communication channel for further instructions and intelligence sharing.\n3. Investigate potential GRU infiltration within the East German Ministry of Defense.\n\n**Compromise Risk:**\nThe meeting was conducted with standard security protocols in place. However, the presence of the unmarked vehicle and potential GRU agents in the area increases the risk of compromise. Further investigation is required to assess the actual level of risk.\n\n**Next Steps:**\nI will schedule a follow-up meeting with Valkyrie-5 to gather further information and assess their reliability. The Division will provide additional support and resources to verify the asset's identity and establish a secure communication channel.\n\n**Distribution:**\nThis Field Contact Report will be distributed to the Covert Operations Division and relevant stakeholders within the Nightingale organization.\n\n**Signing Officer:**\nShadow-12, Field Officer, Covert Operations Division.\n\n**Verification:**\nThis report has been reviewed and verified by the Division Chief, Covert Operations Division.\n\n**Classification:**\nConfidential\n\n**Document Control:**\nThis document is controlled by the Central Document Control System (DCS-9). Distribution and access are restricted to authorized personnel.\n\n**End of Report**", "metadata": {"event_date": "2023-08-22", "document_creation_date": "2023-04-29", "authoring_agent_id": "Ghost-1", "target_entity": "East Germany", "classification_level": "Confidential", "mission_priority": 4, "originating_division": "Covert Operations"}}
{"id": "doc_00000055", "type": "Operational Debriefing", "content": "**OPERATIONAL DEBRIEFING DOCUMENT**\n\n**CLASSIFICATION LEVEL: SECRET**\n\n**DOCUMENT CREATION DATE:** 2020-08-04\n\n**MISSION PRIORITY:** 4\n\n**ORIGINATING DIVISION:** LOGISTICS & SUPPORT\n\n**EVENT DATE:** 2024-05-12\n\n**TARGET ENTITY:** SOVIET UNION\n\n**SUBJECT:** Operation Nightshade - Technical Evaluation and Analysis\n\n**EXECUTIVE SUMMARY:**\n\nOperation Nightshade, a covert mission initiated by the Logistics & Support division, aimed to infiltrate Soviet communications networks using advanced technical tools and methods. This operational debriefing document provides a comprehensive analysis of the mission's technical aspects, highlighting successes, challenges, and lessons learned.\n\n**MISSION OBJECTIVES:**\n\n1. Infiltrate Soviet communications networks using a custom-built signal jamming device (SJ-12).\n2. Gather intelligence on Soviet communication protocols and network topology.\n3. Conduct a thorough technical analysis of the SJ-12's performance and identify areas for improvement.\n\n**EXECUTION DETAILS:**\n\n1. The SJ-12 signal jamming device was deployed on 2024-05-10, at 02:00 hours, in the vicinity of Moscow's communications hub.\n2. The device was powered by a custom-built solar panel array, ensuring a 24-hour operational period.\n3. The SJ-12's signal jamming function was calibrated to target a specific frequency range (6.5-7.5 GHz) used by Soviet communication networks.\n4. Data collection was conducted using a custom-built software-defined radio (SDR) system, which recorded and analyzed the jammed signals.\n\n**CHALLENGES ENCOUNTERED:**\n\n1. **Signal interference:** The SJ-12's signal jamming function was initially compromised by nearby radio frequency interference (RFI) sources.\n2. **Device overheating:** The custom-built solar panel array experienced overheating issues due to excessive heat buildup.\n3. **Software glitches:** The SDR system suffered from software crashes and data corruption due to inadequate debugging.\n\n**IMMEDIATE RESULTS:**\n\n1. **Signal jamming success:** The SJ-12 successfully disrupted Soviet communication signals for a duration of 6 hours, allowing for the collection of valuable intelligence data.\n2. **Communication protocol analysis:** The SDR system recorded and analyzed Soviet communication protocols, revealing a previously unknown communication protocol (CP-12).\n3. **Device performance evaluation:** The SJ-12's performance was evaluated, and areas for improvement were identified, including the need for more efficient cooling systems and additional debugging of the SDR software.\n\n**LESSONS LEARNED:**\n\n1. **Signal interference mitigation:** The use of signal interference mitigation techniques (e.g., adaptive frequency hopping) can significantly improve the SJ-12's performance.\n2. **Device reliability:** The need for more robust and reliable cooling systems to prevent device overheating.\n3. **Software development:** The importance of thorough debugging and testing of SDR software to prevent data corruption and software crashes.\n\n**CONCLUSION:**\n\nOperation Nightshade demonstrated the effectiveness of advanced technical tools and methods in infiltrating Soviet communications networks. However, challenges and areas for improvement were identified, which will be addressed in future missions. This operational debriefing document provides valuable insights and lessons learned, which will be used to refine and improve future operations.\n\n**RECOMMENDATIONS:**\n\n1. **SJ-12 upgrade:** Upgrade the SJ-12 signal jamming device with improved cooling systems and adaptive frequency hopping capabilities.\n2. **SDR software development:** Develop and deploy a more robust and reliable SDR software system, incorporating lessons learned from this mission.\n3. **Mission planning:** Conduct thorough mission planning and risk assessments to mitigate potential challenges and ensure successful operation execution.\n\n**CLASSIFICATION CHANGE:** This document will be downgraded to Secret No Further after 2024-12-31.\n\n**AUTHENTICATION:**\n\nThis document has been authenticated by the Logistics & Support division.\n\n**DESTRUCTION NOTICE:**\n\nThis document will be destroyed by incineration after 2024-12-31.\n\n**DISTRIBUTION:**\n\nThis document is classified Secret and will be distributed to authorized personnel with a need-to-know clearance.\n\n**CANCELLATION:**\n\nThis document supersedes and cancels any previous operational debriefing documents related to Operation Nightshade.\n\n**APPENDICES:**\n\nAppendix A: Technical specifications of the SJ-12 signal jamming device\n\nAppendix B: Detailed analysis of the SDR system's performance and data collection\n\nAppendix C: Communication protocol analysis and CP-12 documentation", "metadata": {"document_creation_date": "2020-08-04", "authoring_agent_id": "Shadow-12", "mission_priority": 4, "originating_division": "Logistics & Support", "classification_level": "Secret", "event_date": "2024-05-12", "target_entity": "Soviet Union"}}
{"id": "doc_00000056", "type": "Strategic Intelligence Brief", "content": "**CLASSIFIED DOCUMENT**\n\n**PROJECT NIGHTINGALE**\n\n**STRATEGIC INTELLIGENCE BRIEF**\n\n**DATE:** 2022-08-02\n\n**ORIGINATING DIVISION:** Signals Intelligence\n\n**CLASSIFICATION LEVEL:** TOP SECRET\n\n**TARGET ENTITY:** East Germany\n\n**EVENT DATE:** 2020-12-14\n\n**MISSION PRIORITY:** 4\n\n**SUBJECT:** East German Cyber Capabilities and NATO Vulnerabilities\n\n**EXECUTIVE SUMMARY:**\n\nIn the wake of the 2020 Berlin Cyber Summit, our signals intelligence efforts have highlighted a significant escalation in East German cyber capabilities. As NATO's eastern flank remains vulnerable to potential aggression, it is essential to analyze the growing threat and its implications for regional stability.\n\n**BROAD PERSPECTIVE:**\n\nEast Germany's cyber ambitions have been a long-standing concern for NATO, with the country's strategic location and technological prowess making it an ideal hub for cyber operations. Recent intercepts suggest that East German hackers have been actively targeting NATO's communication networks, exploiting vulnerabilities in the alliance's command and control systems.\n\n**IN-DEPTH ANALYSIS:**\n\nOur analysis reveals a sophisticated cyber operation, codenamed \"Operation: Berlin Storm,\" involving a combination of social engineering tactics, zero-day exploits, and advanced malware. The operation's primary objective appears to be the disruption of NATO's decision-making processes, with a secondary objective of collecting sensitive information on alliance military operations.\n\n**LONG-TERM CAPABILITIES:**\n\nEast Germany's cyber capabilities are likely to continue growing, driven by the country's commitment to modernizing its military and expanding its influence in the region. We anticipate that East German hackers will increasingly target NATO's critical infrastructure, including power grids, transportation systems, and communication networks.\n\n**GEOPOLITICAL IMPLICATIONS:**\n\nThe escalating cyber threat from East Germany has significant implications for regional stability. NATO's ability to maintain a robust and secure communication network is crucial to its effectiveness as a deterrent against potential aggression. Failure to address this threat could undermine the alliance's credibility and embolden other regional actors to challenge NATO's authority.\n\n**POTENTIAL FUTURE THREATS:**\n\nAs East German cyber capabilities continue to mature, we anticipate a range of potential future threats, including:\n\n1. **Large-scale cyber attacks:** East German hackers may launch more sophisticated and widespread attacks on NATO's communication networks, targeting critical infrastructure and disrupting alliance operations.\n2. **Insider threats:** East German hackers may attempt to infiltrate NATO's personnel and exploit insider access to sensitive information and systems.\n3. **Cyber espionage:** East German hackers may engage in cyber espionage activities, targeting NATO's military operations and gathering sensitive information on alliance planning and strategy.\n\n**RECOMMENDATIONS:**\n\nIn light of this analysis, we recommend that NATO take the following steps to enhance its cyber security:\n\n1. **Enhance communication network security:** Implement advanced encryption protocols and strengthen network access controls to prevent East German hackers from exploiting vulnerabilities.\n2. **Improve insider threat mitigation:** Implement robust insider threat detection and mitigation measures to prevent East German hackers from infiltrating NATO's personnel.\n3. **Develop cyber defense capabilities:** Enhance NATO's cyber defense capabilities, including the development of advanced threat detection and response systems.\n\n**CONCLUSION:**\n\nThe escalating cyber threat from East Germany demands a comprehensive and proactive response from NATO. By enhancing communication network security, improving insider threat mitigation, and developing cyber defense capabilities, the alliance can effectively counter this growing threat and maintain its credibility as a deterrent against potential aggression.\n\n**DISTRIBUTION:**\n\nThis report is classified TOP SECRET and distributed to:\n\n* NATO Strategic Commanders\n* NATO Cyber Defense Agency\n* Alliance Cyber Security Committee\n* National Intelligence Agencies\n\n**ARCHIVAL:** This report will be archived in the Nightingale Historical Record, accessible to authorized personnel with TOP SECRET clearance.\n\n**REVISION HISTORY:**\n\nThis report supersedes all previous analysis on East German cyber capabilities and NATO vulnerabilities. A revised version of this report will be issued upon new information or significant changes to the analysis.\n\n**AUTHENTICATION:**\n\nThis report has been authenticated by the Signals Intelligence Division, Project Nightingale. Authentication code: S-123-456-789.", "metadata": {"document_creation_date": "2022-08-02", "originating_division": "Signals Intelligence", "classification_level": "Top Secret", "target_entity": "East Germany", "event_date": "2020-12-14", "authoring_agent_id": "Viper-6", "mission_priority": 4}}
{"id": "doc_00000057", "type": "Field Contact Report", "content": "**Field Contact Report**\n\n**Classification Level:** Top Secret\n**Mission Priority:** 1\n**Originating Division:** Covert Operations\n**Document Creation Date:** 2023-04-29\n**Event Date:** 2023-10-27\n\n**Target Entity:** Soviet Union\n\n**Encounter Summary:**\n\nOn 2023-10-27, our asset, codename Nightingale-12, provided critical intelligence on Soviet military mobilization in Eastern Europe. This report compares and contrasts with similar cases, highlighting unique features and differences.\n\n**Encounter Details:**\n\nNightingale-12, a high-ranking official within the Soviet military, revealed that a significant mobilization of troops is underway in Eastern Europe, with a focus on the Polish and Czech borders. This information is consistent with previous reports from asset Nightingale-7, who indicated a heightened state of alertness among Soviet military personnel in the region.\n\n**Comparison with Similar Cases:**\n\n1. **Nightingale-7's Report (2022-06-15):** Similar reports from Nightingale-7 in June 2022 indicated a heightened state of alertness among Soviet military personnel in Eastern Europe, with a focus on the Polish and Czech borders. However, Nightingale-12's report suggests a more significant mobilization effort, with a greater emphasis on military readiness.\n2. **Asset Raven-9's Report (2019-02-20):** Raven-9, a mid-level official within the Soviet intelligence community, reported on a similar mobilization effort in Eastern Europe, but with a greater focus on strategic military planning. Nightingale-12's report highlights the operational aspects of the mobilization, including troop movements and equipment deployment.\n3. **Encounter with Asset Phoenix-11 (2018-09-10):** Phoenix-11, a high-ranking official within the Soviet military, reported on a similar mobilization effort in Eastern Europe, but with a greater emphasis on tactical military operations. Nightingale-12's report highlights the strategic implications of the mobilization, including the potential for a wider conflict.\n\n**Unique Features and Differences:**\n\n1. **Scope of Mobilization:** Nightingale-12's report suggests a more significant mobilization effort than previous reports, with a greater emphasis on military readiness and operational capabilities.\n2. **Focus on Eastern Europe:** Nightingale-12's report highlights the focus on the Polish and Czech borders, whereas previous reports have emphasized the importance of the Baltic States and Ukraine.\n3. **Strategic Implications:** Nightingale-12's report highlights the strategic implications of the mobilization, including the potential for a wider conflict and the involvement of NATO forces.\n\n**Recommendations:**\n\n1. **Urgent Review of NATO Military Readiness:** In light of Nightingale-12's report, we recommend an urgent review of NATO military readiness, with a focus on the deployment of troops and equipment to Eastern Europe.\n2. **Intelligence Gathering:** We recommend continued intelligence gathering efforts to confirm the scope and focus of the Soviet mobilization, as well as the strategic implications of the mobilization.\n3. **Strategic Planning:** We recommend strategic planning efforts to address the potential for a wider conflict, including the development of contingency plans and the deployment of assets to support NATO forces.\n\n**Conclusion:**\n\nNightingale-12's report provides critical intelligence on Soviet military mobilization in Eastern Europe, highlighting unique features and differences compared to similar cases. We recommend urgent review of NATO military readiness, continued intelligence gathering efforts, and strategic planning to address the potential for a wider conflict.\n\n**Document Control:**\n\nThis report is classified Top Secret and is intended for the eyes of authorized personnel only. Distribution is restricted to the Covert Operations Division, with copies sent to the Central Intelligence Directorate and the NATO Intelligence Division.\n\n**Signature:**\n\nThis report is signed by the author, Nightingale-5, a senior case officer within the Covert Operations Division.\n\n**Distribution:**\n\n* Covert Operations Division\n* Central Intelligence Directorate\n* NATO Intelligence Division\n\n**Document Number:** CO-2023-04-29-001", "metadata": {"event_date": "2023-10-27", "document_creation_date": "2023-04-29", "authoring_agent_id": "Phoenix-11", "target_entity": "Soviet Union", "classification_level": "Top Secret", "mission_priority": 1, "originating_division": "Covert Operations"}}
{"id": "doc_00000058", "type": "Agent Profile Dossier", "content": "**AGENT PROFILE DOSSIER: NIGHTINGALE-14**\n\n**Document Creation Date:** 2021-02-23\n**Originating Division:** Covert Operations\n**Classification Level:** Confidential\n**Event Date:** 2023-11-15\n**Mission Priority:** 1\n\n**Agent Summary:**\n\nNightingale-14, codename \"Nova,\" is a senior case officer with extensive experience in Eastern European operations. Initially recruited in 2015, Nova demonstrated exceptional talent and adaptability, quickly rising through the ranks to become a key asset in the Covert Operations Division.\n\n**Recruitment History:**\n\nNova's recruitment occurred during a high-stakes operation in Budapest, Hungary. Initially, Nova worked as a freelance journalist, covering events in the region. Covert Operations Division (COD) agents identified Nova's exceptional networking skills and linguistic abilities, which made them an ideal candidate for recruitment. After a series of carefully orchestrated meetings, Nova agreed to cooperate with COD.\n\n**Operational Assignments:**\n\nNova's early assignments focused on gathering intelligence from high-ranking officials within the Hungarian government. Their skills were soon recognized by senior leadership, and Nova began working on more complex operations in Poland, Romania, and Bulgaria. In 2020, Nova led a high-risk operation in Prague, infiltrating a Czech intelligence agency and providing critical information on their operations.\n\n**Psychological Assessments:**\n\nNova's psychological assessments indicate exceptional cognitive abilities, with a high IQ and strong analytical skills. Their personality profile shows a high level of assertiveness, confidence, and adaptability. However, Nova's assessments also reveal a deep-seated need for control and a tendency to push boundaries, which has led to concerns about their potential for reckless behavior.\n\n**Performance Evaluations:**\n\nNova's performance evaluations demonstrate exceptional results, with a 95% success rate in their operations. However, there have been instances where Nova's actions have raised concerns about their judgment and loyalty. In one instance, Nova was accused of compromising a fellow agent's cover, which led to a thorough investigation.\n\n**Personal Background:**\n\nNova's personal background is shrouded in mystery. Little is known about their family or early life. COD agents have reported that Nova's past is marked by a complex web of relationships and connections, which have made it difficult to establish a clear picture of their motivations and allegiances.\n\n**Potential Vulnerabilities:**\n\nNova's vulnerabilities include a deep-seated fear of failure, which can lead to impulsive decisions. Additionally, Nova's tendency to push boundaries and disregard protocol has raised concerns about their ability to maintain operational security.\n\n**Investigation Questions:**\n\n1. What is the nature of Nova's relationship with their handler, Agent Phoenix-11?\n2. Why did Nova compromise the cover of fellow agent Raven-9 in the Budapest operation?\n3. What are the true motives behind Nova's actions in Prague, and how do they align with COD's strategic objectives?\n\n**Solutions and Findings:**\n\nAfter conducting a thorough investigation, we have found that Nova's relationship with their handler, Agent Phoenix-11, is strong but complex. Nova relies heavily on Phoenix-11 for support and guidance, which has created a codependent dynamic.\n\nRegarding the Budapest operation, Nova compromised Raven-9's cover due to a combination of factors, including a desire for control and a need for validation. This incident highlights the need for improved training and support for agents in high-pressure situations.\n\nIn Prague, Nova's actions were motivated by a desire to prove themselves as a key asset in the region. While this ambition is admirable, it has led to concerns about Nova's potential for reckless behavior.\n\n**Recommendations:**\n\nBased on our findings, we recommend the following:\n\n1. Provide Nova with additional training and support to address their need for control and tendency to push boundaries.\n2. Re-evaluate Nova's relationship with Agent Phoenix-11 to ensure that it is not creating a codependent dynamic.\n3. Conduct a thorough review of Nova's past operations to identify potential areas for improvement and risk mitigation.\n\n**Action Items:**\n\n1. Schedule a meeting with Nova and Agent Phoenix-11 to discuss the findings of this investigation and provide recommendations for improvement.\n2. Conduct a thorough review of Nova's past operations to identify potential areas for improvement and risk mitigation.\n3. Develop a plan to provide Nova with additional training and support to address their need for control and tendency to push boundaries.\n\n**Conclusion:**\n\nThe investigation into Nightingale-14 has revealed a complex web of relationships, motivations, and vulnerabilities. While Nova's skills and experience make them an invaluable asset to COD, their behavior and decision-making processes raise concerns about their potential for reckless behavior. By addressing these issues and providing Nova with the necessary support and training, we can ensure that they continue to contribute to COD's strategic objectives while minimizing the risk of operational compromise.", "metadata": {"document_creation_date": "2021-02-23", "authoring_agent_id": "Raven-9", "originating_division": "Covert Operations", "classification_level": "Confidential", "event_date": "2023-11-15", "mission_priority": 1}}
{"id": "doc_00000059", "type": "Field Contact Report", "content": "**FIELD CONTACT REPORT**\n\n**Document ID:** FCR-2024-001\n\n**Document Creation Date:** 2024-05-05\n\n**Target Entity:** Soviet Union\n\n**Classification Level:** TOP SECRET\n\n**Mission Priority:** 1 (High)\n\n**Originating Division:** Signals Intelligence\n\n**Date of Event:** 2020-01-21\n\n**Author:** Sparrowhawk-3, Signals Intelligence Specialist\n\n**Summary:**\n\nThis Field Contact Report outlines a high-priority encounter with a Soviet asset on January 21, 2020. The asset, codename: Nightshade-4 (NS-4), revealed critical information regarding Soviet signals intelligence operations in the Baltic region. The meeting, conducted in a secure dead drop location, yielded actionable intelligence and provided valuable insights into Soviet communications.\n\n**Event Overview:**\n\nNS-4, an experienced asset with a proven track record of providing accurate and timely intelligence, contacted Signals Intelligence on the designated date. The meeting, which lasted approximately 30 minutes, took place in a secure location within the Warsaw Pact-controlled zone. Sparrowhawk-3 (SH-3) facilitated the meeting, ensuring proper security procedures were followed.\n\n**Key Findings:**\n\n1.  **Soviet Signals Intelligence Operations:** NS-4 reported that the Soviet Union has expanded its signals intelligence operations in the Baltic region, focusing on intercepting NATO communications. This information aligns with previous intelligence, indicating a heightened emphasis on signals intelligence.\n2.  **Baltic Region Communications Network:** NS-4 provided detailed information about the Soviet communications network in the Baltic region, including the use of underwater cables and satellite communications. This data will aid in the development of more effective counter-measures against Soviet signals intelligence operations.\n3.  **Asset Recruitment Efforts:** NS-4 revealed that the Soviets are actively recruiting new assets within NATO forces, focusing on personnel with access to sensitive information. This information highlights the need for increased vigilance and counter-intelligence efforts.\n4.  **Communication Protocols:** NS-4 shared information about Soviet communication protocols, including the use of encryption methods and secure communication channels. This knowledge will enable Signals Intelligence to develop more effective techniques for intercepting and decoding Soviet communications.\n\n**Measurable Intelligence:**\n\n*   **NS-4's credibility rating:** A- (Confirmed by multiple independent sources)\n*   **Source access rating:** 1 (Direct access)\n*   **Network penetration index:** 80 (High-level access to Soviet signals intelligence operations)\n*   **Operational security quotient:** 40 (Moderate risk of compromise)\n\n**Recommendations:**\n\n1.  **Intensify Signals Intelligence Operations:** Based on NS-4's information, Signals Intelligence should increase its efforts to intercept and decode Soviet communications in the Baltic region.\n2.  **Enhance Counter-Intelligence Efforts:** The revelation of Soviet asset recruitment efforts within NATO forces necessitates increased counter-intelligence measures to prevent potential compromises.\n3.  **Develop Counter-Measures:** Using the information provided by NS-4, Signals Intelligence should develop more effective counter-measures against Soviet signals intelligence operations.\n\n**Distribution:**\n\nThis Field Contact Report will be distributed to the following entities:\n\n*   **Signals Intelligence Division:** For immediate action and further analysis\n*   **Counter-Espionage Division:** For increased counter-intelligence efforts\n*   **Research & Analysis Division:** For strategic analysis and development of counter-measures\n*   **Division Chiefs:** For situational awareness and strategic planning\n\n**Document Control:**\n\nThis document is classified TOP SECRET and", "metadata": {"event_date": "2020-01-21", "document_creation_date": "2024-05-05", "authoring_agent_id": "Raven-9", "target_entity": "Soviet Union", "classification_level": "Top Secret", "mission_priority": 1, "originating_division": "Signals Intelligence"}}
{"id": "doc_00000060", "type": "Operational Debriefing", "content": "**CLASSIFIED DOCUMENT**\n\n**PROJECT NIGHTINGALE**\n**OPERATIONAL DEBRIEFING**\n**DOC ID:** NIGHTINGALE-12345\n**CREATED:** 2023-05-10\n**MISSION PRIORITY:** 2\n**ORIGINATING DIVISION:** COVERT OPERATIONS\n**CLASSIFICATION LEVEL:** SECRET\n**EVENT DATE:** 2023-03-24\n**TARGET ENTITY:** SOVIET UNION\n\n**MISSION SUMMARY:**\n\nOperation Nightingale-7 (NN-7) aimed to infiltrate the Soviet Union's advanced research facility at Novosibirsk-12, gathering intelligence on their cutting-edge technology and capabilities. On 2023-03-24, a team of two agents, codenamed 'Nova' and 'Aurora,' executed a high-risk, high-reward mission to breach the facility's outer perimeter and establish a secure communication link.\n\n**EXECUTION DETAILS:**\n\n1. **Agent Deployment:** Agents Nova and Aurora were transported to the target area via a specially modified UH-60 Black Hawk helicopter (Serial Number: 84-24055). The aircraft, crewed by experienced US Army personnel, landed at an agreed-upon safe location approximately 10 km from the perimeter.\n2. **Perimeter Breach:** Agents Nova and Aurora, equipped with custom-made lock-picks and cutting tools, successfully breached the outer perimeter fence using a combination of stealth and expertise. The total duration of the breach sequence was 3 minutes and 12 seconds.\n3. **Secure Communication Link:** Agents established a secure communication link using a custom-built, high-gain antenna system (HGA-12) and a modified Motorola handheld radio (Model: AN/PRC-152). The link was maintained for a total of 45 minutes and 21 seconds, during which time agents transmitted real-time intelligence to Nightingale HQ.\n4. **Facility Infiltration:** Agents, utilizing their advanced training and equipment, infiltrated the facility, gathering critical intelligence on the Soviet Union's advanced research and development projects.\n\n**CHALLENGES ENCOUNTERED:**\n\n1. **Hostile Surveillance:** Agents detected a Soviet security team (approx. 4 personnel) patrolling the perimeter 12 minutes after breach. The team successfully evaded detection and continued the mission.\n2. **Equipment Malfunction:** Agent Aurora's HGA-12 antenna system malfunctioned due to a faulty connection. The issue was rapidly resolved using a spare part and on-site repair.\n3. **Communication Interference:** Agents experienced minor communication interference from an unknown source, which was mitigated by switching to a secondary frequency.\n\n**IMMEDIATE RESULTS:**\n\n1. **Intelligence Gathering:** Agents transmitted critical intelligence on the Soviet Union's advanced research and development projects, including details on their hypersonic missile program and next-generation satellite technology.\n2. **Secure Communication Link:** The secure communication link established by agents enabled real-time transmission of intelligence to Nightingale HQ, facilitating rapid analysis and response.\n\n**LESSONS LEARNED:**\n\n1. **Enhanced Communication Protocols:** The mission highlighted the importance of robust communication protocols, including contingency planning for equipment malfunctions and communication interference.\n2. **Advanced Training:** Agents demonstrated the value of advanced training in infiltration, surveillance, and communication techniques.\n3. **Equipment Optimization:** The mission underscored the need for continuous equipment optimization, including the development of advanced lock-picks and cutting tools.\n\n**ANALYTICAL FINDINGS:**\n\n1. **Soviet Research and Development Capabilities:** The intelligence gathered indicates a significant advancement in the Soviet Union's research and development capabilities, particularly in the areas of hypersonic missile technology and next-generation satellite systems.\n2. **Facility Security:** The mission demonstrated the effectiveness of the Soviet Union's facility security measures, highlighting the need for continued evaluation and adaptation of Nightingale's infiltration techniques.\n3. **Hostile Surveillance:** The detection of Soviet security personnel during the mission emphasizes the importance of situational awareness and adaptability in high-risk operations.\n\n**CONCLUSION:**\n\nOperation Nightingale-7 successfully gathered critical intelligence on the Soviet Union's advanced research and development projects. The mission highlights the importance of advanced training, equipment optimization, and robust communication protocols in high-risk, high-reward operations. The findings and lessons learned from this mission will be integrated into future Nightingale operations, ensuring continued adaptability and effectiveness in the face of evolving threats.\n\n**AUTHENTICATION:**\n\nThis document has been authenticated by the Nightingale Operations Director, [Redacted]. The original document is stored in the Nightingale Archives.\n\n**DISTRIBUTION:**\n\nThis document is classified SECRET and is distributed to authorized personnel with a need-to-know clearance.\n\n**DESTRUCTION NOTICE:**\n\nThis document is to be destroyed by incineration or other approved methods after reading. Electronic copies are to be deleted and wiped from all systems.\n\n**Verification Code:** NIGHTINGALE-12345-Verification-Code-Alpha", "metadata": {"document_creation_date": "2023-05-10", "authoring_agent_id": "Orion-5", "mission_priority": 2, "originating_division": "Covert Operations", "classification_level": "Secret", "event_date": "2023-03-24", "target_entity": "Soviet Union"}}
{"id": "doc_00000061", "type": "Operational Debriefing", "content": "**Operational Debriefing Document**\n\n**Document Creation Date:** 2022-11-10\n**Mission Priority:** 1\n**Originating Division:** Covert Operations\n**Classification Level:** Top Secret\n**Event Date:** 2022-12-03\n**Target Entity:** Soviet Union\n\n**Mission Name:** Operation: Frostbite\n\n**Mission Objective:**\n\nIn response to rising Soviet military presence in Eastern Europe, Nightingale's Covert Operations Division embarked on Operation Frostbite, a high-priority mission to infiltrate and gather critical intelligence on the Soviet Union's latest military doctrine. Our objective was to establish a deep-cover asset within the Soviet General Staff and retrieve sensitive documents detailing the Kremlin's strategic intentions.\n\n**Pre-Mission Planning (2022-11-01 - 2022-11-25)**\n\nOur planning phase involved meticulous research and analysis of the Soviet military hierarchy, focusing on potential entry points and vulnerable targets. We identified a key asset, codenamed 'Nova', a disillusioned Soviet officer who had expressed dissatisfaction with the current regime. Our research indicated Nova's growing dissatisfaction with the Soviet military's increasing aggression and his willingness to collaborate with Western intelligence.\n\n**Mission Execution (2022-12-03)**\n\nOn the designated mission day, our team of seasoned operatives, led by experienced case officer Nightingale-7, arrived in Berlin and began to establish a secure communication network. They made contact with Nova, who agreed to meet at a pre-arranged safe house. The operation proceeded smoothly, with Nightingale-7 and his team expertly handling the asset's nerves and convincing him to cooperate.\n\n**Challenges and Complications**\n\nHowever, unforeseen complications arose when a suspicious KGB agent began to follow Nova, compromising the operation's security. Our team swiftly adapted, employing a well-rehearsed contingency plan to mislead the KGB agent and maintain the integrity of the mission.\n\n**Immediate Results**\n\nThe mission concluded successfully, with Nova delivering sensitive documents detailing the Soviet military doctrine. Our team carefully transmitted the retrieved materials to Langley for further analysis. The documents revealed a significant shift in the Soviet military's strategy, indicating a growing emphasis on conventional warfare and a potential increase in Soviet military presence in Eastern Europe.\n\n**Lessons Learned**\n\nOperation Frostbite highlighted the importance of adaptability and contingency planning in high-stakes covert operations. Our team's quick thinking and expertise in handling complex scenarios ensured the mission's success. Additionally, the operation underscored the value of thorough research and analysis in identifying potential entry points and vulnerable targets.\n\n**Recommendations for Future Operations**\n\nBased on the success of Operation Frostbite, we recommend:\n\n1. **Enhanced asset screening**: Implement more rigorous screening procedures to ensure the reliability and trustworthiness of recruited assets.\n2. **Contingency planning**: Develop and regularly update contingency plans to address potential complications and security breaches.\n3. **Advanced communication protocols**: Explore the development of more secure communication channels to minimize the risk of interception and compromise.\n\n**Conclusion**\n\nOperation Frostbite represents a significant achievement in Nightingale's commitment to gathering critical intelligence on the Soviet Union. The mission's success underscores the importance of adaptability, thorough planning, and expertise in covert operations. This debriefing serves as a testament to the dedication and professionalism of our team, and we are confident that the lessons learned from this operation will inform and improve our future missions.\n\n**Distribution:**\n\nThis operational debriefing will be distributed to:\n\n- Nightingale's Covert Operations Division\n- Langley's Strategic Intelligence Branch\n- NATO Intelligence Division\n- Allied Intelligence Services\n\n**Archive:**\n\nThis document will be archived in the Nightingale Historical Record, accessible to authorized personnel with a Top Secret clearance.\n\n**Classification:**\n\nThis document is classified TOP SECRET. Distribution is restricted to personnel with a Level 3 clearance or higher.\n\n**Confidentiality:**\n\nThis document contains sensitive information and should be handled with extreme caution. All personnel with access to this document are required to maintain confidentiality and adhere to Nightingale's operational security protocols.", "metadata": {"document_creation_date": "2022-11-10", "authoring_agent_id": "Raven-9", "mission_priority": 1, "originating_division": "Covert Operations", "classification_level": "Top Secret", "event_date": "2022-12-03", "target_entity": "Soviet Union"}}
{"id": "doc_00000062", "type": "Agent Profile Dossier", "content": "**CLASSIFIED DOCUMENT**\n**PROJECT NIGHTINGALE**\n**AGENT PROFILE DOSSIER**\n**DOCUMENT ID: TOP-2022-003**\n**CREATION DATE: 2022-03-06**\n**ORIGINATING DIVISION: TECHNICAL OPERATIONS**\n**CLASSIFICATION LEVEL: TOP SECRET**\n**EVENT DATE: 2022-06-14**\n**MISSION PRIORITY: 1**\n\n**AGENT DETAILS**\n\n* **AGENT CODE NAME:** Nightingale-8 ( Alias: Dr. Maria Rodriguez)\n* **REAL NAME:** Maria Rodriguez de Santiago\n* **NATIONALITY:** Mexican\n* **DATE OF BIRTH:** 1985-02-12\n* **SEX:** Female\n\n**RECRUITMENT HISTORY**\n\nNightingale-8 was recruited in 2018 through a complex operation involving multiple assets and technical surveillance. The initial contact was made through a dead drop in a park in Mexico City, where she was approached by a cutout (Agent-4). The recruitment process was carefully managed by a junior case officer (Agent-3) under the supervision of a senior case officer (Nightingale-7). The agent's initial motivation was to provide technical expertise in support of a counter-narcotics operation.\n\n**OPERATIONAL ASSIGNMENTS**\n\nNightingale-8 has been assigned to multiple operations, including:\n\n* **Operation Nightshade** (2019): Provided technical support for a mole hunt operation targeting a suspected KGB agent.\n* **Operation Luminari** (2020): Conducted surveillance on a high-priority target in Mexico City.\n* **Operation Azure** (2021): Provided technical expertise in support of a counter-terrorism operation.\n\n**PSYCHOLOGICAL ASSESSMENTS**\n\nNightingale-8 has undergone multiple psychological assessments, including:\n\n* **Operational Personality Inventory (OPI)**: Scored 85% in the \"confident\" category and 90% in the \"adventurous\" category.\n* **Polygraph Examination Report**: Passed with a 99.5% confidence level.\n\n**PERFORMANCE EVALUATIONS**\n\nNightingale-8 has received multiple performance evaluations, including:\n\n* **Division Operational Report** (2020): Rated 95% in operational effectiveness and 92% in teamwork.\n* **Station Intelligence Bulletin** (2021): Rated 98% in technical expertise and 96% in communication skills.\n\n**PERSONAL BACKGROUND**\n\nNightingale-8 has a complex personal background, including:\n\n* **Family:** Married to a Mexican national with two children.\n* **Education:** Ph.D. in computer science from the University of Mexico.\n* **Work Experience:** Formerly worked as a researcher at a Mexican university.\n\n**VULNERABILITIES**\n\nNightingale-8 has several vulnerabilities, including:\n\n* **Financial:** Has a mortgage on her home and is financially dependent on her husband.\n* **Personal:** Has a close relationship with her children and is emotionally vulnerable.\n* **Operational:** Has a history of operational mistakes and has been involved in several close calls.\n\n**COMPARATIVE ANALYSIS**\n\nNightingale-8's profile is similar to that of Nightingale-7 in several ways, including:\n\n* **Recruitment history:** Both agents were recruited through dead drops and were initially motivated by a desire to provide technical expertise.\n* **Operational assignments:** Both agents have been assigned to multiple operations, including counter-narcotics and counter-terrorism operations.\n* **Psychological assessments:** Both agents scored highly on the OPI and polygraph examinations.\n\nHowever, Nightingale-8's profile also has several unique features, including:\n\n* **Technical expertise:** Nightingale-8 has a higher level of technical expertise than Nightingale-7, with a Ph.D. in computer science and extensive experience in the field.\n* **Operational effectiveness:** Nightingale-8 has a higher level of operational effectiveness than Nightingale-7, with a 95% rating in operational effectiveness and a 92% rating in teamwork.\n* **Vulnerabilities:** Nightingale-8 has several vulnerabilities that are not present in Nightingale-7's profile, including a mortgage on her home and a close relationship with her children.\n\n**CONCLUSION**\n\nNightingale-8 is a highly skilled and effective agent with a complex personal background and several vulnerabilities. Her profile is similar to that of Nightingale-7 in several ways, but also has several unique features that set her apart. Further analysis and monitoring are required to ensure that Nightingale-8 remains a valuable asset to the agency.\n\n**RECOMMENDATIONS**\n\nBased on the analysis of Nightingale-8's profile, the following recommendations are made:\n\n* **Continued monitoring:** Nightingale-8 should be continued to be monitored and evaluated on a regular basis to ensure that she remains a valuable asset to the agency.\n* **Operational assignments:** Nightingale-8 should be assigned to operations that utilize her technical expertise and operational skills.\n* **Vulnerability management:** Nightingale-8's vulnerabilities should be addressed through a comprehensive risk management plan.\n\n**CLASSIFICATION LEVEL**\n\nThis document is classified TOP SECRET and is not to be shared with anyone without the proper clearance.\n\n**DISTRIBUTION**\n\nThis document is to be distributed to the following individuals:\n\n* **Nightingale-7:** Senior case officer and Nightingale-8's handler.\n* **Agent-3:** Junior case officer who recruited Nightingale-8.\n* **Agent-4:** Cutout who initially approached Nightingale-8.\n* **Division Chief:** Technical Operations Division.\n\n**ARCHIVAL**\n\nThis document is to be archived in the **Central Personnel Archive** with access logged through **Document Control System DCS-9**.", "metadata": {"document_creation_date": "2022-03-06", "authoring_agent_id": "Nightingale-7", "originating_division": "Technical Operations", "classification_level": "Top Secret", "event_date": "2020-06-14", "mission_priority": 1}}
{"id": "doc_00000063", "type": "Field Contact Report", "content": "**Field Contact Report**\n\n**Document ID:** NIGHT-FCR-20230220-01\n**Event Date:** 2022-01-26\n**Document Creation Date:** 2023-02-20\n**Target Entity:** GRU\n**Classification Level:** Eyes Only\n**Mission Priority:** 4\n**Originating Division:** Covert Operations\n\n**Incident Summary:**\n\nOn 2022-01-26, I (Operational ID: Nightingale-7) encountered a GRU asset, codename: 'Nova-1,' in a secure location in East Berlin. The meeting's purpose was to discuss potential recruitment opportunities within the GRU's military intelligence branch. Nova-1 provided initial intelligence on emerging GRU interests in Eastern Europe, including a focus on NATO's Eastern European Defense Initiative.\n\n**Challenge:**\n\nDuring the meeting, Nova-1 revealed an unusual interest in the activities of a specific GRU officer, codename: 'Lynx-3.' Nova-1 described Lynx-3 as a 'rising star' within the GRU, with an increasing presence in high-level decision-making circles. This information sparked concerns about potential GRU penetration of NATO's Eastern European Defense Initiative.\n\n**Investigation:**\n\nTo further investigate Lynx-3's role and potential influence within the GRU, I initiated a series of discreet inquiries. I accessed the GRU's internal communications network and intercepted several encrypted messages referencing Lynx-3's involvement in a top-secret project codenamed 'Operation: Aurora.' The messages hinted at a significant increase in GRU military presence along the Eastern European border.\n\n**Findings:**\n\nPreliminary analysis suggests that Operation: Aurora may be a GRU-backed effort to establish a network of sleeper agents within NATO's Eastern European Defense Initiative. Lynx-3's involvement in the operation raises concerns about potential GRU penetration of NATO's highest levels. Further investigation is required to fully understand the scope and implications of Operation: Aurora.\n\n**Action Items:**\n\n1. **Recruit additional assets** within the GRU to gather more information on Operation: Aurora and Lynx-3's role.\n2. **Analyze intercepted communications** to identify potential GRU sleeper agents within NATO's Eastern European Defense Initiative.\n3. **Develop a comprehensive counter-intelligence strategy** to address potential GRU penetration of NATO's Eastern European Defense Initiative.\n\n**Classification Notes:**\n\nThis report contains sensitive information regarding GRU operations and potential NATO penetration. Distribution is restricted to senior personnel with a need-to-know clearance.\n\n**Recommendations:**\n\nDue to the potential severity of the situation, I recommend that the Nightingale-7 case file be elevated to a Priority 1 mission. This will ensure the necessary resources and attention are allocated to investigate and counter the GRU's Operation: Aurora.\n\n**Signing Officer:**\n\nNightingale-7 (Operational ID: Nightingale-7)", "metadata": {"event_date": "2022-01-26", "document_creation_date": "2023-02-20", "authoring_agent_id": "Orion-5", "target_entity": "GRU", "classification_level": "Eyes Only", "mission_priority": 4, "originating_division": "Covert Operations"}}
{"id": "doc_00000064", "type": "Operational Debriefing", "content": "**CLASSIFIED DOCUMENT**\n\n**OPERATIONAL DEBRIEFING**\n\n**PROJECT NIGHTINGALE**\n\n**MISSION CODE NAME:** Operation Berlin Spark\n\n**DOCUMENT CREATION DATE:** 30 June 2024\n\n**MISSION PRIORITY:** 2\n\n**ORIGINATING DIVISION:** Logistics & Support\n\n**CLASSIFICATION LEVEL:** Top Secret\n\n**EVENT DATE:** 25 May 2023\n\n**TARGET ENTITY:** East Germany\n\n**OPERATIONAL SUMMARY:**\n\nOperation Berlin Spark, conducted on 25 May 2023, was a successful clandestine operation aimed at infiltrating East German industrial espionage networks. The mission, led by Field Officer Nightingale-7, involved the deployment of a deep-cover operative, codenamed Shadow-12, to gather intelligence on East German military-civilian technology exchange programs. This report provides a comprehensive overview of the mission's objectives, execution, challenges, immediate results, and lessons learned.\n\n**OBJECTIVES:**\n\n1. Infiltrate East German industrial espionage networks.\n2. Gather intelligence on military-civilian technology exchange programs.\n3. Establish a reliable source for future operations.\n\n**EXECUTION DETAILS:**\n\n1. Shadow-12, posing as a West German engineer, established contact with a high-ranking East German official through a series of carefully orchestrated social encounters.\n2. Over several weeks, Shadow-12 gained the official's trust, gaining access to classified information on East German military-civilian technology collaborations.\n3. Shadow-12 collected and transmitted crucial intelligence back to Nightingale-7, who coordinated with Research & Analysis to analyze and validate the information.\n\n**CHALLENGES ENCOUNTERED:**\n\n1. Hostile surveillance: Shadow-12 reported being tailed by East German counterintelligence agents on multiple occasions.\n2. Equipment failure: Shadow-12's dead drop communication device malfunctioned, requiring an emergency extraction and replacement operation.\n3. Asset nervousness: Shadow-12's cover was nearly compromised due to an unexpected encounter with a former acquaintance.\n\n**IMMEDIATE RESULTS:**\n\n1. Intelligence gathered: Shadow-12 provided critical information on East German military-civilian technology collaborations, including details on a top-secret research facility.\n2. Source establishment: Shadow-12 established a reliable source within East German industrial espionage networks.\n3. Network penetration: Nightingale-7 successfully infiltrated the East German espionage network, paving the way for future operations.\n\n**LESSONS LEARNED:**\n\n1. Effective use of social engineering tactics: Shadow-12's ability to establish a rapport with the East German official was crucial to the mission's success.\n2. Importance of contingency planning: The emergency extraction and replacement operation for Shadow-12's communication device highlighted the need for contingency planning in high-risk operations.\n3. Asset management: Nightingale-7's experience managing Shadow-12's nervousness and cover compromise underscored the importance of effective asset management in covert operations.\n\n**MEASUREMENTS & METRICS:**\n\n1. **Network Penetration Index:** 60 (indicating moderate success in infiltrating East German industrial espionage networks)\n2. **Asset Productivity Metrics:** 85 (indicating high intelligence yield from Shadow-12's activities)\n3. **Operational Security Quotient:** 75 (indicating moderate risk of mission compromise)\n\n**AUTHORING AGENT:**\n\nNightingale-7, Senior Case Officer, Berlin Operations\n\n**DISTRIBUTION:**\n\nThis report is classified Top Secret and will be distributed to authorized personnel within the Project Nightingale framework.\n\n**ARCHIVAL:**\n\nThis report will be archived in the Nightingale Historical Record and made available for future analysis and reference.\n\n**END OF REPORT**", "metadata": {"document_creation_date": "2024-06-30", "authoring_agent_id": "Ghost-1", "mission_priority": 2, "originating_division": "Logistics & Support", "classification_level": "Top Secret", "event_date": "2023-05-25", "target_entity": "East Germany"}}
{"id": "doc_00000065", "type": "Operational Debriefing", "content": "**CLASSIFIED DOCUMENT**\n**PROJECT NIGHTINGALE**\n**OPERATIONAL DEBRIEFING**\n**MISSION IDENTIFIER:** NIGHTINGALE-OP-124\n**DOCUMENT CREATION DATE:** 2022-04-16\n**MISSION PRIORITY:** 4\n**ORIGINATING DIVISION:** SPECIAL PROJECTS\n**CLASSIFICATION LEVEL:** TOP SECRET\n**EVENT DATE:** 2024-07-14\n**TARGET ENTITY:** SOVIET UNION\n\n**SUMMARY**\n\nOn 2024-07-14, Special Projects Division executed Operation NIGHTINGALE-OP-124, a high-risk covert mission aimed at infiltrating the Soviet Union's advanced radar systems. This operational debriefing provides an in-depth analysis of the mission's objectives, execution, challenges, immediate results, and lessons learned.\n\n**OBJECTIVES**\n\n1. Identify and compromise the Soviet Union's Long-Range Detection Radar (LRDR) network, specifically the P-30 system.\n2. Extract sensitive technical data on the P-30's radar frequency, pulse repetition frequency, and signal processing algorithms.\n3. Deploy a high-gain antenna to amplify the extracted signals for further analysis.\n\n**EXECUTION**\n\n1. **Reconnaissance Phase:** Utilizing an advanced imaging satellite, we obtained high-resolution photographs of the P-30 radar site, revealing its precise layout and key infrastructure components.\n2. **Deployment Phase:** A specially designed, 1.5-meter-long antenna was deployed using a high-speed, low-profile drone (HSLPD) equipped with a precision-guided, magnetically attached payload.\n3. **Signal Extraction Phase:** The HSLPD hovered at a distance of 500 meters from the P-30 site, deploying the antenna and collecting 10 minutes of radar signals at a sampling rate of 100 MHz.\n4. **Data Transmission Phase:** The collected signals were transmitted back to our operations center through a high-gain, directional antenna, utilizing a modified, 256-QAM modulated, 10-GHz frequency-hopping spread spectrum communication protocol.\n\n**CHALLENGES ENCOUNTERED**\n\n1. **Anti-Drone Countermeasures:** The Soviet Union's advanced air defense systems engaged our HSLPD, necessitating a rapid adaptation of the drone's trajectory and altitude to evade detection.\n2. **Signal Interference:** Unforeseen electromagnetic interference from a nearby, Soviet-operated, 500-kW, 50-MHz radio transmitter compromised the quality of the extracted radar signals, requiring an additional 30 minutes to stabilize the signal-to-noise ratio (SNR) and optimize data acquisition.\n3. **Antenna Deployment Complications:** The high-speed deployment of the antenna resulted in a 3.5\u00b0 deviation from the intended trajectory, necessitating an on-the-fly adjustment of the antenna's azimuth and elevation angles to ensure optimal signal acquisition.\n\n**IMMEDIATE RESULTS**\n\n1. **Radar Signal Extraction:** Successful extraction of 30 minutes of P-30 radar signals, yielding a SNR of 12.5 dB and a signal bandwidth of 5 MHz.\n2. **High-Gain Antenna Deployment:** Successful deployment and operation of the 1.5-meter-long, high-gain antenna, achieving a signal-to-noise ratio improvement of 8 dB.\n3. **Data Transmission:** Successful transmission of the extracted radar signals back to our operations center, achieving a bit error rate (BER) of 1.2 \u00d7 10^(-6) and a data transfer rate of 2.5 Gbps.\n\n**LESSONS LEARNED**\n\n1. **Advanced Reconnaissance Techniques:** Utilizing high-resolution imaging satellites for reconnaissance purposes enabled us to gather critical information on the P-30 radar site's layout and infrastructure components.\n2. **High-Speed Deployment of Antennas:** The deployment of high-gain antennas using high-speed, low-profile drones (HSLPDs) proved effective in acquiring optimal radar signals, but requires careful planning and execution to avoid signal interference and antenna deployment complications.\n3. **Advanced Signal Processing Algorithms:** Utilizing advanced signal processing algorithms and machine learning techniques is essential for optimizing the quality of extracted radar signals and improving the SNR.\n\n**CONCLUSION**\n\nOperation NIGHTINGALE-OP-124 successfully compromised the Soviet Union's P-30 radar system, extracting sensitive technical data and deploying a high-gain antenna. This mission demonstrates the effectiveness of advanced reconnaissance techniques, high-speed antenna deployment, and advanced signal processing algorithms in achieving high-risk, high-reward covert operations.", "metadata": {"document_creation_date": "2022-04-16", "authoring_agent_id": "Raven-9", "mission_priority": 4, "originating_division": "Special Projects", "classification_level": "Top Secret", "event_date": "2024-07-14", "target_entity": "Soviet Union"}}
{"id": "doc_00000066", "type": "Agent Profile Dossier", "content": "**CLASSIFIED DOCUMENT**\n\n**PROJECT NIGHTINGALE**\n**AGENT PROFILE DOSIER**\n**SUBJECT: NIGHTINGALE-47**\n**CREATION DATE:** 2023-01-06\n**ORIGINATING DIVISION:** HUMAN INTELLIGENCE\n**CLASSIFICATION LEVEL:** SECRET\n**EVENT DATE:** 2021-11-14\n**MISSION PRIORITY:** 1\n\n**RECRUITMENT HISTORY**\n\nNightingale-47, codename \"Nova Star,\" was recruited on 2020-05-15 by a seasoned case officer, Sparrowhawk-3, during a high-risk dead drop operation in a secluded Prague alleyway. The agent's initial briefing emphasized the significance of infiltrating the Czech intelligence community, leveraging her extensive connections within the Ministry of Defense.\n\n**OPERATIONAL ASSIGNMENTS**\n\nNova Star's maiden operation involved gathering intelligence on a rogue Czech arms dealer, known to have ties with the Stasi. The agent skillfully navigated a complex web of connections, using her persuasive charm to extract critical information from the target. This success marked the beginning of a long and fruitful partnership between Nova Star and Project Nightingale.\n\n**PSYCHOLOGICAL ASSESSMENT**\n\nA comprehensive psychological evaluation, conducted by a certified psychologist, revealed Nova Star's exceptional adaptability, resourcefulness, and linguistic abilities. The assessment highlighted her strong sense of justice and loyalty, which motivated her to cooperate with Nightingale. However, subtle vulnerabilities emerged, including a deep-seated fear of abandonment and a propensity for emotional attachment.\n\n**PERFORMANCE EVALUATIONS**\n\nNova Star's performance has been consistently commendable, with notable successes in:\n\n1. 2020-06-20: Successfully extracted classified documents from a secure facility in Budapest.\n2. 2020-09-15: Infiltrated a high-stakes meeting between Stasi officials, providing critical insight into their operations.\n3. 2021-03-10: Coordinated the safe exfiltration of a compromised Nightingale agent from Prague.\n\n**PERSONAL BACKGROUND**\n\nNova Star's early life was marked by instability, with her family relocating frequently due to her father's diplomatic career. This nomadic upbringing fostered exceptional linguistic skills and adaptability. She holds a Master's degree in International Relations from Charles University and is fluent in five languages.\n\n**POTENTIAL VULNERABILITIES**\n\nNova Star's deep-seated fear of abandonment may compromise her performance in high-pressure situations. Additionally, her emotional attachment to a few key contacts within the Czech intelligence community could potentially create conflicts of interest.\n\n**SECURITY CLEARANCE**\n\nNova Star possesses a Top Secret clearance, granted after completing a thorough background investigation and undergoing regular polygraph examinations.\n\n**PHYSICAL CHARACTERISTICS**\n\nHeight: 5'8\"\nWeight: 130 lbs\nHair: Dark brown\nEyes: Hazel\nDistinguishing features: Small tattoo of a star on the left ankle\n\n**CONTACT INFORMATION**\n\nHandler: Sparrowhawk-3 (Primary)\nAlternate handler: Nightingale-7 (Secondary)\nSecure communication channels: Nightingale Comms Protocol (NCP-60)\n\n**CONCLUSION**\n\nNightingale-47, codename \"Nova Star,\" has emerged as a valuable asset within Project Nightingale, consistently delivering high-quality intelligence and demonstrating exceptional adaptability. While vulnerabilities exist, her strengths far outweigh potential weaknesses. Continued support and guidance from her handlers will be crucial in maintaining her effectiveness and ensuring the success of future operations.\n\n**RECOMMENDATIONS**\n\n1. Maintain regular communication with Nova Star, utilizing secure channels to discuss mission details and provide emotional support.\n2. Schedule periodic psychological evaluations to monitor Nova Star's mental health and address any emerging concerns.\n3. Ensure Nova Star's security clearance is regularly updated and validated to maintain Top Secret status.\n\n**ARCHIVAL INFORMATION**\n\nThis dossier will be stored in the Central Personnel Archive, accessible only to authorized personnel with a Secret clearance or higher. Distribution of this document is restricted to senior personnel within the Human Intelligence division.\n\n**CLASSIFICATION REMINDER**\n\nThis document is classified SECRET. Unauthorized disclosure or reproduction may result in severe consequences, including but not limited to, revocation of security clearance and possible prosecution under the Espionage Act.", "metadata": {"document_creation_date": "2023-01-06", "authoring_agent_id": "Shadow-12", "originating_division": "Human Intelligence", "classification_level": "Secret", "event_date": "2021-11-14", "mission_priority": 1}}
{"id": "doc_00000067", "type": "Field Contact Report", "content": "**Field Contact Report:**\n\n**Document ID:** FCR-2024-08-13-CE-002\n\n**Event Date:** 2024-08-13\n\n**Document Creation Date:** 2024-07-27\n\n**Target Entity:** KGB\n\n**Classification Level:** Confidential\n\n**Mission Priority:** 1\n\n**Originating Division:** Counter-Espionage\n\n**Summary:**\n\nOn 2024-08-13, our agent, codename: **Nightingale-7**, reported an unusual encounter with a suspected KGB operative in East Berlin. The agent's observations and subsequent analysis reveal striking similarities with a 1968 incident involving a similar operative, codename: **Raven-9**. This report compares and contrasts the two cases, highlighting unique features and differences.\n\n**Encounter Details:**\n\nNightingale-7 reported meeting the suspected KGB operative, identified as **Alexei Petrov**, in a Berlin caf\u00e9 on 2024-08-13. Petrov exhibited nervous behavior, frequently glancing over his shoulder. The agent noted that Petrov's attire and demeanor were consistent with those of a KGB operative. Petrov handed Nightingale-7 a small package, allegedly containing classified information, but the agent declined, sensing a potential setup.\n\n**Similarities with Raven-9:**\n\nIn 1968, Raven-9 encountered a KGB operative, codename: **Victor Kuznetsov**, in a similar Berlin caf\u00e9. Kuznetsov also displayed nervous behavior and handed Raven-9 a package containing classified information. Both incidents involved suspected KGB operatives using similar tactics and modus operandi. However, Petrov's behavior and attire were more aggressive, suggesting a different operational approach.\n\n**Differences:**\n\nNotably, Petrov's package contained a USB drive with encrypted files, whereas Kuznetsov's package contained physical documents. Additionally, Petrov's communication style was more direct, whereas Kuznetsov used a more subtle approach. These differences suggest that the KGB may be adapting their operational tactics to counter Western intelligence efforts.\n\n**Comparison with Other Cases:**\n\nA 1972 incident involving **Ghost-1**, another Nightingale agent, reported a similar encounter with a KGB operative in Prague. However, Ghost-1's operative, codename: **", "metadata": {"event_date": "2024-08-13", "document_creation_date": "2024-07-27", "authoring_agent_id": "Raven-9", "target_entity": "KGB", "classification_level": "Confidential", "mission_priority": 1, "originating_division": "Counter-Espionage"}}
{"id": "doc_00000068", "type": "Operational Debriefing", "content": "**CLASSIFIED DOCUMENT**\n**PROJECT NIGHTINGALE**\n**Signals Intelligence Division**\n**Document Creation Date: 2020-05-10**\n**Mission Priority: 5**\n**Originating Division: Signals Intelligence**\n**Classification Level: Confidential**\n**Event Date: 2020-06-14**\n**Target Entity: East Germany**\n\n**Operational Debriefing Report:**\n\n**Operation:** _EAST GHOST_ (Signals Intelligence Operation to Monitor East German Communications)\n**Event Date:** 2020-06-14\n\n**Mission Overview:**\nOperation _EAST GHOST_ aimed to identify and intercept high-priority East German communications networks, providing real-time intelligence to inform Western strategic decisions.\n\n**Objectives:**\n\n1. Identify and establish a secure communication link with a high-ranking East German official.\n2. Intercept and decode top-secret East German communications, focusing on military and economic matters.\n3. Provide actionable intelligence to inform Western policy decisions.\n\n**Pre-Mission Planning:**\n\n- Conducted extensive research on East German communication protocols, identifying vulnerabilities in their encryption methods.\n- Developed a customized communication device to facilitate secure communication with the target official.\n- Coordinated with local assets to establish a secure meeting point for the initial contact.\n\n**Mission Execution:**\n\n- On 2020-06-14, the designated case officer, Nightingale-14, made contact with the high-ranking East German official at a secure location in East Berlin.\n- The official, known as _RED FALCON_, was persuaded to cooperate, and a secure communication link was established.\n- Nightingale-14 provided RED FALCON with a customized communication device, which allowed for the exchange of encrypted messages.\n\n**Challenges Encountered:**\n\n- RED FALCON initially expressed concerns about the risk of detection, which slowed the communication process.\n- Nightingale-14 had to employ advanced persuasion techniques to reassure RED FALCON of the secure nature of the communication device.\n\n**Immediate Results:**\n\n- Intercepted and decoded top-secret East German communications, including discussions about military mobilization and economic agreements.\n- Provided real-time intelligence to Western policymakers, informing critical decisions.\n\n**Lessons Learned:**\n\n- The importance of thorough research and planning in identifying vulnerabilities in target communication protocols.\n- The need for advanced persuasion techniques in high-stakes communication operations.\n- The value of establishing secure communication links with high-ranking officials to facilitate the exchange of sensitive information.\n\n**Mysteries and Challenges:**\n\n- RED FALCON's motivations and potential biases in providing intelligence remain unclear, raising concerns about the reliability of the information.\n- The extent to which RED FALCON's cooperation has compromised their position within the East German government is unknown.\n\n**Recommendations for Future Operations:**\n\n- Conduct thorough background checks on high-ranking officials to assess their reliability and potential biases.\n- Develop advanced persuasion techniques to address concerns about security and detection.\n- Establish secure communication links with multiple officials to ensure a diversified intelligence network.\n\n**Conclusion:**\nOperation _EAST GHOST_ demonstrated the effectiveness of Signals Intelligence operations in identifying and intercepting high-priority communications. However, concerns about the reliability of the intelligence and potential future risks associated with RED FALCON's cooperation necessitate further investigation and strategic planning.\n\n**Recommendations for Archival:**\n\n- Store this debriefing report in the **Signals Intelligence Archive**, accessible only to authorized personnel.\n- Update the **Personnel File** for Nightingale-14 to reflect their participation in Operation _EAST GHOST_.\n- File a **Technical Analysis Report** documenting the customized communication device and encryption methods used in the operation.\n\n**Distribution:**\n\n- **Signals Intelligence Division**: All personnel with need-to-know access.\n- **Research & Analysis Division**: Senior analysts with expertise in East German communications and strategic planning.\n- **Central Personnel Archive**: Stored in the **Signals Intelligence Archive**, accessible only to authorized personnel.\n\n**Verification:**\n\n- This debriefing report has been reviewed and verified by Nightingale-14, who participated in Operation _EAST GHOST_.\n- The report has been classified as **Confidential** due to the sensitive nature of the information and potential risks associated with RED FALCON's cooperation.\n\n**End of Document**", "metadata": {"document_creation_date": "2020-05-10", "authoring_agent_id": "Ghost-1", "mission_priority": 5, "originating_division": "Signals Intelligence", "classification_level": "Confidential", "event_date": "2020-06-14", "target_entity": "East Germany"}}
{"id": "doc_00000069", "type": "Operational Debriefing", "content": "**CLASSIFIED DOCUMENT**\n\n**PROJECT NIGHTINGALE - OPERATIONAL DEBRIEFING**\n\n**DOCUMENT CREATION DATE:** 2024-10-09\n**MISSION PRIORITY:** 1 (Critical)\n**ORIGINATING DIVISION:** Signals Intelligence\n**CLASSIFICATION LEVEL:** Secret\n**EVENT DATE:** 2022-04-26\n**TARGET ENTITY:** KGB\n\n**SUMMARY:**\n\nThis operational debriefing summarizes the successful execution of **Operation: Redstone** (codename: **Nightshade-1**), a high-priority signals intelligence mission conducted by the Signals Intelligence Division of Project Nightingale. The operation aimed to intercept and decode key KGB communications regarding Soviet strategic nuclear doctrine. This report provides an overview of the mission's objectives, execution, challenges, immediate results, and lessons learned.\n\n**MISSION OBJECTIVES:**\n\n1. Intercept and decode high-priority KGB communications regarding Soviet strategic nuclear doctrine.\n2. Gather intelligence on KGB communication networks and infrastructure.\n3. Establish a secure communication channel with a KGB asset (codename: **Redstone-12**) to facilitate future operations.\n\n**EXECUTION:**\n\nOn 2022-04-26, a team of six Signals Intelligence operators, led by **Sparrowhawk-3**, deployed to the designated intercept site near the Polish-Ukrainian border. The team utilized a customized **Minox X-20** camera system to capture high-resolution images of KGB communication equipment. The images were then transmitted to the **Bad Aibling Station** for processing and analysis.\n\n**CHALLENGES ENCOUNTERED:**\n\n1. **Hostile surveillance:** A KGB counterintelligence team detected the operational team and initiated a surveillance operation, forcing the team to adapt and change their extraction plan.\n2. **Equipment failure:** The Minox X-20 camera system experienced a technical malfunction, resulting in a 30-minute delay in data transmission.\n3. **Communication disruptions:** A brief communication blackout occurred due to a satellite signal loss, requiring the team to switch to a secondary communication channel.\n\n**IMMEDIATE RESULTS:**\n\n1. **Successful interception:** The team intercepted and decoded key KGB communications regarding Soviet strategic nuclear doctrine, providing valuable intelligence on the Soviet Union's nuclear capabilities.\n2. **Asset recruitment:** The team established a secure communication channel with Redstone-12, a KGB asset who agreed to provide future intelligence on KGB operations.\n3. **Network analysis:** The team gained valuable insights into KGB communication networks and infrastructure, enabling the development of more effective future operations.\n\n**LESSONS LEARNED:**\n\n1. **Improved communication protocols:** The team identified the need for more robust communication protocols to ensure seamless data transmission in high-pressure situations.\n2. **Enhanced equipment maintenance:** The team recognized the importance of regular equipment maintenance to prevent technical malfunctions during operations.\n3. **Adaptability and flexibility:** The team demonstrated adaptability and flexibility in response to changing circumstances, ensuring mission success in the face of unexpected challenges.\n\n**CONCLUSION:**\n\nOperation Redstone (Nightshade-1) was a critical success, providing valuable intelligence on KGB operations and establishing a secure communication channel with a KGB asset. The mission highlights the importance of adaptability, flexibility, and effective communication protocols in high-pressure situations. The lessons learned from this operation will inform future Signal Intelligence operations and contribute to the ongoing success of Project Nightingale.\n\n**RECOMMENDATIONS:**\n\n1. **Enhance communication protocols:** Develop and implement more robust communication protocols to ensure seamless data transmission during operations.\n2. **Improve equipment maintenance:** Regularly maintain and inspect equipment to prevent technical malfunctions during operations.\n3. **Develop asset recruitment protocols:** Establish clear guidelines for asset recruitment and management to ensure effective use of human intelligence sources.\n\n**DISTRIBUTION:**\n\nThis report is classified SECRET and will be distributed to the following personnel:\n\n* Signals Intelligence Division, Project Nightingale\n* Central Intelligence Directorate (CID)\n* NATO Intelligence Division (NID)\n* MI6 Eastern Section\n\n**ARCHIVAL:**\n\nThis report will be archived in the Project Nightingale Historical Record, Document Control System DCS-9.", "metadata": {"document_creation_date": "2024-10-09", "authoring_agent_id": "Ghost-1", "mission_priority": 1, "originating_division": "Signals Intelligence", "classification_level": "Secret", "event_date": "2022-04-26", "target_entity": "KGB"}}
{"id": "doc_00000070", "type": "Agent Profile Dossier", "content": "**CLASSIFIED DOCUMENT**\n\n**NIGHTINGALE AGENT PROFILE DOSSIER**\n\n**CREATION DATE:** 2021-08-16\n**ORIGINATING DIVISION:** Covert Operations\n**CLASSIFICATION LEVEL:** Top Secret\n**EVENT DATE:** 2024-10-05\n**MISSION PRIORITY:** 1\n\n**AGENT CODE NAME:** NIGHTINGALE-14\n**REAL NAME:** ALEXANDER NIKOLAEVICH PAVLOV\n**ASSIGNED OPERATIONAL ID:** CO-OP-214\n**PSYCHOLOGICAL PROFILING CODE:** PS-142\n\n**RECRUITMENT HISTORY:**\nNightingale-14 was recruited on 2018-02-27 through a controlled environment in Moscow, utilizing a carefully crafted **Legends** framework and **Cutouts** protocol to ensure plausible deniability. The agent demonstrated exceptional technical skills and adaptability during initial **Field Contact Reports** (FCR-001 to FCR-005) and subsequent **Operational Debriefings** (ODB-001 to ODB-003), solidifying their value as a high-priority asset.\n\n**OPERATIONAL ASSIGNMENTS:**\nNightingale-14 has been assigned to the following operations:\n\n1. **Operation Nightshade** (2019-01-01 to 2019-06-30): Conducted extensive surveillance and reconnaissance on suspected Soviet mole targets within the NATO intelligence apparatus.\n2. **Project Phoenix** (2020-01-01 to 2020-12-31): Participated in a clandestine operation to disrupt and dismantle a sophisticated **Honey Trap** network within the Russian Federal Security Service (FSB).\n3. **Operation Redstone** (2021-01-01 to 2021-12-31): Utilized advanced **Signals Intelligence** (SIGINT) capabilities to intercept and decode high-level communications between the Kremlin and key regional leaders.\n\n**PSYCHOLOGICAL ASSESSMENTS:**\nNightingale-14 underwent comprehensive **Polygraph Examination Reports** (PER-001 to PER-005) and **Operational Personality Inventory** (OPI-001) assessments, revealing a high level of emotional stability and adaptability. Their psychological profile suggests a strong sense of loyalty and duty, which can be leveraged to maintain motivation and engagement throughout their operational tenure.\n\n**PERFORMANCE EVALUATIONS:**\nNightingale-14 has consistently demonstrated exceptional technical expertise and operational acumen, earning high marks in **Mission Execution Reports** (MER-001 to MER-005) and **Operational Debriefings** (ODB-001 to ODB-003). Their performance has been evaluated as follows:\n\n* **Technical Skill Rating:** 9.2/10\n* **Operational Conduct Rating:** 9.5/10\n* **Risk Management Rating:** 8.8/10\n\n**PERSONAL BACKGROUND:**\nNightingale-14 was born on 1990-02-22 in Moscow, Russia. Their family background is complex, with their father serving as a high-ranking official within the Soviet-era KGB. This background has provided the agent with a unique understanding of the operational environment and has allowed them to navigate complex relationships with ease.\n\n**VULNERABILITIES:**\nNightingale-14's primary vulnerabilities include:\n\n* **Financial Dependence:** The agent relies heavily on their operational stipend and may be susceptible to financial coercion or manipulation.\n* **Personal Relationships:** Nightingale-14's complex family background and past relationships may create potential conflicts of interest or emotional vulnerabilities.\n* **Technical Overreliance:** The agent's exceptional technical skills may lead to overreliance on their abilities, making them more susceptible to technical failures or adversary exploitation.\n\n**ANALYTICAL METHODS:**\nNightingale-14's technical expertise and operational acumen make them an ideal candidate for advanced **Signals Intelligence** (SIGINT) and **Cyber Operations** (CO) activities. Their proficiency in **Cryptanalysis** and **Network Exploitation** enables them to extract critical information from complex systems and networks.\n\n**TECHNICAL SPECIFICATIONS:**\nNightingale-14's technical specifications include:\n\n* **Coding Proficiency:** Expert-level proficiency in multiple encryption algorithms, including AES, RSA, and elliptic curve cryptography.\n* **Network Exploitation:** Advanced knowledge of network protocols, including TCP/IP, DNS, and HTTP.\n* **Cyber Operations:** Expertise in various cyber tools and techniques, including malware, social engineering, and network penetration testing.\n\n**MEASUREMENTS & METRICS:**\nNightingale-14's performance has been evaluated using the following metrics:\n\n* **Mission Success Rate:** 98.2%\n* **Technical Accuracy Rate:** 95.6%\n* **Operational Efficiency Rating:** 92.1%\n\n**RECOMMENDATIONS:**\nBased on Nightingale-14's exceptional technical skills, operational acumen, and psychological profile, it is recommended that they be assigned to high-priority operations requiring advanced **Signals Intelligence** (SIGINT) and **Cyber Operations** (CO) capabilities.\n\n**CLASSIFICATION UPDATE:**\nThis document has been classified TOP SECRET//CO-OP-214//PS-142//NIGHTINGALE-14. Distribution is restricted to **Eyes Only** personnel with a need-to-know clearance.\n\n**AUTHENTICATION:**\nThis document has been authenticated by the **Covert Operations** division on 2024-10-05.\n\n**CONCLUSION:**\nNightingale-14 is a highly valuable asset with exceptional technical skills and operational acumen. Their psychological profile suggests a strong sense of loyalty and duty, making them an ideal candidate for high-priority operations.", "metadata": {"document_creation_date": "2021-08-16", "authoring_agent_id": "Nightingale-7", "originating_division": "Covert Operations", "classification_level": "Top Secret", "event_date": "2024-10-05", "mission_priority": 1}}
{"id": "doc_00000071", "type": "Field Contact Report", "content": "**Field Contact Report: Eyes Only**\n\n**Document ID:** FCR-2023-12-14-001\n**Event Date:** 2021-05-09\n**Document Creation Date:** 2023-12-14\n**Target Entity:** Warsaw Pact\n**Classification Level:** Eyes Only\n**Mission Priority:** 4\n**Originating Division:** Signals Intelligence\n**Author:** Sparrowhawk-3, Signals Specialist\n\n**Summary:**\n\nOn 2021-05-09, I encountered a suspicious individual at the Warsaw Pact's East Berlin Radio Broadcasting Station. The individual, later identified as asset code 'Nova-4,' displayed unusual behavior, sparking my interest in potential security breaches. This report outlines the details of our encounter, highlighting potential security concerns and intelligence implications.\n\n**Location:** East Berlin Radio Broadcasting Station, Karl-Liebknecht-Stra\u00dfe 33, East Berlin, Germany\n\n**Time:** 14:45 hours local time\n\nI was conducting routine signals intelligence gathering at the East Berlin Radio Broadcasting Station when I noticed a person lurking around the perimeter fence. The individual, a male, approximately 30 years old, with short, dark hair and a thin build, appeared to be trying to remain inconspicuous. He wore a faded 'Radio Berlin' employee badge, which seemed out of place on his jacket.\n\n**Encounter:**\n\nAs I observed the individual, he caught my eye and quickly looked away, attempting to blend in with the surrounding crowd. I noticed that he was holding a small, encrypted notebook and glanced at it several times, seemingly checking a schedule or coordinates. This behavior struck me as unusual, as I have never seen anyone accessing encrypted materials in such a public area.\n\nI decided to investigate further, keeping a safe distance to avoid detection. The individual began to stroll towards the broadcasting station's main entrance, where I noticed a group of Warsaw Pact guards on high alert. They seemed to be monitoring the area closely, possibly in response to some internal security concern.\n\n**Nova-4's Behavior:**\n\nUpon closer inspection, I observed that the individual (Nova-4) was attempting to exchange a small package with one of the guards. The guard, a tall, imposing figure, seemed hesitant to accept the package, but eventually handed Nova-4 a small key. This exchange sparked my interest, as it appeared to be a clandestine meeting.\n\n**Initial Assessment:**\n\nBased on the information gathered, I believe that Nova-4 may be involved in a potential security breach or espionage operation. His behavior, especially the encrypted notebook and attempted exchange with the guard, suggests a level of sophistication and intent. Further investigation is required to determine the full extent of Nova-4's activities and potential ties to the Warsaw Pact.\n\n**Recommendations:**\n\n1. Conduct further surveillance on Nova-4 to gather more information about his activities and potential connections to the Warsaw Pact.\n2. Attempt to intercept and decode the encrypted notebook to uncover its contents and significance.\n3. Assess the possible implications of this encounter on our overall understanding of Warsaw Pact security procedures and potential vulnerabilities.\n\n**Conclusion:**\n\nThis encounter with Nova-4 highlights the need for continued vigilance and attention to detail in our signals intelligence gathering efforts. The potential for security breaches or espionage operations within the Warsaw Pact demands that we prioritize further investigation and analysis to protect our interests and maintain a competitive edge.\n\n**Distribution:**\n\nThis report will be shared with the Signals Intelligence Division, Covert Operations Division, and relevant senior personnel within the organization.\n\n**End of Report**\n\n**Document Control:**\n\nThis report has been reviewed and approved by:\n\n- Sparrowhawk-3, Signals Specialist (Author)\n- Nightingale-7, Senior Case Officer (Reviewer)\n- Shadow-12, Technical Operations (Reviewer)\n\n**Document Classification:**\n\nEyes Only\n\n**Document Storage:**\n\nThis report will be stored in the Central Personnel Archive, Document Control System DCS-9, with access restricted to authorized personnel.\n\n**Report Endorsement:**\n\nThis report is endorsed by the author, Sparrowhawk-3, and approved by the reviewers, Nightingale-7 and Shadow-12.\n\n**Signature:**\n\nSparrowhawk-3\nSignals Specialist\nProject Nightingale\n2023-12-14", "metadata": {"event_date": "2021-05-09", "document_creation_date": "2023-12-14", "authoring_agent_id": "Nightingale-7", "target_entity": "Warsaw Pact", "classification_level": "Eyes Only", "mission_priority": 4, "originating_division": "Signals Intelligence"}}
{"id": "doc_00000072", "type": "Operational Debriefing", "content": "**CLASSIFIED DOCUMENT**\n\n**PROJECT NIGHTINGALE**\n**OPERATIONAL DEBRIEFING DOCUMENT**\n**SUBJECT: OPERATION NIGHTSHADE - COVERT INFIILTRATION OF EAST GERMAN DEFENSE INDUSTRIES**\n**DOCUMENT CREATION DATE:** 2024-02-28\n**MISSION PRIORITY:** 2\n**ORIGINATING DIVISION:** COVERT OPERATIONS\n**CLASSIFICATION LEVEL:** TOP SECRET\n**EVENT DATE:** 2024-06-20\n**TARGET ENTITY:** EAST GERMANY\n\n**SUMMARY:**\n\nOperation Nightshade aimed to infiltrate key East German defense industries, focusing on the acquisition of cutting-edge technology and strategic intelligence. The operation involved a high-risk, deep-cover approach, utilizing a sophisticated agent network and advanced technical assets. This debriefing document explores the objectives, execution details, challenges encountered, immediate results, and lessons learned from the operation.\n\n**BACKGOUND:**\n\nIn response to the recent escalation of Soviet military activities, the Western intelligence community identified East Germany as a critical target for strategic intelligence collection. Operation Nightshade was designed to exploit vulnerabilities within East German defense industries, leveraging a network of high-level agents and advanced technical assets.\n\n**OBJECTIVES:**\n\n1. **Acquire strategic intelligence** on East German defense industry capabilities, focusing on advanced technology and research developments.\n2. **Infiltrate key target organizations**, including the East German Ministry of Defense, the Ministry of Industry, and select defense contractors.\n3. **Establish a robust agent network**, ensuring reliable and sustainable intelligence collection capabilities.\n\n**EXECUTION:**\n\nOperation Nightshade involved a multi-faceted approach, incorporating both human and technical intelligence collection methods. The operation was divided into three phases:\n\n1. **Phase 1: Agent Recruitment and Infiltration** (March 2023 - May 2023)\n   - Utilized a combination of traditional recruitment techniques and advanced social engineering methods to identify and recruit high-level East German agents.\n   - Successfully infiltrated key target organizations, including the East German Ministry of Defense and the Ministry of Industry.\n\n2. **Phase 2: Technical Asset Deployment and Activation** (June 2023 - August 2023)\n   - Deployed advanced technical assets, including miniature cameras, audio recorders, and secure communication devices, to East German defense industries.\n   - Activated the technical assets, ensuring reliable and sustainable intelligence collection capabilities.\n\n3. **Phase 3: Intelligence Collection and Exfiltration** (September 2023 - June 2024)\n   - Collected and transmitted strategic intelligence on East German defense industry capabilities, focusing on advanced technology and research developments.\n   - Successfully exfiltrated key agents, ensuring the safe removal of personnel and sensitive equipment.\n\n**CHALLENGES ENCOUNTERED:**\n\n1. **Hostile Surveillance:** East German counterintelligence agencies identified and targeted our agent network, leading to a series of close calls and near-misses.\n2. **Technical Asset Failures:** Several technical assets experienced malfunction or failure, compromising the operation's intelligence collection capabilities.\n3. **Agent Vulnerabilities:** Key agents demonstrated vulnerabilities, including financial pressures and personal relationships, which threatened the operation's security and integrity.\n\n**IMMEDIATE RESULTS:**\n\nOperation Nightshade achieved significant success, collecting and transmitting strategic intelligence on East German defense industry capabilities. The operation provided valuable insights into advanced technology and research developments, enhancing our understanding of the Soviet military's capabilities and intentions.\n\n**LESSONS LEARNED:**\n\n1. **Enhanced Agent Security Protocols:** The operation highlighted the importance of robust agent security protocols, including regular polygraph examinations and thorough background checks.\n2. **Advanced Technical Asset Development:** The technical asset failures emphasized the need for ongoing research and development of advanced technical assets, ensuring reliable and sustainable intelligence collection capabilities.\n3. **Operational Flexibility:** The operation demonstrated the importance of operational flexibility, enabling our team to adapt to changing circumstances and respond to emerging challenges.\n\n**CONCLUSION:**\n\nOperation Nightshade successfully infiltrated key East German defense industries, collecting and transmitting strategic intelligence on advanced technology and research developments. The operation highlighted the importance of robust agent security protocols, advanced technical asset development, and operational flexibility. These lessons learned will inform future operations, ensuring continued success in the collection of strategic intelligence.\n\n**RECOMMENDATIONS:**\n\n1. **Enhance Agent Security Protocols:** Implement enhanced agent security protocols, including regular polygraph examinations and thorough background checks.\n2. **Develop Advanced Technical Assets:** Prioritize ongoing research and development of advanced technical assets, ensuring reliable and sustainable intelligence collection capabilities.\n3. **Maintain Operational Flexibility:** Ensure operational flexibility, enabling our team to adapt to changing circumstances and respond to emerging challenges.\n\n**AUTHENTICATION:**\n\nThis document has been authenticated by the following personnel:\n\n* **Nightingale-7** (Senior Case Officer)\n* **Sparrowhawk-3** (Signals Specialist)\n* **Shadow-12** (Technical Operations)\n\n**CLASSIFICATION LEVEL:** TOP SECRET\n\n**DISTRIBUTION:**\n\nThis document is restricted to Level 3 personnel and above, with a distribution list consisting of the following personnel:\n\n* **Central Intelligence Directorate (CID)**\n* **MI6's Eastern Section**\n* **NATO Intelligence Division (NID)**", "metadata": {"document_creation_date": "2024-02-28", "authoring_agent_id": "Viper-6", "mission_priority": 2, "originating_division": "Covert Operations", "classification_level": "Top Secret", "event_date": "2024-06-20", "target_entity": "East Germany"}}
{"id": "doc_00000073", "type": "Operational Debriefing", "content": "**Operational Debriefing: Eyes Only**\n\n**Document Creation Date:** 2021-08-23\n**Mission Priority:** 4\n**Originating Division:** Research & Analysis\n**Classification Level:** Eyes Only\n**Event Date:** 2024-11-01\n**Target Entity:** Poland\n\n**Mission Overview:**\n\nProject Nightingale conducted Operation Amber Fox, a covert mission aimed at recruiting a high-ranking Polish official with access to sensitive information on the country's energy policy. The mission was deemed a priority 4 operation, focusing on gathering background intelligence on potential recruits and assessing the feasibility of establishing a long-term asset within the Polish government.\n\n**Objectives:**\n\n1. Identify and vet potential recruits with access to sensitive information on Poland's energy policy.\n2. Establish a secure communication channel with the target official.\n3. Assess the feasibility of recruiting the target official and integrating them into the Nightingale network.\n\n**Mission Execution:**\n\nThe mission was executed by a team of four agents, comprising two case officers, one technical specialist, and one linguist. The team operated under the codename \"Amber Fox\" and was based in Warsaw.\n\n**Challenges Encountered:**\n\n1. **Hostile Surveillance:** The team encountered persistent surveillance by Polish security services, making it difficult to maintain secure communication channels.\n2. **Target Nervousness:** The target official, codenamed \"Bia\u0142ystok,\" exhibited signs of nervousness during meetings, raising concerns about their reliability.\n3. **Linguistic Barriers:** The linguist, fluent in Polish, struggled to maintain a convincing cover story, which compromised the mission's credibility.\n4. **Equipment Failure:** The technical specialist's equipment malfunctioned during a critical meeting, forcing the team to improvise and adapt.\n\n**Immediate Results:**\n\nDespite the challenges, the team was able to establish a secure communication channel with Bia\u0142ystok and gather background intelligence on their interests and motivations. However, the mission ultimately failed to recruit Bia\u0142ystok due to their increasing nervousness and concerns about their loyalty.\n\n**Lessons Learned:**\n\n1. **Improved Surveillance Detection:** The team must develop more effective surveillance detection techniques to minimize the risk of compromise.\n2. **Enhanced Linguistic Support:** The linguist's performance was a critical failure. The team requires more effective linguistic support to maintain credibility and secure communication channels.\n3. **Reducing Nervousness:** The team must develop strategies to reduce the target's nervousness and increase their confidence in the operation.\n4. **Equipment Reliability:** The technical specialist's equipment must be upgraded to ensure reliability and minimize the risk of compromise.\n\n**Investigative Findings:**\n\nFurther analysis of the mission's data reveals a potential mole within the Polish government, codenamed \"Warsaw.\" This individual appears to have compromised the mission by feeding information to the Polish security services. The investigation is ongoing, and further analysis is required to confirm the identity of the mole and their motives.\n\n**Recommendations:**\n\n1. **Conduct a thorough investigation** into the potential mole and their activities.\n2. **Develop a new recruitment strategy** to address the challenges encountered during Operation Amber Fox.\n3. **Upgrade technical equipment** to ensure reliability and minimize the risk of compromise.\n4. **Provide additional linguistic support** to maintain credibility and secure communication channels.\n\n**Conclusion:**\n\nOperation Amber Fox was a complex and challenging mission that highlighted several critical issues within the Nightingale network. The investigation has identified potential areas for improvement and recommended corrective actions to address these challenges. Further analysis and investigation are required to confirm the identity of the potential mole and their motives.", "metadata": {"document_creation_date": "2021-08-23", "authoring_agent_id": "Ghost-1", "mission_priority": 4, "originating_division": "Research & Analysis", "classification_level": "Eyes Only", "event_date": "2024-11-01", "target_entity": "Poland"}}
{"id": "doc_00000074", "type": "Agent Profile Dossier", "content": "**Agent Profile Dossier**\n\n**Document Creation Date:** 2024-02-19\n**Originating Division:** Research & Analysis\n**Classification Level:** Top Secret\n**Event Date:** 2022-12-19\n**Mission Priority:** 2\n\n**Summary:**\n\nThis Agent Profile Dossier provides a comprehensive overview of Agent \"Nova-5\" (real name: Alexandra Petrova), a Russian-born HUMINT asset operating within the Soviet Union's scientific community. Recruited in 2018, Nova-5 has proven to be a valuable source of information on Soviet nuclear programs and military capabilities. This dossier details Nova-5's recruitment history, operational assignments, psychological assessments, performance evaluations, personal background, and potential vulnerabilities.\n\n**Overview:**\n\nAlexandra Petrova, codename Nova-5, was born on February 15, 1990, in Moscow, Russia. She received her Ph.D. in nuclear physics from the Moscow Engineering Physics Institute in 2015. Nova-5's recruitment by Nightingale occurred in 2018, during a meeting in the Moscow Metro system.\n\n**Recruitment History:**\n\nNova-5's recruitment was facilitated by Nightingale-7, a senior case officer with extensive experience in handling HUMINT assets. The initial contact was established through a dead drop in the Moscow Metro, where Nova-5 deposited a cryptic message that read: \"The stars align in our favor.\" This message served as a signal for Nova-5's recruitment, which was confirmed through a series of encrypted communications.\n\n**Operational Assignments:**\n\nNova-5's primary operational assignments involve providing intelligence on Soviet nuclear programs, including research and development projects, test sites, and military capabilities. Her access to sensitive information has been facilitated through her position as a research scientist at the Russian Academy of Sciences.\n\n**Psychological Assessments:**\n\nNova-5's psychological assessments, conducted through the Operative Personality Inventory (OPI), reveal a high degree of risk tolerance, emotional stability, and loyalty to her handlers. However, her OPI results also indicate a propensity for anxiety and self-doubt, which may be exploited by hostile entities.\n\n**Performance Evaluations:**\n\nNova-5's performance evaluations have consistently demonstrated exceptional performance, with a average rating of 4.8/5 across multiple missions. Her most notable successes include the provision of critical intelligence on the Soviet Union's nuclear testing program and the identification of a potential mole within the Russian scientific community.\n\n**Personal Background:**\n\nNova-5's personal background is characterized by a strong sense of loyalty to her family and a deep-seated resentment towards the Soviet regime. Her father, a former dissident, was arrested and imprisoned for his anti-government activities. Nova-5's recruitment by Nightingale was, in part, motivated by her desire to avenge her father's persecution.\n\n**Potential Vulnerabilities:**\n\nNova-5's potential vulnerabilities include her emotional instability, which may be exploited by hostile entities to compromise her loyalty or extract sensitive information. Additionally, her family ties to the dissident community may create risks for her personal safety and security.\n\n**Measurements & Metrics:**\n\n**Intelligence Reliability Scale:** A-confirmed by multiple independent sources\n**Source Access Rating:** 2-direct access\n**Network Penetration Index:** 80 (deep penetration of Soviet scientific community)\n**Operational Security Quotient:** 4.2 (moderate risk of compromise)\n**Asset Productivity Metrics:** 4.5 (high productivity and efficiency)\n\n**Target Entities:**\n\n**Primary:** Soviet Union (nuclear programs, military capabilities)\n**Secondary:** Russian Academy of Sciences, Moscow Engineering Physics Institute\n\n**Authoring Agents:**\n\n**Nightingale-7** (senior case officer)\n**Sparrowhawk-3** (signals specialist)\n**Nova-5** (HUMINT asset)\n\n**Classification Levels:**\n\n**Top Secret:** restricted access to sensitive information and operational details\n**Eyes Only:** access limited to named individuals for compartmented programs\n**Secret:** covers operational planning and agent identities\n**Confidential:** applies to tactical intelligence\n\n**Document Control System:**\n\n**DCS-9:** access logged for all personnel with Top Secret clearance\n\n**Document Distribution:**\n\n**Restricted access:** Nightingale-7, Sparrowhawk-3\n**Eyes Only:** Nova-5, authorized personnel with Top Secret clearance\n\nThis Agent Profile Dossier provides a comprehensive overview of Agent Nova-5's recruitment history, operational assignments, psychological assessments, performance evaluations, personal background, and potential vulnerabilities. The dossier serves as a valuable resource for Nightingale personnel, providing critical information on Nova-5's strengths and weaknesses, as well as her role in advancing Nightingale's strategic objectives.", "metadata": {"document_creation_date": "2024-02-19", "authoring_agent_id": "Sparrowhawk-3", "originating_division": "Research & Analysis", "classification_level": "Top Secret", "event_date": "2022-12-19", "mission_priority": 2}}
{"id": "doc_00000075", "type": "Field Contact Report", "content": "**CLASSIFIED DOCUMENT**\n**PROJECT NIGHTINGALE**\n**FIELD CONTACT REPORT**\n**FCTR-2024-09-15-001**\n**CLASSIFICATION: SECRET**\n**MISSION PRIORITY: 3**\n**ORIGINATING DIVISION: COUNTER-ESPIONAGE**\n**DOCUMENT CREATION DATE: 2024-06-05**\n**EVENT DATE: 2024-09-15**\n\n**SUBJECT:** Technical Surveillance Countermeasures (TSCM) Evaluation - Comecon Embassy Compound\n\n**SUMMARY:**\n\nOn 15 September 2024, Counter-Espionage Division (CED) agents conducted a TSCM sweep of the Comecon Embassy Compound in Vienna. This report details the technical findings, analysis, and recommendations for future operations.\n\n**EVENT DETAILS:**\n\n1. **Sweep Objectives:** Identify and neutralize potential surveillance devices within the Comecon Embassy Compound.\n2. **Sweep Team:** Consisting of CED Agents Viper-6 (lead), Nightshade-3 (technical analyst), and Ghost-1 (support).\n3. **Equipment:** Utilized the TSCM-8 sweep kit, including:\n\t* AN/PSM-4 portable surveillance detection device\n\t* TSCM-3A signal analyzer\n\t* TSCM-2B acoustic sensor\n\t* TSCM-1A electromagnetic field meter\n4. **Sweep Procedure:** Conducted a thorough sweep of the compound, including all buildings, vehicles, and surrounding areas.\n5. **Findings:**\n\t* **AN/PSM-4:** Detected a low-level signal emanating from a ventilation shaft on the east wing of the main building (Coordinate: 48.2083\u00b0 N, 16.3728\u00b0 E). Analysis revealed a frequency of 24.975 MHz, consistent with a standard Soviet-made bug.\n\t* **TSCM-3A:** Identified a second signal at 17.853 kHz, likely originating from a hidden microphone within the embassy's garden (Coordinate: 48.2085\u00b0 N, 16.3732\u00b0 E).\n\t* **TSCM-2B:** Detected anomalous acoustic patterns near the compound's perimeter fence (Coordinate: 48.2082\u00b0 N, 16.3725\u00b0 E), consistent with a hidden audio transceiver.\n\t* **TSCM-1A:** Measured elevated electromagnetic field readings within the main building's electrical room (Coordinate: 48.2084\u00b0 N, 16.3729\u00b0 E), indicative of a potential RF jamming device.\n6. **Analysis:** The technical evidence suggests the presence of at least three surveillance devices within the Comecon Embassy Compound. The detected signals and anomalies are consistent with Soviet-made equipment, indicating a high probability of KGB involvement.\n7. **Recommendations:**\n\t* **Immediate Action:** Neutralize the detected surveillance devices using CED's standard TSCM protocols.\n\t* **Future Operations:** Recommend increased security measures for all Comecon Embassy personnel, including enhanced encryption and secure communication protocols.\n\t* **Intelligence Gathering:** Suggest targeting KGB personnel and assets within the Comecon Embassy Compound to gather further intelligence on their surveillance capabilities.\n\n**ADDITIONAL NOTES:**\n\n* The TSCM-8 sweep kit and AN/PSM-4 device require routine maintenance and calibration to ensure optimal performance.\n* A detailed report on the detected surveillance devices and their technical specifications is attached to this document (Appendix A).\n* A copy of this report has been forwarded to the Central Intelligence Directorate (CID) for further analysis and distribution.\n\n**CLASSIFICATION CHANGE:** This document shall be classified as SECRET upon receipt.\n\n**AUTHENTICATION:**\n\nThis document has been authenticated by CED Agent Viper-6 (lead) and signed in accordance with Project Nightingale's Operational Security Standard (OSS-15).\n\n**SIGNATURE:**\n\nViper-6\nCED Agent\nCounter-Espionage Division", "metadata": {"event_date": "2024-09-15", "document_creation_date": "2024-06-05", "authoring_agent_id": "Viper-6", "target_entity": "Comecon", "classification_level": "Secret", "mission_priority": 3, "originating_division": "Counter-Espionage"}}
{"id": "doc_00000076", "type": "Operational Debriefing", "content": "**Operational Debriefing Report: \"East German Counterintelligence Operation\"**\n**Document Creation Date:** 2024-03-19\n**Mission Priority:** 2\n**Originating Division:** Counter-Espionage\n**Classification Level:** Confidential\n**Event Date:** 2022-08-09\n**Target Entity:** East Germany\n\n**Introduction:**\n\nOn August 9th, 2022, a covert operation was conducted by a team of Counter-Espionage agents to infiltrate East German counterintelligence networks. The mission, codenamed \" Operation: Phoenix,\" aimed to gather intelligence on the Stasi's (East German Ministry for State Security) internal structures, identify potential vulnerabilities, and assess the current state of their counterintelligence capabilities. This operational debriefing provides a comprehensive summary of the mission's objectives, execution, challenges, and immediate results.\n\n**Pre-Mission Planning:**\n\nPrior to the operation, extensive research was conducted on the Stasi's internal workings, focusing on key personnel, organizational structures, and communication networks. This information was gathered through a combination of human intelligence sources, SIGINT from East German communication intercepts, and open-source research. The team's handlers, experienced case officers with deep knowledge of East German operations, carefully planned the mission to minimize risks and maximize intelligence gathering opportunities.\n\n**Operation Execution:**\n\nA team of three agents, each with a unique skillset, was assembled for the operation. Agent \"Nova-6\" (a seasoned operative with expertise in surveillance and counter-surveillance) led the team, while Agent \"Lynx-3\" (a skilled hacker and technical expert) provided critical support for the mission's technical aspects. Agent \"Raven-9\" (an experienced agent with extensive knowledge of East German culture and language) acted as the team's cultural liaison and provided critical context for the operation.\n\nThe team infiltrated the Stasi's headquarters in East Berlin under the guise of a diplomatic delegation, using carefully crafted cover stories and authentic documents to maintain their cover. Once inside, they established a secure communication channel with their handlers using a pre-arranged dead drop protocol.\n\n**Challenges and Complications:**\n\nAs the team navigated the Stasi's complex internal structures, they encountered several unexpected challenges. A sudden increase in Stasi personnel, possibly triggered by intelligence on the operation, forced the team to adapt their plans on short notice. Agent Nova-6 quickly assessed the situation and implemented a revised plan, leveraging their expertise in counter-surveillance to maintain their cover.\n\nAdditionally, technical issues with the communication equipment, caused by Agent Lynx-3's attempts to bypass security protocols, nearly compromised the entire operation. Agent Raven-9's cultural expertise proved invaluable in resolving the issue, as they were able to convincingly explain the technical difficulties to the Stasi personnel, buying the team crucial time.\n\n**Immediate Results:**\n\nThe operation yielded significant intelligence on the Stasi's internal structures, including the identities of key personnel, organizational charts, and communication protocols. The team successfully extracted a high-priority target, a Stasi officer with access to sensitive information, and established a secure communication channel with him. The extracted officer provided valuable insights into the Stasi's current priorities, including a focus on countering Western intelligence efforts and suppressing dissent within East Germany.\n\n**Lessons Learned:**\n\nThe operation highlighted several critical lessons for future Counter-Espionage operations:\n\n1.  **Adaptability:** The team's ability to adapt to changing circumstances, particularly the sudden increase in Stasi personnel, showcased the importance of flexibility in covert operations.\n2.  **Technical expertise:** Agent Lynx-3's technical expertise proved invaluable in resolving the communication equipment issue, underscoring the need for skilled technical support in covert operations.\n3.  **Cultural knowledge:** Agent Raven-9's cultural expertise played a critical role in resolving the technical issue and maintaining the team's cover, highlighting the importance of cultural knowledge in operational planning.\n4.  **Risk assessment:** The operation's success was heavily dependent on the team's ability to assess and mitigate risks, demonstrating the importance of thorough risk analysis in covert operations planning.\n\n**Conclusion:**\n\nOperation: Phoenix successfully gathered critical intelligence on East Germany's counterintelligence capabilities and provided valuable insights into the Stasi's internal structures. The operation's success was heavily dependent on the team's adaptability, technical expertise, cultural knowledge, and risk assessment skills. This operational debriefing provides a comprehensive summary of the mission's objectives, execution, challenges, and immediate results, serving as a valuable resource for future Counter-Espionage operations.\n\n**Recommendations:**\n\nBased on the operation's outcomes, the following recommendations are made:\n\n1.  **Enhance technical expertise:** The team's technical support should be upgraded to include more experienced and skilled experts, particularly in the areas of surveillance and communication equipment.\n2.  **Increase cultural knowledge:** The team's cultural expertise should be expanded to include more agents with in-depth knowledge of East German culture, language, and customs.\n3.  **Improve risk assessment:** Future operations should prioritize thorough risk assessment, incorporating a more comprehensive evaluation of potential risks and mitigation strategies.\n4.  **Enhance adaptability training:** The team should undergo training to enhance their adaptability skills, including scenario-based exercises and simulations to prepare for unexpected challenges.\n\nBy incorporating these recommendations into future Counter-Espionage operations, the team can continue to gather critical intelligence and achieve successful outcomes in increasingly complex and dynamic environments.\n\n**Appendices:**\n\nThe following appendices are attached to this operational debriefing report:\n\n1.  **Agent profiles:** Detailed profiles of the agents involved in the operation, including their skills, experience, and performance during the mission.\n2.  **Mission chronology:** A detailed timeline of the operation, including key events, challenges, and outcomes.\n3.  **Extracted intelligence:** A summary of the critical intelligence gathered during the operation, including the identities of key personnel, organizational charts, and communication protocols.\n4.  **Lessons learned:** A comprehensive summary of the lessons learned during the operation, including recommendations for future Counter-Espionage operations.\n\n**End of Report**", "metadata": {"document_creation_date": "2024-03-19", "authoring_agent_id": "Phoenix-11", "mission_priority": 2, "originating_division": "Counter-Espionage", "classification_level": "Confidential", "event_date": "2022-08-09", "target_entity": "East Germany"}}
{"id": "doc_00000077", "type": "Operational Debriefing", "content": "**OPERATIONAL DEBRIEFING DOCUMENT**\n\n**Classification Level:** Top Secret\n**Document Creation Date:** 2024-08-16\n**Mission Priority:** 1\n**Originating Division:** Signals Intelligence\n**Event Date:** 2023-08-03\n**Target Entity:** Soviet Union\n\n**OPERATION CODE NAME:** Lysander-12\n\n**OBJECTIVES:**\n\nThe primary objective of Operation Lysander-12 was to intercept and decrypt high-priority Soviet military communications during the August 2023 conflict in Ukraine. Secondary objectives included identifying potential targets for follow-on operations and assessing the effectiveness of the Lysander Protocol for signals intelligence.\n\n**EXECUTION DETAILS:**\n\nSignals Intelligence Division personnel, led by Senior Analyst Nightingale-12, executed a series of complex operations to intercept and process Soviet military communications. Key activities included:\n\n1. **Initial Deployment:** Technical Operations Division personnel installed and activated a high-gain antenna array at the designated listening post (Bad Aibling Station).\n2. **Signal Acquisition:** Signals Intelligence personnel, utilizing advanced signal processing algorithms, acquired and processed multiple Soviet military communication channels.\n3. **Decryption:** Researchers from the Research & Analysis Division, utilizing the Lysander Protocol, successfully decrypted several high-priority communications.\n4. **Analysis and Exploitation:** Analysts from the Signals Intelligence Division, in conjunction with Research & Analysis personnel, analyzed and exploited the decrypted communications, identifying key targets and assessing Soviet military capabilities.\n\n**CHALLENGES ENCOUNTERED:**\n\n1. **Interference:** Soviet electronic warfare capabilities created significant interference, requiring adjustments to the antenna array and signal processing algorithms.\n2. **Encryption Changes:** The Soviet military implemented changes to their encryption protocols, necessitating updates to the Lysander Protocol and additional research efforts.\n3. **Target Movement:** Soviet military units were unexpectedly relocated, requiring rapid adjustments to targeting and signal acquisition efforts.\n\n**IMMEDIATE RESULTS:**\n\n1. **Target Acquisition:** Signals Intelligence Division personnel successfully acquired and decrypted multiple high-priority Soviet military communications.\n2. **Target Identification:** Analysts identified key targets, including Soviet artillery units and command centers.\n3. **Soviet Military Capability Assessment:** Researchers assessed Soviet military capabilities, including artillery and air defense systems.\n\n**LESSONS LEARNED:**\n\n1. **Adaptability:** The ability to adapt quickly to changing Soviet electronic warfare capabilities and encryption protocols was crucial to mission success.\n2. **Collaboration:** Effective collaboration between Signals Intelligence and Research & Analysis personnel was essential for successful decryption and analysis.\n3. **Targeting:** Continuous targeting and signal acquisition efforts were necessary to maintain optimal effectiveness.\n\n**COMPARATIVE ANALYSIS:**\n\nOperation Lysander-12 demonstrates similarities with previous operations, such as Operation Amber Fox (1965) and Operation Nightshade (1975). However, Lysander-12 presents unique features, including:\n\n1. **Advanced Signal Processing:** The use of advanced signal processing algorithms and high-gain antenna arrays enabled more efficient signal acquisition and processing.\n2. **Lysander Protocol Updates:** The successful implementation of the Lysander Protocol updates facilitated decryption and analysis of high-priority Soviet military communications.\n3. **Soviet Military Capability Assessment:** The comprehensive assessment of Soviet military capabilities provides valuable insights for future operations and strategic planning.\n\n**RECOMMENDATIONS:**\n\n1. **Continued Development of the Lysander Protocol:** Updates and refinements to the Lysander Protocol will be necessary to maintain optimal effectiveness in decrypting Soviet military communications.\n2. **Enhanced Signal Processing Capabilities:** Additional research and development of advanced signal processing algorithms will be essential to maintain a technological edge over the Soviet Union.\n3. **Collaboration and Adaptability:** Ongoing collaboration and adaptability between Signals Intelligence, Research & Analysis, and Technical Operations personnel will be crucial to mission success in future operations.\n\n**CLASSIFICATION:**\n\nThis document remains classified TOP SECRET and will be stored in the Nightingale Historical Record. Distribution is restricted to personnel with a need-to-know clearance and is subject to compartmentalization procedures.", "metadata": {"document_creation_date": "2024-08-16", "authoring_agent_id": "Orion-5", "mission_priority": 1, "originating_division": "Signals Intelligence", "classification_level": "Top Secret", "event_date": "2023-08-03", "target_entity": "Soviet Union"}}
{"id": "doc_00000078", "type": "Field Contact Report", "content": "**Document Classification:** Top Secret\n**Mission Priority:** 2\n**Originating Division:** Covert Operations\n**Date:** 2023-07-29\n**Document Creation Date:** 2021-08-09\n\n**Field Contact Report**\n\n**Subject:** KGB Agent Identification and Surveillance Methods\n\n**Location:** Moscow, Soviet Union (KGB Headquarters)\n**Time:** 14:00 hours, 29 July 2023\n**Weather:** Partly Cloudy\n\n**Summary:**\n\nDuring a covert surveillance operation, I (Nightingale-7) encountered a KGB agent utilizing a sophisticated surveillance technique, which appeared to be a variant of the traditional \"bunny hop\" method. The agent, codenamed \"Frost,\" was observed using a miniature camera and audio device, disguised as a standard-issue KGB smartwatch. This encounter has raised several questions regarding the KGB's surveillance capabilities and potential countermeasures.\n\n**Background:**\n\nRecent intelligence reports have suggested the KGB is experimenting with new surveillance techniques, possibly incorporating advanced technology to enhance their operational capabilities. Our mission objective was to gather intelligence on these methods and identify potential vulnerabilities.\n\n**Observations:**\n\n1. **Surveillance Method:** Frost employed a modified \"bunny hop\" technique, characterized by a rapid sequence of short-distance jumps between surveillance points. This method enabled the agent to maintain visual contact with the target while minimizing the risk of detection.\n2. **Disguise:** Frost wore a standard-issue KGB smartwatch, concealing a miniature camera and audio device. The device appeared to be a custom-designed attachment, possibly utilizing advanced encryption and transmission protocols.\n3. **Communication:** Frost utilized an encrypted communication channel, likely utilizing the KGB's proprietary \"Dead Hand\" protocol. The agent received and transmitted data through a secure, short-range transmitter embedded in the smartwatch.\n4. **Target Identification:** Frost was tasked with surveilling a high-ranking KGB officer, suspected of being involved in a significant counterintelligence operation.\n\n**Challenges and Questions:**\n\n1. **Surveillance Countermeasures:** The KGB's adaptation of the \"bunny hop\" method and use of miniature surveillance devices have raised concerns about the effectiveness of our current counter-surveillance techniques.\n2. **Encryption Protocols:**", "metadata": {"event_date": "2023-07-29", "document_creation_date": "2021-08-09", "authoring_agent_id": "Phoenix-11", "target_entity": "KGB", "classification_level": "Top Secret", "mission_priority": 2, "originating_division": "Covert Operations"}}
{"id": "doc_00000079", "type": "Agent Profile Dossier", "content": "**Agent Profile Dossier**\n\n**Document Creation Date:** 2021-06-29\n**Originating Division:** Covert Operations\n**Classification Level:** Top Secret\n**Event Date:** 2021-09-29\n**Mission Priority:** 4\n\n**Summary:**\n\nAgent **Lion-14** (real name: Sophia Kuznetsova) is a high-value asset operating within the Soviet Union's GRU, serving as a senior officer in the **Third Directorate**. Recruited in **2018** through a **Dead Drop Operation** in **Munich**, Lion-14 has consistently provided valuable intelligence on Soviet military capabilities and strategic doctrine. This dossier summarizes her recruitment history, operational assignments, psychological assessments, performance evaluations, personal background, and potential vulnerabilities.\n\n**Recruitment History:**\n\nLion-14 was identified as a potential asset through a **Polyakov Material assessment**, indicating a high level of ideological wavering. A **Junior Case Officer** from Covert Operations, **Lynx-5**, conducted a series of **Brush Passes** in **2018** to establish contact with Sophia Kuznetsova. The initial **Recruitment Briefing** highlighted the potential for Lion-14 to access sensitive GRU intelligence.\n\n**Operational Assignments:**\n\nLion-14's first **Operation**, codenamed **Eclipse**, involved providing strategic assessments of Soviet military doctrine in **2019**. Her subsequent operations, **Nightshade** (2020) and **Vigilant** (2021), focused on high-level GRU officer interactions and access to classified materials. Throughout these assignments, Lion-14 has demonstrated exceptional adaptability and resourcefulness.\n\n**Psychological Assessments:**\n\nThe **Operational Personality Inventory (OPI)** analysis indicates that Lion-14 exhibits a **Highly Motivated** and **Competitive** personality profile. Her **Polygraph Examination Report** shows a **Highly Reliable** subject, with a **Low Risk** for counterintelligence compromise.\n\n**Performance Evaluations:**\n\nLion-14's performance has consistently met or exceeded expectations, with a **96.5%** accuracy rate in intelligence reporting. Her **Quarterly Performance Review** in **2021** highlighted her exceptional **Initiative** and **Creativity** in accessing GRU sensitive areas.\n\n**Personal Background:**\n\nSophia Kuznetsova was born in **1988** in Leningrad (now St. Petersburg). She holds a **Master's Degree** in International Relations from the **Moscow State University** and has worked at the **GRU's Third Directorate** since **2012**. Lion-14 has a **Spouse** and **Two Children**, both living in Moscow.\n\n**Potential Vulnerabilities:**\n\nLion-14's primary vulnerability is her **Spouse's GRU connection**, which could compromise her cover if discovered. Additionally, her **Family Complications** may impact her ability to maintain operational security.\n\n**Recommendations:**\n\nBased on Lion-14's exceptional performance and reliability, it is recommended that she continue to operate under her current cover, with regular **Periodic Reassessment Reviews** to monitor her performance and address any potential vulnerabilities. The Covert Operations division should maintain close communication with Lynx-5, the original case officer, to ensure seamless operational support.\n\n**Document Control System DCS-9** has logged this document as **Access-Controlled**. Distribution is restricted to senior personnel and counterintelligence investigators within the Covert Operations division.\n\n**Classification Level:** Top Secret\n\n**Document ID:** CO-2021-001\n\n**Distribution:** Covert Operations Division, Counter-Espionage Division, Strategic Intelligence Division\n\n**Archive Location:** Central Personnel Archive, Nightingale Historical Record", "metadata": {"document_creation_date": "2021-06-29", "authoring_agent_id": "Phoenix-11", "originating_division": "Covert Operations", "classification_level": "Top Secret", "event_date": "2021-09-29", "mission_priority": 4}}
{"id": "doc_00000080", "type": "Field Contact Report", "content": "**Field Contact Report**\n\n**Identification Code:** NIGHT-2023-12-04-01\n**Event Date:** 2024-05-25\n**Document Creation Date:** 2023-12-04\n**Classification Level:** Confidential\n**Mission Priority:** 3\n**Originating Division:** Signals Intelligence\n**Target Entity:** Warsaw Pact\n\n**Subject:** Warsaw Pact Communication Network Analysis\n\n**Summary:**\n\nOn 2024-05-25, Signals Intelligence Division conducted a technical surveillance operation targeting Warsaw Pact communication networks in Central Europe. The objective was to analyze communication patterns, identify potential vulnerabilities, and assess the feasibility of intercepting high-priority intelligence. This report summarizes the findings from the operation.\n\n**Technical Specifications:**\n\n* **Communication System:** Warsaw Pact forces employed an encrypted communication system based on the K-2 protocol, utilizing a 128-bit key for encryption.\n* **Transmission Method:** Signals were transmitted through a combination of satellite and terrestrial links, with a primary satellite uplink frequency of 10.3 GHz.\n* **Encryption Algorithm:** The K-2 protocol employed a modified version of the Data Encryption Standard (DES) algorithm, with a custom key derivation function.\n* **Key Exchange:** Secret keys were exchanged between units using a Quantum Key Distribution (QKD) system, with a maximum key exchange rate of 100 kbps.\n\n**Analytical Methods:**\n\n* **Spectrum Analysis:** The Signals Intelligence team conducted a spectral analysis of the communication signals, identifying potential frequency hopping patterns and modulation techniques.\n* **Signal Processing:** The team applied a custom signal processing algorithm to enhance the signal-to-noise ratio and extract meaningful information from the encrypted data.\n* **Cryptanalysis:** A cryptanalysis effort was undertaken to break the encryption algorithm, focusing on identifying potential weaknesses and exploiting them.\n\n**Detailed Measurements:**\n\n* **Frequency Hopping Patterns:** The communication signals exhibited a complex frequency hopping pattern, with a maximum frequency shift of 10 MHz and a minimum dwell time of 10 ms.\n* **Modulation Techniques:** The signals employed a combination of phase-shift keying (PSK) and amplitude-shift keying (ASK) modulation techniques.\n* **Key Length:** The secret keys employed by the Warsaw Pact forces had an average length of 256 bits.\n\n**Data-Driven Findings:**\n\n* **Communication Patterns:** The analysis revealed a high degree of coordination between Warsaw Pact units, with a clear hierarchy of command and control.\n* **Vulnerabilities:** The team identified potential vulnerabilities in the communication system, including a weakness in the key derivation function and a susceptibility to jamming attacks.\n* **Feasibility of Intercept:** The analysis concluded that it is feasible to intercept high-priority intelligence from the Warsaw Pact forces, with a recommended intercept rate of 10% for mission-critical information.\n\n**Recommendations:**\n\n* **Enhanced Surveillance:** Conduct regular surveillance operations to monitor Warsaw Pact communication networks and identify potential changes in communication patterns.\n* **Cryptanalysis Efforts:** Continue cryptanalysis efforts to break the encryption algorithm and exploit identified weaknesses.\n* **Jamming Operations:** Develop and implement jamming operations to disrupt Warsaw Pact communication networks and deny them access to high-priority intelligence.\n\n**Conclusion:**\n\nThis report provides a summary of the technical surveillance operation targeting Warsaw Pact communication networks in Central Europe. The analysis revealed a high degree of coordination between Warsaw Pact units, potential vulnerabilities in the communication system, and a feasibility of intercepting high-priority intelligence. These findings are critical to understanding the Warsaw Pact's command and control structure and identifying potential weaknesses to be exploited.\n\n**Distribution:**\n\nThis report is classified Confidential and will be distributed to:\n\n* Signals Intelligence Division\n* Central Intelligence Directorate\n* NATO Intelligence Division", "metadata": {"event_date": "2024-05-25", "document_creation_date": "2023-12-04", "authoring_agent_id": "Sparrowhawk-3", "target_entity": "Warsaw Pact", "classification_level": "Confidential", "mission_priority": 3, "originating_division": "Signals Intelligence"}}
{"id": "doc_00000081", "type": "Operational Debriefing", "content": "**Operational Debriefing Document**\n**Classification Level: Confidential**\n**Document Creation Date: 2023-06-21**\n**Mission Priority: 5**\n**Originating Division: Covert Operations**\n**Event Date: 2020-10-24**\n**Target Entity: GRU**\n\n**Mission Background:**\n\nIn the autumn of 2020, the Covert Operations Division received intelligence suggesting a high-ranking GRU officer, codename \"Phoenix-13,\" would be attending a classified conference in Budapest, Hungary. Phoenix-13 was believed to possess critical knowledge about GRU's ongoing operations in Eastern Europe, including their covert influence efforts within NATO member states. Our objective was to recruit Phoenix-13 as a human asset, providing us with direct access to GRU's inner workings and facilitating the extraction of vital intelligence.\n\n**Mission Planning:**\n\nWe spent several weeks gathering intelligence on Phoenix-13's schedule, habits, and security protocols. Our research indicated that Phoenix-13 would be staying at the luxury Hotel Sofitel in Budapest's city center. We identified a suitable dead drop location, a small caf\u00e9 on the Pest side of the Danube River, as a potential meeting point. Our team in Budapest, comprising Case Officer Nightingale-14 and Technical Specialist Shadow-15, conducted a thorough reconnaissance of the area, ensuring that all necessary assets were in place.\n\n**Mission Execution:**\n\nOn the evening of October 24, 2020, Nightingale-14 and Shadow-15 established themselves at the caf\u00e9, where they maintained a secure surveillance post. At approximately 21:45 hours, Phoenix-13 arrived at the designated meeting point. The two parties engaged in a brief, pre-arranged conversation, and Shadow-15 discreetly activated a concealed recording device to capture the exchange. Phoenix-13, initially cautious, eventually opened up to Nightingale-14, providing critical information about GRU's plans to infiltrate NATO's logistics networks. The meeting lasted approximately 45 minutes, after which Phoenix-13 departed without incident.\n\n**Challenges Encountered:**\n\nDuring the mission, we encountered several challenges. Phoenix-13's security detail, consisting of two heavily armed GRU agents, appeared to be more vigilant than anticipated. At one point, they seemed to be monitoring the caf\u00e9, forcing our team to adapt their surveillance posture. Additionally, a sudden rainstorm rolled in, necessitating a brief evacuation of the dead drop location. These obstacles required quick thinking and decisive action from our team to maintain the operation's integrity.\n\n**Immediate Results:**\n\nThe successful recruitment of Phoenix-13 has provided us with a unique opportunity to gather high-level intelligence on GRU's operations. The extracted information has been analyzed, and our Research & Analysis Division is currently producing a comprehensive report detailing GRU's plans to infiltrate NATO's logistics networks. This intelligence will be invaluable in informing our counterintelligence efforts and enabling us to stay one step ahead of GRU's covert activities.\n\n**Lessons Learned:**\n\nThis mission highlights the importance of thorough planning, adaptability, and creativity in the face of unexpected challenges. Our team's ability to improvise and respond to the changing situation ultimately secured the success of the operation. Furthermore, the use of advanced surveillance technology and secure communication protocols ensured that our assets remained protected throughout the mission.\n\n**Recommendations:**\n\nBased on this operation's outcome, we recommend the following:\n\n1.  Enhanced surveillance protocols for high-priority targets, including the use of advanced sensors and real-time monitoring systems.\n2.  Increased training for Case Officers and Technical Specialists in adaptability, improvisation, and crisis management.\n3.  Enhanced collaboration between Research & Analysis and Covert Operations to ensure seamless integration of intelligence analysis and operational planning.\n\n**Appendix:**\n\nThe following documents are appended to this debriefing for further reference:\n\n1.  Phoenix-13's Agent Profile Dossier\n2.  Nightingale-14's and Shadow-15's Mission Execution Reports\n3.  Extracted Intelligence Report: GRU's Plans to Infiltrate NATO's Logistics Networks\n4.  Technical Analysis Report: Advanced Surveillance Technology Used During the Mission", "metadata": {"document_creation_date": "2023-06-21", "authoring_agent_id": "Raven-9", "mission_priority": 5, "originating_division": "Covert Operations", "classification_level": "Confidential", "event_date": "2020-10-24", "target_entity": "GRU"}}
{"id": "doc_00000082", "type": "Operational Debriefing", "content": "**CLASSIFIED DOCUMENT**\n**PROJECT NIGHTINGALE**\n**OPERATIONAL DEBRIEFING**\n**SUBJECT: COVERT OPERATION \"ECHO-12\"**\n**MISSION CODE NAME: NIGHTSHADE-3**\n**EVENT DATE: 2023-08-11**\n**TARGET ENTITY: SOVIET UNION**\n**CLASSIFICATION LEVEL: TOP SECRET**\n**DOC CREATION DATE: 2022-06-12**\n\n**MISSION SUMMARY:**\nOperation Nightshade-3 aimed to compromise a Soviet research facility in East Germany, identifying vulnerabilities in their advanced cryptographic development. This mission, led by Nightingale-7 with technical support from Shadow-12, involved a complex network of dead drops, live exchanges, and surveillance operations.\n\n**OBJECTIVES:**\n- Infiltrate the Soviet research facility\n- Identify specific vulnerabilities in their cryptographic development\n- Establish a secure communication channel with the target entity\n- Extract critical intelligence on Soviet encryption methods\n\n**EXECUTION DETAILS:**\nThe mission began on 2023-08-05 with the establishment of a dead drop site near the research facility. Nightingale-7, posing as a visiting scientist, created a secure communication channel with the target entity using a Minox camera variant. Shadow-12 assisted in hacking the facility's internal network, providing real-time surveillance and access to secure areas.\n\n**CHALLENGES ENCOUNTERED:**\n1. **Hostile surveillance**: The Soviet KGB had anticipated the operation and deployed counter-surveillance teams, forcing Nightingale-7 to adapt the communication protocol.\n2. **Equipment failure**: A critical encryption device malfunctioned, requiring Shadow-12 to improvise a solution using a spare unit.\n3. **Asset nervousness**: The target entity's nervousness led to a temporary disruption in the communication channel, necessitating a re-establishment of contact.\n\n**IMMEDIATE RESULTS:**\nOperation Nightshade-3 successfully compromised the Soviet research facility, yielding significant intelligence on their cryptographic development. The mission extracted critical information on the Soviet Union's encryption methods, including the Lysander Protocol's vulnerabilities.\n\n**LESSONS LEARNED:**\n1. **Adaptability**: The mission demonstrated the importance of adaptability in the face of unforeseen challenges, particularly in hostile surveillance situations.\n2. **Equipment reliability**: The malfunctioning encryption device highlighted the need for redundant systems and contingency planning.\n3. **Asset management**: The target entity's nervousness underscored the importance of effective asset management and crisis communication.\n\n**COMPARATIVE ANALYSIS:**\nSimilar cases, such as Operation Amber Fox and the Dresden Network Collapse, involved complex dead drop operations and surveillance. However, Nightshade-3's unique features include:\n\n1. **Technical innovation**: The use of a Minox camera variant and Shadow-12's hacking capabilities provided a new level of sophistication in the operation.\n2. **Hostile surveillance**: The Soviet KGB's proactive counter-surveillance efforts created a high-stakes environment, requiring Nightingale-7 to adapt the communication protocol.\n\n**CONCLUSION:**\nOperation Nightshade-3 successfully compromised the Soviet research facility, yielding critical intelligence on their cryptographic development. The mission's adaptability, equipment reliability, and asset management are key takeaways for future operations. This debriefing serves as a valuable reference for Nightingale personnel, highlighting the importance of technical innovation, effective asset management, and contingency planning in the face of unforeseen challenges.\n\n**DISTRIBUTION:**\n\n* Nightingale Division Chiefs\n* Research & Analysis Division\n* Covert Operations Division\n* Strategic Intelligence Division\n\n**RECOMMENDATIONS:**\n\n* Nightingale-7 and Shadow-12 should receive commendations for their exceptional performance in this operation.\n* The Technical Operations Division should review and update their encryption device protocols to prevent similar malfunctions.\n* The Covert Operations Division should integrate lessons learned from this operation into their asset management guidelines.", "metadata": {"document_creation_date": "2022-06-12", "authoring_agent_id": "Viper-6", "mission_priority": 2, "originating_division": "Technical Operations", "classification_level": "Top Secret", "event_date": "2023-08-11", "target_entity": "Soviet Union"}}
{"id": "doc_00000083", "type": "Agent Profile Dossier", "content": "**CLASSIFIED DOCUMENT**\n**PROJECT NIGHTINGALE**\n**AGENT PROFILE DOSSIER**\n**SUBJECT: NIGHTINGALE-13**\n**CREATION DATE: 2024-09-05**\n**ORIGINATING DIVISION: TECHNICAL OPERATIONS**\n**CLASSIFICATION LEVEL: TOP SECRET**\n\n**MISSION SUMMARY**\n\nOn **2020-02-10**, Nightingale-13 (codename: **Aurora**) was deployed as a technical specialist to support Operation **Blue Horizon**, a critical cyber intelligence mission targeting a high-value Soviet asset in Berlin. Aurora's primary objective was to establish a secure communication channel between the Nightingale safe house and the target location.\n\n**RECRUITMENT HISTORY**\n\nAurora was recruited on **2018-06-15** through a complex network of intermediaries, primarily utilizing online personas and secure messaging protocols. Initial contact was made via a cryptic message on a darknet forum, where Aurora expressed interest in collaborating with a Western intelligence agency. Following a series of encrypted meetings, Aurora was vetted and cleared for operation.\n\n**OPERATIONAL ASSIGNMENTS**\n\nAurora has been assigned to the following operations:\n\n1. **Operation Blue Horizon** (2020-02-10): Support cyber intelligence mission in Berlin.\n2. **Operation Starlight** (2019-09-20): Conduct technical surveillance on a suspected Soviet mole in Prague.\n3. **Operation Phoenix** (2018-12-15): Establish secure communication channels for a high-risk asset extraction in Budapest.\n\n**PSYCHOLOGICAL ASSESSMENTS**\n\nAurora's psychological profile has been evaluated through a series of assessments, including:\n\n1. **Operational Personality Inventory (OPI)**: Aurora exhibits high levels of adaptability, creativity, and risk-taking.\n2. **Polygraph Examination Report**: Aurora has consistently demonstrated honesty and integrity throughout the recruitment and operational phases.\n3. **Background Investigation Summary**: Aurora's personal history suggests a strong sense of justice and a desire to contribute to the greater good.\n\n**PERFORMANCE EVALUATIONS**\n\nAurora's performance has been consistently rated as **Exceptional**, with notable achievements in:\n\n1. **Technical expertise**: Aurora has demonstrated exceptional skills in secure communication protocols, encryption, and cyber operations.\n2. **Operational adaptability**: Aurora has consistently demonstrated flexibility and adaptability in response to changing operational requirements.\n3. **Risk management**: Aurora has effectively managed risk throughout operations, minimizing exposure to potential threats.\n\n**PERSONAL BACKGROUND**\n\nAurora's personal background has been thoroughly vetted, revealing:\n\n1. **Family connections**: Aurora's parents are both deceased, with no known living relatives.\n2. **Education**: Aurora holds a degree in computer science from a reputable university.\n3. **Financial situation**: Aurora's financial situation is stable, with access to secure funding channels.\n\n**POTENTIAL VULNERABILITIES**\n\nAurora's profile suggests several potential vulnerabilities, including:\n\n1. **Emotional attachment**: Aurora has demonstrated a strong emotional attachment to certain assets and operations, which may compromise their judgment.\n2. **Overconfidence**: Aurora's exceptional technical skills and operational experience may lead to overconfidence, increasing the risk of mistakes.\n3. **Secrecy**: Aurora's background and personal history suggest a strong desire for secrecy, which may limit their ability to form close relationships.\n\n**CONCLUSION**\n\nNightingale-13 (Aurora) remains a valuable asset to the Nightingale organization, with exceptional technical skills and operational adaptability. However, their emotional attachment and overconfidence may pose risks to future operations. Further training and support may be necessary to mitigate these vulnerabilities.\n\n**RECOMMENDATIONS**\n\n1. **Continued training and support**: Provide Aurora with ongoing training and support to enhance their technical skills and operational adaptability.\n2. **Risk management protocols**: Establish clear risk management protocols to ensure Aurora's overconfidence does not compromise future operations.\n3. **Secure communication channels**: Maintain secure communication channels to protect Aurora's personal and operational information.\n\n**CLASSIFICATION REVIEW**\n\nThis dossier has been reviewed and classified as **TOP SECRET**. Distribution is restricted to authorized personnel with a **Need-to-Know** clearance.\n\n**AUTHORIZATION**\n\nThis dossier has been authorized for release by:\n\n**Nightingale-7** (Senior Case Officer)\n\n**Signature:** ______________________________", "metadata": {"document_creation_date": "2024-09-05", "authoring_agent_id": "Raven-9", "originating_division": "Technical Operations", "classification_level": "Top Secret", "event_date": "2020-02-10", "mission_priority": 2}}
{"id": "doc_00000084", "type": "Field Contact Report", "content": "**Field Contact Report**\n\n**Document ID:** FCR-2024-001\n**Event Date:** 2022-02-14\n**Document Creation Date:** 2024-02-11\n**Target Entity:** East Germany\n**Classification Level:** Secret\n**Mission Priority:** 3\n**Originating Division:** Human Intelligence\n\n**Summary:**\n\nThis Field Contact Report summarizes a routine meeting with a high-value asset, codenamed 'Raven-17,' in East Germany on 2022-02-14. The meeting provided valuable insights into the target entity's industrial espionage activities and confirmed the presence of a potential mole within our network.\n\n**Event Overview:**\n\nOn 2022-02-14, at 1430 hours, I, Nightingale-7 (senior case officer), met with Raven-17, a high-value asset within the East German Ministry of State Security (MfS). The meeting took place at a pre-arranged dead drop location in Berlin, utilizing a standard NCP-60 encrypted transmission schedule.\n\n**Asset Encounter:**\n\nRaven-17, posing as a mid-level MfS officer, provided detailed information on the target entity's industrial espionage activities. The asset revealed that the East German government has been actively targeting Western companies in the aerospace and defense sectors, utilizing a combination of human intelligence (HUMINT) and signals intelligence (SIGINT) to gather sensitive information.\n\n**Key Findings:**\n\n1. **Industrial Espionage:** Raven-17 confirmed that the East German government has been engaged in industrial espionage activities, targeting Western companies in the aerospace and defense sectors.\n2. **Mole Presence:** The asset indicated that there may be a mole within our network, providing sensitive information to the East German government.\n3. **SIGINT Capabilities:** Raven-17 revealed that the East German government has invested heavily in SIGINT capabilities, allowing them to intercept and decrypt sensitive communications.\n\n**Operational Security:**\n\nDuring the meeting, Raven-17 expressed concerns about the security of our communication channels. The asset suggested that our current encryption methods may be vulnerable to East German SIGINT capabilities. I have forwarded this information to Technical Operations Division for further analysis and potential adjustments to our encryption protocols.\n\n**Recommendations:**\n\n1. **Increase Operational Security:** In light of Raven-17's concerns, I recommend that we implement additional security measures to protect our communication channels.\n2. **Investigate Mole Presence:** I recommend that we initiate an investigation into the potential mole within our network, utilizing Counter-Espionage resources to identify and neutralize the threat.\n3. **Update Intelligence:** I recommend that we update our intelligence products to reflect the new information provided by Raven-17, including the targeted sectors and potential vulnerabilities in our communication channels.\n\n**Conclusion:**\n\nThis Field Contact Report summarizes a routine meeting with Raven-17, providing valuable insights into the target entity's industrial espionage activities and potential vulnerabilities in our communication channels. I have forwarded this information to relevant divisions for further analysis and potential action.\n\n**Distribution:**\n\nThis report will be distributed to:\n\n* Nightingale-7 (senior case officer)\n* Raven-17 (asset)\n* Technical Operations Division\n* Counter-Espionage Division\n* Research & Analysis Division\n\n**Document Control:**\n\nThis document will be stored in the Central Personnel Archive, accessible through Document Control System DCS-9.", "metadata": {"event_date": "2022-02-14", "document_creation_date": "2024-02-11", "authoring_agent_id": "Viper-6", "target_entity": "East Germany", "classification_level": "Secret", "mission_priority": 3, "originating_division": "Human Intelligence"}}
{"id": "doc_00000085", "type": "Operational Debriefing", "content": "**OPERATIONAL DEBRIEFING DOCUMENT**\n\n**CLASSIFICATION LEVEL:** Secret\n\n**DOCUMENT CREATION DATE:** 2020-07-25\n\n**MISSION PRIORITY:** 4\n\n**ORIGINATING DIVISION:** Covert Operations\n\n**EVENT DATE:** 2020-06-10\n\n**TARGET ENTITY:** Czechoslovakia\n\n**OBJECTIVES:**\n\nThe mission aimed to establish a secure communication channel with a Czechoslovakian dissident network, codenamed \"Operation Aurora.\" The primary objective was to verify the network's existence, assess its operational capability, and gather intelligence on Czechoslovakian government policies.\n\n**EXECUTION DETAILS:**\n\nThe mission involved a team of three operatives, led by Nightingale-7, who had previously established a rapport with the dissident network. The team conducted a series of dead drops and live meetings, utilizing secure communication protocols and encryption methods.\n\n**TECHNICAL SPECIFICATIONS:**\n\n* **Communication Protocol:** Nightingale Communications Protocol (NCP-60), version 3.2\n* **Encryption Method:** Advanced Encryption Standard (AES), 256-bit key\n* **Secure Communication Device:** Custom-built, high-gain, directional antenna for secure communication with the dissident network\n* **Surveillance Detection:** Utilized a modified version of the Surveillance Detection Route (SDR) algorithm, incorporating real-time location data and AI-powered analysis\n\n**ANALYTICAL METHODS:**\n\nThe team employed a combination of human intelligence (HUMINT) and signals intelligence (SIGINT) to gather and analyze data. The HUMINT component involved direct interaction with the dissident network, while the SIGINT component focused on intercepting and analyzing communication signals.\n\n**DETAILED MEASUREMENTS AND DATA-DRIVEN FINDINGS:**\n\n* **Communication Signal Strength (CSS):** Measured at an average of 45 dBm, with a standard deviation of 2.1 dBm\n* **Encryption Key Exchange (EKE):** Successfully executed 97.5% of the time, with an average error rate of 0.012%\n* **Surveillance Detection Rate (SDR):** Detected 85% of potential surveillance activities, with a false positive rate of 5.2%\n\n**CHALLENGES ENCOUNTERED:**\n\nThe team faced several challenges, including:\n\n* **Surveillance Detection:** Experienced difficulty in detecting surveillance activities, resulting in a 15% false negative rate\n* **Encryption Key Exchange:** Encountered issues with key exchange protocols, leading to a 2.5% failure rate\n* **Communication Signal Strength:** Experienced fluctuations in CSS, affecting communication quality and reliability\n\n**IMMEDIATE RESULTS:**\n\nThe mission successfully established a secure communication channel with the dissident network, allowing for the exchange of sensitive information. The team gathered valuable intelligence on Czechoslovakian government policies, including:\n\n* **Policy Directive:** Identified a new policy directive aimed at suppressing dissent within the country\n* **Government Response:** Documented a significant increase in government response to dissident activities\n\n**LESSONS LEARNED:**\n\nThe mission highlighted several key lessons:\n\n* **Surveillance Detection:** Emphasized the importance of robust surveillance detection protocols and real-time analysis\n* **Encryption Key Exchange:** Highlighted the need for improved encryption key exchange protocols and contingency planning\n* **Communication Signal Strength:** Demonstrated the importance of maintaining a stable communication signal strength and backup protocols\n\n**CONCLUSION:**\n\nOperation Aurora successfully established a secure communication channel with a Czechoslovakian dissident network, gathering valuable intelligence on government policies. The mission highlighted several key challenges and lessons learned, which will inform future operations.\n\n**RECOMMENDATIONS:**\n\n* **Surveillance Detection:** Implement a revised surveillance detection protocol, incorporating real-time analysis and AI-powered tools\n* **Encryption Key Exchange:** Develop and implement improved encryption key exchange protocols and contingency planning\n* **Communication Signal Strength:** Establish a backup communication system and implement measures to maintain a stable communication signal strength\n\n**CLASSIFICATION:**\n\nThis document is classified as Secret and is restricted to personnel with a need-to-know clearance. Distribution is limited to the Covert Operations division and authorized personnel.\n\n**AUTHORIZATION:**\n\nThis document has been authorized by Nightingale-7, senior case officer, Covert Operations division.\n\n**DISTRIBUTION:**\n\nThis document is distributed to:\n\n* Covert Operations division\n* Research & Analysis division\n* Technical Operations division\n* Counter-Espionage division\n\n**ARCHIVAL:**\n\nThis document will be archived in the Central Personnel Archive, with access logged through Document Control System DCS-9.", "metadata": {"document_creation_date": "2020-07-25", "authoring_agent_id": "Nightingale-7", "mission_priority": 4, "originating_division": "Covert Operations", "classification_level": "Secret", "event_date": "2020-06-10", "target_entity": "Czechoslovakia"}}
{"id": "doc_00000086", "type": "Operational Debriefing", "content": "**CLASSIFICATION: TOP SECRET**\n**DOCUMENT ID:** COV-OP-2021-09-22\n**CREATION DATE:** 2020-02-17\n**MISSION PRIORITY:** 4\n**ORIGINATING DIVISION:** Covert Operations\n**TARGET ENTITY:** East Germany\n\n**OPERATIONAL DEBRIEFING**\n\n**Mission Objective:** Conduct a reconnaissance operation to gather intelligence on East German industrial espionage activities, focusing on sensitive technology transfers to the Soviet Union.\n\n**Event Date:** 2021-09-22\n\n**Background:**\n\nIn response to escalating Soviet technological advancements, the Central Intelligence Directorate (CID) tasked Covert Operations with infiltrating East German industrial networks to uncover evidence of sensitive technology transfers. Our operation, codenamed \"Nightshade,\" aimed to identify key players, track transactions, and provide actionable intelligence for strategic planning.\n\n**Pre-Mission Planning:**\n\nOur team, led by experienced case officer Nightingale-7, conducted extensive research on East German industrial complexes and identified potential targets. We developed a sophisticated cover story for our asset, codenamed \"Raven,\" a skilled East German engineer with connections to the targeted industries. Raven's legend was meticulously crafted, including a convincing backstory, fake credentials, and secure communication channels.\n\n**Execution:**\n\nOn 2021-09-22, Raven established contact with a high-ranking East German official, codename \"Falcon,\" at a secure dead drop location in Berlin. The meeting was observed by a surveillance team, ensuring Raven's safety and providing real-time intelligence on Falcon's behavior. Raven gained Falcon's trust by offering a valuable piece of intelligence on a rival East German company, securing an invitation to a high-level meeting at the East German Ministry of Industry.\n\n**Challenges Encountered:**\n\nDuring the meeting, Raven faced intense questioning from Falcon and his associates, testing Raven's cover story and convincing demeanor. Our surveillance team detected suspicious activity from a group of East German counterintelligence agents, who attempted to intercept Raven. We swiftly adapted our plan, using a pre-arranged secure communication channel to alert Raven and provide real-time guidance.\n\n**Immediate Results:**\n\nRaven successfully gathered valuable intelligence on East German industrial espionage activities, including specific details on technology transfers to the Soviet Union. We identified key players, including Falcon and several other high-ranking officials, and documented their connections to the targeted industries. Our surveillance team captured critical footage of the meeting, providing visual evidence of the transactions.\n\n**Lessons Learned:**\n\nThis operation highlighted the importance of thorough pre-mission planning, creative cover story development, and adaptability in the face of unexpected challenges. Our team's expertise in managing complex assets and maintaining secure communication channels proved invaluable. The successful execution of Nightshade demonstrated the effectiveness of our covert operations capabilities and provided critical intelligence on East German industrial espionage activities.\n\n**Recommendations:**\n\nBased on the operation's outcome, we recommend:\n\n1. Continuation of Raven's asset management, focusing on further intelligence gathering and strategic planning.\n2. Development of additional cover stories and safe houses to expand our operational reach in East Germany.\n3. Enhanced surveillance capabilities to address potential counterintelligence threats.\n4. Collaboration with Research & Analysis to analyze the gathered intelligence and develop actionable recommendations for strategic planning.\n\n**Distribution:**\n\nThis debriefing is classified TOP SECRET and will be distributed to:\n\n1. Covert Operations Division, CID\n2. Research & Analysis Division, CID\n3. Strategic Planning Committee, CID\n4. National Intelligence Daily, CIA\n\n**Archival:**\n\nThis document will be archived in the Nightingale Historical Record, accessible to authorized personnel with a need-to-know clearance.\n\n**Signing Off:**\n\nNightshade Operation Team Leader\nNightingale-7\nCovert Operations Division, CID", "metadata": {"document_creation_date": "2020-02-17", "authoring_agent_id": "Shadow-12", "mission_priority": 4, "originating_division": "Covert Operations", "classification_level": "Top Secret", "event_date": "2021-09-22", "target_entity": "East Germany"}}
{"id": "doc_00000087", "type": "Strategic Intelligence Brief", "content": "**Strategic Intelligence Brief: Comparative Analysis of Soviet Union's Military Modernization**\n\n**Document Creation Date:** 2020-03-11\n**Originating Division:** Covert Operations\n**Classification Level:** Restricted\n**Target Entity:** Soviet Union\n**Event Date:** 2021-04-14\n**Mission Priority:** 1\n\n**Introduction:**\n\nThe Soviet Union's military modernization efforts have been a subject of interest for Western intelligence agencies. Recent events, including the April 14, 2021, test of the RS-28 Sarmat intercontinental ballistic missile (ICBM), have raised concerns about the potential threat posed by the Soviet military. This Strategic Intelligence Brief compares and contrasts the Soviet Union's military modernization efforts with similar cases in the past, highlighting unique features and differences.\n\n**Comparative Analysis:**\n\nThe Soviet Union's military modernization efforts can be compared to the Chinese military's modernization efforts during the 1980s and 1990s. Both countries have invested heavily in advanced military technology, including missiles, aircraft, and naval vessels. However, the Soviet Union's efforts have been more focused on developing nuclear-capable ballistic missiles, while China has prioritized developing conventional military capabilities.\n\nIn terms of similarities, both the Soviet Union and China have leveraged their military-industrial complexes to drive modernization efforts. Both countries have also made significant investments in research and development, with a focus on developing advanced technologies such as hypersonic missiles and advanced sensors.\n\nHowever, there are also significant differences between the two cases. The Soviet Union's military modernization efforts have been more focused on maintaining a nuclear deterrence capability, while China has prioritized developing conventional military capabilities to project power in the Asia-Pacific region.\n\n**Unique Features:**\n\nOne unique feature of the Soviet Union's military modernization efforts is the focus on developing advanced nuclear-capable ballistic missiles, such as the RS-28 Sarmat ICBM. This missile has a range of over 6,000 miles and can carry multiple warheads, making it a significant threat to Western military installations.\n\nAnother unique feature of the Soviet Union's military modernization efforts is the emphasis on developing advanced cyber warfare capabilities. Russian military officials have stated that cyber warfare is a key component of their military strategy, and have invested heavily in developing advanced cyber capabilities.\n\n**Differences:**\n\nOne key difference between the Soviet Union's military modernization efforts and previous cases is the level of transparency and openness. The Soviet Union has been relatively open about its military modernization efforts, with regular press briefings and statements from military officials. This is in contrast to previous cases, such as the Chinese military's modernization efforts, which were characterized by a lack of transparency and openness.\n\nAnother key difference is the level of international cooperation and collaboration. The Soviet Union has engaged in significant international cooperation and collaboration on military modernization efforts, including joint exercises and training programs with other countries. This is in contrast to previous cases, where military modernization efforts were often characterized by a lack of international cooperation and collaboration.\n\n**Geopolitical Implications:**\n\nThe Soviet Union's military modernization efforts have significant geopolitical implications. The development of advanced nuclear-capable ballistic missiles and cyber warfare capabilities poses a significant threat to Western military installations and critical infrastructure.\n\nThe emphasis on developing advanced nuclear-capable ballistic missiles also raises concerns about the potential for nuclear proliferation. If the Soviet Union were to develop and deploy nuclear-capable ballistic missiles, it could potentially create a new nuclear threat in the region.\n\n**Potential Future Threats:**\n\nThe Soviet Union's military modernization efforts also raise concerns about potential future threats. The development of advanced cyber warfare capabilities, for example, could potentially be used to disrupt critical infrastructure and compromise national security.\n\nThe emphasis on developing advanced nuclear-capable ballistic missiles also raises concerns about the potential for nuclear conflict. If the Soviet Union were to develop and deploy nuclear-capable ballistic missiles, it could potentially create a new nuclear threat in the region.\n\n**Conclusion:**\n\nIn conclusion, the Soviet Union's military modernization efforts have significant implications for Western military planners and policymakers. The development of advanced nuclear-capable ballistic missiles and cyber warfare capabilities poses a significant threat to Western military installations and critical infrastructure.\n\nThe emphasis on developing advanced nuclear-capable ballistic missiles also raises concerns about the potential for nuclear proliferation and nuclear conflict. It is essential for Western military planners and policymakers to remain vigilant and monitor the Soviet Union's military modernization efforts closely.\n\n**Recommendations:**\n\nBased on this analysis, we recommend the following:\n\n1. Continue to monitor the Soviet Union's military modernization efforts closely.\n2. Develop and deploy advanced cyber defenses to counter the Soviet Union's cyber warfare capabilities.\n3. Invest in developing and deploying advanced missile defense systems to counter the Soviet Union's nuclear-capable ballistic missiles.\n4. Engage in international cooperation and collaboration to address the potential for nuclear proliferation and nuclear conflict.\n\n**Distribution:**\n\nThis Strategic Intelligence Brief is classified Restricted and is intended for the eyes of authorized personnel only. The brief will be distributed to senior military planners and policymakers, as well as to key allies and partners.\n\n**Archive:**\n\nThis Strategic Intelligence Brief will be archived in the Covert Operations Division's Historical Record, with access restricted to authorized personnel only.", "metadata": {"document_creation_date": "2020-03-11", "originating_division": "Covert Operations", "classification_level": "Restricted", "target_entity": "Soviet Union", "event_date": "2021-04-14", "authoring_agent_id": "Ghost-1", "mission_priority": 1}}
{"id": "doc_00000088", "type": "Field Contact Report", "content": "**CLASSIFIED DOCUMENT**\n\n**CONFIDENTIALITY LEVEL: CONFIDENTIAL**\n\n**MISSION PRIORITY: 5**\n\n**EVENT DATE: 2020-02-07**\n\n**DOCUMENT CREATION DATE: 2021-05-30**\n\n**ORIGINATING DIVISION: TECHNICAL OPERATIONS**\n\n**SUBJECT: UNIDENTIFIED RADIO SIGNALS FROM SOVIET UNION**\n\n**SUMMARY:**\n\nOn 2020-02-07, a mysterious radio signal emanating from a Soviet Union location was intercepted by a Technical Operations Division asset. The signal, designated as \"Soviet Echo-7,\" exhibited characteristics consistent with a high-level encryption protocol. This report outlines the investigation and analysis of the signal, highlighting potential implications for Soviet communications security.\n\n**EVENT DETAILS:**\n\nOn 2020-02-07, our asset, codenamed \"Nova-4,\" reported detecting a low-power radio transmission emanating from a Soviet military facility (GRID: 53.4567\u00b0 N, 23.4344\u00b0 E). The signal, operating on a frequency of 4.857 MHz, utilized an unknown encryption protocol. Initial analysis suggested a strong possibility of a high-level communication between Soviet military leaders.\n\n**INVESTIGATION:**\n\nTo elucidate the purpose and significance of the signal, we conducted a series of follow-up intercepts. Our analysis team worked in tandem with the Signals Intelligence Division to decode the signal. After several failed attempts, we discovered a correlation between the signal's key characteristics and an abandoned Soviet encryption standard.\n\n**ANALYSIS:**\n\nBy applying the abandoned encryption standard, we successfully decoded a portion of the signal. The contents revealed a discussion between Soviet military officers regarding the potential deployment of a new, top-secret reconnaissance satellite. This information raises concerns about Soviet advancements in satellite technology and its implications for national security.\n\n**FINDINGS:**\n\nThe investigation uncovered the following key points:\n\n1.  The signal, \"Soviet Echo-7,\" was likely a one-time pad transmission used for high-level communications.\n2.  The abandoned encryption standard used in the signal was previously thought to be obsolete.\n3.  The decoded message implicated Soviet plans for a top-secret reconnaissance satellite.\n\n**RECOMMENDATIONS:**\n\nBased on the findings, we recommend the following:\n\n1.  **Enhanced Monitoring:** Increase surveillance on Soviet military facilities and satellite communications.\n2.  **Technical Analysis:** Conduct a thorough review of the abandoned encryption standard to determine its current vulnerability.\n3.  **Signal Intelligence:** Expand our Signals Intelligence Division's efforts to intercept and analyze similar signals.\n\n**CONCLUSION:**\n\nThe investigation into \"Soviet Echo-7\" has provided valuable insights into Soviet communications security and potential advances in satellite technology. Further analysis and monitoring are necessary to fully grasp the implications of this discovery.\n\n**CLASSIFICATION:**\n\nThis report is classified as **CONFIDENTIAL** and should be handled accordingly.\n\n**DISTRIBUTION:**\n\nThis report will be distributed to the following entities:\n\n*   Technical Operations Division\n*   Signals Intelligence Division\n*   Research & Analysis Division\n*   Strategic Intelligence Unit\n\n**AUTHENTICATION:**\n\nThis report has been authenticated by the Technical Operations Division and cleared for distribution.\n\n**ACKNOWLEDGMENT:**\n\nThe authors acknowledge the contributions of Nova-4, the Signals Intelligence Division, and the Research & Analysis Division to this investigation.\n\n**REVISION HISTORY:**\n\nThis report has undergone the following revisions:\n\n*   Initial draft: 2021-05-15\n*   First revision: 2021-05-20\n*   Final revision: 2021-05-30\n\n**DISCLAIMER:**\n\nThis report contains sensitive information and should be treated with utmost confidentiality. Distribution is restricted to entities with a **NEED-TO-KNOW** clearance.", "metadata": {"event_date": "2020-02-07", "document_creation_date": "2021-05-30", "authoring_agent_id": "Sparrowhawk-3", "target_entity": "Soviet Union", "classification_level": "Confidential", "mission_priority": 5, "originating_division": "Technical Operations"}}
{"id": "doc_00000089", "type": "Operational Debriefing", "content": "**Operational Debriefing: Covert Operations Mission \"Nightshade-7\"**\n\n**Document Creation Date:** 2022-06-28\n**Mission Priority:** 4\n**Originating Division:** Covert Operations\n**Classification Level:** Restricted\n**Event Date:** 2023-06-19\n**Target Entity:** Soviet Union\n\n**Summary:**\n\nMission \"Nightshade-7\" involved the recruitment and handling of a high-value asset within the Soviet Union's military-industrial complex. The operation aimed to gather intelligence on the development and production of Soviet ballistic missiles. This debriefing provides an overview of the mission's objectives, execution, challenges, immediate results, and lessons learned.\n\n**Mission Objectives:**\n\n1. Recruit a high-value asset within the Soviet military-industrial complex.\n2. Gather intelligence on the development and production of Soviet ballistic missiles.\n3. Establish a secure communication channel with the asset.\n\n**Execution:**\n\nThe mission was executed by Covert Operations Division, with the following team members:\n\n* **Handler:** Nightingale-7 (senior case officer)\n* **Asset:** Shadow-14 (high-value asset within the Soviet military-industrial complex)\n* **Technical Specialist:** Sparrowhawk-3 (expert in secure communication protocols)\n\nThe operation began with the identification of a suitable asset, Shadow-14, who possessed access to sensitive information within the Soviet military-industrial complex. Nightingale-7 established initial contact with Shadow-14 through a dead drop in a secure location. The handler and asset agreed on a communication protocol using the Nightingale Communications Protocol (NCP-60).\n\n**Challenges Encountered:**\n\n1. **Hostile Surveillance:** The asset was detected by KGB agents, who were monitoring the dead drop location.\n2. **Technical Issues:** Sparrowhawk-3 encountered difficulties in establishing a secure communication channel with Shadow-14 due to Soviet jamming efforts.\n3. **Asset Vulnerability:** Shadow-14's family was threatened by the KGB, which compromised the asset's security.\n\n**Immediate Results:**\n\n1. **Initial Contact:** Nightingale-7 and Shadow-14 successfully established initial contact through the dead drop.\n2. **Secure Communication Channel:** Sparrowhawk-3 established a secure communication channel with Shadow-14 using the NCP-60 protocol.\n3. **Intelligence Gathering:** Shadow-14 provided crucial information on Soviet ballistic missile development and production.\n\n**Lessons Learned:**\n\n1. **Enhanced Security Measures:** The operation highlights the need for enhanced security measures to protect assets from hostile surveillance and technical issues.\n2. **Asset Vulnerability:** The compromise of Shadow-14's family emphasizes the importance of mitigating asset vulnerabilities to maintain security.\n3. **Technical Expertise:** The success of the operation underscores the value of technical expertise in establishing secure communication channels.\n\n**Conclusion:**\n\nMission \"Nightshade-7\" demonstrated the effectiveness of Covert Operations Division in recruiting and handling high-value assets within the Soviet Union's military-industrial complex. The operation provided valuable intelligence on Soviet ballistic missile development and production. However, the challenges encountered emphasize the need for enhanced security measures, mitigation of asset vulnerabilities, and technical expertise in secure communication protocols.\n\n**Recommendations:**\n\n1. **Enhance Security Measures:** Implement additional security measures to protect assets from hostile surveillance and technical issues.\n2. **Mitigate Asset Vulnerability:** Develop strategies to mitigate asset vulnerabilities and maintain security.\n3. **Invest in Technical Expertise:** Allocate resources to develop technical expertise in secure communication protocols to support future operations.\n\n**Distribution:**\n\nThis debriefing is classified Restricted and will be distributed to the following personnel:\n\n* Covert Operations Division\n* Research & Analysis Division\n* Strategic Intelligence Division\n* Counter-Espionage Division\n\n**Document Control:**\n\nThis document will be stored in the Central Personnel Archive with access logged through the Document Control System (DCS-9).", "metadata": {"document_creation_date": "2022-06-28", "authoring_agent_id": "Ghost-1", "mission_priority": 4, "originating_division": "Covert Operations", "classification_level": "Restricted", "event_date": "2023-06-19", "target_entity": "Soviet Union"}}
{"id": "doc_00000090", "type": "Operational Debriefing", "content": "Operational Debriefing Report\n\nDocument Creation Date: 2021-08-26\nClassification Level: Eyes Only\nMission Priority: 4\nOriginating Division: Signals Intelligence\n\nEvent Date: 2023-01-08\nTarget Entity: Bulgaria\n\n**Mission Objective:** Conduct a technical signals intelligence operation to intercept and analyze Bulgarian military communication networks, focusing on encrypted transmissions and network topology.\n\n**Operational Overview:**\n\nThe mission commenced on 2023-01-08, with a three-person Signals Intelligence team deployed to an undisclosed location near the Bulgarian border. The team consisted of:\n\n1. Team Lead (Signals Intelligence Specialist): Responsible for mission planning, technical setup, and real-time analysis.\n2. Signals Technician: Handled equipment deployment, maintenance, and real-time data processing.\n3. Analyst: Focused on cryptographic analysis, network mapping, and intelligence extraction.\n\n**Technical Setup:**\n\n1. **Surveillance Platform:** A custom-built, high-gain antenna array (HGA) was deployed to maximize signal reception and minimize interference.\n2. **Signal Collection Equipment (SCE):** A state-of-the-art, software-defined radio (SDR) system was used to capture and process signals.\n3. **Cryptanalysis Software:** A customized, open-source tool ( Crypto-Kit) was employed for encrypted transmission analysis.\n\n**Mission Execution:**\n\nThe team conducted a thorough reconnaissance of the target area, identifying optimal signal collection points and verifying the presence of Bulgarian military communication networks. Upon establishing contact, the SCE began capturing and processing signals in real-time.\n\n**Analysis:**\n\n1. **Cryptanalysis:** The Crypto-Kit software successfully cracked a subset of Bulgarian military encryption protocols (AES-256, DES-56), allowing for access to encrypted transmissions.\n2. **Network Mapping:** Detailed network topology maps were generated using the collected data, revealing a complex, hierarchical structure with multiple encryption layers.\n3. **Intelligence Extraction:** Analytical results revealed sensitive information on Bulgarian military operations, including troop deployments, logistics, and strategic plans.\n\n**Challenges Encountered:**\n\n1. **Interference:** Local radio frequency interference (RFI) posed significant challenges, requiring frequent adjustments to the HGA array.\n2. **Signal degradation:** Signal quality suffered due to terrain and distance limitations, necessitating creative solutions to maintain optimal reception.\n3. **Encryption:** The cracked encryption protocols proved more resilient than anticipated, requiring additional computational resources to facilitate efficient analysis.\n\n**Immediate Results:**\n\n1. **Signal capture:** Over 100 hours of encrypted and unencrypted signals were collected, providing a valuable dataset for further analysis.\n2. **Intelligence extraction:** Sensitive information on Bulgarian military operations was successfully extracted, offering strategic insights for future operations.\n3. **Technical advancements:** This mission validated the effectiveness of the Crypto-Kit software and the SDR system in real-world applications.\n\n**Lessons Learned:**\n\n1. **Terrain analysis:** Thorough reconnaissance and terrain analysis are crucial for optimizing signal collection points and mitigating interference.\n2. **Encryption resilience:** Encryption protocols can be more resilient than anticipated; additional computational resources and creative solutions may be necessary to overcome obstacles.\n3. **Signal processing:** Real-time signal processing and analysis are vital for maximizing mission efficiency and extracting valuable intelligence.\n\n**Conclusion:**\n\nThis mission demonstrated the value of technical signals intelligence operations in supporting strategic objectives. The team's dedication, technical expertise, and creative problem-solving ensured the success of the operation, providing critical insights into Bulgarian military operations. The lessons learned will inform future operations, enhancing the effectiveness of Signals Intelligence missions.\n\n**Recommendations:**\n\n1. **Further analysis:** Conduct in-depth analysis of the collected data to identify additional insights and patterns.\n2. **Equipment upgrades:** Explore opportunities for upgrading the SDR system and Crypto-Kit software to enhance signal processing and encryption analysis capabilities.\n3. **Training and exercises:** Develop training programs and exercises to enhance team members' skills in signal collection, analysis, and encryption techniques.\n\n**Signing off:**\n\n[Redacted]\nSignals Intelligence Specialist\n[Redacted]\nTeam Lead\nSignals Intelligence", "metadata": {"document_creation_date": "2021-08-26", "authoring_agent_id": "Shadow-12", "mission_priority": 4, "originating_division": "Signals Intelligence", "classification_level": "Eyes Only", "event_date": "2023-01-08", "target_entity": "Bulgaria"}}
{"id": "doc_00000091", "type": "Strategic Intelligence Brief", "content": "**Confidential Strategic Intelligence Brief**\n**Document Creation Date:** 2023-06-24\n**Originating Division:** Covert Operations\n**Classification Level:** Confidential\n**Target Entity:** East Germany\n**Event Date:** 2022-09-29\n**Mission Priority:** 2\n\n**Subject:** East German Operations: A Shift in Focus\n\n**Narrative Context**\n\nThe past year has witnessed a subtle yet significant shift in East Germany's operational focus, reflecting the country's efforts to counter Western influence and maintain its grip on the region. This trend, observed through a combination of Human Intelligence (HUMINT), Signals Intelligence (SIGINT), and Open-Source Information (OSINT), underscores the government's determination to adapt and respond to the evolving security landscape.\n\n**Operational Overview**\n\nOn September 29, 2022, a major security operation was conducted in the Saxon region, targeting a suspected Western-backed cell reportedly involved in subversive activities. According to field reports from our Nightingale-7 asset, the operation resulted in the arrest of several key individuals, including a high-ranking government official and a prominent dissident. While the official narrative portrayed this as a crackdown on Western espionage, our analysis suggests a more nuanced motivation.\n\n**Intelligence Insights**\n\nOur HUMINT sources indicate that the East German government is increasingly concerned about the growing influence of Western social media platforms, particularly in the younger demographic. This concern is further fueled by the perceived threat posed by dissident movements and the rise of alternative news outlets. As a result, the government has been actively working to counter these perceived threats through a combination of propaganda, surveillance, and repression.\n\n**SIGINT Analysis**\n\nDecrypted communications intercepted by our Technical Operations Division reveal a significant increase in the use of encrypted messaging apps by East German officials and security personnel. This trend, coupled with the development of advanced surveillance capabilities, suggests a concerted effort to monitor and control the flow of information within the country.\n\n**OSINT Observations**\n\nOpen-source analysis of East German media outlets and official publications reveals a consistent theme of anti-Western rhetoric, emphasizing the perceived threats posed by NATO and the European Union. This propaganda effort is aimed at solidifying public opinion in support of the government's hardline stance against Western influence.\n\n**Geopolitical Implications**\n\nThe shift in East German operations reflects a broader regional trend of increased security measures and counter-intelligence efforts. This development has significant implications for the security landscape in Eastern Europe, underscoring the need for continued vigilance and cooperation among Western intelligence agencies.\n\n**Future Threats**\n\nOur analysis suggests that the East German government is likely to continue its efforts to maintain control and suppress dissent. As the country adapts to the evolving security environment, we can expect to see further developments in the areas of surveillance, propaganda, and repression.\n\n**Recommendations**\n\nIn light of these findings, we recommend that our agency:\n\n1. Enhance HUMINT operations to gather more detailed information on East German government activities and plans.\n2. Increase surveillance of encrypted messaging apps and other communication channels used by East German officials and security personnel.\n3. Monitor and analyze East German media outlets and official publications to better understand the country's propaganda efforts.\n\n**Conclusion**\n\nThe shift in East German operations reflects a more complex and nuanced security landscape in Eastern Europe. As we continue to monitor and analyze these developments, it is essential to remain vigilant and adapt our strategies to counter the evolving threats posed by this region.\n\n**Signing off**\n\n[Your Name]\nCovert Operations Division\nConfidential Strategic Intelligence Brief\nDocument Creation Date: 2023-06-24", "metadata": {"document_creation_date": "2023-06-24", "originating_division": "Covert Operations", "classification_level": "Confidential", "target_entity": "East Germany", "event_date": "2022-09-29", "authoring_agent_id": "Nightingale-7", "mission_priority": 2}}
{"id": "doc_00000092", "type": "Field Contact Report", "content": "**Field Contact Report:**\n\n**Event Date:** 2021-04-03\n**Document Creation Date:** 2023-11-15\n**Target Entity:** Soviet Union\n**Classification Level:** Secret\n**Mission Priority:** 2\n**Originating Division:** Covert Operations\n\n**Subject:** Comparative Analysis of Soviet Espionage Activities\n\n**Summary:**\n\nThis report compares and contrasts three recent encounters with Soviet assets, highlighting unique features and differences in their operational tactics. The events occurred on 2021-04-03 in Berlin, East Germany. The primary objective is to provide actionable intelligence on Soviet espionage activities and inform strategic decisions.\n\n**Comparison of Encounters:**\n\n**Case 1:** Shadow-12's report on East German industrial espionage (2021-03-20)\n\n* **Similarity:** Both cases involve Soviet assets targeting Western industrial secrets.\n* **Differences:** This case lacks the sophistication of the 2021-03-20 encounter, with the asset relying on basic dead drops rather than encrypted communication channels.\n\n**Case 2:** Ghost-1's Prague street surveillance summary (2021-03-25)\n\n* **Similarity:** Both cases involve Soviet assets monitoring Western activities in Eastern Europe.\n* **Differences:** The Prague case showcases a more aggressive approach, with the asset using advanced surveillance techniques to gather information.\n\n**Case 3:** Current encounter (2021-04-03)\n\n* **Similarity:** Both cases involve Soviet assets targeting Western secrets.\n* **Differences:** This case demonstrates a more cautious approach, with the asset using a cutout to communicate with the handler.\n\n**Analytical Insights:**\n\nThe three encounters suggest a shift in Soviet espionage tactics, from a more aggressive approach in Prague to a more cautious approach in Berlin. This change may indicate a response to increased Western counterintelligence efforts or a re-evaluation of operational risk.\n\n**Comparison with Similar Cases:**\n\n* **Raven-9's Budapest Incident (1972)**: The use of cutouts in this case is similar to the current encounter, but the sophistication of the operation is lower.\n* **Nightingale-7's Berlin Tunnel monitoring operation (1961)**: The current encounter shares some similarities with this case, including the use of dead drops, but the operational scope is much smaller.\n\n**Recommendations:**\n\n* **Increase surveillance in Berlin** to monitor Soviet activities and gather more intelligence on their operational tactics.\n* **Develop more advanced surveillance techniques** to counter the Soviet asset's use of cutouts and encrypted communication channels.\n* **Re-evaluate operational risk** in light of the Soviet Union's shifting espionage tactics.\n\n**Distribution:**\n\nThis report will be distributed to:\n\n* **Station Chief, Berlin**: For immediate action and further investigation.\n* **Division Head, Covert Operations**: For analysis and strategic decision-making.\n* **Research & Analysis**: For incorporation into the **Quarterly Warsaw Pact Assessment**.\n\n**Classification:**\n\nThis report is classified **Secret** and will be stored in the **Central Personnel Archive** with access logged through **Document Control System DCS-9**.\n\n**Approved by:**\n\nNightingale-7 (Senior Case Officer, Berlin operations)\n\n**Date:** 2023-11-15", "metadata": {"event_date": "2021-04-03", "document_creation_date": "2023-11-15", "authoring_agent_id": "Sparrowhawk-3", "target_entity": "Soviet Union", "classification_level": "Secret", "mission_priority": 2, "originating_division": "Covert Operations"}}
{"id": "doc_00000093", "type": "Field Contact Report", "content": "**Field Contact Report No. FCR-001**\n\n**Document Creation Date:** 18 April 2022\n**Event Date:** 12 December 2022\n**Target Entity:** East Germany\n**Classification Level:** Confidential\n**Mission Priority:** 1\n**Originating Division:** Covert Operations\n\n**Summary:**\nThis report summarizes a successful field contact with a high-value asset (Asset-15) in East Germany on 12 December 2022. The meeting provided critical intelligence on Soviet military operations in the region, including the deployment of surface-to-air missile (SAM) batteries and the movement of armored units. This report details the encounter, intelligence collected, and immediate security concerns.\n\n**Overview:**\nAsset-15, a seasoned East German military officer, was recruited in October 2021 through a carefully managed dead drop operation (Operation Amber). Since then, Asset-15 has provided invaluable insights into East German military planning and operations. The 12 December 2022 meeting, held at a pre-arranged safe house in Leipzig, aimed to gather information on Soviet military movements in the region.\n\n**Meeting Details:**\nThe meeting commenced at 1400 hours with Asset-15 arriving 15 minutes early. The asset was escorted to the meeting location by Covert Operations personnel, ensuring the safe house was secure and surveillance-free. The conversation lasted 45 minutes, during which time Asset-15 provided critical intelligence on Soviet military operations in the region.\n\n**Intelligence Collection:**\nAsset-15 confirmed the deployment of SAM batteries in the vicinity of Dresden, with at least two units operating within a 10-kilometer radius. The asset also reported the movement of armored units, including T-72 tanks, from the East German military base in Leipzig to an undisclosed location. This information is consistent with previous intelligence suggesting a potential Soviet military buildup in the region.\n\n**Immediate Security Concerns:**\nThe meeting raised several security concerns, including:\n\n1. **Surveillance:** Asset-15 reported observing a suspicious East German military vehicle in the vicinity of the safe house, which may have been monitoring the meeting.\n2. **Asset Vulnerability:** Asset-15 expressed concerns regarding their safety and the potential consequences of continued intelligence gathering.\n3. **Operation Security:** The meeting highlighted the need for increased operational security measures to prevent compromise of future operations.\n\n**Recommendations:**\nBased on the information collected during the meeting, Covert Operations recommends:\n\n1. **Immediate Action:** Conduct a thorough analysis of the intelligence collected to determine the potential impact on Soviet military", "metadata": {"event_date": "2022-12-12", "document_creation_date": "2022-04-18", "authoring_agent_id": "Phoenix-11", "target_entity": "East Germany", "classification_level": "Confidential", "mission_priority": 1, "originating_division": "Covert Operations"}}
{"id": "doc_00000094", "type": "Operational Debriefing", "content": "**Operational Debriefing Document**\n\n**Document Creation Date:** 2021-05-13\n**Mission Priority:** 3\n**Originating Division:** Signals Intelligence\n**Classification Level:** Restricted\n**Event Date:** 2022-05-21\n**Target Entity:** Stasi\n\n**Mission Summary:**\n\nA covert signals intelligence operation, codenamed \"Specter,\" aimed to intercept and analyze Stasi communications regarding Eastern European dissident movements. The mission was conducted in collaboration with the Signals Intelligence Division and the Technical Operations Division. This operational debriefing will delve into the objectives, execution details, challenges encountered, immediate results, and lessons learned.\n\n**Objectives:**\n\n1. Intercept and decode Stasi communications related to Eastern European dissident movements.\n2. Identify key Stasi operatives involved in surveillance and intimidation of dissidents.\n3. Analyze communication patterns and networks to understand Stasi's organizational structure and operational methods.\n\n**Execution Details:**\n\nOn 2022-05-21, the Signals Intelligence Division established a listening post in Berlin, leveraging the Technical Operations Division's equipment and expertise. The operation involved a combination of satellite communications and landline intercepts. The team, consisting of three signals analysts and two technical specialists, worked in shifts to monitor and analyze the intercepted communications.\n\n**Challenges Encountered:**\n\n1. **Encryption Complexity:** Stasi communications employed advanced encryption algorithms, which required the team to develop and implement custom decryption software.\n2. **Communication Patterns:** Stasi operatives frequently changed communication protocols, making it challenging to maintain a consistent intercept and analysis flow.\n3. **Technical Issues:** Equipment malfunctions and software glitches disrupted the operation, requiring on-site repairs and adjustments.\n\n**Immediate Results:**\n\n1. **Decoded Communications:** The team successfully decrypted 70% of intercepted communications, providing valuable insights into Stasi's surveillance and intimidation tactics.\n2. **Operative Identification:** The analysis revealed the identities of several key Stasi operatives involved in the surveillance and intimidation of dissidents.\n3. **Communication Network:** The team mapped the Stasi's communication network, highlighting key nodes and relationships between operatives.\n\n**Lessons Learned:**\n\n1. **Encryption Challenges:** The operation demonstrated the importance of developing and maintaining expertise in advanced encryption algorithms and techniques.\n2. **Communication Patterns:** Stasi's adaptability in communication protocols emphasizes the need for flexible and adaptable analytical approaches.\n3. **Technical Expertise:** The operation highlighted the significance of reliable and well-maintained equipment, as well as the importance of on-site technical support.\n\n**Investigative Challenges:**\n\n1. **Stasi's Motivations:** The analysis raises questions about Stasi's motivations and goals regarding Eastern European dissident movements.\n2. **Operative Loyalty:** The team encountered instances of apparent loyalty conflicts within the Stasi, which warrants further investigation.\n3. **Potential Compromises:** The operation revealed potential vulnerabilities in Stasi's communication networks, which may be exploited by dissident groups or other adversaries.\n\n**Future Directions:**\n\n1. **Enhanced Encryption Expertise:** The Signals Intelligence Division should continue to develop and maintain expertise in advanced encryption algorithms and techniques.\n2. **Adaptive Analytical Approaches:** The team should adopt flexible and adaptable analytical methodologies to account for Stasi's changing communication patterns.\n3. **Technical Support:** The Technical Operations Division should prioritize equipment reliability and on-site technical support to minimize disruptions to operations.\n\n**Conclusion:**\n\nThe Specter operation provided valuable insights into Stasi's surveillance and intimidation tactics, as well as their communication networks and organizational structure. The challenges encountered and lessons learned highlight the importance of developing expertise in encryption, adapting to communication patterns, and maintaining reliable technical support. Future directions will focus on enhancing encryption expertise, adopting adaptive analytical approaches, and prioritizing technical support to ensure the success of future operations.\n\n**Recommendations:**\n\n1. **Authorize Further Encryption Research:** Allocate resources for the development and implementation of advanced encryption algorithms and techniques.\n2. **Establish Adaptive Analytical Protocols:** Develop and implement flexible and adaptable analytical methodologies to account for Stasi's changing communication patterns.\n3. **Prioritize Technical Support:** Ensure reliable and well-maintained equipment, as well as on-site technical support, to minimize disruptions to operations.\n\n**Classified Annex:**\n\nThis document contains classified information and should be handled accordingly. The annex includes additional details on the operation, including technical specifications, encryption methods, and communication protocols. Access is restricted to personnel with a need-to-know clearance.\n\n---\n\n**Document Control:**\n\nThis document is classified **Restricted** and is subject to the **Document Control System DCS-9**. Distribution is limited to personnel with a need-to-know clearance. Access is restricted to authorized personnel, and copies are not to be shared without proper clearance.\n\n**Revision History:**\n\n* 2021-05-13: Initial document creation\n* 2022-05-21: Updated with mission summary and results\n* 2022-06-15: Revised to include recommendations and classified annex\n\n**Document Custodian:**\n\nThis document is the property of the **Signals Intelligence Division** and is under the custodianship of **Agent-42**, Signals Intelligence Division.", "metadata": {"document_creation_date": "2021-05-13", "authoring_agent_id": "Phoenix-11", "mission_priority": 3, "originating_division": "Signals Intelligence", "classification_level": "Restricted", "event_date": "2022-05-21", "target_entity": "Stasi"}}
{"id": "doc_00000095", "type": "Operational Debriefing", "content": "**Operational Debriefing: \"Operation Frostbite\"**\n\n**Document Creation Date:** 2020-11-24\n**Mission Priority:** 2\n**Originating Division:** Human Intelligence\n**Classification Level:** Restricted\n**Event Date:** 2021-12-13\n**Target Entity:** Stasi\n\n**Summary:**\n\nOperation Frostbite, a Human Intelligence (HUMINT) operation conducted by Nightingale, aimed to penetrate the Stasi's East German industrial espionage network. This debriefing provides a detailed analysis of the mission's objectives, execution, challenges, immediate results, and lessons learned.\n\n**Mission Objectives:**\n\n1. Establish a trusted asset within the Stasi's industrial espionage division.\n2. Gather intelligence on the Stasi's industrial espionage operations, including targets, methodology, and personnel involved.\n3. Identify potential vulnerabilities in the Stasi's communication networks and protocols.\n\n**Mission Execution:**\n\n1. The operation began with the recruitment of a potential asset, codenamed \"Frostbite-1,\" a mid-level Stasi officer with access to sensitive information.\n2. Frostbite-1 was contacted via a secure dead drop, located in a Berlin park, using a pre-arranged signal (a specific type of flower placed in a specific location).\n3. The initial contact was facilitated by a Nightingale case officer, who established a rapport with Frostbite-1 and provided a secure communication channel (a cryptographically secure communication protocol, utilizing a pre-shared key and a specific encryption algorithm).\n4. Over the course of several weeks, Frostbite-1 provided intelligence on the Stasi's industrial espionage operations, including targets, methodology, and personnel involved.\n5. The intelligence was transmitted via a secure communication channel, using a specific type of cipher (a variant of the Vigen\u00e8re cipher, with a pre-determined keyword).\n\n**Challenges Encountered:**\n\n1. Frostbite-1's initial hesitation to cooperate, due to concerns about the potential risks of being discovered.\n2. The difficulty in establishing a secure communication channel, due to the Stasi's sophisticated surveillance capabilities.\n3. The need to constantly monitor and adapt to changes in the Stasi's communication protocols and networks.\n\n**Immediate Results:**\n\n1. Frostbite-1 provided intelligence on several key targets, including a German electronics company and a French automotive manufacturer.\n2. The intelligence revealed a sophisticated methodology, involving the use of advanced surveillance techniques and encryption protocols.\n3. Frostbite-1 identified several key personnel involved in the industrial espionage operations, including a high-ranking Stasi officer.\n\n**Lessons Learned:**\n\n1. The importance of establishing a strong rapport with the asset, in order to build trust and facilitate cooperation.\n2. The need to continuously monitor and adapt to changes in the target organization's communication protocols and networks.\n3. The value of using advanced encryption protocols and secure communication channels, in order to protect the asset and the operation from detection.\n\n**Technical Specifications:**\n\n1. The dead drop was located in a Berlin park, using a specific type of flower (a variant of the Bellis perennis) placed in a specific location.\n2. The pre-arranged signal was a specific type of flower, placed in a specific location, at a specific time.\n3. The secure communication channel was established using a cryptographically secure communication protocol, utilizing a pre-shared key and a specific encryption algorithm (a variant of the Advanced Encryption Standard, with a 256-bit key).\n4. The cipher used was a variant of the Vigen\u00e8re cipher, with a pre-determined keyword (a 20-character string, consisting of a combination of letters and numbers).\n\n**Analytical Methods:**\n\n1. The use of a polygraph examination report, to assess the asset's credibility and potential vulnerabilities.\n2. The analysis of Frostbite-1's background, including their education, work experience, and personal characteristics.\n3. The use of a risk assessment matrix, to evaluate the potential risks associated with the operation and to identify potential mitigation strategies.\n\n**Detailed Measurements:**\n\n1. The asset's communication channel was monitored for a total of 30 minutes, using a specific type of intercept device (a variant of the SIGINT intercept device, with a 10-mHz frequency range).\n2. The asset's communication channel was encrypted using a specific type of encryption protocol (a variant of the Advanced Encryption Standard, with a 256-bit key).\n3. The asset's communication channel was transmitted via a specific type of transmission medium (a variant of the fiber-optic transmission medium, with a 10-Gbps bandwidth).\n\n**Data-Driven Findings:**\n\n1. The analysis of Frostbite-1's communication channel revealed a sophisticated encryption protocol, using a specific type of cipher (a variant of the Vigen\u00e8re cipher, with a pre-determined keyword).\n2. The analysis of Frostbite-1's communication channel revealed a specific type of transmission medium (a variant of the fiber-optic transmission medium, with a 10-Gbps bandwidth).\n3. The analysis of Frostbite-1's communication channel revealed a specific type of intercept device (a variant of the SIGINT intercept device, with a 10-mHz frequency range).\n\n**Conclusion:**\n\nOperation Frostbite was a successful HUMINT operation, which penetrated the Stasi's industrial espionage network and provided valuable intelligence on the target organization's operations and personnel. The operation highlights the importance of establishing a strong rapport with the asset, using advanced encryption protocols and secure communication channels, and continuously monitoring and adapting to changes in the target organization's communication protocols and networks.", "metadata": {"document_creation_date": "2020-11-24", "authoring_agent_id": "Ghost-1", "mission_priority": 2, "originating_division": "Human Intelligence", "classification_level": "Restricted", "event_date": "2021-12-13", "target_entity": "Stasi"}}
{"id": "doc_00000096", "type": "Strategic Intelligence Brief", "content": "**CONFIDENTIAL**\n\n**STRATEGIC INTELLIGENCE BRIEF**\n\n**SUBJECT:** Warsaw Pact Capabilities and Intentions: A Deep Dive into the 2020-2021 Period\n\n**ORIGINATING DIVISION:** Human Intelligence\n\n**DOCUMENT CREATION DATE:** 2023-01-31\n\n**CLASSIFICATION LEVEL:** Confidential\n\n**TARGET ENTITY:** Warsaw Pact\n\n**EVENT DATE:** 2020-04-27\n\n**MISSION PRIORITY:** 4\n\nAs the world grappled with the COVID-19 pandemic in 2020, the Warsaw Pact, comprising the Soviet Union, East Germany, Poland, Czechoslovakia, Hungary, and Bulgaria, was undergoing significant transformations. Our Human Intelligence division conducted an in-depth analysis of the Pact's military capabilities, intentions, and geopolitical implications, providing a comprehensive understanding of the region's dynamics.\n\n**MILITARY CAPABILITIES**\n\nThe Warsaw Pact's military capabilities were a significant concern for NATO and its allies. Our SIGINT operations, supported by Technical Operations Division, intercepted and analyzed Soviet military communications, revealing a complex web of strategic and tactical operations. We identified increased activity around key military installations in Eastern Europe, including the Soviet Union's Baltic Fleet and the Polish People's Army's First Army Corps.\n\nNotably, our HUMINT sources within the Pact's military apparatus reported a significant shift in focus towards asymmetric warfare, with an emphasis on guerrilla tactics, sabotage, and unconventional operations. This shift was likely in response to the Soviet Union's economic struggles and the need to adapt to the changing global security landscape.\n\n**GEOPOLITICAL IMPLICATIONS**\n\nThe Warsaw Pact's intentions and geopolitical implications were multifaceted. Our OSINT analysis of regional media outlets and diplomatic correspondence revealed a concerted effort to project Soviet influence in Eastern Europe, often through economic and cultural means.\n\nThe Soviet Union's support for the Lukashenko regime in Belarus, for instance, was a clear demonstration of its willingness to maintain control over the region. Similarly, the Pact's involvement in the 2020 Belarusian presidential election highlighted the importance of maintaining a favorable balance of power in the region.\n\n**LONG-TERM CAPABILITIES AND THREATS**\n\nLooking ahead to the 2020s, our analysis suggests that the Warsaw Pact will continue to evolve, driven by a combination of internal and external factors. The Soviet Union's economic struggles, for instance, may lead to increased reliance on asymmetric warfare and unconventional operations, which could pose significant challenges to NATO and its allies.\n\nThe Pact's military capabilities, while still a concern, are expected to decline in the face of modernization efforts and budget constraints. However, the region's complex geopolitics and the Soviet Union's ongoing influence make it essential to maintain a high level of vigilance.\n\n**RECOMMENDATIONS**\n\nBased on our analysis, we recommend that NATO and its allies:\n\n1. Continue to monitor the Warsaw Pact's military capabilities, with a focus on asymmetric warfare and unconventional operations.\n2. Enhance cooperation with regional partners, such as Poland and the Czech Republic, to address common security concerns.\n3. Develop strategies to counter the Soviet Union's influence in Eastern Europe, including through economic and cultural means.\n4. Maintain a high level of preparedness for potential military conflicts, while also exploring opportunities for diplomacy and conflict resolution.\n\n**CONCLUSION**\n\nThe Warsaw Pact's capabilities and intentions in the 2020-2021 period were marked by a complex interplay of internal and external factors. Our analysis provides a comprehensive understanding of the region's dynamics, highlighting the need for continued vigilance and strategic adaptation.\n\nBy staying informed about the Pact's capabilities and intentions, NATO and its allies can better address the challenges and opportunities presented by this complex and ever-evolving region.\n\n**DISSEMINATION**\n\nThis Strategic Intelligence Brief has been distributed to:\n\n* NATO Strategic Command\n* US Department of State\n* UK Ministry of Defence\n* Canadian Ministry of National Defence\n* French Ministry of the Armed Forces\n\n**CLASSIFICATION**\n\nThis document is classified CONFIDENTIAL. Distribution is restricted to authorized personnel with a need-to-know clearance.", "metadata": {"document_creation_date": "2023-01-31", "originating_division": "Human Intelligence", "classification_level": "Confidential", "target_entity": "Warsaw Pact", "event_date": "2020-04-27", "authoring_agent_id": "Phoenix-11", "mission_priority": 4}}
{"id": "doc_00000097", "type": "Field Contact Report", "content": "**Field Contact Report**\n\n**Document ID:** FCR-21-007\n**Date:** 2021-10-07\n**Creation Date:** 2021-10-07\n**Event Date:** 2020-02-23\n**Classification Level:** Top Secret\n**Mission Priority:** 4\n**Originating Division:** Human Intelligence\n**Target Entity:** East Germany\n\n**Agent ID:** Nightingale-12\n**Handler:** Sparrowhawk-3\n**Location:** Dresden, East Germany\n**Meeting Type:** Live Drop\n\n**Summary:**\n\nThis field contact report details a meeting with asset Nightingale-12 on 2020-02-23, where he provided information on East German industrial espionage activities. Comparison with previous reports reveals a unique aspect of this meeting: the asset's concern about a potential mole within his network.\n\n**Meeting Details:**\n\nNightingale-12, a trusted source within the East German industrial sector, met with Handler Sparrowhawk-3 in a secure location in Dresden. The meeting lasted for 45 minutes and produced valuable intelligence on East German espionage activities.\n\n**Intelligence:**\n\n1.  **Industrial Espionage:** Nightingale-12 reported on a recent East German attempt to acquire advanced manufacturing technology from a Western European company. This attempt was thwarted by a Western intelligence agency, which compromised the East German operation.\n2.  **Mole Concerns:** Nightingale-12 expressed concern about a potential mole within his network, citing suspicious behavior from a colleague. This concern is unique to this meeting and warrants further investigation.\n3.  **Counterintelligence:** Nightingale-12 provided information on East German counterintelligence efforts, including their use of deception tactics to identify and recruit Western assets.\n\n**Comparison with Similar Cases:**\n\n1.  **Similarity to FCR-20-005:** The meeting with Nightingale-12 bears some resemblance to FCR-20-005, where an asset reported on East German espionage activities in the automotive sector. However, the mole concern in this report is a new development that requires further investigation.\n2.  **Differences from FCR-20-008:** Unlike FCR-20-008, which focused on East German military intelligence activities, this report details industrial espionage and counterintelligence efforts.\n\n**Analytical Insights:**\n\n1.  **Mole Concerns:** The mole concern in this report highlights the potential for compromised assets within the East German industrial sector. Further investigation is necessary to determine the extent of this compromise.\n2.  **Counterintelligence Efforts:** The information provided by Nightingale-12 on East German counterintelligence efforts suggests that the East Germans are actively working to identify and recruit Western assets.\n\n**Recommendations:**\n\n1.  **Investigate Mole Concerns:** Further investigation is necessary to determine the extent of the mole concern within the East German industrial sector.\n2.  **Monitor Counterintelligence Efforts:** Continued monitoring of East German counterintelligence efforts is necessary to understand their strategy and tactics.\n\n**Distribution:**\n\nThis report is classified Top Secret and is intended for distribution to the following personnel:\n\n1.  **Sparrowhawk-3:** Handler for Nightingale-12\n2.  **Research & Analysis Division:** For analysis and strategic assessment\n3.  **Counterintelligence Division:** For investigation and compromise mitigation\n\n**End of Report**", "metadata": {"event_date": "2020-02-23", "document_creation_date": "2021-10-07", "authoring_agent_id": "Raven-9", "target_entity": "East Germany", "classification_level": "Top Secret", "mission_priority": 4, "originating_division": "Human Intelligence"}}
{"id": "doc_00000098", "type": "Agent Profile Dossier", "content": "**Agent Profile Dossier:**\n\n**Document Creation Date:** 2021-10-28\n**Originating Division:** Covert Operations\n**Classification Level:** Top Secret\n**Event Date:** 2021-02-14\n**Mission Priority:** 4\n\n**Agent Designation:** Nightingale-14 (codename: \"Specter\")\n**Recruitment History:**\nNightingale-14 was recruited by a junior case officer in 2018 during a routine surveillance operation in Eastern Europe. The agent demonstrated exceptional skills in infiltration and sabotage, eventually earning the codename \"Specter\" due to their ability to blend into even the most secure environments.\n\n**Operational Assignments:**\nSpecter has been assigned to multiple high-priority missions, including Operation Phoenix (counter-surveillance training) and Operation Frostbite (deep-cover infiltration of a high-security facility). Their performance has been consistently evaluated as \"excellent\" by their handlers.\n\n**Psychological Assessments:**\nThe Operational Personality Inventory (OPI) revealed that Specter exhibits high levels of adaptability, resilience, and strategic thinking. However, their emotional intelligence and empathy scores were slightly below average, suggesting potential difficulties in building and maintaining relationships.\n\n**Performance Evaluations:**\nSpecter's performance evaluations consistently demonstrate exceptional skill in infiltration, sabotage, and counter-surveillance. Their handlers have praised their creativity, resourcefulness, and ability to think on their feet.\n\n**Personal Background:**\nSpecter's personal background is shrouded in mystery, with limited information available on their pre-recruitment life. Their handlers have described them as \"highly intelligent\" and \"culturally aware,\" with an exceptional ability to blend into various environments.\n\n**Potential Vulnerabilities:**\nOur investigation has revealed several potential vulnerabilities in Specter's profile:\n\n1. **Emotional Intelligence:** Specter's below-average emotional intelligence scores suggest difficulties in building and maintaining relationships. This may impact their ability to work effectively with other agents and handlers.\n2. **Lack of Personal Connections:** Specter's enigmatic personal background and limited information on their pre-recruitment life raise concerns about their potential motivations and loyalty.\n3. **High-Risk Behavior:** Specter's history of high-risk behavior, as demonstrated in Operation Phoenix, may indicate a tendency towards recklessness and impulsiveness.\n\n**Recommendations:**\nBased on our investigation, we recommend:\n\n1. **Enhanced Psychological Evaluation:** Conduct a comprehensive psychological evaluation to further assess Specter's emotional intelligence, empathy, and potential vulnerabilities.\n2. **Increased Handler Support:** Provide Specter with additional handler support to help maintain relationships and address potential emotional intelligence issues.\n3. **Risk Management Protocol:** Develop a risk management protocol to mitigate the potential consequences of Specter's high-risk behavior.\n\n**Conclusion:**\nNightingale-14, codename \"Specter,\" is a highly skilled and effective agent with exceptional infiltration and sabotage abilities. However, their potential vulnerabilities, including emotional intelligence issues and lack of personal connections, require close monitoring and support. With careful management and handler support, Specter can continue to be a valuable asset to the Covert Operations division.\n\n**Recommendations for Future Operations:**\n\n1. **Operation Eclipse:** Utilize Specter's skills in infiltration and sabotage to target high-priority targets.\n2. **Operation Nightshade:** Assign Specter to a high-risk mission, providing close handler support to mitigate potential consequences.\n3. **Agent Development Program:** Offer Specter opportunities to develop their leadership and interpersonal skills to address potential emotional intelligence issues.\n\n**Document Control:** This dossier is classified Top Secret and is restricted to authorized personnel with a need-to-know clearance. Distribution is limited to the Covert Operations division and relevant handler personnel.\n\n**Document ID:** CO-2021-10-28-N14\n**Revision Number:** 1\n**Revision Date:** 2021-10-28\n\n**Document Creator:** Nightingale-7 (case officer)\n**Document Approver:** Viper-6 (division chief)\n\n**Classification Change Request:** If any changes to this dossier are made, please notify the document creator and approver.", "metadata": {"document_creation_date": "2021-10-28", "authoring_agent_id": "Ghost-1", "originating_division": "Covert Operations", "classification_level": "Top Secret", "event_date": "2021-02-14", "mission_priority": 4}}
{"id": "doc_00000099", "type": "Agent Profile Dossier", "content": "**CLASSIFIED DOCUMENT**\n**EYES ONLY**\n**PROJECT NIGHTINGALE**\n**AGENT PROFILE DOSSIER**\n\n**OVERVIEW**\n\nThis dossier provides a comprehensive profile of Agent Nightingale-13, codename \"Moonlight\", a high-value asset recruited by the Research & Analysis Division of Project Nightingale. The document covers recruitment history, operational assignments, psychological assessments, performance evaluations, personal background, and potential vulnerabilities.\n\n**RECRUITMENT HISTORY**\n\nAgent Nightingale-13 was recruited on 2018-02-15 through a joint operation with the Gehlen Organization, utilizing the \"Raven's Wings\" safe house network in Munich. The agent was initially identified as a potential source through signals intelligence intercepts, which revealed his involvement in high-level discussions with East German intelligence officials.\n\n**OPERATIONAL ASSIGNMENTS**\n\nAgent Nightingale-13 has been assigned to the following operations:\n\n1. **Operation Silver Lining** (2018-03-01 - 2019-06-15): Provided critical intelligence on Soviet military mobilization plans, including the deployment of tactical nuclear assets.\n2. **Operation Nightshade** (2019-07-01 - 2020-03-15): Assisted in the identification and neutralization of a suspected mole within Project Nightingale.\n3. **Operation Starlight** (2020-04-01 - 2021-09-15): Gathered intelligence on Chinese military modernization efforts, including the development of advanced cyber warfare capabilities.\n\n**PSYCHOLOGICAL ASSESSMENTS**\n\nAgent Nightingale-13 has undergone multiple psychological assessments, including:\n\n1. **Operational Personality Inventory (OPI)** (2018-03-01): Revealed a high level of risk tolerance and adaptability, with a moderate level of emotional stability.\n2. **Personality Assessment Inventory (PAI)** (2020-04-01): Indicated a strong sense of loyalty and duty, with a moderate level of anxiety and stress.\n3. **Mental Health Evaluation (MHE)** (2022-07-17): Suggests a high level of resilience and coping mechanisms, with a moderate level of emotional vulnerability.\n\n**PERFORMANCE EVALUATIONS**\n\nAgent Nightingale-13 has received the following performance evaluations:\n\n1. **Exceptional Service Medal** (2019-06-15): Awarded for outstanding performance in Operation Silver Lining.\n2. **Meritorious Service Medal** (2020-03-15): Awarded for exceptional service in Operation Nightshade.\n3. **Commendation Award** (2021-09-15): Awarded for outstanding performance in Operation Starlight.\n\n**PERSONAL BACKGROUND**\n\nAgent Nightingale-13 was born on 1990-02-12 in Berlin, Germany. He holds a degree in computer science from the Technical University of Berlin and has worked as a software engineer for several years before joining Project Nightingale.\n\n**POTENTIAL VULNERABILITIES**\n\nAgent Nightingale-13 has several potential vulnerabilities that must be addressed:\n\n1. **Financial instability**: Agent Nightingale-13 has a history of financial difficulties, which could be exploited by hostile forces.\n2. **Emotional vulnerability**: Agent Nightingale-13 has a moderate level of emotional vulnerability, which could be leveraged by adversaries.\n3. **Lack of technical expertise**: Agent Nightingale-13 has limited technical expertise, which could hinder his ability to gather and transmit intelligence.\n\n**RECOMMENDATIONS**\n\nBased on the information contained in this dossier, we recommend the following:\n\n1. **Provide additional training and support**: Agent Nightingale-13 should receive additional training and support to address his technical expertise and emotional vulnerability.\n2. **Monitor financial stability**: Agent Nightingale-13's financial stability should be closely monitored to prevent exploitation by hostile forces.\n3. **Rotate operational assignments**: Agent Nightingale-13's operational assignments should be rotated regularly to prevent burnout and maintain his effectiveness.\n\n**CLASSIFICATION**\n\nThis document is classified **EYES ONLY** and is restricted to personnel with a **Need-to-Know** clearance.\n\n**AUTHENTICATION**\n\nThis document was created on 2021-04-08 by Research & Analysis Division, Project Nightingale. The authenticity of this document is guaranteed by the signature of the Division Chief.\n\n**EVENT DATE**\n\nThe information contained in this dossier is current as of 2022-07-17.\n\n**MISSION PRIORITY**\n\nThe mission priority for Agent Nightingale-13 is **3**, indicating a routine intelligence gathering operation.\n\n**DISPOSITION**\n\nThis document will be stored in the **Central Personnel Archive** and will be accessible to authorized personnel through the **Document Control System DCS-9**.", "metadata": {"document_creation_date": "2021-04-08", "authoring_agent_id": "Orion-5", "originating_division": "Research & Analysis", "classification_level": "Eyes Only", "event_date": "2022-07-17", "mission_priority": 3}}
